Workbook

Sheet あらすじ全文
A1: genre | B1: rank | C1: 区分 | D1: title | E1: author | F1: work_url | G1: catchphrase | H1: intro | I1: intro_len | J1: tags | K1: star | L1: star_gain | M1: star_per_day | N1: episodes | O1: chars | P1: elapsed_days | Q1: status
A2: 現代ファンタジー | B2: 1 | C2: 継続 | D2: S級探索者を5人育てたら全員に独立された中年コーチ、暇つぶしの初心者講座配信が「人類の攻略常識」を書き換え始める 〜教え子たちが「先生の本当の価値」に気付いて騒ぎ出すまで、あと3日〜 | E2: さくらろ | F2: https://kakuyomu.jp/works/2912051604434822405 | G2: 育てた俺が、一番育っていなかったらしい。……世界の評価基準のほうがな。 | H2: 「アンタの育成論、ただの寄生だろ」 S級探索者を5人育てた俺は、その全員に独立され、業界から追放同然に引退した。 戦闘の才能はB級止まり。確かに俺自身は、何者にもなれなかった。 ――だから、暇つぶしだった。 初心者向けの攻略講座配信なんて、誰も見ないと思っていた。 「基礎ステップの踏み方が変だね。それじゃ三層で死ぬよ」 「え、なんで分かるんですか！？」 落ちこぼれE級の少女に教えた「ただの基礎」が、一週間でC級相当の動きに化けた。 切り抜きが拡散され、攻略wikiが書き換わり、大手クランの研究班がざわつき始める。 【あの講座、人類最強・剣条玲の動きと同じ事を言ってないか？】 【おい、誰かこのコーチの経歴調べろ】 そして配信に、見覚えのありすぎる人類最強がコメントを残す。 ――『先生。見つけました』 俺を置いていったはずの教え子たちが、世界中で勝手に騒ぎ始めた。 ※主人公は無自覚です。教え子と業界が勝手に騒ぎ、俺を捨てた連中が勝手に曇ります。基本ノンストレス・サクサク更新。 | I2: 442 | J2: 現代ダンジョン|配信|師匠|おっさん主人公|無自覚|曇らせ|成り上がり|AI本文利用 | K2: 4745 | L2: 377 | M2: 377 | N2: 28 | O2: 95360 | P2: 17 | Q2: 連載中
A3: 現代ファンタジー | B3: 2 | C3: 継続 | D3: 氷河期ストレージ ～生き返った俺はすべての甘さを捨てて、この絶望を生き抜く～ | E3: 宵白レン | F3: https://kakuyomu.jp/works/2912051605717497440 | G3: 生きるためなら、人はどこまで人を捨てられるのか。 | H3: 世界を襲った、予測不能の異常寒波。 気温は急降下し、物流は止まり、電気も水道も失われていく。 食料が尽き、救助も来ないと悟った時、人々が当たり前だと思っていた秩序は崩れ始めた。 奪う者。従う者。裏切る者。そして、生きるために誰かを見捨てる者。 法律も善意も意味を失った極寒の世界で、人はどこまで人間でいられるのか。 そんな世界で一度命を落とした神崎蓮は、寒波が訪れる一ヶ月前へと戻っていた。 手にしたのは、あらゆる物資を保存できる謎の能力。 前の人生で人を信じ、裏切られ、雪の中で死んだ蓮は決める。 今度は、すべての甘さを捨てる。 善意ではなく対価を。情ではなく合理を。助ける人間さえ、自分で選ぶ。 やがて文明が崩れたその先で、生き残った人々は再び集まり、新たな秩序を作り始める。 それは以前と同じ社会なのか。 それとも、生存だけを正義とする別の何かなのか。 これは極寒の世界を舞台に、人間の本質と、崩壊した文明の先に生まれる新たな社会を描く物語。 | I3: 428 | J3: 現代ファンタジー|終末|秩序崩壊|人間ドラマ|ざまぁ|タイムリープ|群像劇|AI本文一部利用 | K3: 4608 | L3: 173 | M3: 173 | N3: 104 | O3: 626994 | P3: 27 | Q3: 連載中
A4: 現代ファンタジー | B4: 3 | C4: 継続 | D4: 穏やかゲーマー配信者、ストレス発散でブチ切れながらモンスターを蹂躙している姿が世界中で拡散され無事本性がバレてしまう | E4: くるみ | F4: https://kakuyomu.jp/works/2912051605963241331 | G4: 「ダンジョン攻略したらガチャ石大量配布！？ 任せろ全部蹂躙してやる」 | H4: ダンジョン配信が世界中で流行る中、俺――白楽燕璃《しらくえんり》はゲーム配信をしていた。 そんな時、とある出来事からストレスでブチギレそうになってしまう。だが、リスナーの前でそんな姿を見せるわけにはいかない。考えた結果ダンジョンでモンスターを蹂躙してストレスを発散することにした。 ストレスで我慢が出来なくなっていた俺はそこでたまたま居合わせた可愛らしい探索者のことなんて気にせずにとんでもない暴言を吐き捨て、モンスターを一体も残らずに殺して周った。後日、その探索者が実は有名ダンジョン配信者で、俺のブチギレ暴言モンスター蹂躙姿が世界中で拡散されてしまう。 あれよあれよと流され、気づけばダンジョン配信をする羽目に……！ そして金髪お姫様やバーサーカー気質な女性、お忍びS級海外美女探索者といった個性あふれる人々と出会い、俺の世界は瞬く間に変わっていく。 いや、俺ゲームしたいだけなんだが……。 え？ダンジョン配信したら課金用のお金くれるの！？！？ じゃあやる！！ 「来たモンスターぶっ殺しニキだ！」「今日も清々しいまでにモンスターを蹂躙してくれ！」「俺達のトラウマモンスターが完膚なきまでに叩きのめされてて気持ちい！！」 この物語はただのゲーム配信者だった俺が一つのきっかけをもとに様々な出会いを経てダンジョンを蹂躙していく物語 | I4: 573 | J4: 男主人公|主人公最強|ダンジョン|ゲーマー|配信|無双|無自覚ハーレム|ヤンデレ・バーサーカー・お嬢様 | K4: 3019 | L4: 231 | M4: 231 | N4: 25 | O4: 79035 | P4: 20 | Q4: 連載中
A5: 現代ファンタジー | B5: 4 | C5: 継続 | D5: クビになった錬金術師のおっさん、回復薬をネット販売したらエリクサー扱いされました～初心者冒険者を救っていたら、俺をクビにした大手製薬会社が後悔し始めた～ | E5: あずーる | F5: https://kakuyomu.jp/works/2912051606449893780 | G5: 初心者応援！ 自作の薬草水、1本100円で出品します。 | H5: ダンジョンが出現した日本・東京都。45歳の錬金術師、佐伯修一は、大手製薬会社で冒険者向けの薬を作っていた。 初心者でも買える安価な回復薬を作り続けてきた修一だが、「利益にならない」と会社をクビになってしまう。 そんな日に、金がなく回復薬を買えなかった初心者冒険者の死亡事故を見る。「薬が高いから死ぬなんて、おかしいだろ」――修一は自分の薬をネット販売することに。 一瓶100円。本人はただの薬草水のつもりだったが、購入者から「瀕死から全回復した」「これ、エリクサーじゃないの？」と驚きの声が殺到。口コミは広がり、やがて修一の薬は冒険者たちの必需品になっていく。 一方、修一を切り捨てた大手製薬会社は、売上の急減に直面していた。 クビになったおっさん錬金術師は、今日も知らず知らずのうちに冒険者を救っていく。 「薬が足りない？ じゃあ、もう一本送っとくか」 本人だけが自分の作る薬が「エリクサー」と呼ばれていることを知らないまま――。 | I5: 423 | J5: ダンジョン|おっさん主人公|錬金術師|無自覚|追放|ざまぁ|勘違い|AI補助利用 | K5: 2394 | L5: 196 | M5: 196 | N5: 40 | O5: 127341 | P5: 18 | Q5: 完結済
A6: 現代ファンタジー | B6: 5 | C6: 継続 | D6: 俺の裏山、世界最高難度らしい ～中古ドローンでいつものダンジョンを配信したら世界中が騒ぎ始めた～ | E6: 山ノ上商会 | F6: https://kakuyomu.jp/works/2912051606470936014 | G6: 俺にとっては、ただの遊び場だった。――世界がその異常さに気付くまでは。 | H6: 相川湊、大学二年生。 彼には、人にはあまり言っていない趣味がある。 それは――実家の裏山にあるダンジョンを攻略すること。 中学生の頃に偶然見つけてから七年間。 誰にも知られていないその場所は、湊にとって秘密基地のような遊び場だった。 そんなある日、バイト仲間との何気ない会話から、ダンジョン配信がお金になることを知る。 そして譲ってもらったのは、五年前の中古配信用ドローン。 「まあ、試しにやってみるか」 軽い気持ちで始めた初配信。 一階に現れたB級魔物を普段着で倒し、見たこともないアイテムを「いらない」と置いていく湊。 視聴者は騒然。 有名探索者まで配信を見始め、ついには探索者協会まで動き出す。 しかし、湊だけは知らない。 七年間遊び続けてきた実家の裏山が、既存の常識では測れない異常なダンジョンであることを。 そして、その環境で育った自分自身もまた――普通ではなくなっていることを。 これは、一人の青年が中古ドローンと共に世界へ知られていき、仲間と出会い、まだ誰も知らないダンジョンの深部へ挑んでいく物語。 | I6: 457 | J6: 配信|ダンジョン|現代日本|ファンタジー|主人公が強い|冒険|無自覚|AI本文利用 | K6: 1697 | L6: 176 | M6: 176 | N6: 36 | O6: 248594 | P6: 17 | Q6: 連載中
A7: 現代ファンタジー | B7: 6 | C7: 継続 | D7: 追放された結界師、田舎の空き家を守ってただけなのに日本唯一の安全地帯になった 〜俺を切った探索者協会、首都ダンジョン崩壊で終わる〜 | E7: 花月乃機鳥 | F7: https://kakuyomu.jp/works/2912051603397858459 | G7: 俺を捨てた日、日本の安全保障が終わった | H7: 人気探索者チーム《暁の王冠》で結界係をしていた白瀬結斗は、「防御しかできない」「配信映えしない荷物持ち」と笑われ、公開配信で追放される。 だが実際には、彼の結界がモンスターの索敵、瘴気、呪毒、空間崩壊、通信障害をすべて抑えていた。 行き場を失った結斗は、祖母の残した田舎の空き家へ帰る。戸締まりのつもりで家の周囲に結界を張ったその夜、全国のダンジョンが暴走し始める。なのに、結斗の空き家の周囲だけはモンスターも瘴気も入れない。 逃げ込んできた若手トップ探索者、災害配信者、避難民、子供たち。古い空き家は、いつの間にか「日本唯一の安全地帯」になる。 一方、結斗を追放した《暁の王冠》と探索者協会は、結斗の功績を奪ったまま国家級攻略ライブに挑む。偽装結界は深層で破綻し、首都ダンジョンは崩壊。過去の不正、暴言、功績詐称は全国配信で暴かれる。 結斗は復讐しない。ただ、守るべき人だけを守る。 | I7: 397 | J7: AI本文利用|現代ファンタジー|現代ダンジョン|追放ざまぁ|主人公最強 | K7: 2180 | L7: 51 | M7: 51 | N7: 59 | O7: 87861 | P7: 60 | Q7: 連載中
A8: 現代ファンタジー | B8: 7 | C8: 継続 | D8: 百鬼夜行(スタンピード)の人柱にされた俺、千年も修行して現代へ帰還したんだけど、普通に暮らすのが目標です。 | E8: いな＠ | F8: https://kakuyomu.jp/works/2912051599970235830 | G8: 『放課後屋上に来い！』と脅されたが、ダンジョンに稼ぎに行くので、無理。 | H8: 高校入学初日に人生最大の幸運、ダンジョン適応値が前代未聞のSオーバーと判明。 だが、続いて最悪な不運、スキル無しとも知られてしまう。 捨てる神あれば拾う神あり。適応値ランクの高さから、政府から必要とされ、Sランクダンジョン【黄泉比良坂】の百鬼夜行(スタンピード)を封じるための協力者に抜擢された。 だがそれは人柱、生け贄として必要だっただけのことだった。 人柱の間で待っていたのは死……ではなく、一人の妖怪だった。 「あなた、面白いわね。私が鍛えてあげる」 玉藻前を名乗る妖怪、瑞姫との出会い。 そして始まる、千年にも及ぶ地獄の修行。 前鬼、後鬼、牛鬼、天狗、酒呑童子……。 数多の妖怪たちに鍛えられ、何度も死を経験した俺は、規格外の力を手に入れる。 そして帰還した外の世界では一時間しか経っていなかった。 妹の待つ家へ帰るため、現代へ戻った俺。 でも待っていたのは、平穏な日常ではない、当然のように無能扱いされる学校。 千年の修行で手に入れた強さを武器に、理不尽な悪意を振りほどき、普通の生活を目指すことになるが……。 | I8: 470 | J8: ダンジョン・現代ダンジョン|妖怪・百鬼夜行|男主人公|主人公最強・隠れ最強|ざまぁ|カクヨムオンリー | K8: 1259 | L8: 94 | M8: 94 | N8: 35 | O8: 84223 | P8: 21 | Q8: 連載中
A9: 現代ファンタジー | B9: 8 | C9: 継続 | D9: TS転生してダンジョンで暮らしていた俺、迷子になって配信に映り込む | E9: モヘンジョロ | F9: https://kakuyomu.jp/works/2912051606811828023 | G9: 災害級？ 俺の家の近くにはもっとでかいのがいるけど | H9: 現代日本で死に、女性の身体で異世界へTS転生した主人公。しかし、転生先は街でも村でもなかった。 気づけばダンジョンの遥か奥。 自分が何階にいるのかすら分からない場所だった。 それから長い年月を生き延び、今では謎の白いモフモフ「モチ」と暮らすのが彼（♀）の日常になっていた。 そんなある日、見知らぬ魔法陣によって知らない場所へ飛ばされ、巨大な魔物に襲われている女性を助けることになる。 主人公にとっては、家の近くにいるものより小さな「でかいトカゲ」。 しかし地上では――災害級モンスターだった。 助けた女性は、有名なダンジョン配信者…！ その戦いは世界中へ生配信されていて……。 魔物も、薬も、素材も、装備も。 主人公の「普通」は、地上ではまるで普通ではない。 そして誰も知らない。 彼（♀）が今まで、一体どこで暮らしていたのかを。 | I9: 373 | J9: TS転生|ダンジョン配信|主人公最強|異世界|もふもふ|配信|AI本文使用 | K9: 709 | L9: 66 | M9: 66 | N9: 20 | O9: 125100 | P9: 11 | Q9: 連載中
A10: 現代ファンタジー | B10: 9 | C10: 継続 | D10: 異世界で魔王を倒して帰還した俺、気分転換にVRMMOを始めたら戦闘技術がおかしいらしい | E10: 海鳴 雫 | F10: https://kakuyomu.jp/works/2912051605507569959 | G10: 世界を救った剣技でゲームしてるだけなのに、なぜか配信がバズっている。 | H10: 十二年間の旅の果て、勇者・天城悠真は魔王を倒した。 多くの出会いと別れを経験し、何度も死線を潜り抜け、ようやく成し遂げた世界の平和。 その功績を称えた女神から「望む褒美を与えましょう」と告げられた悠真が願ったものは、富でも名誉でも最強の力でもなかった。 「元の世界に、帰してください」 そして悠真は帰還する。 十六歳だった、あの日へ。 異世界で過ごした十二年間の記憶と経験、そのすべてを残したまま。 家族がいる。 学校がある。 命を狙ってくる魔物はいない。 そんな当たり前の日常を噛み締めていた悠真は、ある日、世間で大流行しているフルダイブ型VRMMORPG《Another Frontier Online》――通称AFOの存在を知る。 「気分転換には、ちょうどいいか」 軽い気持ちでAFOを購入した悠真は、ゲーム内に誰でも利用できる配信機能があることを知り、せっかくだからと配信を始める。 最初の視聴者は、たった三人。 しかし、その三人はすぐに気づいてしまった。 『……今の避け方なに？』 『初心者だよな？』 『なんでゴブリンの急所を一発で抜けるんだよ』 敵の攻撃は紙一重で回避。 剣を振れば急所へ直撃。 難しいはずのパリィさえ、異世界で培った技術で当然のように成功させる。 悠真にとって、それは十二年間生き残るために身につけた当たり前の技術。 だがAFOプレイヤーからすれば――完全に異常だった。 やがて一つの切り抜き動画をきっかけに、無名だった悠真の配信は爆発的に広まっていく。 トップ配信者。 最強のPvPプレイヤー。 大手ギルド。 そして世界中の猛者たち。 さまざまなプレイヤーが謎の新人《ユーマ》へ注目し始める。 けれど悠真が求めているのは、最強の称号でも有名配信者の座でもない。 かつての冒険では、負ければ誰かが死んだ。 今度は違う。 失敗してもやり直せる。 仲間が倒れても、また会える。 これは世界を救った元勇者が―― 今度こそ純粋に「冒険」を楽しむ物語。 | I10: 898 | J10: VRMMO|配信|主人公最強|男主人公|異世界帰還|ラブコメ|現代|カクヨムオンリー | K10: 1158 | L10: 62 | M10: 62 | N10: 32 | O10: 83907 | P10: 30 | Q10: 連載中
A11: 現代ファンタジー | B11: 10 | C11: 継続 | D11: カラスの悪魔がやって来る 〜泣き寝入りするのをやめた元社畜、世界中のカラスを支配して、ナメた探索者を狩り尽くす〜 | E11: 川野笹舟 | F11: https://kakuyomu.jp/works/2912051604153063294 | G11: 悪いことするとカラスの悪魔が来るよ | H11: 残業の帰り道、理不尽な探索者にいきなり殴られた男は警察やダンジョン協会にかけあったが、誰一人として彼を助ける者はいなかった。『暴力こそ正義』という真理に気づいた彼は探索者になることを決意した。覚醒したスキルは『魔人（八咫烏）』『カラスの王』『道案内』。後に『カラスの悪魔』と呼ばれ世界中から恐れられるようになる男の物語。 | I11: 160 | J11: 成り上がり|ざまぁ|主人公最強|現代ダンジョン | K11: 5914 | L11: 43 | M11: 43 | N11: 33 | O11: 104145 | P11: 32 | Q11: 連載中
A12: 現代ファンタジー | B12: 11 | C12: 継続 | D12: 異世界で魔法を覚えたら、高校中退引っ越しバイトから令嬢の護衛筆頭にまで格上がった件 | E12: 甲賀流 | F12: https://kakuyomu.jp/works/2912051600397486794 | G12: 身体強化を覚えたら、人生変わった。 | H12: 高校を中退した佐倉清史は、唯一自分を雇ってくれた引っ越し会社で働いていた。 学歴も資格もない。 先輩たちから軽く扱われても、拾ってくれた社長への恩を返すため、預かった荷物だけは誰より丁寧に運んでいた。 そんなある日、清史は仕事中に段ボールを抱えたまま異世界へ召喚される。 「あれ。荷運び用の使い魔を召喚したはずなんだけど……？」 彼を呼び出したのは、魔力を節約したい新米召喚士リーリャ・フェルン。 頼まれたのは魔王討伐でも世界救済でもない。 散らかった倉庫から、失くした魔石を探すことだった。 清史は引越し現場で培った作業効率で、リーリャの倉庫を片付けていく。 そんな時、清史は自力では重く持てない鉱石箱にまでたどり着く。 「これは一人では持ち上がりません」 「そんなの、身体強化を使えば持てるでしょ」 身体強化。 リーリャが口に出したそれは、この世界でいう魔法の一種らしい。 魔法なんてものを信じたわけじゃない。 けれどもし、本当に重い荷物を安全に運ぶ方法があるのなら。 僕は少しだけ知りたいなと思ってしまった。 | I12: 473 | J12: 魔法|異世界|成り上がり|主人公いずれ最強|お仕事|異世界転移|スキル|ヒロイン | K12: 3605 | L12: 35 | M12: 35 | N12: 41 | O12: 156617 | P12: 40 | Q12: 連載中
A13: 現代ファンタジー | B13: 12 | C13: 継続 | D13: アンチだらけの元最強プロゲーマー、ダンジョン配信でも永久コンボでハメ殺す ～国民的アイドルの妹と夕飯を食べたいだけなのに、世界だけが毎回大炎上～ | E13: 白洲りつ | F13: https://kakuyomu.jp/works/2912051605643694466 | G13: 夕飯を獲りに行っただけなのに、毎回世界が大炎上。 | H13: 【第1章完結！ 第2章『隠れない配信』毎日20:00更新中！】 元最強プロゲーマー、二年ぶりの復活配信。 復帰配信の舞台は、まさかのダンジョン。 ダンジョンで永久コンボ。SNS大炎上。 ──本人の目的は、妹との夕飯だった。 永久コンボで格ゲー界を大炎上させ、姿を消した元最強プロゲーマー《REN》。 その正体は、国民的アイドルの妹と暮らす、ごく普通の兄。 二年ぶりに始めた配信は、まさかの現代ダンジョン配信だった。 忙しく働く妹との貴重な休日に、美味しい夕飯を食べさせたい。 そのために高級ダンジョン食材を獲りに行くだけなのに…… 世界中が勝手に騒ぎ始める。 Aランク推奨モンスターを一度も行動させない永久コンボ。 切り抜き動画は爆発的に拡散。 探索者協会も芸能界も巻き込み、SNSは毎回トレンド入り。 それでも本人だけは、 「スーパーで買うより狩った方が安い」 と本気で思っている。 今日の夕飯を獲りに行くだけなのに、世界だけが毎回大騒ぎ。 これは、兄妹の食卓から始まるダンジョン配信コメディ。 | I13: 465 | J13: ダンジョン|兄妹|主人公最強|配信|探索者|掲示板|AI本文利用|グルメ | K13: 1590 | L13: 20 | M13: 20 | N13: 32 | O13: 140783 | P13: 27 | Q13: 連載中
... A78: 現代ファンタジー | B78: 77 | C78: 継続 | D78: 〝金銀花〟は止まらない | E78: 白神 怜司 | F78: https://kakuyomu.jp/works/16818622173230370861 | G78: 【コミカライズ連載予定】オタク少女と反骨精神溢れるギャル達が開拓する | H78: 当たり前にダンジョンがあり、〝ダンジョン因子〟を得ることで様々な力を得られる現代日本。主人公である八咫島流霞こと引っ込み思案のオタク少女は、ひょんなことから同じ学校、同じクラスのスクールカーストトップのギャル、姫屋奏星とその仲間たちと交流を深めることになり、一緒にダンジョンに行くことになる。パーティ〝金銀花――《カプリフォリオ》〟はダンジョンダイブ配信を始めて……。 ◆補足：執筆に関してAIは使用してないです。（最近AIどうのこうの増えてきたので念の為明言しておきます） ◆無断転載禁止 | I78: 245 | J78: 女主人公|カクヨム先行|反骨精神のギャル|オタクとギャル|いずれは最強|配信|現代ダンジョン|主人公はヤベーヤツ | K78: 4617 | L78: 12 | M78: 12 | N78: 344 | O78: 1252814 | P78: 337 | Q78: 連載中
A79: 現代ファンタジー | B79: 78 | C79: 新規ランクイン | D79: ダンジョン配信に映り込むピクトグラムの怪異になった | E79: ＠脳タリン | F79: https://kakuyomu.jp/works/2912051606788687244 | G79: 困った時、危ない時にひょっこり登場 | H79: 注意)めちゃくちゃ緩い内容です！ 趣味なので許して！ 本作はAI作品になります ダンジョン配信に、時折映り込む謎のピクトグラム。 配信者にもモンスターにも、その姿は見えない。 けれど、配信を見ている視聴者にだけは、はっきりと見えていた。 瀕死の探索者がいれば医者の姿になって治療し、危険なモンスターが現れれば武器を持った姿へ変わる。 映像にしか存在しないように見えて、その手は確かに現実へ干渉する。 誰なのか。 何なのか。 なぜダンジョン配信に現れるのか。 今日もまた、どこかの配信画面の端から、白い人型が歩いてくる。 | I79: 266 | J79: ダンジョン|配信|ピクトグラム|人外|掲示板|AI作品|現代ダンジョン | K79: 203 | N79: 76 | O79: 342955 | P79: 6 | Q79: 完結済
A80: 現代ファンタジー | B80: 79 | C80: 継続 | D80: 魔剣を拾ったら中身が飯にしか興味のない生意気少女だった 〜無限の魔力と空間魔法でダンジョン無双〜 | E80: 竜刃丸 | F80: https://kakuyomu.jp/works/2912051604673684115 | G80: 「力が欲しいか‼︎ 力が欲しいなら……飯をくれ!」 | H80: ダンジョンの奥底で拾ったのは最強の魔剣。それは装備したものに無限の魔力を与える。 しかしその正体は飯にしか興味のない生意気少女だった。 荷物持ちとして捨てられた俺は、この生意気な相棒と無限の魔力、目覚めたチートスキル空間魔法EXでダンジョン無双を始める。 チート無双×ダンジョン×飯テロ、開幕。 毎日7:10投稿 2026.8.24 ⭐︎祝22,000PV⭐︎ 2026.8.29 ⭐︎祝30,000PV⭐︎ 2026.9.01 ⭐︎祝40,000PV⭐︎ 応援ありがとうございます😭 | I80: 246 | J80: 成り上がり|主人公最強|チート|ダンジョン|飯テロ|ざまぁ|配信/掲示板|AI補助利用 | K80: 206 | L80: 11 | M80: 11 | N80: 52 | O80: 213137 | P80: 41 | Q80: 連載中
A81: 現代ファンタジー | B81: 80 | C81: 継続 | D81: 大切な家族を守ります 世界崩壊サバイバル ～俺だけドロップテーブルが見える～ | E81: 月瀬リュカ | F81: https://kakuyomu.jp/works/2912051607326206740 | G81: 食料も、薬も、おむつも。今は魔物から手に入れろ！ | H81: 世界が崩壊した日、朝倉かなめが手に入れたのは《ドロップ》というギフトだった。 魔物を見るだけで、何を落とすのかが分かる《ドロップテーブル》。 ゴブリンなら食料や医療品。 角ウサギなら日用品。 別の魔物なら、燃料や装備まで。 そして《運》を上げれば上げるほど、より希少なもの、より自分に必要なものが手に入りやすくなる。 力を上げれば、自分は強くなれる。 体力を上げれば、生き残りやすくなる。 それでも、かなめが選んだのは――《運》だった。 自分一人が強くなるより、妻と一歳の娘が生きるために必要なものを持ち帰りたい。 食料が足りなければ、食料を落とす魔物を狩る。 薬がなくなれば、医療品を落とす魔物を探す。 娘のおむつが必要なら、日用品を落とす魔物を狙う。 そして足りない戦闘力は、ドロップした装備で補えばいい。 停電した街。 止まった物流。 あふれ出した魔物。 昨日まで金を出せば買えたものが、もう店にはない。 だから今日も、かなめは必要なものを落とす魔物を探しに行く。 家族三人で、この崩壊した世界を生き残るために。 | I81: 471 | J81: 世界崩壊|サバイバル|愛する家族|レベルアップ|ドロップ|レア装備 | K81: 80 | L81: 4 | M81: 4 | N81: 13 | O81: 63841 | P81: 5 | Q81: 連載中
A82: 現代ファンタジー | B82: 81 | C82: 継続 | D82: 外れスキル《強化》は、倒した魔物の特性を吸収する 〜同接三人の底辺探索者、銀座ダンジョン配信で成り上がる〜 | E82: 夕暮れ | F82: https://kakuyomu.jp/works/2912051603538764208 | G82: 外れ扱いされた《強化》は、魔物の特性を吸収する成長スキルだった。 | H82: 世界に七つの巨大な穴――ダンジョンが現れてから十年以上。 アメリカ、ブラジル、日本、中国、ドイツ、南アフリカ共和国、アラブ首長国連邦。 それぞれに一つずつ現れた穴から魔物が溢れ、人類は一度、大きな被害を受けた。 だが、魔物を倒した者は魔力を吸収し、最初の一体を倒した時にスキルを得る。 人類はその力で魔物を押し返し、やがてダンジョン探索は一大産業となった。 日本唯一のダンジョンは、東京・銀座にある。 銀座ダンジョン第一層で日銭を稼ぐ底辺探索者、朝倉蓮司。 彼のスキルは《強化》。 説明はただ一つ。 敵を倒すほど強くなる。 しかし、この世界では魔物を倒せば誰でも成長する。 そのため《強化》は「そんなの全員そうだろ」と笑われ、実質スキルなしの外れ扱いを受けていた。 同接三人。 登録者も少ない。 第一層の雑魚魔物にも手間取る。 そんな蓮司の日常は、ある日の配信中に崩れ始める。 第二層から逃げてきた探索者。 瀕死のまま第一層へ上がってきた格上の魔物。 逃げ場を失った蓮司は、最後の保険だった魔法道具で魔物にトドメを刺す。 その瞬間、視界に今まで見たことのない文字が浮かんだ。 岩皮猿の特性を吸収しました。 筋力が上昇しました。 耐久が上昇しました。 打撃耐性が上昇しました。 外れだと思われていた《強化》の正体。 それは、倒した魔物の特性を少しずつ自分に取り込む成長スキルだった。 底辺探索者だった蓮司は、配信を通して少しずつ注目されていく。 これは、誰にも期待されなかった外れスキル持ちが、銀座ダンジョンの底辺から成り上がっていく物語。 | I82: 684 | J82: ダンジョン|成り上がり|外れスキル|探索者|配信|現代ダンジョン|コメント欄|AI本文利用 | K82: 1001 | L82: 15 | M82: 15 | N82: 73 | O82: 495735 | P82: 58 | Q82: 連載中
A83: 現代ファンタジー | B83: 82 | C83: 継続 | D83: 【書籍化！】 ま！ よ！ け！ の！ 塩！ （１２０年分） | E83: 哀森賢人／哀しみを背負ったゴリラ | F83: https://kakuyomu.jp/works/16818093076856145897 | G83: 少女を【モリガミサマ】から助ける為に少年は体から塩を出した。 | H83: 【書籍化決定！】2026年08月24日 GCノベルズ（GCN文庫）様より発売中です！ 自分の部屋の天井の四隅を同時に見てみよう。 大丈夫。何も起きないから。絶対なにも起きないから、大丈夫だから。ね？ね？ 夜の山をじっと見続けると、何か光るモノが見えるよ。 それが動いていたら、スマホで動画を撮ってみよう。 きっとバズるよ。ほら撮って。 寝る前に布団にはいったら『誰かいますか？』って聞いてみよう。きっとそこに 「 うるっせぇえええ！！！！ 塩撒いてオラあああああ！！！！！！」 少年誌のホラー漫画で義務教育を終えた少年（バカ）は震えながら今日も塩を撒く。 【書籍版タイトル】 洒落怖な世界で、少年は塩を撒く ～ま！ よ！ け！ の！ 塩！ （１２０年分）～ ※「小説家になろう」「ハーメルン」にてマルチ投稿しています。 | I83: 366 | J83: ホラー|オカルト|都市伝説|怪談|怪異|うす塩|ヤンデレ|コメディ | K83: 737 | L83: 8 | M83: 8 | N83: 49 | O83: 281079 | P83: 847 | Q83: 連載中
A84: 現代ファンタジー | B84: 83 | C84: 継続 | D84: 【書籍化】最強以外ありえない | E84: てんぞー | F84: https://kakuyomu.jp/works/822139845517663944 | G84: ―――遺産は最初にSランクマスターに至った俺の血を引く孫のものとする。 | H84: 馬鹿みたいな遺言を残してかつて最強の座に君臨した事のある男は死んだ。ダンジョンが存在し、それに抵抗する為にモンスターを使役するモンスターマスターが存在する世界で、それがかつて遊んでいたゲームの世界に酷似すると知ってもなお特別何かをする気もなかった鴉羽尊は祖父の遺言を皮切りに強制的に巻き込まれる。 育成、合体、大会、ダンジョン攻略にランク認定戦。モンスターマスターの頂点を目指す尊の人生が始まる。 HJノベルス様より書籍化します！ この作品はハーメルンでもマルチ投稿しています。 | I84: 243 | J84: 架空原作|育成|牧場|ダンジョン|合体|掲示板|転生|成長 | K84: 2077 | L84: 0 | M84: 0 | N84: 310 | O84: 1443531 | P84: 196 | Q84: 連載中
A85: 現代ファンタジー | B85: 84 | C85: 継続 | D85: ユニークスキル『箱庭ガチャ』でハーレム＆スローライフ！〜集まったのはなぜか子供と老人とおっさんでした〜 | E85: 砂糖 | F85: https://kakuyomu.jp/works/2912051601796271626 | G85: まさか勝負パンツのお陰でSランク冒険者が助かった……！？ | H85: ここ現代日本では100人に1人の確率でスキルなどを得られた人のことを“覚醒者”と呼ぶ。 社会人三年目の俺、高梨春樹は24歳になっても覚醒者になることはなく、日々ブラック企業で働く毎日。 そんなある日、朝目覚めると目の前には覚醒者にしか現れないスキル画面が！ スキル名は……『箱庭ガチャ』？ これはブラック企業で働きずて、疲れた心を可愛いメイドに癒されてハーレム＆スローライフだ！と意気込むが実際には子供と老人とおっさんしか集まらない日常コメディ。 | I85: 227 | J85: スローライフ|箱庭ガチャ|お仕事|男主人公|ポンコツ|街づくり|ほのぼの日常|勘違いコメディ | K85: 924 | L85: 7 | M85: 7 | N85: 72 | O85: 131800 | P85: 67 | Q85: 連載中
A86: 現代ファンタジー | B86: 85 | C86: 継続 | D86: 『転生したのに転移で地球に戻っちゃった?! しかも何故43歳?! 王国の魔法革命児 〜爆鳴の鬼と呼ばれた男Ⅱ』 | E86: だいきち | F86: https://kakuyomu.jp/works/2912051605849299462 | G86: 転生したのに現代へ転移?! しかも主人公は転生前のオジサンに?! | H86: 43歳、心筋梗塞で人生を終えた松本賢人は、異世界ノキア王国の少年・ケントとして転生した。 そこで現代知識で魔法を強化し、爆鳴気でなにもかも吹き飛ばす理不尽暴君となっていた。 龍を狩っている時に、真龍が出てきて道連れに自爆 したのだが、気が付くとそこは転生前の自分の部屋 そして自分も43歳の「松本賢人」に 傷も消えた愛する女たちも一緒に転移してきて、何故かイグアナサイズの龍もいる 「ねえ旦那！あの箱走ってるのは何でだ?!」「あそこを歩いてる人が来てる服綺麗だわ」「ケ、ケント様、このベッドの下の本はウェヘヘヘ」 「……まいったなあ」 ケント、いや賢人は令和の日本で、すぐ敵を殺しちゃう彼女達とどう生きるのか というか養っていけるのか?! 小説家になろうでも投稿してます 使用AIはgeminiでAI本文利用 2000字程度のプロット書いて、それを基にAIに書いてもらい、それを手直ししたり文をいれかえたりで作ってます、結局6割程度は自分が書いてますが、AI本文利用としてます | I86: 444 | J86: おっさん|魔法|異世界転生|ハーレム|現代ファンタジー|異世界帰還|AI補助利用 | K86: 531 | L86: 9 | M86: 9 | N86: 24 | O86: 83387 | P86: 23 | Q86: 連載中
A87: 現代ファンタジー | B87: 86 | C87: 継続 | D87: 魔王を倒したおっさん、三十年ぶりに日本へ帰還し現代ダンジョンで無双する ～今どきダンジョン攻略も科学の時代らしいけど、おじさんは昔ながらに剣と魔法で戦うよ～ | E87: 厳座励主（ごんざれす） | F87: https://kakuyomu.jp/works/2912051605598246153 | G87: S級ダンジョン？ おじさんにはちょっと物足りないなあ | H87: 十五歳で異世界へ転移してから、はや三十年。 勇者となった日比野は、仲間たちと共に魔王を討ち果たした。 あとは討伐の証を持ち帰り、人間と魔族の戦争を終わらせる……はずだったのだが、魔王が死に際に放った謎の魔法に巻き込まれ、日本へ帰還してしまう。 三十年が経過した日本は、大きく変わっていた。 魔力と科学技術を組み合わせた最新装備で、ダンジョンを攻略するようになっていたのだ。 そんなことを何も知らない日比野は、帰還早々、空港を襲った強力な魔物――ドラゴンを借り物のビニール傘で一刀両断。 どうやら三十年も異世界で戦っているうちに、現代日本では少々規格外の存在になってしまったらしい。 しかし日比野には、日本でチヤホヤされるつもりなど毛頭ない。 異世界には、日比野の帰還を待つ人々がいる。 戦争を終わらせるためにも、もう一度、異世界転移を起こさなくてはならない。 科学でダンジョンを攻略する現代人たちと、剣と魔法で戦う原始的なおっさん勇者。 三十年ぶりの故郷で、規格外なおっさんの最強譚が幕を開ける。 | I87: 453 | J87: カクヨムオンリー|イケオジ|おっさん|剣と魔法|現代ダンジョン|ダンジョン配信|チート|無双 | K87: 942 | L87: 8 | M87: 8 | N87: 15 | O87: 48316 | P87: 14 | Q87: 完結済
A88: 現代ファンタジー | B88: 87 | C88: 継続 | D88: ダンジョン配信のカメラマンをしている俺、S級美少女配信者が全滅しかけたので画角の外でボスを瞬殺したら、全部生放送に映っていました | E88: 沢田美 | F88: https://kakuyomu.jp/works/2912051606113383940 | G88: 「戦えないとは一度も言っていません」―カメラが捉えた最強のカメラマン | H88: 「俺は探索者じゃない。ただのカメラマンだ」 世界各地にダンジョンが出現し、探索者による攻略配信が一大娯楽となった現代。 久瀬直人（くぜ・なおと）は、探索者資格すら持たない底辺カメラマンとして、人気配信者たちの後ろを歩いていた。 戦闘能力はゼロ。荷物持ち同然。視聴者からも雇用主からも軽く扱われる存在。 ――だが実際は、戦う必要がなかったから戦わなかっただけだった。 ある日、直人はＳ級美少女パーティー《ルミナス》の攻略配信に同行する。しかし、予定されたボスの代わりに現れたのは、都市すら滅ぼす災害級魔物。 Ｓ級探索者たちが全滅寸前まで追い詰められる中、直人はカメラを地面へ置いた。 「カメラ壊したら怒られるよな……」 自分が画角から外れたことを確認し、災害級魔物を拳の一撃で瞬殺。 誰にも見られていない――はずだった。 ところが、その姿は鏡のような岩壁に反射し、すべて生配信に映っていた。 切り抜き動画は瞬く間に拡散され、底辺カメラマンは一夜にして世界で最も注目される男となる。 彼に命を救われ、専属カメラマンになってほしいと願うＳ級美少女・天城玲奈（あまぎ・れいな）。 直人の本当の力を昔から知る、黒髪の幼馴染・朝比奈結衣（あさひな・ゆい）。 彼を特例Ｓ級探索者としてスカウトしようとする、史上最年少の美人ギルドマスター・御堂綾香（みどう・あやか）。 直人を使い潰してきた会社や、彼の実力を認めない探索者たちが次々と接触してくるが、そのたびに配信と公式記録が圧倒的な実力を証明してしまう。 本人はただ、画角の外で静かにカメラを回したいだけ。 しかし、異常を起こし始めたダンジョンも、彼に惹かれる美少女たちも、もはや直人を放っておいてはくれない。 これは、誰にも注目されなかった底辺カメラマンが、その規格外の力を世界中に生配信され、最強の探索者へと成り上がっていく物語。 | I88: 820 | J88: ダンジョン配信|主人公最強|成り上がり|配信|美少女|勘違い|無双|規格外 | K88: 269 | L88: 2 | M88: 2 | N88: 23 | O88: 63173 | P88: 19 | Q88: 連載中
A89: 現代ファンタジー | B89: 88 | C89: 継続 | D89: 就職氷河期オブ・ザ・デッド ～世界は酷い有様だけど、異世界で魔王を倒した用務員のおじさんがモテモテに。なお、世界が救われるかは不明～ | E89: Ｙ．Ａ | F89: https://kakuyomu.jp/works/2912051602077226807 | G89: ゾンビ溢れる世界で、就職氷河期おじさんがモテモテに | H89: 就職氷河期世代として苦労し、今はとある地方の有名エリート私立高校の用務員を務める伊作 幸三（いざく こうぞう）、４９歳。 彼は多くの生徒たちからバカにされる存在であったが、唯一ギャルの格好しているために校内で浮いている、白井 瑠璃（しらい るり）とは用務員室でよく話す間柄であった。 もうすぐ夏休みという時、幸三が仕事を終えて自宅アパートで就寝して目が覚めたら異世界へ。 自分を召喚した王様の命令で魔王を倒し、褒美を貰って元の世界に戻ってきたら、一晩しか時が経っていなかった。 残りの人生、用務員なんて辞めて褒美を売ったお金で遊んで暮らそう期待に胸を膨らませる幸三であったが、なんと部屋の外はゾンビだらけで、異世界で上げたレベルも１に戻っていた。 「……生き残るのが優先だ！」 魔王を倒して戦闘経験豊富な幸三は次々とゾンビを倒してレベルを上げ、残りの人生を快適に暮らせるよう、あちこちに移動して可能な限り必要な食料、物資などを集め続けた。 「祖父さんが住んでいた、山奥の村に行くか……」 ある程度レベルを上げ、大量の物資を『アイテムボックス』に集めた幸三にゾンビを殲滅して世界を救う気なんてなく、祖父の実家がある廃村を目指す。 だがその前に、白井 瑠璃が生きているか気になってしまったので、職場である学校を目指すことに……。 そして彼女を探している途中、また別の美少女を助けてしまう幸三であった。 「ゾンビにされるところを助けていただき、ありがとうございます」 「（しまった！ 先のことをまったく考えていなかった！）」 その後、瑠璃とも合流できたのはよかったが、幸三は二人の安全を確保するために奔走することに。 このお話は、ゾンビ溢れる現代世界を、就職氷河期のオジさんが美少女や美女たちと共に生き抜いていく物語である。 小説家になろうと、カクヨムに同時連載開始！ 目指せ！ 漫画原作！ | I89: 794 | J89: ゾンビ|魔法|チート|ハーレム|グルメ|内政|現代|就職氷河期 | K89: 2327 | L89: 15 | M89: 15 | N89: 84 | O89: 272969 | P89: 78 | Q89: 連載中
A90: 現代ファンタジー | B90: 89 | C90: 継続 | D90: 男女比1:100の貞操逆転世界でヒーラーとして生きたい！ | E90: 智者猫 | F90: https://kakuyomu.jp/works/2912051605640458336 | G90: 男女比1:100の貞操逆転世界だけど、僕は女の子を助けるために――― | H90: トラックにひかれ転生したらそこは… 男女比1:100の貞操逆転世界だったーーーー！？ 現代社会にダンジョン！？魔法！？冒険者！？ 前世のネトゲでヒーラーとして活動していた白間 法経（しろま ほうけい）性別：男はヒーラーとして冒険者になることを決心する。 そんな世界で必死に貞操を守りつつ、ヒーラーとして冒険者になるというお話。 不定期更新予定？ | I90: 177 | J90: 男性向け|学園|貞操逆転|男女比|魔法|ダンジョン|ヒーラー | K90: 236 | L90: 2 | M90: 2 | N90: 28 | O90: 76371 | P90: 27 | Q90: 連載中
A91: 現代ファンタジー | B91: 90 | C91: 継続 | D91: 魔女だらけのレストランで働いてるけど毎日死にそう（でも飯が美味いので辞められない） | E91: タカザ | F91: https://kakuyomu.jp/works/2912051597609166733 | G91: 週休二日。サボりのペナルティは死。 | H91: 魔女しか来ないレストランで働いてます。 なお、普通に死にかけます。 客は全員やばい女。オーナーもやばい女。 でも料理はめちゃくちゃ美味いので（あとイカれた契約書を交わしたので）辞められません。 そんな地獄の職場で生き延びる俺が、休日に出会ったのは理想ど真ん中の清楚な女性。 ──ただし彼女も、やっぱり魔女でした。そんなことある？ 最終的に、ろくでもない女しかいないハーレムが出来上がる模様です。 誰か助けてください。 | I91: 211 | J91: 男主人公|一人称|魔女|レストラン|グルメ|料理|コメディ|人外ヒロイン | K91: 2939 | L91: 0 | M91: 0 | N91: 107 | O91: 612915 | P91: 141 | Q91: 連載中
... A97: 現代ファンタジー | B97: 96 | C97: 継続 | D97: ハズレスキル【キャンプ設営】を授かった……追放されたわけじゃないけど、戦えないのでキャンプしてたら、安全地帯を作れるチートスキルだった | E97: ＡＮ＠ＲＣＨＹ | F97: https://kakuyomu.jp/works/2912051597492612020 | G97: 自由を楽しむために、俺は今日もテントを張る | H97: 世界中の人類へ突如与えられた「ユニークスキル」。 剣術、槍術、身体強化――戦闘向きスキルを得た者たちは、現れたダンジョンへ挑み始めた。 そんな中、大学生の九十八（にのまえ）翼（つばさ）が与えられたのは、意味不明なハズレスキル【キャンプ設営】。 友人たちはダンジョンへ向かい、翼は次第に孤立していく。 戦えない自分にできることはない――そう思った彼は、趣味だったキャンプへのめり込むようになった。 だが、そのスキルは『ただのキャンプ』では終わらなかった。 自ら設営したテントの中を、外敵侵入禁止のセーフエリアへ変える能力。 暴力も犯罪も拒絶する絶対安全圏。 そしてスキルが成長した先には、時間すら操る力が眠っていた。 料理、加工、農業、醸造―― 戦えないからこそ辿り着いた、生産と安全の最前線。 これは、世界がダンジョンに飲み込まれていく中で、 １人のキャンパーが「帰れる場所」を作り続ける物語。 | I97: 415 | J97: ハズレスキル|キャンプ|ダンジョン|現代ファンタジー|生産系|スローライフ風|配信|ＡＩ補助利用 | K97: 1481 | L97: 6 | M97: 6 | N97: 101 | O97: 259317 | P97: 99 | Q97: 連載中
A98: 現代ファンタジー | B98: 97 | C98: 新規ランクイン | D98: 貞操逆転世界で没落お嬢様のダンジョン配信を裏方で手伝っていたら、従者の俺がバズりました ～男女比1:9の世界では男が女を守るのは珍しいらしい～ | E98: たけのこ | F98: https://kakuyomu.jp/works/2912051607243871368 | G98: 守られるのが男の常識？ 俺はお嬢様を守る従者ですが。 | H98: 男女比が、およそ一対九の世界。 男は希少で、女性に守られるのが当たり前。華奢で大人しく、女性の庇護を受ける男性ほど好まれる――そんな現代日本で、九条征司は少しばかり普通から外れた高校生だった。 代々、名家・十六夜家に仕えてきた家系に生まれ、幼い頃から要人警護の訓練を受けてきた征司は、同級生であり主人でもある十六夜紅羽に今も従者として仕えている。 そんなある日、没落した十六夜家を再興したい紅羽が言い出した。 「私、ダンジョン配信を始めるわ」 紅羽が有名になり、十六夜の名前を世間に広める。そのためなら協力するのが従者の役目だ。 征司は撮影係兼護衛として、紅羽のダンジョン配信に同行する。 ところが初配信で予定外の魔物が出現。 危機に陥った紅羽を守るため、征司がカメラを置いて前へ出た結果――。 『男が女を守ってる！？』 『この男誰！？』 『従者って設定じゃなくて本物なの？』 なぜか紅羽ではなく、征司の方まで大バズりしてしまった。 女性を守る男が珍しい？ 男が料理をするのも珍しい？ 女の荷物を持っただけで勘違いされる？ 本人にとっては、どれも従者として当たり前のこと。 没落お嬢様のダンジョン配信を支えるだけだったはずが、人気配信者、数字に厳しい同級生、女性探索者たちまで征司へ注目し始めて――。 これは、男が守られることが常識の世界で、お嬢様を守ることしか考えていない従者が、無自覚に女性たちの常識を壊しながらバズっていくダンジョン配信ラブコメ。 | I98: 640 | J98: 貞操逆転|勘違い|ハーレム|配信|あべこべ|現代ダンジョン|お嬢様 | K98: 51 | N98: 13 | O98: 46610 | P98: 6 | Q98: 連載中
A99: 現代ファンタジー | B99: 98 | C99: 継続 | D99: 住んでる場所が田舎すぎて、ダンジョン探索者が俺一人なんだが？【書籍3巻発売中！】 | E99: 赤月ヤモリ | F99: https://kakuyomu.jp/works/16817330661274615404 | G99: 「仲間？ 他の探索者？ そんなの居ないよ。ここは田舎だからね」 | H99: 【7月10日、第3巻発売！】 【書籍１～3巻発売中！】 【3月3日よりカドコミ・ニコニコ漫画でコミカライズが連載中です！】 【四章準備中】 『ダンジョン配信者』の存在により、世はまさに空前のダンジョンブームとなっていた。 しかしそれは都会に限った話。 Aランク探索者である相馬創の住む田舎町には他に探索者が居らず、彼は仕事に忙殺される日々を送っていた。 これは活動拠点が田舎のため、いまいちパッとしない少年が世界中にその名を轟かせる物語。 ※なろうハーメルンにも公開しております。 | I99: 245 | J99: ダンジョン|ハーレム|主人公最強|配信|掲示板|人妻|コメディ | K99: 46046 | L99: 3 | M99: 3 | N99: 158 | O99: 535555 | P99: 572 | Q99: 連載中
A100: 現代ファンタジー | B100: 99 | C100: 継続 | D100: ウチの山に異世界の騎士が落ちてきた | E100: 道造 | F100: https://kakuyomu.jp/works/2912051606816175074 | G100: ウチの山に異世界の騎士が落ちてきた話 | H100: タイトルまんま。イケオジ小説コンテスト期間中、午後7時更新 ハーメルンでも掲載しています | I100: 45 | J100: 女主人公|ライトノベル|騎士|現代転送|コメディ|女性向け|成り上がり|因習村 | K100: 284 | L100: 9 | M100: 9 | N100: 11 | O100: 33316 | P100: 12 | Q100: 連載中
A101: 現代ファンタジー | B101: 100 | C101: 新規ランクイン | D101: 推しにささげるダンジョングルメ〜最強探索者VTuberになる〜 | E101: モノクロウサギ | F101: https://kakuyomu.jp/works/16817330649436334413 | G101: 書籍版5巻 4月30日に発売いたします!! もう買えるので是非!! | H101: 『ダンジョン産の食材を食べる機会があったんですけど、それが凄く美味しくって──』 推しのVTuberが配信でそんなことを言っていたので、最強探索者の主人公が中小規模の事務所のライバーとしてデビューして、推しとオフコラボでご飯を振る舞うことを目指すお話。 ──なお、当初の予定以上に伸びてしまって、いろいろな面で段々と引くに引けなくなっていく模様。 | I101: 175 | J101: VTuber|ダンジョン|主人公最強|飯テロ|スレ|配信|スキル|ハーレム | K101: 42263 | N101: 349 | O101: 1141104 | P101: 1367 | Q101: 連載中
A102: 異世界ファンタジー | B102: 1 | C102: 継続 | D102: 鎧騎兵、走る～大好きなロボット作品っぽい世界に転生したけど、プロローグで滅ぶ場所にいます。生き残りたい！ すごく生き残りたい！！～ | E102: 秋津 モトノブ | F102: https://kakuyomu.jp/works/2912051605955633703 | G102: 原作知識で無双したいのに、原作が始まる前に死ぬかもしれん。 | H102: 【完結まで毎日12時投稿！】【祝！日間総合ランキング1位！】 ロイド＝ベルクは『鎧騎兵(ガイキヘイ)』と呼ばれるヒト型ロボットのパイロット、『騎手』候補生であり……転生者である。 彼は、前世で大いにハマり込んだ名作ファンタジー小説『帝歴1002 鎧騎兵、走る』シリーズそのものか、非常に酷似した異世界へ転生してしまった。 『大好きな作品世界に来れた！』と、5歳の時に前世の記憶を思い出した当初は狂喜乱舞した彼であったが……年号を確認した瞬間、絶望の淵に叩き落とされてしまう。 彼が騎手になって初めて赴くであろう赴任先……『西方辺境領』は、原作1巻の『プロローグ』で滅んでしまう場所だということを知ったからだ。 ならば騎手にならなければいいかと言えば、それも無理。 彼の亡き父は騎士爵を持つ騎手であり、残された家族の生活の為に、ベルク家長男であるロイドはソレを継ぐ必要がある。 通常は継承できない一代限りの騎士爵だが、騎手になれば特例で継承できるのだ。 そして……『騎士爵持ちの騎手』が配置されるのは、決まって『西方辺境領』なのだ。 「ちくしょう……神様の馬鹿野郎……！」 家族の為に逃げることもできないロイドは、原作にもほとんど描写のない地獄の『プロローグ』を生き残るために、今日も騎手訓練校で訓練に励んでいる。 「原作知識は唸るほどあるのに！ 原作が始まる前に死にたくねぇよ～！！」 これは、転生者ロイド＝ベルクが原作にたどり着くために死に物狂いで生きる物語である。 ……死に物狂いで生き過ぎた結果、原作を大いに破壊しまくる物語でもある。 | I102: 682 | J102: 異世界転生|ロボット|成りあがり|一人称|エルフ|男性主人公|知識チート | K102: 6553 | L102: 597 | M102: 597 | N102: 24 | O102: 124563 | P102: 23 | Q102: 連載中
A103: 異世界ファンタジー | B103: 2 | C103: 継続 | D103: 【日間34万PV】過労死寸前で会社をクビになった俺、悪役貴族に転生し三年後に処刑されるまで好き放題やる ～使い潰された有能な美少女奴隷を安く買い叩いていたら、なぜか神待遇と喜ばれ忠誠を誓われる～ | E103: NIKE | F103: https://kakuyomu.jp/works/2912051606315298034 | G103: 【第三章】三年後に処刑？ なら酒も金も女も、今のうち好き放題してやる！ | H103: 退職代行会社で過労死寸前まで限界社畜となって働いていたのに、依頼者を助けたい一心で相手の会社をコテンパンにしてしまい会社をクビになった瀬野春之、39歳。 目を覚ますと、そこは生前に遊んでいたファンタジーRPGの世界。しかも転生したのは、三年後に主人公たちによって処刑される悪役貴族ゼノ・ヴァルディスだった。 だが、ゼノは破滅を回避する気などなかった。 「どうせ三年後に死ぬなら、それまで好き放題してやる！！！」 前世では散々使い潰される側だったのだ。 今度は自分が人を使う側になり、酒！ 金！ 女！ 贅沢の限りを尽くしてやる。 そんなゼノの前に現れたのは、悪徳商人に使い潰され、今にも死にそうな銀髪の美少女奴隷ネマ。 誰からも役立たず扱いされていた彼女だが、ゼノの固有スキル【人物鑑定】で見れば、とんでもなく優秀な訳あり人材だった。 ならば、その価値を商人に教えてやる必要などない。 「弱り切っている。奴隷としての価値は低い。俺が買ってやろう」 ゼノはネマを安く買い叩く。 有能な奴隷なら徹底的に働かせる。 ただし、死なれれば損だから食事を与える。 壊れれば損だから治療する。 長く使うために寝床を与え、働きすぎれば休ませる。 さらに戦闘能力に優れた金髪の美少女奴隷メソも安く買い叩き、護衛としてこき使う。 すべては自分が楽をして、三年後まで好き放題に暮らすため。 ――そのはずだった。 「こんな神待遇、見たことがありません」 「私は一生、旦那様にお仕えします」 使い潰されていた有能な奴隷たちは次々と才能を開花させ、なぜかゼノへ忠誠を誓い始める。 横領していた家令を切れば使用人に感謝され、役立たずな管理者を追い出せば仕事が回り、気づけば領地まで豊かになっていく。 そしてついには王国中で、 「悪名高きゼノ・ヴァルディスは、実は稀代の善政領主なのでは？」 と噂されるようになってしまい――。 「何を勘違いしている？ 俺は善人じゃない」 ゼノはまだ知らない。 自分では悪役貴族らしく好き放題しているつもりの行動が、ことごとく人を救い、三年後の処刑からどんどん遠ざかっていることを。 ※8/25 原作ゲーム名を『エルディア・サーガ』→『パルディア・サーガ』に変更しました。 有名作品の国名と被っていたためです。改稿漏れがありましたらお手数ですがお知らせください。 ※8/25 8/23更新分の一部・タイトルの表現を改稿しました。 ※20歳未満者の飲酒シーンがありますが、作品内社会では既に成人済みであり、飲酒禁止年齢についての規制がありません。法律違反を推奨する意図はありません。その上で問題がありましたら改稿可能です。 | I103: 1137 | J103: 異世界転生|悪役貴族|おっさん主人公|勘違い|ざまぁ|領地経営|訳あり人材|ハーレム | K103: 3511 | L103: 360 | M103: 360 | N103: 89 | O103: 81258 | P103: 18 | Q103: 連載中
A104: 異世界ファンタジー | B104: 3 | C104: 継続 | D104: 田舎の魔剣鍛冶、都会に来たら神童だった ～ダメ元で名門校を受けたら、大魔導皇学部とかいう凄いのに受かった～ | E104: 俺の水ぜんぶ抜く | F104: https://kakuyomu.jp/works/2912051599406264044 | G104: 研究費使い放題。授業、国家防衛。 | H104: 田舎では神童。 でも、都会に出ればただの人。 ブレンダン・ウォーカーは、本気でそう思っていた。 病室で短い生涯を終え、異世界へ転生して十七年。 限界集落で祖父と暮らし、農作業と魔導の修練、そして魔剣鍛冶に明け暮れてきたブレンダンは、祖父の死を機に村を出ることになる。 叔母に勧められ、ダメ元で受験したのは王都の名門〈マギアス魔導大学校〉。 ダメだ元々────そう思っていた彼に届いた合格通知には、見覚えのない配属先が記されていた。 〈大魔導皇学部〉 学費の大幅優遇。専用研究室あり。研究費は潤沢。 好きなだけ魔剣を打てる、夢のような環境。 ただし、危険な実地任務と国家防衛への従事が義務だった。 同級生はわずか七人。 高慢な令嬢剣士、天才医師、眠たげな火薬使い、空飛ぶ魔女――全員クセが強く、全員とんでもなく強い。 そしてブレンダン自身もまた、彼らと同じ側の人間だった。 初めての学校。初めての友達。初めてのお茶会。 そして、初めての国家防衛。 | I104: 432 | J104: 異世界転生|学園|カクヨムオンリー|主人公最強|魔剣|鍛冶|コメディ|成長 | K104: 7563 | L104: 161 | M104: 161 | N104: 40 | O104: 168523 | P104: 27 | Q104: 連載中
A105: 異世界ファンタジー | B105: 4 | C105: 継続 | D105: １０歳から始める冒険者生活 | E105: 霜月雹花 | F105: https://kakuyomu.jp/works/2912051605905477135 | G105: １０歳から始める冒険者生活 | H105: エリクは１０歳の儀式を終えてから村を出る。 家族からは居ない者同然の扱いを受けて育ったエリクは王都に来て冒険者となった。 それまでの人生で既に色々と経験をしていたエリクは、それらの知識と技術を使って冒険者生活の基盤を作っていく。 夢や目標は無いが、ただ生き続けたいと言う思いを持つ少年の物語。 | I105: 146 | J105: 男主人公|ステータス|スキル|剣と魔法|ダンジョン|冒険者 | K105: 11875 | L105: 245 | M105: 245 | N105: 100 | O105: 214214 | P105: 24 | Q105: 連載中
A106: 異世界ファンタジー | B106: 5 | C106: 継続 | D106: 異世界転移した料理人ですが、帝都の路地裏で定食屋を開いたら、帝国の女帝が毎日お忍びで食べに来るようになりました | E106: カバルドン | F106: https://kakuyomu.jp/works/2912051605756085920 | G106: 「こんな美味しいご飯は初めてだ……」女帝が路地裏の定食屋に堕ちる。 | H106: 異世界に飛ばされた日本の料理人・哲。 獣の解体場に通いつめ、この世界の食材の末に、日本の味を完全に再現する。 帝都の片隅にひっそりと開いた、看板すらない小さなあばら屋。 そこで哲が振るうのは、暴力的なまでに食欲をそそる極上の定食。 剣も魔法もない。あるのは、最高の一杯で客の心を撃ち抜く料理人の誇りだけだった。 一方、連日の権力闘争と重圧にすり減らされていた帝国の若き女帝・エリザベートは、冷え切った心と胃を抱えたまま、偶然その路地裏に迷い込む。 漂ってきた強烈な匂いに導かれ、恐る恐る暖簾をくぐった彼女を待っていたのは――。 腹の底から温まる、異世界グルメファンタジー開幕！ | I106: 294 | J106: 異世界|グルメ|王女|飯テロ|料理人|癒し|男主人公|チートなし | K106: 6563 | L106: 206 | M106: 206 | N106: 27 | O106: 70727 | P106: 26 | Q106: 連載中
A107: 異世界ファンタジー | B107: 6 | C107: 継続 | D107: ヤニ好きの底辺オッサン冒険者。実は最大最強クランの元クランマスター。 | E107: 巌本ムン | F107: https://kakuyomu.jp/works/2912051603716028250 | G107: タバコは人生だ。（大勢の敵に囲まれた中で余裕でタバコを吸うオッサン） | H107: 帝国最大最強クラン『ドラゴロスロンド』。 帝国各地に冒険者ギルドに代わって支部があるほどのクランだ。 その初代クランマスターが英雄的死去をしてから４年の月日が流れた。 ハロウェイというソロの中年冒険者がいる。 いつも煙草を吸っているヤニカスで、依頼も殆ど受けず、その日暮らしが出来ればいいというスタンスだ。 冒険者の階級も低いアイアン級のままだ。中年でアイアンは俗に底辺と蔑まれていた。 これはそんなヤニ好きのオッサン冒険者がタバコ吹かしながらのらりくらりとなんか生きる物語。 そして彼が最大最強クラン『ドラゴロスロンド』の死んだはずの初代クランマスターとは誰も知らない。 | I107: 288 | J107: オッサン|冒険者|クラン|煙草|ハードボイルド|無双|主人公最強|男主人公 | K107: 1961 | L107: 208 | M107: 208 | N107: 24 | O107: 59553 | P107: 6 | Q107: 連載中
A108: 異世界ファンタジー | B108: 7 | C108: 継続 | D108: 四人の天才妹を虐げ続けた兄、英雄となった妹たちに断罪される | E108: 宵白レン | F108: https://kakuyomu.jp/works/2912051606302075193 | G108: 世界を救った四姉妹は、最低の兄を許さない | H108: 世界を救った四人の姉妹がいた。 剣の頂点に立つ剣聖セリナ。 魔法の頂点に立つ賢者リリア。 錬金術の常識を塗り替えた天才ミリア。 そして世界最大級の商会を築き上げた大商人エマ。 若くしてそれぞれの道の頂点へ辿り着いた彼女たちは、人々から英雄として讃えられていた。 しかし、そんな四姉妹には誰にも語りたくない過去がある。 ――兄、レオン。 幼い妹を魔物の棲む森へ置き去りにした。 毎日のように過酷な虐待を繰り返した。 努力して手に入れた褒美を奪った。 才能を妬み、販路を潰し、夢を邪魔し続けた。 それでも四姉妹は兄に屈することなく、自らの力で世界の頂点まで上り詰めた。 そして魔王との戦いを終えた彼女たちの前に現れたのは、変わり果てた姿となった魔神の兄だった。 すべての因縁に決着がついた後、レオンが犯してきた数々の罪を裁くため、神託裁判が開かれる。 証人は四人の妹。 そして証拠は、過去に起きた出来事をありのままに映し出す神器――《真実の鏡》。 世界中が見守る中、四姉妹は兄から受けた仕打ちを一つずつ告発していく。 誰もが思っていた。 これは、稀代の悪党が犯した罪のすべてを暴き、その報いを受けさせるための裁判なのだと。 だが――。 真実の鏡に映し出された過去は、彼女たちの記憶と同じはずなのに、どこかがおかしい。 一つの真実が明らかになるたび、新たな疑問が生まれる。 世界を救った四人の英雄と、彼女たちの人生を弄び続けた最低の兄。 長きにわたる因縁に、今、決着の時が訪れる――。 | I108: 657 | J108: 異世界ファンタジー|シリアス|サスペンス|至って真面目|四姉妹|手加減を知らない兄|ちょっと恥ずかしい迷作|AI本文一部利用 | K108: 1702 | L108: 198 | M108: 198 | N108: 37 | O108: 227116 | P108: 19 | Q108: 連載中
A109: 異世界ファンタジー | B109: 8 | C109: 継続 | D109: 杖と剣の異世界に舞い降りた天才〜片田舎の少年は王都で神童となりて〜 | E109: 御子柴奈々 | F109: https://kakuyomu.jp/works/2912051606967540258 | G109: 片田舎に眠っていた天才が解き放たれる | H109: 剣を尊ぶ騎士と杖を掲げる魔術師。二つの勢力が競い合う異世界に転生したリオンは、片田舎の孤児院で暮らしていた。彼は幼い頃から近所の老夫婦に剣と魔術を教わっていたが、二人が元剣聖と元賢者であることを知らないままだった。 十五歳になったリオンは王都を訪れ、騎士試験と魔術師試験を受験する。結果は――両方共にトップ合格。 『彼の才能がこちら側でよかった』 騎士と魔術師たちは互いにそう安堵していたが、リオンは片翼の天才ではなかった。王国史上初の快挙を成し遂げた少年を巡り、騎士公爵家と魔術公爵家は令嬢との婚約まで持ちかけて争い始める。そして周囲は、その未知の才能に翻弄されていくことになる。 「俺、資格を取りに来ただけなんだが……」 杖と剣──〝両翼の天才〟が今、舞い降りる。 | I109: 339 | J109: 異世界転生|主人公最強|天才|才能|剣と魔法|スキル|ハーレム | K109: 1037 | L109: 214 | M109: 214 | N109: 7 | O109: 29480 | P109: 6 | Q109: 連載中
A110: 異世界ファンタジー | B110: 9 | C110: 継続 | D110: めちゃくちゃ強靭な身体に転生したので、凡才だけど魔法極めてみた | E110: あおぞら@『無限再生』9月13日頃発売！ | F110: https://kakuyomu.jp/works/2912051603504957531 | G110: 身体が超強い代わりに魔法が超強い奴 | H110: ——魔法使いになりたい。 ただの魔法使いなんかじゃない。汎ゆる分野の魔法を操る最高にして万能の魔法使いに、である。 それが剣と魔法の世界に転生した主人公——カルシム・バッドアスの夢だ。 だが、彼に魔法の才はなかった。 魔力は極めて少なく、魔力回路の数も乏しい。 オマケに記憶を取り戻したのは自分が知るラノベ転生者達の三年も遅いときた。 ——しかしその程度で諦めたりしなかった。 幸いなことに、彼は三歳ながら高い木の上から落ちても傷一つ付かない頑丈な身体を持っていた。 その身体なら、どんなに無茶な鍛錬だって掠り傷に等しい。 一日中魔力切れを起こそうが、魔法失敗の反動だろうが、気合さえあればなんとかできる。 彼はその気合を持っていた。 故に最高の魔法使いを目指して、ひたすら自殺紛いな鍛錬に明け暮れた。 その結果——天才さえ超越するバケモノが誕生した。 | I110: 395 | J110: 主人公いずれ最強|主人公おかしい|コメディー|ラブコメあり|魔法|モンスター | K110: 3597 | L110: 157 | M110: 157 | N110: 27 | O110: 77614 | P110: 26 | Q110: 連載中
A111: 異世界ファンタジー | B111: 10 | C111: 継続 | D111: クラス転移で追放されたハズレ職〝回収士〟の俺は、捨てられた物ほど強く直せる。～聖女の幼馴染と魔境を楽園に変えてスローライフを満喫していたら、陽キャ勇者たちが戻ってこいと言い出した。もう遅い～ | E111: 九条蓮@MF文庫J『#壊れ君』発売中！ | F111: https://kakuyomu.jp/works/2912051606104373978 | G111: 捨てられた俺には、捨てられたものすべてを最強にする力があった。 | H111: 「久世。ハズレ職の君は、連れていけない。……悪いけど、出ていってくれ」 修学旅行の観光バスが、トンネルに入ると同時にクラスごと異世界へ召喚された。 勇者、剣聖、大魔導師、聖騎士。次々と強力な職業を授かるクラスメイトたちの中で、久世映司だけが〝回収士〟。壊れた物と、捨てられた物にしか使えない力。 ハズレ職──そう判定された映司は、その力を一度も試されないまま、クラスの中心にいた〝勇者〟が主導する多数決で追放される。渡されたのは三日分の食料と、水袋が二つ。別れを言いに来た者は、一人もいなかった。 ただ一本だけ、反対に挙がった手がある。〝聖女〟に選ばれた、幼馴染のものだ。 「私、映司くんについていくから。だって、映司くんが足手まといだなんて、有り得ないし」 送られた先は、魔力汚染で二十年前に捨てられた廃村。井戸は枯れ、屋根の残った家には壁がない。 だが、誰も知らなかった。映司の力は、捨てられた物ほど、以前より優れた姿で蘇らせるものだと。 枯れた井戸は水脈ごと戻り、崩れた廃屋は二人の家になる。折れた剣は、風の刃を生む魔剣へ。鉄屑と呼ばれて城の中庭に放置された観光バスは、走る城へ。親を失った狼獣人の娘も、故郷を追われたダークエルフの錬金術師も、捨てられた者たちが次々と集まってくる。 一方、勇者一行は気づきはじめていた。壊れた装備を直せる者がいない。汚染を浄化できる者がいない。食料が保たない──そして、聖女がいない。 魔境が楽園に変わったころ、彼らは言った。「戻ってこい」と。 だが、もう遅い。 捨てられた俺には、捨てられたものすべてを最強にする力があった。 ──── 小説家になろうにも投稿しています。 | I111: 714 | J111: クラス転移|追放|ざまぁ|スローライフ|異世界開拓|主人公最強|幼馴染|鬱勃起ざまぁ | K111: 923 | L111: 216 | M111: 216 | N111: 18 | O111: 74642 | P111: 4 | Q111: 連載中
A112: 異世界ファンタジー | B112: 11 | C112: 継続 | D112: 外れスキル『会話』で公爵家を勘当されたけど、魔獣の本音が分かるようになったので、いつの間にか神龍や神獣たちが懐いてくるんだが？～知らぬ間に最強領地になっていたので、俺を追放した家族たちが青ざめてる～ | E112: どまどま | F112: https://kakuyomu.jp/works/2912051606432977067 | G112: 誰にも理解されない魔獣たちと話しただけで、なぜか懐かれるんだが？ | H112: 悪役貴族として転生した主人公――ルーフェウス。 この世界では１８歳になると、誰もがスキルを開花させる。 だが彼が授かったのは、「会話」というあからさまな《外れスキル》。 体裁を誰よりも重視する父は、 そんな息子をクズ扱いし、なんの実りもない荒野の地へと追放してしまう。 だが、それこそが主人公の狙いだった。 どのみちこの公爵家は、後のシナリオで悪事がバレ、主人公たちに殺されてしまう。 だから今のうちに公爵家から距離を取り、品行方正に生きていくことで、その破滅ルートを回避しようとしたのである。 そんな折、ルーフェウスには「会話」という謎スキルの真価を知る。 ――あらゆる魔獣や神獣たちの言葉を完全に理解し、意思疎通を可能にする力。 それによっていつの間にか史上類を見ない最強の軍勢が誕生し、 王国全軍をも凌駕する最強の軍事力を持つ「独立領地」へと大成長。 一方のオルファウス公爵家は、 自分たちが「とんでもない化け物」を野放しにしてしまったという絶望的な事実を知り、 恐怖に青ざめるのであった。 | I112: 455 | J112: 主人公最強|ハーレム？|勘違い|ざまぁ|追放|悪役転生|成り上がり|カクヨムオンリー | K112: 1639 | L112: 218 | M112: 218 | N112: 18 | O112: 54739 | P112: 17 | Q112: 連載中
A113: 異世界ファンタジー | B113: 12 | C113: 継続 | D113: 北方領主によるローゼリア大陸戦記 | E113: イコ | F113: https://kakuyomu.jp/works/2912051605497205076 | G113: 戦記物の皮を被った、嫁チート！！！ | H113: 戦略シミュレーションゲーム『キングス・オブ・レガリア』の世界に転生した主人公は、辺境の弱小領地を発展させるために、努力を続ける。 しかし、成長して領主になり、過酷な環境に疲れ果てていた矢先、他領から妻を迎えることになる。 藁にも縋る思いで、食料欲しさに迎えた妻は、ゲームに登場しない名もなき少女リゼットだった。 戦略シミュレーションゲームとして、努力しながらも精神をすり減らす主人公。だが、妻を迎えてからの環境は次第に変化を生み始める。 主人公は大陸統一というゲームのクリア条件を満たせるのか？ それとも本当にここは戦略シミュレーションゲームの世界なのか？ 結末はいかに？ | I113: 296 | J113: 戦略シミュレーションゲーム？|戦記物？（陣取り合戦）|主人公転生者|嫁チート|溺愛|シリアス|ラブコメ|AI補助利用 | K113: 2610 | L113: 81 | M113: 81 | N113: 61 | O113: 201762 | P113: 29 | Q113: 連載中
... A176: 異世界ファンタジー | B176: 75 | C176: 継続 | D176: 仲間を庇って落ちた奈落から舞い戻ったら婚約者に裏切られ、財産は奪われ、パーティーからも追放されていたからもう知らん～なお彼を追い出した奴らは次々に崩壊していく模様 | E176: 蒼井星空 | F176: https://kakuyomu.jp/works/2912051606374053458 | G176: 今さら後悔しても遅いんだよ！なお、俺を信じた元婚約者の妹だけは助ける | H176: 俺はこの街のトップ冒険者パーティーのリーダーだ。 ダンジョン探索は文字通り生死をかけた戦いだ。今日も俺たちは準備万端で挑む。 しかし仲間の盗賊<シーフ>がやらかしやがった。罠解除はお前の役割だろ？なんでそんなに綺麗に踏み抜くんだよ。しかし俺は咄嗟にリーダーとしてそのシーフを庇った結果、奈落と呼ばれるダンジョン深層へと落ちてしまった。 そこからは地獄の日々だった。襲い来る超強力なモンスター。飢餓と毒との戦い。どこに進めばいいのかも分からない中で死に物狂いで戦い続け、ようやく帰っていた。 そこで待っていたのは、恋人とシーフの裏切りだった。 ふざけんなよ？ なんで俺が罠にかかって仲間を危険に晒したことになってんだ！？ 街から出て行けだと？ 言われなくてもこっちから願い下げだよ！ と思ったんだが、元恋人の妹だけは慰めてくれた。 あのあと、街もパーティも大変らしいがざまぁ！！！！ と思ってたら、妹ちゃんがピンチ……。 当然助けるぜ？ 奈落を生き抜いた俺の力を見せてやるぜ！ ※本作は過去に投稿した作品をコンテスト用に改稿したものです。(20話くらいまでは微修正、その後展開を変える予定です) | I176: 503 | J176: 裏切り|婚約破棄|パーティ追放|市民権剥奪|ざまぁ|スタンピード|借金と不正|曇らせ | K176: 455 | L176: 35 | M176: 35 | N176: 20 | O176: 49382 | P176: 18 | Q176: 連載中
A177: 異世界ファンタジー | B177: 76 | C177: 継続 | D177: クラスで集団異世界転移。毎日ゴミ拾いしていたことで善行ポイントがカンストしてたので、ポイント消費して強さよりも生き残ることを優先します。 | E177: 雪風 | F177: https://kakuyomu.jp/works/2912051606883618436 | G177: 毎日のゴミ拾いで善行ポイントがカンストしてた。 | I177: 0 | J177: 異世界|転移|恋愛|学園|サバイバル|戦争|戦記|現代 | K177: 111 | L177: 17 | M177: 17 | N177: 2 | O177: 17699 | P177: 5 | Q177: 連載中
A178: 異世界ファンタジー | B178: 77 | C178: 継続 | D178: 追放された解析職、俺が独占していた攻略法をすべて無料公開する～「お前の代わりなどいくらでもいる」と捨てられたが、街の掲示板に討伐メモを貼ったら新人が格上を瞬殺し、ボッタクリギルドが翌週潰れました～ | E178: kuni | F178: https://kakuyomu.jp/works/2912051606777645553 | G178: これは復讐じゃない。ただの、情報公開だ。世界が無料の知でひっくり返る。 | H178: 「お前のような事務員、代わりなどいくらでもいるんだよ！」 大陸最大級のギルド『黄金錠』で、魔物の生態・行動・弱点を解析し続けて十年。 筆頭解析官レイ・ウォードは、看板冒険者たちに手柄を奪われた末、一方的にクビを宣告された。 レイは怒鳴り散らすこともなく、淡々とギルドを去る。 「資料の持ち出しはしていませんよ。――全部、俺の頭に入っていますから」 翌日、街の掲示板に一枚の紙が張り出された。 そこには、ギルドが『死者多数の超難関』と偽って高額な討伐料をぼったくっていた魔物の【誰でも３分でノーダメージ完封できる手順】が書かれていた。 「これ……街の薬草と、ただの短剣があれば勝てるってことか……？」 半信半疑で試した底辺の新人冒険者が、格上の中堅魔物をあっさり撃破。 情報は瞬く間に都市中へ、そして世界中へと拡散していく。 「秘伝」を失ったぼったくりギルドは即座に破産。 独占されていた技術、高額な粗悪武器、利権まみれの魔法―― レイが気まぐれに情報をばら撒くたび、腐った既得権益が音を立てて崩壊していく。 当のレイは、情報で救われた元雑用少女ミナと共にのんびり街角で過ごしていた。 「俺は世界最強になりたいわけじゃない。ただ、知っていれば誰も死なずに済むだろう？」 これは、戦わずして世界をひっくり返した男の、規格外の知略ファンタジー。 | I178: 577 | J178: 追放|ざまぁ|主人公最強|成り上がり|知略|おっさん|掲示板|AI利用 | K178: 291 | L178: 14 | M178: 14 | N178: 12 | O178: 25345 | P178: 11 | Q178: 連載中
A179: 異世界ファンタジー | B179: 78 | C179: 継続 | D179: 幼竜の俺を拾ったボロボロの少女、数年後に最強のドラゴンナイトになって俺を執着溺愛してくるんだが？ | E179: 冰藍雷夏(ヒョウアイライカ) | F179: https://kakuyomu.jp/works/2912051606572229208 | G179: 【人外龍転生×激重少女ヒロイン】最弱の幼竜、最強の竜騎士を育てる。 | H179: ​前世の記憶を持ったまま、翼の折れた『最弱の幼竜』として異世界に転生したジル。 森で死にかけていたところを救ってくれたのは、村で「不吉な子」と虐げられていたボロボロの少女・エレナだった。 ​自分を命がけで守ろうとする健気な彼女に恩を返すため、ジルは前世の知識と竜の知恵を駆使し、陰から彼女の『師匠』として魔術と剣技を仕込み始める。 ​——数年後。 ジルのスパルタ（？）指導により、エレナは王国史上最年少にして最強の『竜騎士』へと覚醒していた。 ​「ジル、今日も可愛いね。……大丈夫だよ、私からジルを奪おうとする奴は、国ごと斬り伏せてあげるから」 ​あれ？ おかしくない？ 守ってあげたはずの少女が、俺に執着する無敵の激重ヤンデレ騎士になっちゃったんだけど！？ ​肩乗りサイズの幼竜と、愛が重すぎる最強竜騎士が織りなす、勘違い＆無双成り上がり | I179: 375 | J179: 人外転生|ざまぁ|激重感情|幼竜転生|短編シリーズ|たぶん短編 | K179: 301 | L179: 16 | M179: 16 | N179: 15 | O179: 28539 | P179: 15 | Q179: 連載中
A180: 異世界ファンタジー | B180: 79 | C180: 継続 | D180: 伝説の老騎士、定年退職して裏路地で屋台を始める | E180: 犬斗 | F180: https://kakuyomu.jp/works/2912051596456970950 | G180: 街の裏路地。大きな事件はなくとも、そこにはいくつもの人生があった。 | H180: 六十歳を迎えた老騎士ルマート。 剣の腕は超一流ながら、自己を犠牲にして騎士団の改革を訴えたため、出世とは無関係の騎士生活を送ってきた。 厳格ながらも優しく公平な性格で、全騎士から尊敬を集めていたルマート。 引退を惜しむ弟子たちに見送られ、四十五年間勤めた王立騎士団を定年退職した。 騎士一筋だったルマートには、もう一つの夢があった。 それは串焼き屋を開くこと。 偶然の出会いから、裏路地に屋台を構えることになった。 そこでルマートは知る。 大きな事件はなくとも、街の裏路地にはいくつもの人生があることを。 これは伝説の老騎士が、裏路地の屋台で始める第二の人生の物語。 ※小説家になろうでも公開しています。 | I180: 307 | J180: 主人公最強|イケ爺|師匠|騎士|屋台|定年退職|第二の人生 | K180: 383 | L180: 19 | M180: 19 | N180: 26 | O180: 60334 | P180: 20 | Q180: 連載中
A181: 異世界ファンタジー | B181: 80 | C181: 継続 | D181: ロストワーカー～騙された傭兵はヒモ生活を夢に見る～ | E181: ココア | F181: https://kakuyomu.jp/works/822139846598449886 | G181: 復讐なんてするよりも、ヒモ生活を目指すか | H181: ロストワーカーと呼ばれる傭兵が居た。 気分次第で依頼を受け、敵を殲滅する。凄腕だが、少々気分屋の傭兵だ。 しかし、彼はやりすぎてしまった。 気分次第でどの勢力にでも付く彼は、平和になり始めた世界にとって邪魔になったのだ。 国が。ギルドが。教会が。彼1人を消す為に動きだした。 偽の依頼を受けて現れた彼を、世界トップクラスの戦力が待ち構えていた。 そして、ロストワーカ－は表舞台から姿を消した……。 これは騙された結果やる気を無くした男の、二度目の物語である。 | I181: 236 | J181: 魔法|男主人公|勇者の娘|ヒモ | K181: 1221 | L181: 31 | M181: 31 | N181: 57 | O181: 206906 | P181: 175 | Q181: 連載中
A182: 異世界ファンタジー | B182: 81 | C182: 継続 | D182: 魔王を倒した勇者パーティの雑用係、異世界の辺境村でスローライフを始めました。～のんびり暮らしたいだけなのに規格外の連中が居座り始めた件～ | E182: タジリユウ | F182: https://kakuyomu.jp/works/2912051605408281657 | G182: 最強じゃない、でも誰よりも頼られる万能スキル持ち雑用係のサードライフ！ | H182: 魔王討伐を果たした勇者パーティの陰の功労者・シンヤ。 【万能スキル】と前世の知識を駆使し、索敵、装備のメンテナンス、調合、料理まで、多くを裏で支えてきた彼は影は薄いが「完璧すぎる雑用係」だった。 魔王が倒れ平和が訪れたとき、彼が選んだのは富や名声ではなく隠居。 前世からの夢だった「のんびりスローライフ」を叶えるため、第三の人生として静かな辺境の村へ一人移住する。 万能スキルで快適な家を建て、畑を耕し、釣りや狩りをして美味しいご飯を食べる――はずだったのだが……。 生活能力が破綻した元パーティメンバー、旅の途中で命を助けた獣人、さらには元魔王軍四天王までが居心地の良すぎるシンヤの村へ続々と押しかけて居座り始めた。 果ては勇者と王女様まで新婚旅行でやってきて、シンヤが万能スキルで開拓した辺境村は、気づけば『世界最強達が集う史上最も安全で快適な村』へと変貌していき――！？ 本人は静かに暮らしたいだけなのに規格外な連中に囲まれてゆっくりと暮らせない、そんな元雑用係のドタバタ辺境開拓記！ | I182: 447 | J182: 異世界転生|スローライフ|開拓|飯テロ|チート|ストレスフリー|万能スキル|雑用係 | K182: 772 | L182: 23 | M182: 23 | N182: 25 | O182: 56882 | P182: 29 | Q182: 連載中
A183: 異世界ファンタジー | B183: 82 | C183: 継続 | D183: 【書籍化】俺は勇者に向いていない 〜主人公を譲ってあげたら世界が滅亡しかけてるんだが……〜【旧題】王道系ファンタジー漫画の主人公キャラに転生したら、村にもう一人転生者がいた〜何やら……〜 | E183: 出来立てホヤホヤの鯛焼き | F183: https://kakuyomu.jp/works/16818093074173866568 | G183: 絆？ 愛？ それでパワーアップとかしろと？ 出来る気が欠片もしないぜ☆ | H183: MFブックス様より8月25日に書籍が発売されました。近況ノートに本の表紙を載せています。 それに伴い、題名が 「俺は勇者に向いていない 〜主人公を譲ってあげたら世界が滅亡しかけてるんだが……〜」 に変わります。 【旧題】「王道系ファンタジー漫画の主人公キャラに転生したら、村にもう一人転生者がいた〜何やら主人公に成り代わりたいみたいなので譲ってあげたら世界が滅亡しかけてるんだが……〜」 タイトルが100文字だったので、【旧題】の全ては書けませんでした。 「俺は英雄になんてなれる気がしないし、なりたくもない」 主人公ブレイブは転生者だ。それも、前世で暇潰しに読んだことのある、魔王を討伐する王道系ファンタジー漫画の主人公に転生した。 ブレイブも当初は、主人公に転生したのなら責任を以て原作通りに進めないといけないな、と考えていたのだが…… なんと、自分以外にもなんと同じ村に転生者がいたのだ。しかも、主人公の座を狙っているのである。 だから、ブレイブは――――譲った。譲っちゃったのだ。いかにも、ざまぁされそうな展開だと思った為である。 こうして、世界はもう一人の転生者によって救われ――――なかった。普通に敗北したのだ。そして世界は、王道ファンタジー世界から終末ファンタジー世界系へと変化していくのだった。 HARDモードな世界を救う旅にブレイブは出る！ | I183: 591 | J183: カクヨムオンリー|異世界転生|魔法|主人公最強格|男主人公|ファンタジー|魔王|シリアス | K183: 21592 | L183: 13 | M183: 13 | N183: 304 | O183: 923901 | P183: 883 | Q183: 完結済
A184: 異世界ファンタジー | B184: 83 | C184: 継続 | D184: 『異世界で10年男勇者だった俺、帰還したら元の美少女に戻っていた』 ～正体を隠してVTuberになったら、ダンジョン配信で世界最強だとバレました～ | E184: @takamatuhorihori | F184: https://kakuyomu.jp/works/2912051605166648134 | G184: 元に戻っただけだ――あっ、そういえば俺、女だったわ。 | H184: 事故に遭った俺は、異世界へと転移した。 しかも、転移先で与えられた肉体は屈強な男だった。 最初こそ戸惑ったものの、剣と魔法を身につけ、仲間たちと冒険し、魔王を倒し――気づけば10年。 俺はすっかり、男として生きることに慣れていた。 そして魔王討伐を果たした直後、まばゆい光に包まれた俺は、懐かしい現代日本の病院で目を覚ます。 だが、鏡に映っていたのは美少女だった。 「お、俺……女になってるぅぅぅっ!?」 突然のTSに絶叫する俺。 しかし、駆けつけた家族から昔の写真を見せられ、ようやく思い出す。 「……あっ。そういえば俺、元の世界では女だったなぁ」 異世界で男として過ごした10年が長すぎて、完全に忘れていたのだ。 しかも、現代では事故からほとんど時間が経っていなかった。 見た目は美少女。 中身は10年間、男勇者として生きてきた元女子。 そんな俺が生活費を稼ぐために始めたのは、顔を出さずに活動できるVTuberだった。 雑談、ゲーム実況、歌配信。 平穏に活動するつもりだったのだが、ある日、視聴者から現代に出現したダンジョンの配信を勧められる。 「初心者向けダンジョン？ これなら俺でも安全に配信できそうだな」 しかし、異世界最強の勇者だった俺にとって、現代のダンジョンなど子供の遊び場同然だった。 巨大な魔物を素手で吹き飛ばし、罠を勘だけで見破り、誰も倒せなかった階層ボスを雑談しながら一撃で粉砕する。 コメント欄は大騒ぎ。 『ラスボス瞬殺で草』 『待って、今何した!?』 『本人だけ初心者のつもりなの怖すぎる』 『海外ニキがもう切り抜き翻訳してるぞ！』 ただ生活費を稼ぎたかっただけなのに、配信は世界中で大バズり。 企業、探索者ギルド、政府機関、海外のトップ配信者まで、謎の新人VTuberに注目し始める。 だが、本人だけはまだ気づいていない。 自分が現代最強の探索者であることも。 世界一かわいいVTuberとして人気になっていることも。 そして――異世界で倒したはずの魔王の気配が、現代のダンジョンから漂い始めていることも。 これは、異世界で10年間男勇者だった元女子が、美少女の身体に戻ってVTuberとなり、勘違いと無自覚無双で世界中を熱狂させる物語。 | I184: 966 | J184: ダンジョン配信|俺TEEEE|Vtuber|TS|AI本文使用 | K184: 762 | L184: 6 | M184: 6 | N184: 70 | O184: 358397 | P184: 35 | Q184: 連載中
A185: 異世界ファンタジー | B185: 84 | C185: 継続 | D185: 流れ者のおっさん、なんか強い。 | E185: ファンタスティック小説家 | F185: https://kakuyomu.jp/works/2912051607199056455 | G185: 何事も過程こそが楽しい | H185: 孤児オルランドは、貧しさから逃れるため、剣で身を立てることを決意する。行商人の馬車に忍び込み護衛を押し売り、都で冒険者を経験したのち傭兵に転向。数々の戦役で武功を立て、貴族に召し抱えられ、叙勲を受け、騎士となり、名誉ある銀獅子団の長を努めた。 その後、狼の騎士団を設立、王国最強の戦闘集団として名を馳せる。ひいては予言の災厄、暗黒竜を討つため、王国中から選び抜かれた英雄集団『竜滅隊』に抜擢され、見事これを討ち、王国の滅びすら防いだ。 そして、今回、伝説の英雄オルランドは、王の勅命により、南方にて全七軍総兵力120万からなる蛮族蹂躙大軍を指揮することに。これは膠着した南方戦線に決定的な一撃を加え、王国の支配を盤石にする侵攻だったが──。 「……えー、全軍撤退」 全軍司令官オルランド公爵は、なんの気の迷いか全軍に撤退命令を残し、忽然と姿を消してしまった。 これは成り上がり終えて「コレジャナイ」と悟ったおっさんが新しい冒険を始める物語。 | I185: 429 | J185: 主人公最強|おっさん|剣士|魔法|隠れた実力者|カクヨムオンリー|コメディ|成り上がり | K185: 177 | L185: 10 | M185: 10 | N185: 5 | O185: 26023 | P185: 4 | Q185: 連載中
A186: 異世界ファンタジー | B186: 85 | C186: 新規ランクイン | D186: いずれ全能の大魔王へ至る暴食者〜喰らった相手のスキルを奪い、襲い来る敵達を返り討ちにして世界最強へ〜 | E186: 無名 | F186: https://kakuyomu.jp/works/2912051598629273143 | G186: 異界人・英雄・勇者・魔王など、数多の強者からスキルを奪う | H186: 子供を助けて命を落とした青年は、異世界で一匹のオークとして転生した。 そこで得た特異な力は、喰らった相手のスキルを奪う大罪スキル【暴食】。 人間だった記憶と、魔物としての本能。相反する二つを抱えながら、彼は生き抜くために魔物を狩り続ける。 だが、力を蓄えるほど世界は彼を危険視する。 Sランク冒険者や勇者に狙われ、同じく大罪を冠する魔王達にも敵視される存在へ。 ならば、襲い来る敵は全て喰らい、その力を己のものにするだけだ。 これは、【暴食】の力を宿した一匹のオークが、全能の大魔王へ至る物語。 | I186: 259 | J186: 異世界|魔物転生|成長|主人公最強|魔王|勇者|強奪|AI補助利用 | K186: 806 | N186: 126 | O186: 374517 | P186: 125 | Q186: 連載中
A187: 異世界ファンタジー | B187: 86 | C187: 継続 | D187: レベル０な無能悪役貴族のノブレスオブリージュ～転生したらチートもなく死亡フラグしかなかったので、知識チートで全てをへし折る！～ | E187: 御峰。 | F187: https://kakuyomu.jp/works/2912051598760105457 | G187: 増えた銀貨を使ってスラム街に住んでる下民を働かせたらまた銀貨が増える！ | H187: ゲーム世界“ホーリーソード”の最初に成敗される悪役キャラに転生した主人公。 無能な父と母によって財政状況は最悪で、いずれゲーム主人公によって命を落とす運命にあった。 しかも転生したキャラは運営が面白半分で作った“レベル０”という一切に強くなることが許されていないキャラだった。 せっかく異世界に転生したのに二度目の死は嫌な主人公は、自分を溺愛してくれる両親を説得し領地改革に乗り出す。 才能もチートスキルもない主人公だが、持ち前の明るい気持ちでどんどん改革を進めていく。 クズ商人の成敗、悪徳傭兵団を取り込んで味方にしたり、最強軍団を作ったり、知識を使って新しい事業を始めて大成功させてみたり、ハチャメチャなことをやりまくる！ | I187: 314 | J187: 転生|成り上がり|知識チート|領地経営|ノブレスオブリージュ|貴族|救済|がっぽがっぽ | K187: 2559 | L187: 28 | M187: 28 | N187: 96 | O187: 239378 | P187: 111 | Q187: 連載中
A188: 異世界ファンタジー | B188: 87 | C188: 継続 | D188: 魔力０なのに名門魔法学校に入学した俺、ダンジョンに置き去りにされる | E188: 唐土唐助 | F188: https://kakuyomu.jp/works/2912051601772429444 | G188: 最強のモンスターと共存して、ダンジョンを生き抜く | H188: 「俺の失態を知っているお前が生きていては困るんだ。あばよ、魔力0の無能」 ――タクトはダンジョン探索の最中、同じパーティのダグラスに裏切られ、ダンジョンの深層に置き去りにされる。 誰もが生還不可能と言う人類未踏の魔境。 絶体絶命のタクトを救ったのは、魔力を探知して喰らう、凶悪な植物型の魔物だった。 魔力測定値『０』ゆえに、魔物から獲物として見向きもされないタクト。彼は生き延びるため、自作の魔導ポーションを植物の魔物に捧げ、奇妙な共存生活を始める。 過酷な環境での日々、タクトの肉体は少しずつ変化を遂げていく。 なんとか深層での生活が軌道に乗ってきたと思ったある日、運悪くダンジョン内に魔物の異常発生が勃発してしまう。 凶悪な魔物がタクトを襲う。 遥かに格上の魔物相手に、タクトはついに自作のナイフを握りしめる――。 ◇ 死線を越えた先に待っていたのは、新たな仲間。 凶悪な植物の魔物の娘『ライア』との出会いだった。 ◇ 一方タクトのパーティメンバーだったダグラス達は、今までタクトを奴隷のように扱い頼り切りだった『つけ』が回ってくる。 タクトが抜けたことで学校の成績を落とし、化けの皮が剥がれていく。 ◇ そしてタクトは深層で、大賢者の遺した隠れ家を発見。 そこで、自身の身体に刻まれた『魔力０の真実』を知ることになる。 地獄の底から這い上がった少年が、家族を守るために安定した職と平穏を目指すハイファンタジー！ | I188: 624 | J188: 学園|魔力無し|置き去り|魔法|覚醒|ざまぁ|人外|ラブコメ | K188: 2511 | L188: 9 | M188: 9 | N188: 81 | O188: 209322 | P188: 83 | Q188: 連載中
A189: 異世界ファンタジー | B189: 88 | C189: 継続 | D189: 前世で遊んでいたアウトロー系アプリゲームのキャラクター達を召喚したら、いつの間にか裏社会のドンになっていたんですけど？ | E189: Crosis@奴隷使役重版決定！！ | F189: https://kakuyomu.jp/works/2912051603718210639 | G189: 私はただのオジさんですっ！（どうしてこうなったのですかっ！） | H189: ある日、主人公であるダルク・フィン・クヴィスト（３８歳）は潰れかけの冒険者クラン、黒竜の爪のクランマスターを引き継ぐ事となる。 本人は今までの恩もある為、潰れ行くと分かっていても残ってくれているメンバーの為にクランマスターを引き継ぐのだが、どうやらこれがダルクの持っている能力の解放条件だったようだ。 その能力とは前世でプレイしていたスマホゲーム『極悪道・天下統一』の能力を引き継ぐというものであった。 その結果ダルクはで極悪道・天下統一で手に入れたキャラクター達をこの世界に呼び出しクランの立て直しを図るのだが、気が付けば裏社会のドンへと上り詰めていたのであった。 | I189: 286 | J189: 悪役|裏社会|異世界|俺tueee|おっさん|ハーレム | K189: 568 | L189: 23 | M189: 23 | N189: 56 | O189: 59874 | P189: 52 | Q189: 連載中
A190: 異世界ファンタジー | B190: 89 | C190: 継続 | D190: 転生した凡人は天才に憧れ努力を続ける | E190: 霜月雹花 | F190: https://kakuyomu.jp/works/2912051599423692353 | G190: 天才達に憧れ続けた凡人の物語 | H190: ただの冒険者であったアルフ。 住んでいた街が魔物に襲われ、たった一人で魔物の大群と戦い命を落とした。 しかし、次に目が覚めるとアルフレッド・フォン・ヴェルゴールドとして新たな人生を送っていた。 前世の記憶を思い出したアルフレッドは、前の人生では届かなかった天才達を超える力を得る為に努力をする事にした。 二度目の人生でも才能は無いアルフレッドは、前世の記憶を使って高みを目指す。 | I190: 189 | J190: 転生|努力|冒険者|魔法|剣 | K190: 2481 | L190: 9 | M190: 9 | N190: 147 | O190: 300568 | P190: 116 | Q190: 連載中
A191: 異世界ファンタジー | B191: 90 | C191: 継続 | D191: 異世界転移に紛れ込んだおっさんは静かに世界を燃やす | E191: 柊木犀 | F191: https://kakuyomu.jp/works/2912051599523320748 | G191: 頼るのは己の勘、不穏な世界を灰燼と化していくおっさんの放浪譚 | H191: 【リアル寄り異世界転移のため軽さはありません】 突然異世界に転移した高校生、１クラス総勢３４名。 そこに、３７歳のおっさんが紛れ込んだ。 おっさんは、唯一の家族であった愛息子を飲酒運転の男に轢き殺され、法の裁きを与えるために司法に望みをかけていた。 しかしその想いは叶わず、懲役最大７年の過失致死傷罪という到底納得できるものではなかった。 そして実力行使に出た男が目覚めたところは…… これは全てを失って生きる希望を無くした男が、クラス転移に紛れ込んだあと、異世界の不条理に抗って行くストーリー 【注意】 ・主人公は簡単に人を殺します（冒頭に理由あり） ・ファンタジー世界としては微妙に現実的な世界を、年齢相当に考えながら動きます ・普通の一般人の大人なので完璧ではなく、経験則による行動が多くなります ・作者はある程度成熟した『おっさん』を好むので察してください ※おっさんの殻を被ったお子ちゃまではありませんので、やっちゃいましたーとか、すぐに恋愛に発展なんてことはありません | I191: 446 | J191: カクヨムオンリー|アラフォー|容赦なし|主人公最強？|年齢相当|男主人公|クラス転移|シリアス | K191: 1553 | L191: 19 | M191: 19 | N191: 62 | O191: 227922 | P191: 82 | Q191: 連載中
A192: 異世界ファンタジー | B192: 91 | C192: 継続 | D192: 迷宮都市の石路〜その日暮らしの転生者〜 | E192: 出来立てホヤホヤの鯛焼き | F192: https://kakuyomu.jp/works/2912051595259985810 | G192: 転生者は迷宮の未知なんてどうでもよかった。ただ生きていければそれだけで | H192: 異世界のスラム街のような場所に転生した主人公、クロウはチンピラ達とシノギを削りながら、毎日を生きていた。 チンピラ達を倒せるぐらいには強くなっていたクロウだが、前世の日本との暮らしとは比較にならないほど生活水準が低い上、治安も悪い。 とうとう異世界での故郷ともいえるそんな街を捨て、栄えているという迷宮都市に乗り込むことを彼は決心した。 残酷なスラム街に適応して、精神的にヤサグレた彼は、迷宮で名声を得て称賛が欲しい訳ではなかった。ただ、マトモな寝床とマトモな食事を求めている。 自分も信用しておらず、他人はもっと信用していない。彼は一人だった。 これは転生者が、自身の権利や自由を主張するために強さを、そして、失った倫理的なものを取り戻していくお話。 | I192: 328 | J192: カクヨムオンリー|異世界転生|魔法|ファンタジー|ダンジョン|男主人公|成長|男性向け | K192: 18830 | L192: 12 | M192: 12 | N192: 176 | O192: 583052 | P192: 175 | Q192: 連載中
A193: 異世界ファンタジー | B193: 92 | C193: 継続 | D193: 誰だ、そよ風のレオンなんて言った奴は！ | E193: 暇野無学 | F193: https://kakuyomu.jp/works/822139836880422144 | G193: 奴は化け物だぞ。そよ風の名に騙されて酷い目にあっちまったじゃねえか！ | H193: 日本からの転生者レオン、授けの儀で授かったのは風魔法一つ。日本で見たアニメやラノベの記憶と知識を利用して、風魔法を使い無双する。アイアンランクから冒険者の最高プラチナランクへとのし上がっていく物語です。 | I193: 101 | J193: 風魔法|冒険者|スキル|精霊|成り上がり | K193: 28194 | L193: 12 | M193: 12 | N193: 204 | O193: 808055 | P193: 209 | Q193: 完結済
A194: 異世界ファンタジー | B194: 93 | C194: 継続 | D194: 魔王を倒して消えた勇者は一年後に帰還した。俺を死んだと思っていた四人のヤンデレが手放してくれない | E194: 秋雨 淳@毎日2回以上更新 | F194: https://kakuyomu.jp/works/2912051606423922712 | G194: 俺は元の世界へ帰るつもりで消えた。彼女たちは、俺が死んだと思っていた。 | H194: 魔王を討ち、世界を救った勇者は、その直後に消えた。 神託に選ばれた勇者の一人でありながら、普段は弱く、面倒ごとを嫌う主人公。けれど仲間が死にかけた時だけ、彼は誰よりも強くなる。 魔王討伐の瞬間、主人公は前世で交通事故に遭った直前と同じ謎の光を見つける。元の世界へ帰れるかもしれない――そう信じて光へ飛び込んだ。 しかし次に目を覚ますと、そこは一年後の、同じ魔王城の玉座の間だった。 残された聖女、天才魔法使い、エルフのお姫様は、主人公が自分たちを守って死んだのだと信じていた。主人公は、旅の最初に自分を嫌っていた三人へ、わざわざ会いに行くつもりはない。勇者を辞め、幼馴染シスターの待つ故郷で静かに暮らそうとする。 けれど、主人公を失った一年で、彼女たちの愛し方は壊れていた。 「今度は、絶対に手放しません」 これは、死んだと思われた元勇者と、二度と彼を失いたくない四人のヒロインによる、重すぎる異世界帰還ラブファンタジー。 | I194: 418 | J194: ヤンデレ|ハーレム|執着|重い愛|曇らせ|異世界転生|勇者|泥沼 | K194: 282 | L194: 6 | M194: 6 | N194: 20 | O194: 78988 | P194: 17 | Q194: 連載中
A195: 異世界ファンタジー | B195: 94 | C195: 継続 | D195: 最強おじさん宇宙へ行く 喋る宇宙船と魔法で無双する話 | E195: タビサキ リョジン | F195: https://kakuyomu.jp/works/2912051605637151413 | G195: SFの皮を被った異世界ファンタジーだと思えば大体あってる。 | H195: 色んな異世界を渡り歩いた最強おじさんが、SFっぽい世界で宇宙船を手に入れて無双する話です。 タイトル以上の中身がない！ ノンストレス！ だいたい雰囲気で流してオッケー！ 一応科学っぽい雰囲気をだしたりもしてますけど、とてもSFのジャンルに入れる勇気のなかった感じのヤツです！ 文庫にして、一冊分くらいの分量は更新保証します。 | I195: 166 | J195: カクヨムオンリー|喋る宇宙船|スペースオペラ|主人公最強|【不使用】AI 生成 | K195: 617 | L195: 23 | M195: 23 | N195: 31 | O195: 79475 | P195: 27 | Q195: 連載中
A196: 異世界ファンタジー | B196: 95 | C196: 継続 | D196: 【第一章完結】とぼけたS級冒険者と悪役令嬢 | E196: 佐倉真稀 | F196: https://kakuyomu.jp/works/2912051602109856395 | G196: 追放上等！生き抜いてやるわ！ところで、貴方護衛お願いできる？ | H196: 私、ディアベイル・リアーガーン。元公爵令嬢。婚約者だった第三王子に婚約破棄され冤罪で国外追放に。隣国に入った途端、馬車が襲撃される。護衛は全滅。壊れた馬車から走って逃げているところに小山のような大きな魔物が飛んできた。 追いかけてきた襲撃者はその魔物に轢き殺された。その魔物をぶっ飛ばしたのは無精ひげを生やした中年S級冒険者パド。解体を手伝い護衛を頼む。身だしなみを整えた彼は、意外と見られる容姿をしていた。街に着いたら護衛は契約終了と思っていたら、何故か領都まで一緒に行くことになってしまう。襲撃はまだある様子。どうなる私！ 第一章完結 応援ありがとうございます！ 第二章再開まで2週間ほどお休みいたします。 ※小説家になろう様にも投稿しています※ | I196: 326 | J196: 異世界転生|悪役令嬢|冒険者|乙女ゲーム|イケオジ | K196: 894 | L196: 29 | M196: 29 | N196: 26 | O196: 46872 | P196: 24 | Q196: 連載中
A197: 異世界ファンタジー | B197: 96 | C197: 継続 | D197: この【オープンワールド】ってユニークスキル、実はヤバい気がする | E197: 東出祐一郎 | F197: https://kakuyomu.jp/works/2912051602444081482 | G197: 【第一部完結！】そうか……物理バグとやらで人は死ぬのか…… | H197: １５歳になると神からランダムでスキルが与えられる世界で、 侯爵家の三男であるレオツ・スカイリーンは【オープンワールド】という 訳の分からないスキルを与えられてしまう。 【インターネット】みたいに「使えない」ユニークスキルか、と 落胆していたレオツだが、使っている内に気付く。 「あっ、これヤバい。ヤバいスキルですよコレは」 使えないはずのユニークスキルで（そこそこ）無双する感じのお話。 ただし敵もユニークスキルを使ってくるぞ！ 「時間停止するんだな、このボタンを押すと。で、ポーションをいっぱい飲んで回復して……」 「なんで心臓を突いたのに復活してるの！？」 「なんで俺は空中浮遊しながら全身の関節がひねり潰されてるのおお！？」 「ごめん、それ僕にも分かんないんだマジで。ハヴォ……何とかみたいな 神様のせいだって説明があったけど」 「そんな神様聞いた事ないよおおおあわびゅ！？」 ――世界を侵せ。望むままに。 | I197: 411 | J197: カクヨムオンリー|ユニークスキル|いずれ最強|成り上がり|オープンワールド|物理演算バグ | K197: 3234 | L197: 18 | M197: 18 | N197: 64 | O197: 195101 | P197: 55 | Q197: 連載中
A198: 異世界ファンタジー | B198: 97 | C198: 新規ランクイン | D198: 追放されたので田舎でのんびり理想の錬金術暮らしを満喫する筈が、なぜか世界再誕の英傑と言われている～国を築いて王女や公爵令嬢と結婚したら、のんびりできないんじゃ？～ | E198: 相野仁 | F198: https://kakuyomu.jp/works/2912051605481146115 | G198: マスター、「造化」は天地を創造するという意味です（できそうですね） | H198: 平民錬金術師のロドリックは、伯爵家のディアスに目をつけられ、 追い出されてしまう。 だが、ロドリックは実は歴史に名を刻む大天才錬金術師だった。 ロドリックがいなくなって王都は困り、ディアスが取り入ろうとしていた 公爵家もロドリックを絶賛して、彼を取り込むための一大勢力を築きはじめる。 一方でロドリックは辺境でしがらみなくのびのび活動することで、 本来の実力を存分に発揮できるようになった結果、神霊や神獣と 契約してしまう。 気づいたときにはどんな国家をも超越した理想郷が誕生していた。 | I198: 246 | J198: 追放|男主人公|ハーレム|SUGEEEE|錬金術|ざまぁ|勘違い？ | K198: 222 | N198: 12 | O198: 27606 | P198: 11 | Q198: 連載中
A199: 異世界ファンタジー | B199: 98 | C199: 新規ランクイン | D199: 転生付与術師オーレリアの難儀な婚約 | E199: カレヤタミエ | F199: https://kakuyomu.jp/works/16818792436546970549 | H199: 「この婚約は無かったことにしてほしい」 結婚のためはるばる王都までやってきたその日、オーレリアに突きつけられたのはそんな言葉だった。 家族もなく故郷も半ば捨ててきたオーレリアにあるものは、付与術と前世の記憶のみ。 幸い付与術師は仕事に困ることだけはない。 何ももたないオーレリアは一人、王都で生きていこうと決めるのだった。 恋愛までたどり着くのに時間がかかります。 舞台は19世紀半ばから20世紀前半の文化、風習を参考にしていますが、魔法のある世界で色々と違う歴史を辿っている設定です。現実の歴史とは一切関わりがありません。 作中に出てくる文化・習慣・宗教・風俗等は全て架空のものです。 あくまで創作上のものとして楽しんでいただければ幸いです。 | I199: 324 | J199: ファンタジー|異世界恋愛|女主人公|異世界転生|女性向け | K199: 5427 | N199: 260 | O199: 981314 | P199: 416 | Q199: 連載中
A200: 異世界ファンタジー | B200: 99 | C200: 継続 | D200: 王家待望の末っ子王子、溺愛してくる五人の姉に開拓されながら気軽に無双する | E200: 風遊ひばり | F200: https://kakuyomu.jp/works/822139846195913224 | G200: 戦闘メイドゴーレムはロマン！（力説） | H200: 長い間女性しか生まれてこなかった『ハルメシア王国』の王家。その日、ついに待望の男子が誕生しました。『カイゼル』と名付けられた彼は五人の姉に愛されながらすくすくと成長し、次期国王に相応しいよう、様々な力を身に付けました。そして同時に、世界は彼を中心に大きく動き始めたのです。 これは永劫たるハルメシア王国と、その歴史に名を刻む偉大なる王の叙事詩。 | I200: 173 | J200: 転生|末っ子王子|王女|無双|戦闘メイドゴーレム|こいつら全員最強過ぎない？|癖の渋滞 | K200: 140 | L200: 33 | M200: 33 | N200: 12 | O200: 28282 | P200: 8 | Q200: 連載中
A201: 異世界ファンタジー | B201: 100 | C201: 継続 | D201: 婚約破棄された加護なし令嬢、前世の知識で絶品あったかご飯を作ります～嫁ぎ先の極寒の隣国で、皆から恐れられる【狂犬皇子】が、毎食おかわりを要求して離してくれません | E201: 茨木野 | F201: https://kakuyomu.jp/works/2912051606588785996 | G201: 魔力ゼロだけど、前世の料理スキルと知識で無双します！ | H201: 「レティシア……お前との婚約を破棄させてもらう！」 婚約者である王太子マナヤから一方的にそう告げられ、聖女カスミィにその座を奪われた公爵令嬢レティシア。 ここが乙女ゲームの世界であり、自身が『加護なし』のコンプレックスから性格を歪ませる悪役令嬢であることは、幼少期に前世の記憶を取り戻した時から知っていた。 前世の記憶のおかげで心が歪むことはなく、ただ大好きな料理を作りたかった彼女。 しかし、厳しい王妃教育に縛られ、厨房に立つことすら許されない日々を送っていた。 だからこそ、婚約破棄を突きつけられた彼女の胸の内は……大いに歓喜していた。 （ これで王妃教育から解放される！） 厄介払いとして、極寒の隣国にいる【狂犬皇子】ルークの元へ嫁がされる過酷な条件ではあったが、自由に料理ができるのならと、彼女はあっさりと婚約破棄を受け入れる。 そうして極寒の地へ降り立ったレティシアは、さっそく温かいご飯を作るべく腕を振るい始める。 旨味たっぷりの野菜ポタージュ、肉汁溢れるハンバーグに、ふっくらと焼き上げた発酵パン。 前世の知識と丁寧な下ごしらえから生まれる「あったかご飯」。 その美味しそうな匂いに釣られ、辺境の人々のみならず、魔力の塊である精霊たちまでもがこぞって彼女の周りに集まってくる。 そして、人間不信で周囲から恐れられていた狂犬皇子ルークもまた、彼女の作る優しく温かい料理に、凍てついていた心を溶かされていき――。 「……おかわり、あるか？」 いつしかルークは毎食おかわりを要求するようになり、レティシアを心から溺愛し、手放せなくなっていく。 一方その頃、婚約破棄を成し遂げて浮かれているマナヤは、加護を持たずとも料理を通じて精霊たちから深く愛されていたレティシアを失ったことで、自分たちの王国が徐々に傾いていくことに、まだ気づいていなかった……。 ※小説家になろうでも掲載してます。 | I201: 812 | J201: 女主人公|チートなし|婚約破棄|ざまぁ|追放|溺愛|グルメ|もう遅い | K201: 428 | L201: 27 | M201: 27 | N201: 17 | O201: 94757 | P201: 13 | Q201: 連載中
C202: 圏外落ち | D202: スキルのせいで性別も種族も変わったんだが？！ | E202: おでんの中のがんもどき | G202: 期待して手に入れたスキル…それは『魔女』いやいや、俺男なんだが… | H202: 時は近世…ではなく魔法と科学の発達した現代。この世界では神代の時代からダンジョンというものがある。そんな世界だ。 自分。乙女ヶ崎 夢(おとめがさき ゆめ)はダンジョン配信者を目指しているただの高校生。『一攫千金！』というバカみたいな夢を掲げ毎日ダンジョンについての勉強を行ってる。そしてダンジョン配信者になるためには15歳に鑑定の儀というものを行い、スキルの発現をさせないといけない。 「さて、俺の番ってかねぇ…。何が出るかなっと！」 …そこで目にしたものとは？
C203: 圏外落ち | D203: 喫茶店のマスターはバイトのJKを救うためにダンジョンへ向かうそうですよ？～ダンジョン配信で人気の女子高校生を救ったおじさん、実はダンジョン黎明期を戦って今の日本を作った生きる伝説でした～ | E203: リヒト | G203: 最前線から退いても最強のおじさんは、バイトのJKと共に今一度成り上がる | H203: 飯野可憐は、今を時めく女子高校生ダンジョン配信者だった。 高校生離れした高い実力と、可愛らしい容姿。 その二つを武器に、瞬く間に人気を集めた彼女はこのまま順調に実力を磨き続ければ、日本を代表する探索者になると誰もが思っていた。 しかし、ある日の配信中。 「……い、いやっ！」 イレギュラーと呼ばれる圧倒的な力を持つ魔物と遭遇し、可憐は為す術なく追い詰められてしまう。 絶体絶命。 そんな彼女の前に現れたのは、 「ご無事ですかな？」 一人の冴えない中年男性だった。 「何でマスターがここに！？」 その男の名は、神崎健一。 可憐が人気配信者になるよりも前からバイトしている売れない喫茶店のマスターだった。 売れない喫茶店を構える冴えないオジサンだと思っていたその人物の正体。 それは、ダンジョンが出現したばかりのファンタジー黎明期の日本で最強の探索者として君臨し、幾多の命を救って日本のダンジョン攻略の礎を築いた───生きる伝説だった。 一度は最前線を退き、静かな喫茶店のマスターとして余生を過ごしていた神崎健一。 しかし、女子高校生ダンジョン配信者を救ったその瞬間。 忘れられていた英雄の名が、再び日本中を駆け巡る時、また一つ、世界が変わっていく───。
C204: 圏外落ち | D204: いきなり許嫁候補！？ ～分家序列最下位からの成り上がり？！私、望んでませんから！ほっといてくださいよ！～ | E204: 天野建 | G204: 記憶を持ったまま、転生した！？ よろしい！先行逃げ切りを目指そう！ | H204: 私は前世、戦場で死んだー。 これでやっと休めると思ったら、次の瞬間には生まれ変わっていた。 なんだと！？少しは休ませて欲しいのである！ それになんということか！ 生まれた世界は、前世とはまったく異なっていたのである！ そこには馬もつけずに高速で走る乗り物、車なるもの。 金属の平面に、人間が入り込み情報を無限に発するもの、テレビなるもの。 私が驚愕する数々の文明の利器が、この世界にはあったのである！ この世界でなら、前世死ぬ直前に思った願いがなせるかもしれない！ 何かなしたかったという、曖昧な望みがな！ はははは！ 曖昧な望み！大いに結構である！ 私はその望みを胸に奮い立つ！ 私は早くからの努力を惜しまない！ そう、赤子からでもだ！ ……そう思っていた時もありました。 その気持ちは忘れてはいない。 けれど、この世界を楽しまねば、生まれてきた意味なし！ せっかく自由な世界に生まれてきたのである！ 少しはのんびりしても問題なかろう？ はっ！父よ！今なんと！本家からの招待状（命令書）が届いた！？ 本家の跡取り息子、７才の許嫁を選ぶ為、儀式に１８才までの分家の女子は全員参加せよ！？ 分家である我が家灰咲家。私は５才。本家の命令は絶対である。 断ることなどできはしない。きな臭くなってきたのである。 が、父曰く、我が家は分家序列最下位。その上、末流の末であるとのこと。 ならば、許嫁に選ばれる可能性は限りなく低かろう！ よかろう！若君の許嫁を選ぶ儀式とやらに参加しようではないか！ ５才になり、初めての遠出、新しい情報が満載に得られよう！ そして！本家は金持ちであると聞いている。我が家では食べられぬ美味なるものが、私を待っていよう！ それらを存分に味わいに行くのである！ ああ！！何事であるか！？予定外の事が起ったようである！ 本家の方々、速やかな解決をお願いする！ え！？無理そう！？ 仕方ないのである！私が手を貸そうではないか！！ この作品は、小説家になろう、ハーメルンでも掲載。
C205: 圏外落ち | D205: 領地を救うため命を捧げた俺、忘れてほしいのに許嫁も聖女もメイドも誰ひとり忘れてくれない 〜俺の記念日を作るとか、聖人認定するとか、復讐するとかやめてください〜 | E205: 三船十矢 | G205: 「誰も彼も、あなたを忘れられないようにしますから」 | H205: ヴェイル・アスフォルムは、キャラが死にまくる鬱ゲーＲＰＧ『煉獄聖騎士アルベルト』の悪役令息に転生した元サラリーマンである。原作では今日、地下で地脈の封印が破れ、領地が壊滅する。このままだと許嫁のヘラも、聖女ミレイユも、メイドで元暗殺者のリアナも死んでしまう。 ヴェイルは「俺のいない世界で、俺を忘れて、君らしい幸せをつかんで欲しい」と親しい彼女たちに手紙を送り、己の命を犠牲に地脈の暴走を封印する。 全てを救い、死んだ――はずが、なぜか霊体となって目を覚ます。誰にも見えず、声も届かないが、災害で壊れた土地に干渉して癒せる存在に！？ 一方、ヴェイルの死を嘆き悲しんだ３人も、重い感情を抱えたまま動き出す。許嫁は「ヴェイルの名を国史に刻む」と国家規模の政治工作を始め、聖女はヴェイルを信仰の対象として祭り上げ、メイドは「ヴェイル様を追い詰めた人間は殺す」と暗躍を始める。 「そんなことしないでいいから！ 俺のことなんて忘れていいから！」 そう届かない声で叫ぶも、誰ひとり忘れてくれない。おまけにコソコソ進めていた領地の復興作業まで『ヴェイル様の奇跡』として語り継がれ、領民たちによる神格化まで留まることを知らず――！？
C206: 圏外落ち | D206: 異世界転生･･････ってマイナススタートかよ!?〜前世でも嫌われ、転生先でも嫌わている俺は自由を掴むために好感度を稼ぐ〜 | E206: ドラゴロイド | G206: 前世でも転生しても嫌われるのは勘弁だぞ!? | H206: 男の人生は最悪だった。 告白されたと思ったら罰ゲームであり笑いものにされ、 自分から告白して付き合った女性は寝取られて、 また告白されたと思ったら･･････冤罪で襲った罪を着せられて、 家族や友達にも信じてもらえず、最後は自分自身の手で人生に幕を引いた･･････だったんだが、 「･･････ここはどこだ?」 気がついたらふかふかなベッドに豪華な装飾。 これは異世界転生ってやつで俺は勝ち組なのでは!? と思ったら、めっちゃ嫌なやつだったらしく婚約者やメイドとめっちゃ嫌われていたのだ。 「前世でも嫌われて、今世もそうなのかよ!?」 もうあんな惨めな目に遭うのは嫌だ!! 俺は自由に生きたいんだ!! これは前世でお祓いが必要レベルで地獄だった男が、 転生先で幸せを手に入れるために好感度を稼ぐ･･････はずが、 何故か好感度が異常に上がって依存される存在になってしまう物語。
C207: 圏外落ち | D207: 「今日で英雄辞めます」世界を裏から救っていた第零魔法師が学園へ青春しに行った結果、残された国家上層部が崩壊寸前なんだが？ | E207: kuni | G207: 世界を救うより、放課後に友達と買い食いする方が難しい | H207: 「陛下、約束通り――今年から学校に行かせていただきます」 歴史の影で数々の厄災を葬り、世界を救い続けてきた国家最高戦力《第零魔法師》レイン・アークライト（17歳）。 功績のすべてを他人に譲り、命がけで働き詰めてきた彼のささやかな夢――それは、 「放課後に友達と買い食いがしたい。学食の日替わり定食を一緒に食べたい」 という、ごくごく普通の【青春】を送ることだった！ 魔力量の測定結果は、狙い通りの「凡庸なＣランク」。 周囲のエリート貴族たちから「平民の落ちこぼれ」と見下されても、レインは内心ガッツポーズ。 （よし！ 完璧な一般生徒だ！ これで友達ができるぞ！） だが、彼の本当の異常さは『１の魔力で１万を出力する異常効率』と『神の魔法式すら書き換える消去眼』。 学園で次々と起こる魔獣の襲撃や暴走事故に対し、レインは全力で【隠蔽工作】を開始する！ 「あ、ゴーレムが爆散したのは設備の老朽化です！」 「結界が強化された？ たまたま風向きが良かっただけですよ！」 ――一方その頃。 レインが抜け、一人で維持していた国家防衛結界の真実を知った上層部は、未曾有の大パニックに陥っていた……。 最強の力を持つ少年が、平穏な青春を守るために全力で「凡人」を演じ抜く、勘違い＆隠蔽系学園ファンタジー、開幕！

Sheet 順位上昇
A1: genre | B1: rank | C1: rank_prev | D1: rank_change | E1: title | F1: catchphrase | G1: あらすじ | H1: author | I1: star | J1: star_gain | K1: star_per_day | L1: ep_gain | M1: elapsed_days
A2: 現代ファンタジー | B2: 30 | C2: 50 | D2: 20 | E2: ダンジョンで拾った卵から生まれた少女に「ぱぱ」と懐かれたので育てることにした――なお、危険度は国家消滅級らしい | F2: 周り「絶対に刺激するな」少女「ぱぱ、だっこ」 | G2: ダンジョン探索中、ソロ探索者の結城朔は、地図には存在しない小部屋で一つの卵を見つける。 魔物の卵なのか、それとも未知のアイテムなのか。鑑定してみても結果は『測定不能』。どう考えても怪しく、関わらない方がいいはずだった。 ところが、朔がどうするか迷っている目の前で、卵にひびが入る。 「……割れた？」 殻の中から現れたのは、魔物ではなかった。 銀色の髪をした、小さな少女だった。 少女はしばらく朔の顔を見つめると、嬉しそうに両手を伸ばす。 「……ぱぱ？」 「違う」 「ぱぱ！」 「だから違うって」 なぜか完全に父親だと思われ、そのままとんでもなく懐かれてしまう。 しかも、この少女――ミアは、どうやら普通の子供ではない。 朔では苦戦するはずの魔物が、ミアを見るだけで逃げ出す。地図に存在しない通路を見つけ、誰にも開けられなかった扉を当たり前のように開いてしまう。 そして朔に危険が迫った時だけ、ダンジョンそのものが異常な反応を見せる。 さすがに何かがおかしい。 そう考えた朔がミアを探索者協会で詳しく調べてもらった結果、告げられた判定は想像を遥かに超えていた。 ――推定危険度、国家消滅級。 「……嘘だろ？」 「ぱぱ、だっこ」 国家消滅級と言われても、朔の腕の中にいるのはどう見ても甘えん坊の小さな女の子だ。 ただ一つだけ、確かなことがある。 あの卵を拾った日から、朔の知っているダンジョンは、もう以前と同じ場所ではなくなっていた。 | H2: アリババ | I2: 144 | J2: 23 | K2: 23 | L2: 1 | M2: 5
A3: 現代ファンタジー | B3: 70 | C3: 89 | D3: 19 | E3: ダンジョンの最下層に落ちた俺は神からいただいたスキルで最強になる･･････のに周りから化け物扱いなんだけど!? | F3: 突如足元が崩落→ダンジョンの最下層に落ちる→結果、化け物誕生 | G3: 高校1年生の波多野 弘大(はたの こうた)はある日、 親のお使いで外に出ていたときに謎の地震によって理由もわからないところに落とされた。 そこには大好きなラノベとかで読んでいる異世界のような場所だったのだ。 いきなりそんな場所に、何の武器とかもない弘大は息を殺して逃げることしかできなかったのだが、ある場所にたどり着いてしまう。 石碑のような場所であり、そこから現れたのはなんとこの世界の神という少女が。 神様いわく、 ①どうやら、この地球が資源が枯渇してしまいいずれ滅びの一途をたどる!? ②そこで目をつけたのが、別の星の管理をしている神が生み出したダンジョンとのこと。 ･･････つまり、現在俺はこの神が生み出したダンジョンの最下層に落とされてしまったらしい。 そして、俺はその神様から最初の最下層到達記念としてあるスキルをもらい地上に帰還する。 これは不運でダンジョン最下層に落ちてしまった男が世界最強になるまでの物語です。 | H3: ドラゴロイド | I3: 85 | J3: 24 | K3: 24 | L3: 1 | M3: 5
A4: 現代ファンタジー | B4: 80 | C4: 99 | D4: 19 | E4: 大切な家族を守ります 世界崩壊サバイバル ～俺だけドロップテーブルが見える～ | F4: 食料も、薬も、おむつも。今は魔物から手に入れろ！ | G4: 世界が崩壊した日、朝倉かなめが手に入れたのは《ドロップ》というギフトだった。 魔物を見るだけで、何を落とすのかが分かる《ドロップテーブル》。 ゴブリンなら食料や医療品。 角ウサギなら日用品。 別の魔物なら、燃料や装備まで。 そして《運》を上げれば上げるほど、より希少なもの、より自分に必要なものが手に入りやすくなる。 力を上げれば、自分は強くなれる。 体力を上げれば、生き残りやすくなる。 それでも、かなめが選んだのは――《運》だった。 自分一人が強くなるより、妻と一歳の娘が生きるために必要なものを持ち帰りたい。 食料が足りなければ、食料を落とす魔物を狩る。 薬がなくなれば、医療品を落とす魔物を探す。 娘のおむつが必要なら、日用品を落とす魔物を狙う。 そして足りない戦闘力は、ドロップした装備で補えばいい。 停電した街。 止まった物流。 あふれ出した魔物。 昨日まで金を出せば買えたものが、もう店にはない。 だから今日も、かなめは必要なものを落とす魔物を探しに行く。 家族三人で、この崩壊した世界を生き残るために。 | H4: 月瀬リュカ | I4: 80 | J4: 4 | K4: 4 | L4: 1 | M4: 5
A5: 現代ファンタジー | B5: 74 | C5: 87 | D5: 13 | E5: 悪役令嬢（本物）ですが、現代ダンジョンで高飛車に配信したらツンデレお嬢様と崇められてスパチャが止まりませんわ！ | F5: この汚ねえアンチコメントは何ですの？ | G5: ​「オーホッホッホ！ この程度の魔物、わたくしの敵ではありませんわ！」 ​乙女ゲームの悪役令嬢エレオノーラは、断罪の果てに現代日本の「底辺ダンジョン配信者」の少女へと転生した。 魔法も失われ、気品もなきこの荒廃した世界で、彼女は決意する――「この現代社会でも、わたくしが頂点に君臨して差し上げますわ！」 ​手始めにダンジョンへ乗り込み、圧倒的な細剣術と魔術でモンスターを華麗に蹴散らしていくエレオノーラ。 高貴な高飛車スタイルを一切崩さない彼女の配信に、ネット民（リスナー）は一瞬で大騒ぎとなる。 ​『うわぁ……痛いキャラ作り配信者だ……』 ↓ 『待って、剣術のキレがガチすぎるんだが！？』 ↓ 『高額スパチャ投げたら「わたくしを金で買う気ですの！？」って本気でブチギレられたｗｗｗ』 ↓ 『「ツンデレ助かる」「神のレスバ」「もっと罵って」』 ​本人は大真面目に下民（現代人）を見下し、金を積んでくる無礼者に激怒しているだけ。 なのに、育ちの良さからくる「礼儀正しさ」と「圧倒的な実力」が裏目に出て、リスナーからは「てぇてぇ神ツンデレ」「煽りの語彙力が高貴すぎる」と大絶賛！ ​アンチを気品あるレスバで黙らせ、高額スパチャ（お小遣い）の嵐にパニックになりながら、彼女はいつの間にか世界を熱狂させる伝説のS級配信者へと駆け上がっていく～？ | H5: 冰藍雷夏(ヒョウアイライカ) | I5: 116 | J5: 18 | K5: 18 | L5: 1 | M5: 7
A6: 異世界ファンタジー | B6: 76 | C6: 89 | D6: 13 | E6: クラスで集団異世界転移。毎日ゴミ拾いしていたことで善行ポイントがカンストしてたので、ポイント消費して強さよりも生き残ることを優先します。 | F6: 毎日のゴミ拾いで善行ポイントがカンストしてた。 | H6: 雪風 | I6: 111 | J6: 17 | K6: 17 | L6: 0 | M6: 5
A7: 現代ファンタジー | B7: 42 | C7: 54 | D7: 12 | E7: 寄生虫と行く現代ダンジョン | F7: 選択肢は無い、バレる前に強くなれ | G7: 現代日本に、突如としてダンジョンが発生した。 危険な異形、未知の鉱石、現実ではありえないアイテム。政府も企業も対応に追われる中、世間では未発見の入口を探す者たちが現れ始めていた。 三十歳の会社員である主人公には、夢も目標もなかった。家庭もなく、熱中できる趣味もない。ただ働き、ただ日々を過ごすだけの人生。そんな彼の心を、ダンジョンという未知の存在が初めて強く揺さぶった。 今逃したら、一生後悔する。 その思いに突き動かされ、主人公は会社を辞める。退職までの有休消化期間、彼は最低限の装備を整え、未発見のダンジョンを探し歩いた。 そしてある日。 人目につかない場所で、彼はそれを見つける。 現実には存在しないはずの入口。暗闇の奥から、冷たい空気が流れ出している。 報告すれば、ここはすぐに封鎖される。自分はただの第一発見者で終わる。 少しだけなら。 そう自分に言い聞かせながら、彼はダンジョンの前に立っていた。 高鳴る鼓動は胎動にも似ていた。 本作はAIを設定・プロット相談、本文草稿・改稿、文章検査、資料整理に使用。方針決定・採否・加筆修正・最終稿確定は作者が行っています | H7: ＠脳タリン | I7: 1222 | J7: 19 | K7: 19 | L7: 2 | M7: 77
A8: 現代ファンタジー | B8: 88 | C8: 100 | D8: 12 | E8: 就職氷河期オブ・ザ・デッド ～世界は酷い有様だけど、異世界で魔王を倒した用務員のおじさんがモテモテに。なお、世界が救われるかは不明～ | F8: ゾンビ溢れる世界で、就職氷河期おじさんがモテモテに | G8: 就職氷河期世代として苦労し、今はとある地方の有名エリート私立高校の用務員を務める伊作 幸三（いざく こうぞう）、４９歳。 彼は多くの生徒たちからバカにされる存在であったが、唯一ギャルの格好しているために校内で浮いている、白井 瑠璃（しらい るり）とは用務員室でよく話す間柄であった。 もうすぐ夏休みという時、幸三が仕事を終えて自宅アパートで就寝して目が覚めたら異世界へ。 自分を召喚した王様の命令で魔王を倒し、褒美を貰って元の世界に戻ってきたら、一晩しか時が経っていなかった。 残りの人生、用務員なんて辞めて褒美を売ったお金で遊んで暮らそう期待に胸を膨らませる幸三であったが、なんと部屋の外はゾンビだらけで、異世界で上げたレベルも１に戻っていた。 「……生き残るのが優先だ！」 魔王を倒して戦闘経験豊富な幸三は次々とゾンビを倒してレベルを上げ、残りの人生を快適に暮らせるよう、あちこちに移動して可能な限り必要な食料、物資などを集め続けた。 「祖父さんが住んでいた、山奥の村に行くか……」 ある程度レベルを上げ、大量の物資を『アイテムボックス』に集めた幸三にゾンビを殲滅して世界を救う気なんてなく、祖父の実家がある廃村を目指す。 だがその前に、白井 瑠璃が生きているか気になってしまったので、職場である学校を目指すことに……。 そして彼女を探している途中、また別の美少女を助けてしまう幸三であった。 「ゾンビにされるところを助けていただき、ありがとうございます」 「（しまった！ 先のことをまったく考えていなかった！）」 その後、瑠璃とも合流できたのはよかったが、幸三は二人の安全を確保するために奔走することに。 このお話は、ゾンビ溢れる現代世界を、就職氷河期のオジさんが美少女や美女たちと共に生き抜いていく物語である。 小説家になろうと、カクヨムに同時連載開始！ 目指せ！ 漫画原作！ | H8: Ｙ．Ａ | I8: 2327 | J8: 15 | K8: 15 | L8: 0 | M8: 78
A9: 現代ファンタジー | B9: 79 | C9: 90 | D9: 11 | E9: 魔剣を拾ったら中身が飯にしか興味のない生意気少女だった 〜無限の魔力と空間魔法でダンジョン無双〜 | F9: 「力が欲しいか‼︎ 力が欲しいなら……飯をくれ!」 | G9: ダンジョンの奥底で拾ったのは最強の魔剣。それは装備したものに無限の魔力を与える。 しかしその正体は飯にしか興味のない生意気少女だった。 荷物持ちとして捨てられた俺は、この生意気な相棒と無限の魔力、目覚めたチートスキル空間魔法EXでダンジョン無双を始める。 チート無双×ダンジョン×飯テロ、開幕。 毎日7:10投稿 2026.8.24 ⭐︎祝22,000PV⭐︎ 2026.8.29 ⭐︎祝30,000PV⭐︎ 2026.9.01 ⭐︎祝40,000PV⭐︎ 応援ありがとうございます😭 | H9: 竜刃丸 | I9: 206 | J9: 11 | K9: 11 | L9: 1 | M9: 41
A10: 現代ファンタジー | B10: 56 | C10: 66 | D10: 10 | E10: 世界樹ダンジョンで囮にされた僕、風精霊と同化して銀髪美少女へ 〜学園では落ちこぼれDクラスなのに、配信者を救いまくっていたらネットの神になっていた件〜 | F10: 落ちこぼれDクラスの銀髪美少女、実は同接200万の救世主でした | G10: 「おいアルト、お前ここで囮な」 世界樹ダンジョン深層で、所属クラン『剛腕の鉄血隊』に囮として切り捨てられた少年・一ノ瀬アルト。 瀕死の底で彼が出会ったのは、消えかけていた風の大精霊の核だった。 自身の固有スキル『魔力調律』で精霊を救おうとした瞬間――魂が完全同調し、アルトは白銀の髪を持つ美少女『ノア』へと新生・受肉してしまう。 人智を超えた権能【大気統律】を手に入れたノアは、地上への帰還途中に超人気美少女配信者・水無瀬マリンの遭難現場に遭遇。 白い仮面で素顔を隠し、災害級の変異種を一瞬でサイコロステーキにして立ち去る。 ――その様子が全世界200万人に生配信されていたとも知らずに。 ネット上では「世界樹の守護天使」「翠光の仮面様」と崇められ、カルト的人気で神格化されていく一方、当の本人は探索者学園の支援科（2年Dクラス）へ編入。 「目立たず平穏に、学食のかけうどん（200円）を食べて暮らしたい……！」 そう願うノアだったが、オタクな回復術士、大型ワンコ系闇タンク後輩、氷の生徒会長、そして過保護な元Sランク担任教師に囲まれ、日常でもダンジョンでも無自覚に規格外の存在感を発揮してしまい――！？ ※元男子のお荷物サポートが、TS美少女精霊として無双しながらネットの神になるお話です。 ※元仲間へのざまぁ・学園無双・配信バズ・掲示板要素を含みます。 | H10: あかぱん | I10: 86 | J10: 9 | K10: 9 | L10: 2 | M10: 6
A11: 異世界ファンタジー | B11: 64 | C11: 73 | D11: 9 | E11: 俺の幼馴染婚約者が勇者と夜の聖騎士団を結成していた件について。長ネギ1本から復讐します。 | F11: 婚約者は勇者のハーレムへ。俺に残されたのは、長ネギ一本。 | G11: 幼馴染で婚約者の松阪蘭子とともに異世界へ転移させられた四日市習作。目的は「勇者レオンを支える人材」の確保。蘭子はユニークスキル《聖騎士》を授かり王国中から持て囃されるが、習作はスキルなし、ステータス補正なしの完全な「ハズレ」だった。 「君のような無能はいらない」——王宮から追放された習作を、蘭子は一瞥もしなかった。 放浪の果て、死に際の旅芸人から知らされる世界の裏側の法則。「能力は、他人からたった一つだけ譲り受けられる」。彼が遺してくれたのは《長ネギを自由に生成する能力》。誰もが嗤うその力の、本当の恐ろしさに気づいた時、習作の復讐が始まる。 一方その頃、蘭子は勇者のハーレム「夜の聖騎士団」の一員として魔王討伐へ。しかし旅の途中、団員九名が全員身籠り、討伐は無期限中断。王国の威信は音を立てて崩れていく。 先に魔王城へ辿り着いた習作は、長ネギの暴威で四天王を撃破。魔王をも下し、魔王の娘ゼオラを娶って「真なる魔王」として君臨する。 これは、世界に捨てられた男が、長ネギ一本から世界のすべてを奪い返す物語。 | H11: すーぱーりっかちゃん | I11: 711 | J11: 53 | K11: 53 | L11: 1 | M11: 28
A12: 異世界ファンタジー | B12: 65 | C12: 74 | D12: 9 | E12: 魔力値１で生まれた令嬢は――死んでたまるか！ | F12: 死んでたまるか！ ど根性令嬢は、自立を目指す | G12: ケミライネン子爵家の長女イルヴァは、生まれ持つ魔力値が１と診断された。事実上、有効な魔法を使うことができない値だ。 七歳になって「空間」という加護を得るが、その加護を使用したとたん魔力値を使い果たし、命に関わるとされる。 結果、イルヴァは出来損ないとされ、実母の死後、父と後妻の企図で領地邸の一室に閉じ込められる。食事も最低限に減らされ、さまざまな事情で自然死を願われているらしい。 餓死寸前に追い込まれたイルヴァは、命をかけた選択を決意する。 | H12: eggy | I12: 622 | J12: 38 | K12: 38 | L12: 0 | M12: 26
A13: 現代ファンタジー | B13: 39 | C13: 48 | D13: 9 | E13: 元パーティに置き去りにされた運び屋、配信切り忘れで実力バレ | F13: 荷物持ちの本気、全国配信中 | G13: 不遇職「運び屋」として、人気探索者パーティの後方で荷物持ちを続けていた鈴木悠作。 戦闘には参加させてもらえず、配信では画面外に追いやられ、手柄も認められない。それでも悠作は目立つことを嫌い、最低限の仕事だけを淡々とこなしていた。 だが、新宿第七ダンジョンの中層攻略中、悠作は元パーティに危険地帯で置き去りにされる。しかも、その様子は配信機材の切り忘れによって視聴者に流れ続けていた。 単独で帰還しようとする悠作の前に、本来なら複数人で挑むはずの中層ボスが現れる。誰もが絶望する中、悠作は虚無顔のまま最小限の動きでボスを処理し、何事もなかったように素材を回収する。 その一部始終は全国に拡散され、SNS、切り抜き、Vtuberの同時視聴、探索協会の記録確認を巻き込んで大炎上と大バズを引き起こす。 本人はただ帰りたかっただけ。 だが世間は、彼をもうただの荷物持ちとは見てくれない。 元パーティの過去発言は掘り返され、探索協会は彼の記録を見直し、配信者やVtuberたちは次々に彼の実力へ気づいていく。 これは、目立ちたくない運び屋が、配信事故をきっかけに正当評価され、元パーティの信用を記録と実力でひっくり返していく、ダンジョン配信系爽快コメディ。 ※実力S級の俺のリメイク版です。 | H13: 伊達ジン | I13: 2940 | J13: 13 | K13: 13 | L13: 0 | M13: 53
A14: 現代ファンタジー | B14: 34 | C14: 42 | D14: 8 | E14: 世界最高峰の大賢者、失声症の少女に転生する | F14: 不器用でも、不便でも、この気持ちが伝わるのなら… | G14: 無数にある世界のうちの、たった一つの小さな世界。 そこには『大賢者』と呼ばれ、その身を犠牲に、魔王を討ち滅ぼした男がいた。 彼は死んだはずだった。魔王と共に。これからの世界に自分は必要ないと、そう信じて。 しかし、何の因果か、そして何故そうなったかも知らぬまま、彼は再び目を覚ました。 『地球』という世界で。失声症を患った幼き少女として。 かつて魔王を打ち破った『大賢者』は、ダンジョンが存在する現代世界で戸惑いつつも生きていく。 魔法の行使に必要不可欠な詠唱ができずとも、前世の経験を活かし、地球の常識を打ち砕きながら。 | H14: パパ目 | I14: 220 | J14: 32 | K14: 32 | L14: 1 | M14: 13
A15: 異世界ファンタジー | B15: 43 | C15: 51 | D15: 8 | E15: のんべえ令嬢のニッポン飲み歩き！！ーオフの日は異世界から、愛するグルメ天国ニッポンへ。美味しいもので逆無双しますー | F15: 完璧なご令嬢？ただの呑兵衛です。 | G15: 誰もが羨む完璧な公爵令嬢ディアーヌ。 彼女には休日の密かな楽しみがあった。 愛するグルメ天国「ニッポン」でご機嫌な呑兵衛と化したご令嬢が日頃のストレスを癒すため、美味しいものを飲みまくり食べまくる。 ニッポンで得た「食」の知識は、やがて異世界で起こる様々な問題を解決するヒントになっていく。 商人の揉め事、魚の流通問題、王都の新しい市場。 そんなある日、異世界の住人がディアーヌの「ニッポン通い」に気づき始め――。 美味しいものを食べるのも、一人で飲むのも、自分らしく生きるため。 異世界令嬢の、ちょっと変わったグルメライフ。 ※お店はモデルはありますが実在はしません。 | H15: ちくわ族の生き残り | I15: 675 | J15: 55 | K15: 55 | L15: 1 | M15: 15
A16: 異世界ファンタジー | B16: 84 | C16: 92 | D16: 8 | E16: 流れ者のおっさん、なんか強い。 | F16: 何事も過程こそが楽しい | G16: 孤児オルランドは、貧しさから逃れるため、剣で身を立てることを決意する。行商人の馬車に忍び込み護衛を押し売り、都で冒険者を経験したのち傭兵に転向。数々の戦役で武功を立て、貴族に召し抱えられ、叙勲を受け、騎士となり、名誉ある銀獅子団の長を努めた。 その後、狼の騎士団を設立、王国最強の戦闘集団として名を馳せる。ひいては予言の災厄、暗黒竜を討つため、王国中から選び抜かれた英雄集団『竜滅隊』に抜擢され、見事これを討ち、王国の滅びすら防いだ。 そして、今回、伝説の英雄オルランドは、王の勅命により、南方にて全七軍総兵力120万からなる蛮族蹂躙大軍を指揮することに。これは膠着した南方戦線に決定的な一撃を加え、王国の支配を盤石にする侵攻だったが──。 「……えー、全軍撤退」 全軍司令官オルランド公爵は、なんの気の迷いか全軍に撤退命令を残し、忽然と姿を消してしまった。 これは成り上がり終えて「コレジャナイ」と悟ったおっさんが新しい冒険を始める物語。 | H16: ファンタスティック小説家 | I16: 177 | J16: 10 | K16: 10 | L16: 0 | M16: 4
A17: 異世界ファンタジー | B17: 55 | C17: 62 | D17: 7 | E17: 「マスター、このままだと潰れちゃいますよ」って言われるために弱小ギルドを立ち上げたら、なぜか周りが勝手に最強ギルドを作ろうとしているんですが？ | F17: ギルド内にカフェを作った結果、なぜか最強ギルドができてしまう | G17: 「マスター、このままだと潰れちゃいますよ」 前世からの俺の夢は暇な喫茶店のマスターになることだ。 閑古鳥の鳴く店内でバイトの子に呆れられながらも、お気に入りの音楽を流してまったりとした日々を送る。 そんな夢を叶えるために俺は自ら弱小ギルドを立ち上げた。 目指すのは客も依頼も少ないのんびりとしたギルドライフ。 そのだったはずなのに……。 「マスター、このままだと潰れちゃいますよ！」 「そうか、潰れちゃうほど経営が危うくなったんだな」 「違います！ 依頼が多すぎて手が回りません！」 「………………え？」 なぜかギルドは大繁盛。毎日のように上級冒険者たちが加入を志願してきたり、国からの依頼が舞い込んできたり。 やがて最強ギルドと称されることになって——、 「この身を賭してでも、このギルドを最強にしてみせます！」 「仕方がないですねぇ。聖女である私がギルドを大きくしてみせます！」 「お前が上を目指すってんなら俺たちが全力で支えるぜ！」 なぜギルドメンバーたちはこんなにもやる気があるのだろうか。俺はただ平穏な毎日を過ごしたいだけなのに。 「はぁ……コーヒー飲んで現実逃避しよ」 これは弱小ギルドで平穏に暮らしたいギルドマスターと、勝手に最強ギルドを目指して奮闘するギルドメンバーたちの勘違いギルド運営ファンタジー。 | H17: とおさー@ファンタジア大賞《金賞》 | I17: 519 | J17: 12 | K17: 12 | L17: 1 | M17: 26
A18: 異世界ファンタジー | B18: 88 | C18: 95 | D18: 7 | E18: 前世で遊んでいたアウトロー系アプリゲームのキャラクター達を召喚したら、いつの間にか裏社会のドンになっていたんですけど？ | F18: 私はただのオジさんですっ！（どうしてこうなったのですかっ！） | G18: ある日、主人公であるダルク・フィン・クヴィスト（３８歳）は潰れかけの冒険者クラン、黒竜の爪のクランマスターを引き継ぐ事となる。 本人は今までの恩もある為、潰れ行くと分かっていても残ってくれているメンバーの為にクランマスターを引き継ぐのだが、どうやらこれがダルクの持っている能力の解放条件だったようだ。 その能力とは前世でプレイしていたスマホゲーム『極悪道・天下統一』の能力を引き継ぐというものであった。 その結果ダルクはで極悪道・天下統一で手に入れたキャラクター達をこの世界に呼び出しクランの立て直しを図るのだが、気が付けば裏社会のドンへと上り詰めていたのであった。 | H18: Crosis@奴隷使役重版決定！！ | I18: 568 | J18: 23 | K18: 23 | L18: 0 | M18: 52
... A80: 異世界ファンタジー | B80: 8 | C80: 9 | D80: 1 | E80: 杖と剣の異世界に舞い降りた天才〜片田舎の少年は王都で神童となりて〜 | F80: 片田舎に眠っていた天才が解き放たれる | G80: 剣を尊ぶ騎士と杖を掲げる魔術師。二つの勢力が競い合う異世界に転生したリオンは、片田舎の孤児院で暮らしていた。彼は幼い頃から近所の老夫婦に剣と魔術を教わっていたが、二人が元剣聖と元賢者であることを知らないままだった。 十五歳になったリオンは王都を訪れ、騎士試験と魔術師試験を受験する。結果は――両方共にトップ合格。 『彼の才能がこちら側でよかった』 騎士と魔術師たちは互いにそう安堵していたが、リオンは片翼の天才ではなかった。王国史上初の快挙を成し遂げた少年を巡り、騎士公爵家と魔術公爵家は令嬢との婚約まで持ちかけて争い始める。そして周囲は、その未知の才能に翻弄されていくことになる。 「俺、資格を取りに来ただけなんだが……」 杖と剣──〝両翼の天才〟が今、舞い降りる。 | H80: 御子柴奈々 | I80: 1037 | J80: 214 | K80: 214 | L80: 1 | M80: 6

Sheet 順位下落
A1: genre | B1: rank | C1: rank_prev | D1: rank_change | E1: title | F1: catchphrase | G1: あらすじ | H1: author | I1: star | J1: star_gain | K1: star_per_day | L1: ep_gain | M1: elapsed_days
A2: 現代ファンタジー | B2: 87 | C2: 70 | D2: -17 | E2: ダンジョン配信のカメラマンをしている俺、S級美少女配信者が全滅しかけたので画角の外でボスを瞬殺したら、全部生放送に映っていました | F2: 「戦えないとは一度も言っていません」―カメラが捉えた最強のカメラマン | G2: 「俺は探索者じゃない。ただのカメラマンだ」 世界各地にダンジョンが出現し、探索者による攻略配信が一大娯楽となった現代。 久瀬直人（くぜ・なおと）は、探索者資格すら持たない底辺カメラマンとして、人気配信者たちの後ろを歩いていた。 戦闘能力はゼロ。荷物持ち同然。視聴者からも雇用主からも軽く扱われる存在。 ――だが実際は、戦う必要がなかったから戦わなかっただけだった。 ある日、直人はＳ級美少女パーティー《ルミナス》の攻略配信に同行する。しかし、予定されたボスの代わりに現れたのは、都市すら滅ぼす災害級魔物。 Ｓ級探索者たちが全滅寸前まで追い詰められる中、直人はカメラを地面へ置いた。 「カメラ壊したら怒られるよな……」 自分が画角から外れたことを確認し、災害級魔物を拳の一撃で瞬殺。 誰にも見られていない――はずだった。 ところが、その姿は鏡のような岩壁に反射し、すべて生配信に映っていた。 切り抜き動画は瞬く間に拡散され、底辺カメラマンは一夜にして世界で最も注目される男となる。 彼に命を救われ、専属カメラマンになってほしいと願うＳ級美少女・天城玲奈（あまぎ・れいな）。 直人の本当の力を昔から知る、黒髪の幼馴染・朝比奈結衣（あさひな・ゆい）。 彼を特例Ｓ級探索者としてスカウトしようとする、史上最年少の美人ギルドマスター・御堂綾香（みどう・あやか）。 直人を使い潰してきた会社や、彼の実力を認めない探索者たちが次々と接触してくるが、そのたびに配信と公式記録が圧倒的な実力を証明してしまう。 本人はただ、画角の外で静かにカメラを回したいだけ。 しかし、異常を起こし始めたダンジョンも、彼に惹かれる美少女たちも、もはや直人を放っておいてはくれない。 これは、誰にも注目されなかった底辺カメラマンが、その規格外の力を世界中に生配信され、最強の探索者へと成り上がっていく物語。 | H2: 沢田美 | I2: 269 | J2: 2 | K2: 2 | L2: 0 | M2: 19
A3: 現代ファンタジー | B3: 99 | C3: 83 | D3: -16 | E3: ウチの山に異世界の騎士が落ちてきた | F3: ウチの山に異世界の騎士が落ちてきた話 | G3: タイトルまんま。イケオジ小説コンテスト期間中、午後7時更新 ハーメルンでも掲載しています | H3: 道造 | I3: 284 | J3: 9 | K3: 9 | L3: 1 | M3: 12
A4: 異世界ファンタジー | B4: 96 | C4: 80 | D4: -16 | E4: この【オープンワールド】ってユニークスキル、実はヤバい気がする | F4: 【第一部完結！】そうか……物理バグとやらで人は死ぬのか…… | G4: １５歳になると神からランダムでスキルが与えられる世界で、 侯爵家の三男であるレオツ・スカイリーンは【オープンワールド】という 訳の分からないスキルを与えられてしまう。 【インターネット】みたいに「使えない」ユニークスキルか、と 落胆していたレオツだが、使っている内に気付く。 「あっ、これヤバい。ヤバいスキルですよコレは」 使えないはずのユニークスキルで（そこそこ）無双する感じのお話。 ただし敵もユニークスキルを使ってくるぞ！ 「時間停止するんだな、このボタンを押すと。で、ポーションをいっぱい飲んで回復して……」 「なんで心臓を突いたのに復活してるの！？」 「なんで俺は空中浮遊しながら全身の関節がひねり潰されてるのおお！？」 「ごめん、それ僕にも分かんないんだマジで。ハヴォ……何とかみたいな 神様のせいだって説明があったけど」 「そんな神様聞いた事ないよおおおあわびゅ！？」 ――世界を侵せ。望むままに。 | H4: 東出祐一郎 | I4: 3234 | J4: 18 | K4: 18 | L4: 1 | M4: 55
A5: 現代ファンタジー | B5: 49 | C5: 34 | D5: -15 | E5: 【悲報】遊び気分で厨二病ダンジョン配信者を始めたらバズってしまう。恥ずかしすぎるからたとえ幼馴染や家族だとしても絶対に正体がバレるわけにはいかない。 | F5: 助けた人が実は超人気配信者で俺の大捜索が始まってるんだけど！？！？ | G5: 中二病ダンジョン攻略ごっこをしていた零泉紫焔《れいせんしえん》は動きの無い配信に流石に飽きていた。2年経っても面白い出来事が無く、もうやめようと思っていたその時、イレギュラーモンスターが出現する。 そこでとある女性を助けたのだが、なんとその女性が実は超人気配信者で戦いの様子が全世界に発信されていた。 そして配信には中二病ごっこをして超カッコつける俺の姿が映っていて、世界中で俺の中二病ダンジョン攻略の姿が謎の黒仮面として話題になり、大捜索が始まることになる。 「絶対にバレたら終わる。俺の人生終わる。最愛の妹からはきっと冷えた目で見られるし幼馴染には笑われる......。絶対にバレないようにしないと......！」 「私の......私だけのカッコいい兄さんだったのに......！」 「しえんの凄さを知ってるのは私だけ。あとから出てきたぽっと出の女なんて許さないわ！」 これは恥ずかしさの故に黒歴史を絶対にバレたくない男の物語。 | H5: くるみ | I5: 1714 | J5: 6 | K5: 6 | L5: 0 | M5: 31
A6: 現代ファンタジー | B6: 47 | C6: 33 | D6: -14 | E6: 迷宮の大図書館に2000年間引き籠っていた大賢者の僕、迷い込んできた美少女ダンジョン配信者に見つかってしまう～失われた古代魔法を使ったらコメント欄が大混乱に～ | F6: 静かに本を読みたいだけなのに……世界が僕を見つけてしまった | G6: 2000年前、人類は魔法文明を築いていた。 しかし時は流れ、魔法は失われ、今ではダンジョン攻略もスキルと科学が主流の時代。 そんな現代の誰も知らない迷宮最奥──【大図書館】には、2000年間ひとりで本を守り続ける男がいた。 名前は──ラグロ＝バティーシャ 世界中の魔導書を読みつくし、失われた古代魔法を自在に操る最後の魔法使い。 「あー……そろそろ未読本が底をつきそうだ」 なんて考えていたある日、一人の美少女ダンジョン配信者が迷い込んできた 天井から落ちてきた彼女を、ラグロは何気なく魔法を使って助けてしまう。 「え、何今の？」「魔法じゃない？」「っていうかダンジョンに図書館！？」「どうなってんの！？」 彼女が回していた配信は世界中で大バズり。 静かに本を読んで暮らしたいだけなのに、政府、最恐探索者、研究者、はたまた配信者まで、正体不明の【図書館の主】を探し始める 迷宮図書館の大魔法使い×ダンジョン配信 | H6: 善知鳥 朧 | I6: 2164 | J6: 9 | K6: 9 | L6: 0 | M6: 19
A7: 現代ファンタジー | B7: 71 | C7: 57 | D7: -14 | E7: 超成長スキルを持って転生したけど、生まれる場所を間違えた | F7: 世界でただ一人妖魔を鏖殺できるムキムキと、翻弄される世界 | G7: 転生した俺には「超成長」のスキルがある。生命力、魔力、そして身体を成長させる優れたスキルだ。 しかし、これには一つ落とし穴があった。 俺が転生したのは現代日本で退魔バトルをする世界だったのだ。 そこで使われるのは「霊力」であって「魔力」ではない。 「超成長」の強みの半分は死んだ。 かくして俺は、めちゃくちゃ恵まれた身体と生命力を有した一般通過ゴリラとして退魔バトルの世界に関わることになってしまった―― | H7: 暁刀魚 | I7: 695 | J7: 0 | K7: 0 | L7: 0 | M7: 8
A8: 異世界ファンタジー | B8: 93 | C8: 79 | D8: -14 | E8: 魔王を倒して消えた勇者は一年後に帰還した。俺を死んだと思っていた四人のヤンデレが手放してくれない | F8: 俺は元の世界へ帰るつもりで消えた。彼女たちは、俺が死んだと思っていた。 | G8: 魔王を討ち、世界を救った勇者は、その直後に消えた。 神託に選ばれた勇者の一人でありながら、普段は弱く、面倒ごとを嫌う主人公。けれど仲間が死にかけた時だけ、彼は誰よりも強くなる。 魔王討伐の瞬間、主人公は前世で交通事故に遭った直前と同じ謎の光を見つける。元の世界へ帰れるかもしれない――そう信じて光へ飛び込んだ。 しかし次に目を覚ますと、そこは一年後の、同じ魔王城の玉座の間だった。 残された聖女、天才魔法使い、エルフのお姫様は、主人公が自分たちを守って死んだのだと信じていた。主人公は、旅の最初に自分を嫌っていた三人へ、わざわざ会いに行くつもりはない。勇者を辞め、幼馴染シスターの待つ故郷で静かに暮らそうとする。 けれど、主人公を失った一年で、彼女たちの愛し方は壊れていた。 「今度は、絶対に手放しません」 これは、死んだと思われた元勇者と、二度と彼を失いたくない四人のヒロインによる、重すぎる異世界帰還ラブファンタジー。 | H8: 秋雨 淳@毎日2回以上更新 | I8: 282 | J8: 6 | K8: 6 | L8: 1 | M8: 17
A9: 異世界ファンタジー | B9: 68 | C9: 56 | D9: -12 | E9: 転生料理人の最強グルメ領地経営 〜『役立たず』と捨てられた転生悪役貴族が、料理スキルで貧困村を大陸一の都市に変えるまで〜 | F9: ハズレスキル『料理』は斬撃も火炎も食事バフも扱える最強スキルでした | G9: ※感想、☆評価、作品フォローをしていただけますとモチベーションになります！ 暖かいコメント、レビューを頂けると嬉しいです！ タイトル・内容は変更する場合があります。 本作はフィクションです。 この物語は、法律・法令に反する行為を容認・推奨するものではありません。 コメントは削除することもあります。 コメントのアイデアを作中で利用することがあります。 暖かく応援してくださると嬉しいです！ | H9: 夜桜ユノ | I9: 3586 | J9: 13 | K9: 13 | L9: 1 | M9: 42
A10: 現代ファンタジー | B10: 41 | C10: 29 | D10: -12 | E10: 妻と上司に裏切られ事故に遭った俺、異世界で魔王と戦い死んで帰還する ～42歳元勇者、現実世界のクズどもに負ける要素が何一つない～ （ベースは：中年オヤジは元勇者！ 42歳から始まる勝ち組人生です） | F10: 本物の地獄を知る帰還勇者にこの世界の理不尽など一切通用しない | G10: 42歳のサラリーマン・今井泰章の人生はどん底だった。 体調不良で早退した家で目撃したのは、妻と尊敬する上司の不倫。味方だと思っていた娘にまで嘲笑われ、絶望のまま家を飛び出した泰章はトラックにはねられてしまう。 目を覚ました先は、人類が滅びかけている絶望の異世界。 勇者として戦うも……圧倒的な魔族の数を前に、泰章は無念の死を遂げた。 だが、再び目を覚ますとそこは日本の病室。経過した時間はわずか1週間。 人類滅亡の地獄を味わい、死線をくぐり抜けた泰章の精神と身体には「死闘の果てに得た力」が刻み込まれていた。 「あの時の絶望に比べれば、こんな事など大したことは無い」 異世界で敗れ、すべてを失った男が、現実世界の理不尽を圧倒的な力で粉砕する人生逆転劇！ 中年オヤジは元勇者！ 42歳から始まる勝ち組人生。【MFブックス】イケオジ小説コンテスト【中編】ように加筆修正した物です。 ですが、途中から大きく物語は変わります。 この作品は、誤字脱字 文章表現 など、推敲、校正の範囲のみGEMINIを使っています。 | H10: 石のやっさん | I10: 4685 | J10: 32 | K10: 32 | L10: 0 | M10: 10
A11: 異世界ファンタジー | B11: 63 | C11: 52 | D11: -11 | E11: スキル「ゴミ」いや、マジで | F11: ハズレスキルで召喚した前世のゴミは、異世界の宝の山でした | G11: 【ありがとう 総計１０００万ＰＶへ】 １２歳の誕生日に「前世が日本人の歴史ヲタの大卒者だった」って記憶を取り戻しちゃったオレは、大陸最大の国家「サスティナブル王国」の伯爵家の長男として生まれた。魔法もスキルって概念もなくて、オレだけが「スキル」を持っている。ただしスキル名は「ゴミ」。ゴミを出せるスキルだ。いや～ 驚いたし、最初はガッカリしたさ。 でもね、気付いちゃったんだよね。どんなゴミでも取り寄せられる「ゴミ」は最高のスキルだってこと。なにしろ、前世の日本のゴミは、お宝の山。公爵御三家の娘達を始め、高位貴族の美少女達を総取りして、今、スキル・ゴミの無双が始まる。行きがかり上、大陸統一を目指します。 大変長い物語なので、フォローしてお楽しみいたけると嬉しいです。 ※書籍版は、内政チートを主体にしています。 メインヒロインがバネッサちゃん。 ｗｅｂ版の大陸制覇とはテイストが違って 違うテイストをお楽しみください。 ＡＩ補助利用（誤字訂正と、ネタの計算に使っています） | H11: 新川さとし | I11: 7737 | J11: 17 | K11: 17 | L11: 0 | M11: 980
A12: 異世界ファンタジー | B12: 70 | C12: 60 | D12: -10 | E12: 辺境の無名は天才たちの星となりて | F12: 少年のあまりにも強大な才能は、天才たちを震撼させる── | G12: 世界最高の魔法師リシェル＝グランドが、その生涯に幕を下ろした。彼女は生涯弟子を取らなかったことで有名だった。そんな彼女の遺書には、たった一文だけが記されていた。 ──皆様。この〝未知〟を祝福いたしましょう。 その後。世界最高峰の名門魔法学院に辺境出身の少年が入学する。名はアルト＝ローウェン。彼の推薦状には師として、今は亡きリシェル＝グランドの名が刻まれていた。 天才。秀才。そして、鬼才。 唯一無二の鬼才は魔法の歴史を塗り替えていくことになる。しかし、誰もが目を奪われるその才能は天才たちの運命を狂わせ、彼自身にも逃れられない宿命を刻んでいく。未知の才能に翻弄される群像劇異世界ファンタジー開幕。 才能は呪いか。 ──それとも祝福か。 | H12: 御子柴奈々 | I12: 1252 | J12: 24 | K12: 24 | L12: 0 | M12: 27
A13: 現代ファンタジー | B13: 51 | C13: 41 | D13: -10 | E13: 『【多重連撃（威力1/10）】はゴミスキル？ ——いいえ、固定ダメージを10倍叩き込む神バグです』 〜聖女の幼馴染に打算で捨てられた俺、100円の産廃装備と鉄球で100万ダメージ叩き出して無双する〜 | F13: 攻撃力90%カットのゴミ？いいえ、固定ダメ10倍の神バグです | G13: 【「威力1/10」の減衰補正？ ——ハハッ、掛け算の元の数字をデカくして、固定衝撃を重複させれば即死コンボ（神バグ）じゃん】 現代日本にダンジョンと『スキル』が出現して半世紀。 15歳の能力鑑定儀式で、高校生の九重湊（くのえ・みなと）が授かったのは——【多重連撃】。 一回の攻撃で10回の追撃が発生する当たりスキル……と思いきや、追加されたのは【全攻撃の威力が一律1/10（90%カット）になる】という残酷なペナルティ補正だった！ 「装甲値50の敵に威力10で叩いてもダメージゼロ！ 一生かすり傷すらつけられないポカポカパンチのゴミスキルじゃねえかｗｗｗ」 学園の生徒や『剣聖』のライバル・一条蓮から猛烈な嘲笑を浴びる湊。 『聖女』のスキルを発現させた幼馴染・神崎葵も、「落ちこぼれと付き合ったら損をする」という冷たい打算から湊を捨て、一条のパーティーへと乗り換えていく。 しかし、嘲笑され見捨てられた湊の口元は、不敵に歪んでいた。 前世の記憶と冷静な分析力を持つ湊は、この世界のダメージ計算式に潜む【重大なバグ（仕様の穴）】に気づいていたのだ。 （ステータス攻撃力が1/10に減衰する？ ……なら、物理的な入力エネルギーを極限まで引き上げて『固定追加衝撃』を定着・重複させたらどうなる？） 投げ売りされていた『固定追加衝撃』が残るジャンク品の革手袋。 同じく「ゴミスキル」と冷遇されていた少女・白銀莉音が【錬金術】で作る、誤差ゼロの「真円高密度鉄球」。 そして、湊が前世から鍛え上げた高圧「指弾」。 これらを組み合わせた瞬間—— 1/10の減衰計算をシステム上完全バイパスし、敵の外殻を一切傷つけず体内の核（コア）だけを共振粉砕する【内部破壊コンボ】が完成する！！ 「お前らが自慢する『剣聖』の斬撃じゃ素材を傷つけて査定ガタ落ちだろ？ 俺たちは無傷で特級素材を100%最高額回収させてもらうわ」 テンプレの％倍率に頼るエリートたちを遥か置き去りにし、圧倒的合理主義の理屈屋が計算式ひとつで世界の理を塗り替える、痛快無双ファンタジー開幕！ | H13: ぺんぢる | I13: 1544 | J13: 6 | K13: 6 | L13: 0 | M13: 36
... A83: 異世界ファンタジー | B83: 99 | C83: 98 | D83: -1 | E83: 王家待望の末っ子王子、溺愛してくる五人の姉に開拓されながら気軽に無双する | F83: 戦闘メイドゴーレムはロマン！（力説） | G83: 長い間女性しか生まれてこなかった『ハルメシア王国』の王家。その日、ついに待望の男子が誕生しました。『カイゼル』と名付けられた彼は五人の姉に愛されながらすくすくと成長し、次期国王に相応しいよう、様々な力を身に付けました。そして同時に、世界は彼を中心に大きく動き始めたのです。 これは永劫たるハルメシア王国と、その歴史に名を刻む偉大なる王の叙事詩。 | H83: 風遊ひばり | I83: 140 | J83: 33 | K83: 33 | L83: 1 | M83: 8

Sheet スター速度
A1: genre | B1: rank | C1: title | D1: catchphrase | E1: あらすじ | F1: star | G1: star_gain | H1: star_per_day | I1: growth_pct | J1: elapsed_days | K1: episodes
A2: 異世界ファンタジー | B2: 1 | C2: 鎧騎兵、走る～大好きなロボット作品っぽい世界に転生したけど、プロローグで滅ぶ場所にいます。生き残りたい！ すごく生き残りたい！！～ | D2: 原作知識で無双したいのに、原作が始まる前に死ぬかもしれん。 | E2: 【完結まで毎日12時投稿！】【祝！日間総合ランキング1位！】 ロイド＝ベルクは『鎧騎兵(ガイキヘイ)』と呼ばれるヒト型ロボットのパイロット、『騎手』候補生であり……転生者である。 彼は、前世で大いにハマり込んだ名作ファンタジー小説『帝歴1002 鎧騎兵、走る』シリーズそのものか、非常に酷似した異世界へ転生してしまった。 『大好きな作品世界に来れた！』と、5歳の時に前世の記憶を思い出した当初は狂喜乱舞した彼であったが……年号を確認した瞬間、絶望の淵に叩き落とされてしまう。 彼が騎手になって初めて赴くであろう赴任先……『西方辺境領』は、原作1巻の『プロローグ』で滅んでしまう場所だということを知ったからだ。 ならば騎手にならなければいいかと言えば、それも無理。 彼の亡き父は騎士爵を持つ騎手であり、残された家族の生活の為に、ベルク家長男であるロイドはソレを継ぐ必要がある。 通常は継承できない一代限りの騎士爵だが、騎手になれば特例で継承できるのだ。 そして……『騎士爵持ちの騎手』が配置されるのは、決まって『西方辺境領』なのだ。 「ちくしょう……神様の馬鹿野郎……！」 家族の為に逃げることもできないロイドは、原作にもほとんど描写のない地獄の『プロローグ』を生き残るために、今日も騎手訓練校で訓練に励んでいる。 「原作知識は唸るほどあるのに！ 原作が始まる前に死にたくねぇよ～！！」 これは、転生者ロイド＝ベルクが原作にたどり着くために死に物狂いで生きる物語である。 ……死に物狂いで生き過ぎた結果、原作を大いに破壊しまくる物語でもある。 | F2: 6553 | G2: 597 | H2: 597 | I2: 10.023506 | J2: 23 | K2: 24
A3: 現代ファンタジー | B3: 1 | C3: S級探索者を5人育てたら全員に独立された中年コーチ、暇つぶしの初心者講座配信が「人類の攻略常識」を書き換え始める 〜教え子たちが「先生の本当の価値」に気付いて騒ぎ出すまで、あと3日〜 | D3: 育てた俺が、一番育っていなかったらしい。……世界の評価基準のほうがな。 | E3: 「アンタの育成論、ただの寄生だろ」 S級探索者を5人育てた俺は、その全員に独立され、業界から追放同然に引退した。 戦闘の才能はB級止まり。確かに俺自身は、何者にもなれなかった。 ――だから、暇つぶしだった。 初心者向けの攻略講座配信なんて、誰も見ないと思っていた。 「基礎ステップの踏み方が変だね。それじゃ三層で死ぬよ」 「え、なんで分かるんですか！？」 落ちこぼれE級の少女に教えた「ただの基礎」が、一週間でC級相当の動きに化けた。 切り抜きが拡散され、攻略wikiが書き換わり、大手クランの研究班がざわつき始める。 【あの講座、人類最強・剣条玲の動きと同じ事を言ってないか？】 【おい、誰かこのコーチの経歴調べろ】 そして配信に、見覚えのありすぎる人類最強がコメントを残す。 ――『先生。見つけました』 俺を置いていったはずの教え子たちが、世界中で勝手に騒ぎ始めた。 ※主人公は無自覚です。教え子と業界が勝手に騒ぎ、俺を捨てた連中が勝手に曇ります。基本ノンストレス・サクサク更新。 | F3: 4745 | G3: 377 | H3: 377 | I3: 8.6309524 | J3: 17 | K3: 28
A4: 異世界ファンタジー | B4: 2 | C4: 【日間34万PV】過労死寸前で会社をクビになった俺、悪役貴族に転生し三年後に処刑されるまで好き放題やる ～使い潰された有能な美少女奴隷を安く買い叩いていたら、なぜか神待遇と喜ばれ忠誠を誓われる～ | D4: 【第三章】三年後に処刑？ なら酒も金も女も、今のうち好き放題してやる！ | E4: 退職代行会社で過労死寸前まで限界社畜となって働いていたのに、依頼者を助けたい一心で相手の会社をコテンパンにしてしまい会社をクビになった瀬野春之、39歳。 目を覚ますと、そこは生前に遊んでいたファンタジーRPGの世界。しかも転生したのは、三年後に主人公たちによって処刑される悪役貴族ゼノ・ヴァルディスだった。 だが、ゼノは破滅を回避する気などなかった。 「どうせ三年後に死ぬなら、それまで好き放題してやる！！！」 前世では散々使い潰される側だったのだ。 今度は自分が人を使う側になり、酒！ 金！ 女！ 贅沢の限りを尽くしてやる。 そんなゼノの前に現れたのは、悪徳商人に使い潰され、今にも死にそうな銀髪の美少女奴隷ネマ。 誰からも役立たず扱いされていた彼女だが、ゼノの固有スキル【人物鑑定】で見れば、とんでもなく優秀な訳あり人材だった。 ならば、その価値を商人に教えてやる必要などない。 「弱り切っている。奴隷としての価値は低い。俺が買ってやろう」 ゼノはネマを安く買い叩く。 有能な奴隷なら徹底的に働かせる。 ただし、死なれれば損だから食事を与える。 壊れれば損だから治療する。 長く使うために寝床を与え、働きすぎれば休ませる。 さらに戦闘能力に優れた金髪の美少女奴隷メソも安く買い叩き、護衛としてこき使う。 すべては自分が楽をして、三年後まで好き放題に暮らすため。 ――そのはずだった。 「こんな神待遇、見たことがありません」 「私は一生、旦那様にお仕えします」 使い潰されていた有能な奴隷たちは次々と才能を開花させ、なぜかゼノへ忠誠を誓い始める。 横領していた家令を切れば使用人に感謝され、役立たずな管理者を追い出せば仕事が回り、気づけば領地まで豊かになっていく。 そしてついには王国中で、 「悪名高きゼノ・ヴァルディスは、実は稀代の善政領主なのでは？」 と噂されるようになってしまい――。 「何を勘違いしている？ 俺は善人じゃない」 ゼノはまだ知らない。 自分では悪役貴族らしく好き放題しているつもりの行動が、ことごとく人を救い、三年後の処刑からどんどん遠ざかっていることを。 ※8/25 原作ゲーム名を『エルディア・サーガ』→『パルディア・サーガ』に変更しました。 有名作品の国名と被っていたためです。改稿漏れがありましたらお手数ですがお知らせください。 ※8/25 8/23更新分の一部・タイトルの表現を改稿しました。 ※20歳未満者の飲酒シーンがありますが、作品内社会では既に成人済みであり、飲酒禁止年齢についての規制がありません。法律違反を推奨する意図はありません。その上で問題がありましたら改稿可能です。 | F4: 3511 | G4: 360 | H4: 360 | I4: 11.424944 | J4: 18 | K4: 89
A5: 異世界ファンタジー | B5: 4 | C5: １０歳から始める冒険者生活 | D5: １０歳から始める冒険者生活 | E5: エリクは１０歳の儀式を終えてから村を出る。 家族からは居ない者同然の扱いを受けて育ったエリクは王都に来て冒険者となった。 それまでの人生で既に色々と経験をしていたエリクは、それらの知識と技術を使って冒険者生活の基盤を作っていく。 夢や目標は無いが、ただ生き続けたいと言う思いを持つ少年の物語。 | F5: 11875 | G5: 245 | H5: 245 | I5: 2.1066208 | J5: 24 | K5: 100
A6: 現代ファンタジー | B6: 16 | C6: 妹の入院費のため深夜のダンジョン清掃バイトを始めたら、掃除した階層が「単独完全攻略」扱いされて世界が騒然〜時給1,200円を喜んでいるだけなのに、正体不明の「人類最強」を巡って各国が動き出す〜 | D6: 深夜3時、世界が探す人類最強は、モップを絞っていた。 | E6: 「悪いが、数字にならない人間を雇う余裕はないんだ」 大手クラン・ゼノギアを解雇された雑用係の灰崎湊、23歳。 持っているのは、汚れを消すだけのハズレスキル【クリーンアップ】。入院中の妹の治療費を稼ぐため、湊は深夜のダンジョン清掃バイトを始める。 ——だがその夜、湊が「散らかってるなあ」と掃除した階層は、人類未踏破の第47層だった。 魔物の群れも、災害級の呪いも、残留魔素も。湊にとってはぜんぶ、ただの「汚れ」。 翌朝、ダンジョン協会は観測史上初の【単独完全攻略】を検知。正体不明の攻略者《ファントム》の存在に、世界中の探索者が、国家が、人類最強が動き出す。 「時給、ちょっと上がらないかな。妹に、いちご買ってやりたいんだよな」 本人だけが、何も知らない。 一方その頃、湊を切り捨てた古巣のクランでは、原因不明の事故が相次いでいて——。 これは、世界で一番静かな最強が、世界を綺麗にしていく物語。 | F6: 2789 | G6: 233 | H6: 233 | I6: 9.1158059 | J6: 41 | K6: 70
A7: 現代ファンタジー | B7: 3 | C7: 穏やかゲーマー配信者、ストレス発散でブチ切れながらモンスターを蹂躙している姿が世界中で拡散され無事本性がバレてしまう | D7: 「ダンジョン攻略したらガチャ石大量配布！？ 任せろ全部蹂躙してやる」 | E7: ダンジョン配信が世界中で流行る中、俺――白楽燕璃《しらくえんり》はゲーム配信をしていた。 そんな時、とある出来事からストレスでブチギレそうになってしまう。だが、リスナーの前でそんな姿を見せるわけにはいかない。考えた結果ダンジョンでモンスターを蹂躙してストレスを発散することにした。 ストレスで我慢が出来なくなっていた俺はそこでたまたま居合わせた可愛らしい探索者のことなんて気にせずにとんでもない暴言を吐き捨て、モンスターを一体も残らずに殺して周った。後日、その探索者が実は有名ダンジョン配信者で、俺のブチギレ暴言モンスター蹂躙姿が世界中で拡散されてしまう。 あれよあれよと流され、気づけばダンジョン配信をする羽目に……！ そして金髪お姫様やバーサーカー気質な女性、お忍びS級海外美女探索者といった個性あふれる人々と出会い、俺の世界は瞬く間に変わっていく。 いや、俺ゲームしたいだけなんだが……。 え？ダンジョン配信したら課金用のお金くれるの！？！？ じゃあやる！！ 「来たモンスターぶっ殺しニキだ！」「今日も清々しいまでにモンスターを蹂躙してくれ！」「俺達のトラウマモンスターが完膚なきまでに叩きのめされてて気持ちい！！」 この物語はただのゲーム配信者だった俺が一つのきっかけをもとに様々な出会いを経てダンジョンを蹂躙していく物語 | F7: 3019 | G7: 231 | H7: 231 | I7: 8.2855093 | J7: 20 | K7: 25
A8: 異世界ファンタジー | B8: 11 | C8: 外れスキル『会話』で公爵家を勘当されたけど、魔獣の本音が分かるようになったので、いつの間にか神龍や神獣たちが懐いてくるんだが？～知らぬ間に最強領地になっていたので、俺を追放した家族たちが青ざめてる～ | D8: 誰にも理解されない魔獣たちと話しただけで、なぜか懐かれるんだが？ | E8: 悪役貴族として転生した主人公――ルーフェウス。 この世界では１８歳になると、誰もがスキルを開花させる。 だが彼が授かったのは、「会話」というあからさまな《外れスキル》。 体裁を誰よりも重視する父は、 そんな息子をクズ扱いし、なんの実りもない荒野の地へと追放してしまう。 だが、それこそが主人公の狙いだった。 どのみちこの公爵家は、後のシナリオで悪事がバレ、主人公たちに殺されてしまう。 だから今のうちに公爵家から距離を取り、品行方正に生きていくことで、その破滅ルートを回避しようとしたのである。 そんな折、ルーフェウスには「会話」という謎スキルの真価を知る。 ――あらゆる魔獣や神獣たちの言葉を完全に理解し、意思疎通を可能にする力。 それによっていつの間にか史上類を見ない最強の軍勢が誕生し、 王国全軍をも凌駕する最強の軍事力を持つ「独立領地」へと大成長。 一方のオルファウス公爵家は、 自分たちが「とんでもない化け物」を野放しにしてしまったという絶望的な事実を知り、 恐怖に青ざめるのであった。 | F8: 1639 | G8: 218 | H8: 218 | I8: 15.341309 | J8: 17 | K8: 18
A9: 異世界ファンタジー | B9: 10 | C9: クラス転移で追放されたハズレ職〝回収士〟の俺は、捨てられた物ほど強く直せる。～聖女の幼馴染と魔境を楽園に変えてスローライフを満喫していたら、陽キャ勇者たちが戻ってこいと言い出した。もう遅い～ | D9: 捨てられた俺には、捨てられたものすべてを最強にする力があった。 | E9: 「久世。ハズレ職の君は、連れていけない。……悪いけど、出ていってくれ」 修学旅行の観光バスが、トンネルに入ると同時にクラスごと異世界へ召喚された。 勇者、剣聖、大魔導師、聖騎士。次々と強力な職業を授かるクラスメイトたちの中で、久世映司だけが〝回収士〟。壊れた物と、捨てられた物にしか使えない力。 ハズレ職──そう判定された映司は、その力を一度も試されないまま、クラスの中心にいた〝勇者〟が主導する多数決で追放される。渡されたのは三日分の食料と、水袋が二つ。別れを言いに来た者は、一人もいなかった。 ただ一本だけ、反対に挙がった手がある。〝聖女〟に選ばれた、幼馴染のものだ。 「私、映司くんについていくから。だって、映司くんが足手まといだなんて、有り得ないし」 送られた先は、魔力汚染で二十年前に捨てられた廃村。井戸は枯れ、屋根の残った家には壁がない。 だが、誰も知らなかった。映司の力は、捨てられた物ほど、以前より優れた姿で蘇らせるものだと。 枯れた井戸は水脈ごと戻り、崩れた廃屋は二人の家になる。折れた剣は、風の刃を生む魔剣へ。鉄屑と呼ばれて城の中庭に放置された観光バスは、走る城へ。親を失った狼獣人の娘も、故郷を追われたダークエルフの錬金術師も、捨てられた者たちが次々と集まってくる。 一方、勇者一行は気づきはじめていた。壊れた装備を直せる者がいない。汚染を浄化できる者がいない。食料が保たない──そして、聖女がいない。 魔境が楽園に変わったころ、彼らは言った。「戻ってこい」と。 だが、もう遅い。 捨てられた俺には、捨てられたものすべてを最強にする力があった。 ──── 小説家になろうにも投稿しています。 | F9: 923 | G9: 216 | H9: 216 | I9: 30.551627 | J9: 4 | K9: 18
A10: 異世界ファンタジー | B10: 8 | C10: 杖と剣の異世界に舞い降りた天才〜片田舎の少年は王都で神童となりて〜 | D10: 片田舎に眠っていた天才が解き放たれる | E10: 剣を尊ぶ騎士と杖を掲げる魔術師。二つの勢力が競い合う異世界に転生したリオンは、片田舎の孤児院で暮らしていた。彼は幼い頃から近所の老夫婦に剣と魔術を教わっていたが、二人が元剣聖と元賢者であることを知らないままだった。 十五歳になったリオンは王都を訪れ、騎士試験と魔術師試験を受験する。結果は――両方共にトップ合格。 『彼の才能がこちら側でよかった』 騎士と魔術師たちは互いにそう安堵していたが、リオンは片翼の天才ではなかった。王国史上初の快挙を成し遂げた少年を巡り、騎士公爵家と魔術公爵家は令嬢との婚約まで持ちかけて争い始める。そして周囲は、その未知の才能に翻弄されていくことになる。 「俺、資格を取りに来ただけなんだが……」 杖と剣──〝両翼の天才〟が今、舞い降りる。 | F10: 1037 | G10: 214 | H10: 214 | I10: 26.00243 | J10: 6 | K10: 7
A11: 異世界ファンタジー | B11: 6 | C11: ヤニ好きの底辺オッサン冒険者。実は最大最強クランの元クランマスター。 | D11: タバコは人生だ。（大勢の敵に囲まれた中で余裕でタバコを吸うオッサン） | E11: 帝国最大最強クラン『ドラゴロスロンド』。 帝国各地に冒険者ギルドに代わって支部があるほどのクランだ。 その初代クランマスターが英雄的死去をしてから４年の月日が流れた。 ハロウェイというソロの中年冒険者がいる。 いつも煙草を吸っているヤニカスで、依頼も殆ど受けず、その日暮らしが出来ればいいというスタンスだ。 冒険者の階級も低いアイアン級のままだ。中年でアイアンは俗に底辺と蔑まれていた。 これはそんなヤニ好きのオッサン冒険者がタバコ吹かしながらのらりくらりとなんか生きる物語。 そして彼が最大最強クラン『ドラゴロスロンド』の死んだはずの初代クランマスターとは誰も知らない。 | F11: 1961 | G11: 208 | H11: 208 | I11: 11.865374 | J11: 6 | K11: 24
A12: 異世界ファンタジー | B12: 5 | C12: 異世界転移した料理人ですが、帝都の路地裏で定食屋を開いたら、帝国の女帝が毎日お忍びで食べに来るようになりました | D12: 「こんな美味しいご飯は初めてだ……」女帝が路地裏の定食屋に堕ちる。 | E12: 異世界に飛ばされた日本の料理人・哲。 獣の解体場に通いつめ、この世界の食材の末に、日本の味を完全に再現する。 帝都の片隅にひっそりと開いた、看板すらない小さなあばら屋。 そこで哲が振るうのは、暴力的なまでに食欲をそそる極上の定食。 剣も魔法もない。あるのは、最高の一杯で客の心を撃ち抜く料理人の誇りだけだった。 一方、連日の権力闘争と重圧にすり減らされていた帝国の若き女帝・エリザベートは、冷え切った心と胃を抱えたまま、偶然その路地裏に迷い込む。 漂ってきた強烈な匂いに導かれ、恐る恐る暖簾をくぐった彼女を待っていたのは――。 腹の底から温まる、異世界グルメファンタジー開幕！ | F12: 6563 | G12: 206 | H12: 206 | I12: 3.2405223 | J12: 26 | K12: 27
A13: 異世界ファンタジー | B13: 7 | C13: 四人の天才妹を虐げ続けた兄、英雄となった妹たちに断罪される | D13: 世界を救った四姉妹は、最低の兄を許さない | E13: 世界を救った四人の姉妹がいた。 剣の頂点に立つ剣聖セリナ。 魔法の頂点に立つ賢者リリア。 錬金術の常識を塗り替えた天才ミリア。 そして世界最大級の商会を築き上げた大商人エマ。 若くしてそれぞれの道の頂点へ辿り着いた彼女たちは、人々から英雄として讃えられていた。 しかし、そんな四姉妹には誰にも語りたくない過去がある。 ――兄、レオン。 幼い妹を魔物の棲む森へ置き去りにした。 毎日のように過酷な虐待を繰り返した。 努力して手に入れた褒美を奪った。 才能を妬み、販路を潰し、夢を邪魔し続けた。 それでも四姉妹は兄に屈することなく、自らの力で世界の頂点まで上り詰めた。 そして魔王との戦いを終えた彼女たちの前に現れたのは、変わり果てた姿となった魔神の兄だった。 すべての因縁に決着がついた後、レオンが犯してきた数々の罪を裁くため、神託裁判が開かれる。 証人は四人の妹。 そして証拠は、過去に起きた出来事をありのままに映し出す神器――《真実の鏡》。 世界中が見守る中、四姉妹は兄から受けた仕打ちを一つずつ告発していく。 誰もが思っていた。 これは、稀代の悪党が犯した罪のすべてを暴き、その報いを受けさせるための裁判なのだと。 だが――。 真実の鏡に映し出された過去は、彼女たちの記憶と同じはずなのに、どこかがおかしい。 一つの真実が明らかになるたび、新たな疑問が生まれる。 世界を救った四人の英雄と、彼女たちの人生を弄び続けた最低の兄。 長きにわたる因縁に、今、決着の時が訪れる――。 | F13: 1702 | G13: 198 | H13: 198 | I13: 13.164894 | J13: 19 | K13: 37
... A115: 異世界ファンタジー | B115: 67 | C115: 世界唯一の解呪魔法使い～追放された伯爵五男、奴隷少女を買って解呪したら天使の翼が生えてきた～ | D115: 『身体能力と魔力量、10倍にするね』――天使の力で最強支援魔法！？ | E115: 伯爵家の五男である俺は家から追放され、兄弟から命を狙われているという状況の中、護衛として呪われた少女の奴隷を買った。 俺は彼女にかかっていた呪いを解呪した結果 「身体能力と魔力量、10倍にするね」 ――実は彼女は規格外な支援魔法を使えることが判明。 さらには恩義を感じたのか、俺に忠誠を誓ってくれるようになった。 貴族や異教徒たちから命を狙われながらも、二人は規格外な支援魔法を駆使し、その名を世界中に轟かせていく。 | F115: 479 | G115: 17 | H115: 17 | I115: 3.6796537 | J115: 13 | K115: 10
A116: 異世界ファンタジー | B116: 76 | C116: クラスで集団異世界転移。毎日ゴミ拾いしていたことで善行ポイントがカンストしてたので、ポイント消費して強さよりも生き残ることを優先します。 | D116: 毎日のゴミ拾いで善行ポイントがカンストしてた。 | F116: 111 | G116: 17 | H116: 17 | I116: 18.085106 | J116: 5 | K116: 2
A117: 異世界ファンタジー | B117: 59 | C117: 謎職業【墓堀処刑人《アンダーテイカー》】を授かって追放された俺、厄災の魔女と死者を蘇らせていたら、なぜか曇ったヒロインたちに囲まれて世界最強の国ができていた | D117: 俺は別に不幸じゃないのに、どうしてみんな曇っているんだ？ | E117: 成人の儀で、誰も知らない謎職業【墓堀処刑人《アンダーテイカー》】を授かったグレイ。 不吉な職業だと恐れられ、名門騎士家から追放。 幼馴染との婚約まで破棄され、最果ての墓場へ送られてしまう。 ――もっとも、本人はそれほど気にしていなかった。 「まあ、家を出るいい機会だったと思えばいいか」 そんなグレイが墓場で最初に蘇らせたのは、数百年前に封印された【厄災の魔女】。 「私が怖くないの？」 「それより腹減ってないか？」 世界中から恐れられる魔女を普通の少女として扱った結果、なぜか彼女はグレイから離れなくなってしまう。 さらに、グレイの力で死者の魂を呼び戻し、魔女の魔法で肉体を再生することで――二人は死者を完全に蘇らせられると判明。 「ここに、私たちの国を作りましょう」 墓場で始まった国造り。 住民を増やすために死者を蘇らせているだけなのに、目覚めるのは処刑された聖女、忘れ去られた大魔導師、滅びた国の騎士団長など、とんでもない者ばかり。 気づけば墓場には、国々を滅ぼしかねない最強勢力が出来上がっていた。 その一方で――。 厄災の魔女からグレイを救おうとする姫騎士。 追放された彼について行かなかったことを後悔し続ける元婚約者。 「今度こそ、必ず私があなたを救います！」 「どうして私を殺さないの……？」 「いや、俺は別に困ってないんだけど？」 グレイ本人は、自分が不幸だとはまったく思っていない。 なのにヒロインたちは、 ――家族に捨てられても笑っている。 ――傷ついても弱音を吐かない。 ――自分を見捨てた相手すら恨もうとしない。 そんな彼を見て勝手に曇り、罪悪感と愛情をどんどん重くしていく。 これは、自分が不幸だとまったく思っていない男と、 「今度こそ絶対に彼を幸せにする」 と曇り続ける少女たちによる―― 墓場から始まる、すれ違い勘違い建国ファンタジー。 | F117: 321 | G117: 17 | H117: 17 | I117: 5.5921053 | J117: 23 | K117: 24
A118: 異世界ファンタジー | B118: 74 | C118: 皇帝に成りたくない男の不本意奴隷ハーレム | D118: 皇帝位からもハーレムからも、もう逃げられないぞ！ | E118: 転生者の主人公が皇位争いから上手くドロップアウトしようと思ったら、奴隷たちに囲まれてる話。 伯爵家の四男エドモンドは、転生者である。彼はきたる皇位継承戦に向けて功績を積むため、両親からダンジョン攻略を命じられてしまう。しかも所属する国家が奴隷を推進する国だったため、不本意ながら購入することに。彼自身は奴隷たちに反乱されぬ様に程よい“雇用関係”を築こうと思っていたが、周囲を囲まれるどころか、成りたくないはずの皇帝位まで近づいて来て……。 | F118: 440 | G118: 16 | H118: 16 | I118: 3.7735849 | J118: 24 | K118: 28
A119: 異世界ファンタジー | B119: 78 | C119: 幼竜の俺を拾ったボロボロの少女、数年後に最強のドラゴンナイトになって俺を執着溺愛してくるんだが？ | D119: 【人外龍転生×激重少女ヒロイン】最弱の幼竜、最強の竜騎士を育てる。 | E119: ​前世の記憶を持ったまま、翼の折れた『最弱の幼竜』として異世界に転生したジル。 森で死にかけていたところを救ってくれたのは、村で「不吉な子」と虐げられていたボロボロの少女・エレナだった。 ​自分を命がけで守ろうとする健気な彼女に恩を返すため、ジルは前世の知識と竜の知恵を駆使し、陰から彼女の『師匠』として魔術と剣技を仕込み始める。 ​——数年後。 ジルのスパルタ（？）指導により、エレナは王国史上最年少にして最強の『竜騎士』へと覚醒していた。 ​「ジル、今日も可愛いね。……大丈夫だよ、私からジルを奪おうとする奴は、国ごと斬り伏せてあげるから」 ​あれ？ おかしくない？ 守ってあげたはずの少女が、俺に執着する無敵の激重ヤンデレ騎士になっちゃったんだけど！？ ​肩乗りサイズの幼竜と、愛が重すぎる最強竜騎士が織りなす、勘違い＆無双成り上がり | F119: 301 | G119: 16 | H119: 16 | I119: 5.6140351 | J119: 15 | K119: 15
A120: 現代ファンタジー | B120: 43 | C120: 努力だけで超能力者になった俺、就職せずに人生舐めて生きる | D120: 「才能?ないよ。13年やっただけ。だから遠慮なく人生楽しみます」 | E120: 超能力なんて、生まれつきの才能だと思ってないか? 九条蓮、22歳。小4で「念力はあるはず」と確信してから13年間、毎日欠かさず修練を続けた結果、ついに『空間掌握』に覚醒した。テレキネシス、飛行、バリア、透視――全部この一つの原理の応用だ。 さて、努力は十分した。ここからは人生を舐めて生きる。 就職?しない。スクラッチくじを透視して当たりだけ買い、カジノで荒稼ぎし、原油先物で資産を転がす。マイルールはただ一つ、「個人からは盗らない」。 これは、努力の天才が全力で怠惰に生きる物語。 | F120: 8180 | G120: 16 | H120: 16 | I120: 0.19598236 | J120: 60 | K120: 96
A121: 現代ファンタジー | B121: 67 | C121: 人間不信の錬金術師 〜捨てられた少年は最高の術師に至り、人の道を外れる〜 | D121: 【40万PV感謝です！】人間は裏切る。だから信じられる者を創る。 | E121: 現代にダンジョンが出現して50年。スキル「錬金術師」を持つ少年・藤宮悟は、医療関係のスキルを持つエリートの家族から「寄生虫」と蔑まれ、信頼していたパーティー仲間からは、奈落の底へ突き落とされる。 絶望の果て、ダンジョン最深部で出会ったのは、孤独な神狼。彼により「神格」と、万物を創り出す究極のスキルを得た時、悟の運命は一変する。 「もう、俺は我慢しない」 絶対的な力を手に入れ、最愛のメイドを従えた悟は、自分を裏切った全てのものへの残酷な復讐を開始する。 その復讐はジワジワと対象を蝕んでいく。 人の道を外れた最高の術師による、容赦なき逆転劇が今、幕を開ける。 ※この作品では、投稿前の誤字脱字チェックにのみAIを使用しております。 | F121: 1886 | G121: 16 | H121: 16 | I121: 0.85561497 | J121: 88 | K121: 48
A122: 現代ファンタジー | B122: 81 | C122: 外れスキル《強化》は、倒した魔物の特性を吸収する 〜同接三人の底辺探索者、銀座ダンジョン配信で成り上がる〜 | D122: 外れ扱いされた《強化》は、魔物の特性を吸収する成長スキルだった。 | E122: 世界に七つの巨大な穴――ダンジョンが現れてから十年以上。 アメリカ、ブラジル、日本、中国、ドイツ、南アフリカ共和国、アラブ首長国連邦。 それぞれに一つずつ現れた穴から魔物が溢れ、人類は一度、大きな被害を受けた。 だが、魔物を倒した者は魔力を吸収し、最初の一体を倒した時にスキルを得る。 人類はその力で魔物を押し返し、やがてダンジョン探索は一大産業となった。 日本唯一のダンジョンは、東京・銀座にある。 銀座ダンジョン第一層で日銭を稼ぐ底辺探索者、朝倉蓮司。 彼のスキルは《強化》。 説明はただ一つ。 敵を倒すほど強くなる。 しかし、この世界では魔物を倒せば誰でも成長する。 そのため《強化》は「そんなの全員そうだろ」と笑われ、実質スキルなしの外れ扱いを受けていた。 同接三人。 登録者も少ない。 第一層の雑魚魔物にも手間取る。 そんな蓮司の日常は、ある日の配信中に崩れ始める。 第二層から逃げてきた探索者。 瀕死のまま第一層へ上がってきた格上の魔物。 逃げ場を失った蓮司は、最後の保険だった魔法道具で魔物にトドメを刺す。 その瞬間、視界に今まで見たことのない文字が浮かんだ。 岩皮猿の特性を吸収しました。 筋力が上昇しました。 耐久が上昇しました。 打撃耐性が上昇しました。 外れだと思われていた《強化》の正体。 それは、倒した魔物の特性を少しずつ自分に取り込む成長スキルだった。 底辺探索者だった蓮司は、配信を通して少しずつ注目されていく。 これは、誰にも期待されなかった外れスキル持ちが、銀座ダンジョンの底辺から成り上がっていく物語。 | F122: 1001 | G122: 15 | H122: 15 | I122: 1.5212982 | J122: 58 | K122: 73
A123: 現代ファンタジー | B123: 88 | C123: 就職氷河期オブ・ザ・デッド ～世界は酷い有様だけど、異世界で魔王を倒した用務員のおじさんがモテモテに。なお、世界が救われるかは不明～ | D123: ゾンビ溢れる世界で、就職氷河期おじさんがモテモテに | E123: 就職氷河期世代として苦労し、今はとある地方の有名エリート私立高校の用務員を務める伊作 幸三（いざく こうぞう）、４９歳。 彼は多くの生徒たちからバカにされる存在であったが、唯一ギャルの格好しているために校内で浮いている、白井 瑠璃（しらい るり）とは用務員室でよく話す間柄であった。 もうすぐ夏休みという時、幸三が仕事を終えて自宅アパートで就寝して目が覚めたら異世界へ。 自分を召喚した王様の命令で魔王を倒し、褒美を貰って元の世界に戻ってきたら、一晩しか時が経っていなかった。 残りの人生、用務員なんて辞めて褒美を売ったお金で遊んで暮らそう期待に胸を膨らませる幸三であったが、なんと部屋の外はゾンビだらけで、異世界で上げたレベルも１に戻っていた。 「……生き残るのが優先だ！」 魔王を倒して戦闘経験豊富な幸三は次々とゾンビを倒してレベルを上げ、残りの人生を快適に暮らせるよう、あちこちに移動して可能な限り必要な食料、物資などを集め続けた。 「祖父さんが住んでいた、山奥の村に行くか……」 ある程度レベルを上げ、大量の物資を『アイテムボックス』に集めた幸三にゾンビを殲滅して世界を救う気なんてなく、祖父の実家がある廃村を目指す。 だがその前に、白井 瑠璃が生きているか気になってしまったので、職場である学校を目指すことに……。 そして彼女を探している途中、また別の美少女を助けてしまう幸三であった。 「ゾンビにされるところを助けていただき、ありがとうございます」 「（しまった！ 先のことをまったく考えていなかった！）」 その後、瑠璃とも合流できたのはよかったが、幸三は二人の安全を確保するために奔走することに。 このお話は、ゾンビ溢れる現代世界を、就職氷河期のオジさんが美少女や美女たちと共に生き抜いていく物語である。 小説家になろうと、カクヨムに同時連載開始！ 目指せ！ 漫画原作！ | F123: 2327 | G123: 15 | H123: 15 | I123: 0.64878893 | J123: 78 | K123: 84
A124: 現代ファンタジー | B124: 95 | C124: 伝奇鬱ゲーの才能のないモブに転生したけど、推しの負けヒロインを救うために努力して最強を目指します | D124: 最低ランクのモブ陰陽師なので、努力だけで推しの死亡ルートを攻略します | E124: 伝奇鬱ゲー『黄昏ノ禍祓』の世界に転生した雨宮朔。 しかし彼は原作には名前すら存在しないただのモブだった。 朔が救いたいのは、最推しの負けヒロイン・白峰冬花。 十七歳の冬、世界を救うため自らを犠牲にし、原作のどのルートでも未来を失う少女だ。 未来を知っているなら今度こそ救える。 そう思っていた朔だったが、三歳で判明した霊脈適性は最低の九等級。 普通の陰陽師なら一秒もかからず使える基礎符一枚に、朔は四十秒を必要とした。 それでも諦めない。 一秒で撃てないなら、四十秒を前の日に払えばいい。 強い術が使えないなら、弱い術を組み合わせればいい。 才能がないなら、時間と知識と準備で埋めればいい。 誰でも知っている基礎術。 誰も主戦法にはしない古い技術。 禍の性質、道具、地形、そして時間。 使えるものをすべて手札に変えて、最低ランクのモブは最強の攻略者を目指す。 これは、天才たちですら受け入れるしかなかった 「彼女を犠牲にすれば世界は救われる」 という正解そのものを、才能のない少年がひっくり返す物語。 | F124: 266 | G124: 15 | H124: 15 | I124: 5.9760956 | J124: 17 | K124: 22
A125: 異世界ファンタジー | B125: 45 | C125: 忘れられ令嬢は気ままに暮らしたい | D125: えっ、勝手に生きろ！？……じゃあ、気ままに暮らすことにします。 | E125: 母の死と新たに父に嫁いできた女性の出現により、辺境の屋敷へ移住することになった主人公。 しかし、来るはずの使用人は到着せず、自家に問い合わせても「もう面倒を見ないから、あとは勝手に生きろ」という非情な回答が返ってくるだけ。 だったら言われた通り、勝手気ままに暮らすことにしよう。 そう決意した令嬢が、周囲に翻弄されつつ気ままな日常を手に入れるためにあれこれ頑張る物語。 旧題：忘れられ令嬢の気ままな日常 MFブックス様より書籍版が発売中です。 | F125: 11377 | G125: 15 | H125: 15 | I125: 0.13201901 | J125: 1573 | K125: 175
A126: 現代ファンタジー | B126: 32 | C126: 【書籍化決定】はい、こちらダンジョン捜索隊！ ～相棒のタヌキがうっかり記録用録画を配信したら、全世界でバズってしまいました～ | D126: これより要救助者の捜索を開始します。 | E126: ダンジョンが初めて生成された22年前、主人公の三石悟はダンジョン内で生まれた。 生まれながらにして『総合身体能力強化』のスキルを手に入れた悟は、成長とともに並外れた身体能力を発揮するようになる。 その能力を生かすべく、ダンジョン内で行方不明になった人や救助要請があった時に出動する民間企業『株式会社ATORA捜索隊』に入社した悟は、二十二歳の誕生日を迎えたその日、出動時の相棒としてサクラを紹介された。 「よろしくね、悟くん。私、レッサーパンダのサクラって言うの」 「いや、タヌキじゃ？」 「ぬわぁ～んですってぇ～！？」 これは感情の起伏が薄いダンジョン生まれの青年と、自分をレッサーパンダと疑わない雌タヌキの、人命救助物語である。 たぶん。 ＊他サイトでも投稿しております。 旧タイトル：はい、こちらダンジョン捜索隊～自分はレッサーパンダだと言い張る相棒の♀タヌキが、うっかり記録用録画を配信してしまった件。 | F126: 1851 | G126: 15 | H126: 15 | I126: 0.81699346 | J126: 489 | K126: 259
A127: 現代ファンタジー | B127: 94 | C127: 『ゴミスキル【調理】で追放された俺、モンスター料理で最強になる～ダンジョン飯配信を始めたら世界中が腹を空かせて待っている～』 | D127: 最弱料理人の飯テロ配信が、世界の常識を変えていく！ | E127: 世界各地にダンジョンが出現し、探索の様子を生配信する「ダンジョン配信」が人気となった現代。 御厨レンが授かったスキルは、戦闘には何の役にも立たない【調理】だった。 「ダンジョンで料理して、何の役に立つんだよ」 荷物持ちや雑用ばかりを押しつけられた末、レンは所属していた人気探索者パーティーから追放されてしまう。 一人でダンジョンに取り残されたレンは、空腹を満たすため、仲間たちが捨てていったモンスターの肉を【調理】して食べることにした。 すると――。 《ホーンラビットの香草焼きを食べました》 《俊敏性が上昇しました》 《スキル【跳躍】を獲得しました》 実は【調理】とは、モンスターが持つ力を料理へ変え、食べた者に与える規格外のスキルだった。 オーク肉をステーキにすれば筋力が上がり、ポイズンスライムをゼリーにすれば毒耐性を獲得する。 強力なモンスターを料理して食べるほど、レンはどんどん強くなっていった。 しかし、モンスターを倒して食べるだけでは生活費を稼げない。 そこでレンは、ダンジョン内で料理を作る様子を配信することにした。 巨大な魔獣を丸ごと焼き、スライムを宝石のようなスイーツに変え、ドラゴンの肉を豪快なステーキに仕上げていく。 最初は誰にも注目されなかった配信だったが、見たこともないモンスター料理と、食べるたびに強くなっていくレンの姿が話題となり――。 『討伐はいいから、早く料理してくれ！』 『今日の飯テロはまだか！？』 『ドラゴンステーキ、俺にも食わせてくれ！』 気づけばレンの配信には、戦闘ではなく料理を見るため、世界中から視聴者が集まっていた。 さらに、有名配信者やトップ探索者、巨大企業までもが、レンの料理を求め始める。 一方、レンを追放したパーティーは、彼の料理によって自分たちが強化されていたことを知らず、急速に落ちぶれていき――。 これは、ゴミスキルと笑われた料理人が、モンスターを倒し、料理して、食べて強くなり、世界一のダンジョン配信者へと成り上がる物語。 | F127: 381 | G127: 14 | H127: 14 | I127: 3.8147139 | J127: 33 | K127: 67
A128: 現代ファンタジー | B128: 33 | C128: 人斬り高校生は普通の暮らしを送りたいのに、配信で永遠にバズり散らかしてしまう～信濃新陰流の最後の使い手？いやぁ、人違いじゃないですかね～ | D128: ダンジョン配信が流行るようなこの現代で人斬り、ですかぁ？ | E128: 20年前に突如、全世界に発生したダンジョンは長い年月の末に人間の生活の中に組み込まれ、ダンジョンの中で配信をするに至った。 街中にはダンジョン探索用の武器、防具を携えた老若男女が溢れ、ダンジョン配信でバズることを誰もが夢見るような時代になった。 2026年、令和8年の春。 今年で15歳になる男子高校生、諏訪野 拓海は生まれ育ったド田舎もド田舎の村から離れ、東京へ上京することになった。 ケミカルなハンバーガー、牛の糞の臭いがしない道、キラキラビカビカ光る町並み、午後六時になっても閉店しない店。 拓海はそういった「都会に住む普通の高校生の普通の生活」というものに憧れを抱いて上京することになる。 なるのだが、一つ二つ、彼には問題がある。 一つ、彼はまったくもって現代社会というものを知らない。携帯電話の知識はガラケーで止まっているし、実家には現役の黒電話があるし、彼のおじいちゃんなんて携帯電話すら持っていなかった。 二つ、彼は失伝したはずの【信濃新陰流】の最後の使い手であり、平たく言えば人斬りの才能に溢れた少年であったということ。 平和な普通の生活を望む人斬り高校生は望まずに欲望渦巻くダンジョン配信の渦中へと放り込まれ、 そうして失われるはずであった人斬りの才能が存分に開花することになってしまう。 一度抜けば人が死ぬまで収められぬ、血塗れの刃。業の技と言えば聞こえはいいが、つまるところは殺しの技術。 ダンジョン配信の流行るようなこの現代で人斬り、ですかぁ？ とどのつまり、これはそういう物語。 | F128: 1497 | G128: 14 | H128: 14 | I128: 0.94403237 | J128: 38 | K128: 48
... A195: 現代ファンタジー | B195: 83 | C195: 【書籍化】最強以外ありえない | D195: ―――遺産は最初にSランクマスターに至った俺の血を引く孫のものとする。 | E195: 馬鹿みたいな遺言を残してかつて最強の座に君臨した事のある男は死んだ。ダンジョンが存在し、それに抵抗する為にモンスターを使役するモンスターマスターが存在する世界で、それがかつて遊んでいたゲームの世界に酷似すると知ってもなお特別何かをする気もなかった鴉羽尊は祖父の遺言を皮切りに強制的に巻き込まれる。 育成、合体、大会、ダンジョン攻略にランク認定戦。モンスターマスターの頂点を目指す尊の人生が始まる。 HJノベルス様より書籍化します！ この作品はハーメルンでもマルチ投稿しています。 | F195: 2077 | G195: 0 | H195: 0 | I195: 0 | J195: 196 | K195: 310

Sheet 新規ランクイン
A1: genre | B1: rank | C1: title | D1: catchphrase | E1: あらすじ | F1: author | G1: star | H1: elapsed_days | I1: episodes | J1: intro_len | K1: tags
A2: 現代ファンタジー | B2: 78 | C2: ダンジョン配信に映り込むピクトグラムの怪異になった | D2: 困った時、危ない時にひょっこり登場 | E2: 注意)めちゃくちゃ緩い内容です！ 趣味なので許して！ 本作はAI作品になります ダンジョン配信に、時折映り込む謎のピクトグラム。 配信者にもモンスターにも、その姿は見えない。 けれど、配信を見ている視聴者にだけは、はっきりと見えていた。 瀕死の探索者がいれば医者の姿になって治療し、危険なモンスターが現れれば武器を持った姿へ変わる。 映像にしか存在しないように見えて、その手は確かに現実へ干渉する。 誰なのか。 何なのか。 なぜダンジョン配信に現れるのか。 今日もまた、どこかの配信画面の端から、白い人型が歩いてくる。 | F2: ＠脳タリン | G2: 203 | H2: 6 | I2: 76 | J2: 266 | K2: ダンジョン|配信|ピクトグラム|人外|掲示板|AI作品|現代ダンジョン
A3: 異世界ファンタジー | B3: 85 | C3: いずれ全能の大魔王へ至る暴食者〜喰らった相手のスキルを奪い、襲い来る敵達を返り討ちにして世界最強へ〜 | D3: 異界人・英雄・勇者・魔王など、数多の強者からスキルを奪う | E3: 子供を助けて命を落とした青年は、異世界で一匹のオークとして転生した。 そこで得た特異な力は、喰らった相手のスキルを奪う大罪スキル【暴食】。 人間だった記憶と、魔物としての本能。相反する二つを抱えながら、彼は生き抜くために魔物を狩り続ける。 だが、力を蓄えるほど世界は彼を危険視する。 Sランク冒険者や勇者に狙われ、同じく大罪を冠する魔王達にも敵視される存在へ。 ならば、襲い来る敵は全て喰らい、その力を己のものにするだけだ。 これは、【暴食】の力を宿した一匹のオークが、全能の大魔王へ至る物語。 | F3: 無名 | G3: 806 | H3: 125 | I3: 126 | J3: 259 | K3: 異世界|魔物転生|成長|主人公最強|魔王|勇者|強奪|AI補助利用
A4: 異世界ファンタジー | B4: 97 | C4: 追放されたので田舎でのんびり理想の錬金術暮らしを満喫する筈が、なぜか世界再誕の英傑と言われている～国を築いて王女や公爵令嬢と結婚したら、のんびりできないんじゃ？～ | D4: マスター、「造化」は天地を創造するという意味です（できそうですね） | E4: 平民錬金術師のロドリックは、伯爵家のディアスに目をつけられ、 追い出されてしまう。 だが、ロドリックは実は歴史に名を刻む大天才錬金術師だった。 ロドリックがいなくなって王都は困り、ディアスが取り入ろうとしていた 公爵家もロドリックを絶賛して、彼を取り込むための一大勢力を築きはじめる。 一方でロドリックは辺境でしがらみなくのびのび活動することで、 本来の実力を存分に発揮できるようになった結果、神霊や神獣と 契約してしまう。 気づいたときにはどんな国家をも超越した理想郷が誕生していた。 | F4: 相野仁 | G4: 222 | H4: 11 | I4: 12 | J4: 246 | K4: 追放|男主人公|ハーレム|SUGEEEE|錬金術|ざまぁ|勘違い？
A5: 現代ファンタジー | B5: 97 | C5: 貞操逆転世界で没落お嬢様のダンジョン配信を裏方で手伝っていたら、従者の俺がバズりました ～男女比1:9の世界では男が女を守るのは珍しいらしい～ | D5: 守られるのが男の常識？ 俺はお嬢様を守る従者ですが。 | E5: 男女比が、およそ一対九の世界。 男は希少で、女性に守られるのが当たり前。華奢で大人しく、女性の庇護を受ける男性ほど好まれる――そんな現代日本で、九条征司は少しばかり普通から外れた高校生だった。 代々、名家・十六夜家に仕えてきた家系に生まれ、幼い頃から要人警護の訓練を受けてきた征司は、同級生であり主人でもある十六夜紅羽に今も従者として仕えている。 そんなある日、没落した十六夜家を再興したい紅羽が言い出した。 「私、ダンジョン配信を始めるわ」 紅羽が有名になり、十六夜の名前を世間に広める。そのためなら協力するのが従者の役目だ。 征司は撮影係兼護衛として、紅羽のダンジョン配信に同行する。 ところが初配信で予定外の魔物が出現。 危機に陥った紅羽を守るため、征司がカメラを置いて前へ出た結果――。 『男が女を守ってる！？』 『この男誰！？』 『従者って設定じゃなくて本物なの？』 なぜか紅羽ではなく、征司の方まで大バズりしてしまった。 女性を守る男が珍しい？ 男が料理をするのも珍しい？ 女の荷物を持っただけで勘違いされる？ 本人にとっては、どれも従者として当たり前のこと。 没落お嬢様のダンジョン配信を支えるだけだったはずが、人気配信者、数字に厳しい同級生、女性探索者たちまで征司へ注目し始めて――。 これは、男が守られることが常識の世界で、お嬢様を守ることしか考えていない従者が、無自覚に女性たちの常識を壊しながらバズっていくダンジョン配信ラブコメ。 | F5: たけのこ | G5: 51 | H5: 6 | I5: 13 | J5: 640 | K5: 貞操逆転|勘違い|ハーレム|配信|あべこべ|現代ダンジョン|お嬢様
A6: 異世界ファンタジー | B6: 98 | C6: 転生付与術師オーレリアの難儀な婚約 | E6: 「この婚約は無かったことにしてほしい」 結婚のためはるばる王都までやってきたその日、オーレリアに突きつけられたのはそんな言葉だった。 家族もなく故郷も半ば捨ててきたオーレリアにあるものは、付与術と前世の記憶のみ。 幸い付与術師は仕事に困ることだけはない。 何ももたないオーレリアは一人、王都で生きていこうと決めるのだった。 恋愛までたどり着くのに時間がかかります。 舞台は19世紀半ばから20世紀前半の文化、風習を参考にしていますが、魔法のある世界で色々と違う歴史を辿っている設定です。現実の歴史とは一切関わりがありません。 作中に出てくる文化・習慣・宗教・風俗等は全て架空のものです。 あくまで創作上のものとして楽しんでいただければ幸いです。 | F6: カレヤタミエ | G6: 5427 | H6: 416 | I6: 260 | J6: 324 | K6: ファンタジー|異世界恋愛|女主人公|異世界転生|女性向け
A7: 現代ファンタジー | B7: 100 | C7: 推しにささげるダンジョングルメ〜最強探索者VTuberになる〜 | D7: 書籍版5巻 4月30日に発売いたします!! もう買えるので是非!! | E7: 『ダンジョン産の食材を食べる機会があったんですけど、それが凄く美味しくって──』 推しのVTuberが配信でそんなことを言っていたので、最強探索者の主人公が中小規模の事務所のライバーとしてデビューして、推しとオフコラボでご飯を振る舞うことを目指すお話。 ──なお、当初の予定以上に伸びてしまって、いろいろな面で段々と引くに引けなくなっていく模様。 | F7: モノクロウサギ | G7: 42263 | H7: 1367 | I7: 349 | J7: 175 | K7: VTuber|ダンジョン|主人公最強|飯テロ|スレ|配信|スキル|ハーレム

Sheet 圏外落ち
A1: genre | B1: rank_prev | C1: title | D1: catchphrase | E1: あらすじ | F1: author | G1: star_prev | H1: work_id
B2: 88 | C2: いきなり許嫁候補！？ ～分家序列最下位からの成り上がり？！私、望んでませんから！ほっといてくださいよ！～ | D2: 記憶を持ったまま、転生した！？ よろしい！先行逃げ切りを目指そう！ | E2: 私は前世、戦場で死んだー。 これでやっと休めると思ったら、次の瞬間には生まれ変わっていた。 なんだと！？少しは休ませて欲しいのである！ それになんということか！ 生まれた世界は、前世とはまったく異なっていたのである！ そこには馬もつけずに高速で走る乗り物、車なるもの。 金属の平面に、人間が入り込み情報を無限に発するもの、テレビなるもの。 私が驚愕する数々の文明の利器が、この世界にはあったのである！ この世界でなら、前世死ぬ直前に思った願いがなせるかもしれない！ 何かなしたかったという、曖昧な望みがな！ はははは！ 曖昧な望み！大いに結構である！ 私はその望みを胸に奮い立つ！ 私は早くからの努力を惜しまない！ そう、赤子からでもだ！ ……そう思っていた時もありました。 その気持ちは忘れてはいない。 けれど、この世界を楽しまねば、生まれてきた意味なし！ せっかく自由な世界に生まれてきたのである！ 少しはのんびりしても問題なかろう？ はっ！父よ！今なんと！本家からの招待状（命令書）が届いた！？ 本家の跡取り息子、７才の許嫁を選ぶ為、儀式に１８才までの分家の女子は全員参加せよ！？ 分家である我が家灰咲家。私は５才。本家の命令は絶対である。 断ることなどできはしない。きな臭くなってきたのである。 が、父曰く、我が家は分家序列最下位。その上、末流の末であるとのこと。 ならば、許嫁に選ばれる可能性は限りなく低かろう！ よかろう！若君の許嫁を選ぶ儀式とやらに参加しようではないか！ ５才になり、初めての遠出、新しい情報が満載に得られよう！ そして！本家は金持ちであると聞いている。我が家では食べられぬ美味なるものが、私を待っていよう！ それらを存分に味わいに行くのである！ ああ！！何事であるか！？予定外の事が起ったようである！ 本家の方々、速やかな解決をお願いする！ え！？無理そう！？ 仕方ないのである！私が手を貸そうではないか！！ この作品は、小説家になろう、ハーメルンでも掲載。 | F2: 天野建 | G2: 530 | H2: 7667601420112820499
B3: 91 | C3: 「今日で英雄辞めます」世界を裏から救っていた第零魔法師が学園へ青春しに行った結果、残された国家上層部が崩壊寸前なんだが？ | D3: 世界を救うより、放課後に友達と買い食いする方が難しい | E3: 「陛下、約束通り――今年から学校に行かせていただきます」 歴史の影で数々の厄災を葬り、世界を救い続けてきた国家最高戦力《第零魔法師》レイン・アークライト（17歳）。 功績のすべてを他人に譲り、命がけで働き詰めてきた彼のささやかな夢――それは、 「放課後に友達と買い食いがしたい。学食の日替わり定食を一緒に食べたい」 という、ごくごく普通の【青春】を送ることだった！ 魔力量の測定結果は、狙い通りの「凡庸なＣランク」。 周囲のエリート貴族たちから「平民の落ちこぼれ」と見下されても、レインは内心ガッツポーズ。 （よし！ 完璧な一般生徒だ！ これで友達ができるぞ！） だが、彼の本当の異常さは『１の魔力で１万を出力する異常効率』と『神の魔法式すら書き換える消去眼』。 学園で次々と起こる魔獣の襲撃や暴走事故に対し、レインは全力で【隠蔽工作】を開始する！ 「あ、ゴーレムが爆散したのは設備の老朽化です！」 「結界が強化された？ たまたま風向きが良かっただけですよ！」 ――一方その頃。 レインが抜け、一人で維持していた国家防衛結界の真実を知った上層部は、未曾有の大パニックに陥っていた……。 最強の力を持つ少年が、平穏な青春を守るために全力で「凡人」を演じ抜く、勘違い＆隠蔽系学園ファンタジー、開幕！ | F3: kuni | G3: 139 | H3: 2912051607041182131
B4: 92 | C4: 喫茶店のマスターはバイトのJKを救うためにダンジョンへ向かうそうですよ？～ダンジョン配信で人気の女子高校生を救ったおじさん、実はダンジョン黎明期を戦って今の日本を作った生きる伝説でした～ | D4: 最前線から退いても最強のおじさんは、バイトのJKと共に今一度成り上がる | E4: 飯野可憐は、今を時めく女子高校生ダンジョン配信者だった。 高校生離れした高い実力と、可愛らしい容姿。 その二つを武器に、瞬く間に人気を集めた彼女はこのまま順調に実力を磨き続ければ、日本を代表する探索者になると誰もが思っていた。 しかし、ある日の配信中。 「……い、いやっ！」 イレギュラーと呼ばれる圧倒的な力を持つ魔物と遭遇し、可憐は為す術なく追い詰められてしまう。 絶体絶命。 そんな彼女の前に現れたのは、 「ご無事ですかな？」 一人の冴えない中年男性だった。 「何でマスターがここに！？」 その男の名は、神崎健一。 可憐が人気配信者になるよりも前からバイトしている売れない喫茶店のマスターだった。 売れない喫茶店を構える冴えないオジサンだと思っていたその人物の正体。 それは、ダンジョンが出現したばかりのファンタジー黎明期の日本で最強の探索者として君臨し、幾多の命を救って日本のダンジョン攻略の礎を築いた───生きる伝説だった。 一度は最前線を退き、静かな喫茶店のマスターとして余生を過ごしていた神崎健一。 しかし、女子高校生ダンジョン配信者を救ったその瞬間。 忘れられていた英雄の名が、再び日本中を駆け巡る時、また一つ、世界が変わっていく───。 | F4: リヒト | G4: 702 | H4: 2912051605388942408
B5: 98 | C5: スキルのせいで性別も種族も変わったんだが？！ | D5: 期待して手に入れたスキル…それは『魔女』いやいや、俺男なんだが… | E5: 時は近世…ではなく魔法と科学の発達した現代。この世界では神代の時代からダンジョンというものがある。そんな世界だ。 自分。乙女ヶ崎 夢(おとめがさき ゆめ)はダンジョン配信者を目指しているただの高校生。『一攫千金！』というバカみたいな夢を掲げ毎日ダンジョンについての勉強を行ってる。そしてダンジョン配信者になるためには15歳に鑑定の儀というものを行い、スキルの発現をさせないといけない。 「さて、俺の番ってかねぇ…。何が出るかなっと！」 …そこで目にしたものとは？ | F5: おでんの中のがんもどき | G5: 379 | H5: 2912051604136221250
B6: 99 | C6: 領地を救うため命を捧げた俺、忘れてほしいのに許嫁も聖女もメイドも誰ひとり忘れてくれない 〜俺の記念日を作るとか、聖人認定するとか、復讐するとかやめてください〜 | D6: 「誰も彼も、あなたを忘れられないようにしますから」 | E6: ヴェイル・アスフォルムは、キャラが死にまくる鬱ゲーＲＰＧ『煉獄聖騎士アルベルト』の悪役令息に転生した元サラリーマンである。原作では今日、地下で地脈の封印が破れ、領地が壊滅する。このままだと許嫁のヘラも、聖女ミレイユも、メイドで元暗殺者のリアナも死んでしまう。 ヴェイルは「俺のいない世界で、俺を忘れて、君らしい幸せをつかんで欲しい」と親しい彼女たちに手紙を送り、己の命を犠牲に地脈の暴走を封印する。 全てを救い、死んだ――はずが、なぜか霊体となって目を覚ます。誰にも見えず、声も届かないが、災害で壊れた土地に干渉して癒せる存在に！？ 一方、ヴェイルの死を嘆き悲しんだ３人も、重い感情を抱えたまま動き出す。許嫁は「ヴェイルの名を国史に刻む」と国家規模の政治工作を始め、聖女はヴェイルを信仰の対象として祭り上げ、メイドは「ヴェイル様を追い詰めた人間は殺す」と暗躍を始める。 「そんなことしないでいいから！ 俺のことなんて忘れていいから！」 そう届かない声で叫ぶも、誰ひとり忘れてくれない。おまけにコソコソ進めていた領地の復興作業まで『ヴェイル様の奇跡』として語り継がれ、領民たちによる神格化まで留まることを知らず――！？ | F6: 三船十矢 | G6: 327 | H6: 2912051605688903855
B7: 100 | C7: 異世界転生･･････ってマイナススタートかよ!?〜前世でも嫌われ、転生先でも嫌わている俺は自由を掴むために好感度を稼ぐ〜 | D7: 前世でも転生しても嫌われるのは勘弁だぞ!? | E7: 男の人生は最悪だった。 告白されたと思ったら罰ゲームであり笑いものにされ、 自分から告白して付き合った女性は寝取られて、 また告白されたと思ったら･･････冤罪で襲った罪を着せられて、 家族や友達にも信じてもらえず、最後は自分自身の手で人生に幕を引いた･･････だったんだが、 「･･････ここはどこだ?」 気がついたらふかふかなベッドに豪華な装飾。 これは異世界転生ってやつで俺は勝ち組なのでは!? と思ったら、めっちゃ嫌なやつだったらしく婚約者やメイドとめっちゃ嫌われていたのだ。 「前世でも嫌われて、今世もそうなのかよ!?」 もうあんな惨めな目に遭うのは嫌だ!! 俺は自由に生きたいんだ!! これは前世でお祓いが必要レベルで地獄だった男が、 転生先で幸せを手に入れるために好感度を稼ぐ･･････はずが、 何故か好感度が異常に上がって依存される存在になってしまう物語。 | F7: ドラゴロイド | G7: 270 | H7: 2912051606349982956

Sheet 成長カーブ
A1: genre | B1: 日数帯 | C1: 観測数 | D1: スター中央 | E1: スター下限 | F1: スター25p | G1: スター75p | H1: 話数中央 | I1: スター/日中央
A2: 現代ファンタジー | B2: 〜7日 | C2: 324 | D2: 154 | E2: 22 | F2: 102 | G2: 232 | H2: 9 | I2: 30.8
A3: 現代ファンタジー | B3: 8-14日 | C3: 484 | D3: 356 | E3: 54 | F3: 199 | G3: 675 | H3: 16 | I3: 32.4
A4: 現代ファンタジー | B4: 15-21日 | C4: 400 | D4: 488 | E4: 84 | F4: 264 | G4: 752 | H4: 23 | I4: 27.1
A5: 現代ファンタジー | B5: 22-30日 | C5: 377 | D5: 686 | E5: 74 | F5: 395 | G5: 1194 | H5: 33 | I5: 26.4
A6: 現代ファンタジー | B6: 31-45日 | C6: 447 | D6: 1274 | E6: 109 | F6: 556 | G6: 2646 | H6: 47 | I6: 33.5
A7: 現代ファンタジー | B7: 46-60日 | C7: 344 | D7: 2264 | E7: 379 | F7: 999 | G7: 3328 | H7: 62 | I7: 42.7
A8: 現代ファンタジー | B8: 61-90日 | C8: 311 | D8: 2995 | E8: 506 | F8: 1386 | G8: 4595 | H8: 78 | I8: 39.9
A9: 現代ファンタジー | B9: 91-180日 | C9: 307 | D9: 1812 | E9: 247 | F9: 1130 | G9: 5940 | H9: 132 | I9: 13.4
A10: 現代ファンタジー | B10: 181-400日 | C10: 207 | D10: 4335 | E10: 304 | F10: 1580 | G10: 19650 | H10: 164 | I10: 14.9
A11: 現代ファンタジー | B11: 400日〜 | C11: 191 | D11: 23385 | E11: 647 | F11: 1822 | G11: 42224 | H11: 210 | I11: 39
A12: 異世界ファンタジー | B12: 〜7日 | C12: 311 | D12: 216 | E12: 54 | F12: 158 | G12: 322 | H12: 8 | I12: 43.2
A13: 異世界ファンタジー | B13: 8-14日 | C13: 524 | D13: 394 | E13: 62 | F13: 266 | G13: 690 | H13: 15 | I13: 35.8
... A21: 異世界ファンタジー | B21: 400日〜 | C21: 205 | D21: 8567 | E21: 456 | F21: 3386 | G21: 15341 | H21: 226 | I21: 14.3

Sheet 滞在日数
A1: genre | B1: title | C1: あらすじ | D1: 滞在日数 | E1: 観測回数 | F1: 初回順位 | G1: 最終順位 | H1: 最高順位 | I1: 順位変動 | J1: 実測スター増 | K1: 実測スター/日 | L1: 最終経過日数
A2: 異世界ファンタジー | B2: レベル０な無能悪役貴族のノブレスオブリージュ～転生したらチートもなく死亡フラグしかなかったので、知識チートで全てをへし折る！～ | C2: ゲーム世界“ホーリーソード”の最初に成敗される悪役キャラに転生した主人公。 無能な父と母によって財政状況は最悪で、いずれゲーム主人公によって命を落とす運命にあった。 しかも転生したキャラは運営が面白半分で作った“レベル０”という一切に強くなることが許されていないキャラだった。 せっかく異世界に転生したのに二度目の死は嫌な主人公は、自分を溺愛してくれる両親を説得し領地改革に乗り出す。 才能もチートスキルもない主人公だが、持ち前の明るい気持ちでどんどん改革を進めていく。 クズ商人の成敗、悪徳傭兵団を取り込んで味方にしたり、最強軍団を作ったり、知識を使って新しい事業を始めて大成功させてみたり、ハチャメチャなことをやりまくる！ | D2: 40 | E2: 15 | F2: 86 | G2: 86 | H2: 73 | I2: 0 | J2: 548 | K2: 14.1 | L2: 111
A3: 異世界ファンタジー | B3: 異世界転移に紛れ込んだおっさんは静かに世界を燃やす | C3: 【リアル寄り異世界転移のため軽さはありません】 突然異世界に転移した高校生、１クラス総勢３４名。 そこに、３７歳のおっさんが紛れ込んだ。 おっさんは、唯一の家族であった愛息子を飲酒運転の男に轢き殺され、法の裁きを与えるために司法に望みをかけていた。 しかしその想いは叶わず、懲役最大７年の過失致死傷罪という到底納得できるものではなかった。 そして実力行使に出た男が目覚めたところは…… これは全てを失って生きる希望を無くした男が、クラス転移に紛れ込んだあと、異世界の不条理に抗って行くストーリー 【注意】 ・主人公は簡単に人を殺します（冒頭に理由あり） ・ファンタジー世界としては微妙に現実的な世界を、年齢相当に考えながら動きます ・普通の一般人の大人なので完璧ではなく、経験則による行動が多くなります ・作者はある程度成熟した『おっさん』を好むので察してください ※おっさんの殻を被ったお子ちゃまではありませんので、やっちゃいましたーとか、すぐに恋愛に発展なんてことはありません | D3: 40 | E3: 26 | F3: 91 | G3: 90 | H3: 72 | I3: 1 | J3: 761 | K3: 19.5 | L3: 82
A4: 現代ファンタジー | B4: 神様にもらった回復チートで荒稼ぎしてたら、普通に脱税で捕まりました | C4: ブラック企業を辞めて無職になった青柳りおん（26歳）のもとに、ある日、神様が現れた。 授かった能力は二つ。 「回復」——どんな病も、傷も、欠損すら、細胞レベルで治せる力。 「鑑定」——人の本名・体調・性格・企み・腹の中まで、なんでも見抜ける力。 来月の家賃もやばい状況で、りおんが選んだのは——若返り・治療ビジネス。原価ゼロ、失敗ゼロ、鑑定で悪い客は即お断り。完璧な商売だ。 やがて、塩対応の優秀な秘書・橘七海を雇い、商店街の9,800円から、政財界の大物を相手にする桁違いの商売へ。田舎のボロ屋に地下3階建ての秘密要塞を作り、ドローンとロボットで守らせる。 物理的に死なない俺、腹の中まで見える鑑定、鉄壁のシェルター。 ……完璧なはずだった。 なのに最後にぜんぶひっくり返したのは、国税だった。 ドローンも、ロボットも、政財界の大物の人脈も。 紙切れ一枚（追徴課税）の前には、意味がなかった。 痛快・チート商売コメディ、開幕。 | D4: 40 | E4: 34 | F4: 7 | G4: 66 | H4: 7 | I4: -59 | J4: 1539 | K4: 39.5 | L4: 68
A5: 現代ファンタジー | B5: クビになった解体屋のおっさん、深夜のS級素材解体配信が人類最強に見つかる 〜まかない飯を出してたら、俺を切った大手クランが勝手に曇っていく〜 | C5: 「戦えない奴に払う給料はない」──大手クラン専属の解体師・真壁巧（34）は、十年支えた職場をコストカットで追い出された。 再就職もないまま始めた深夜の解体配信。視聴者は3人。だが、骨一本傷つけずS級魔獣を捌くその手元は、いつしか「人間国宝」と呼ばれ始める。 フードトラックで出す魔獣素材のまかない飯には、なぜかフードを目深に被った腹ペコの少女が通い詰め──彼女の正体は、人類最強と呼ばれるランカー1位で。 一方その頃、巧を切り捨てたクランでは、素材の買取価格が暴落を始めていた。 本人だけが気づいていない。彼の「ただの職人技」が、世界でただ一人のユニークスキルだということに。 | D5: 40 | E5: 34 | F5: 6 | G5: 27 | H5: 6 | I5: -21 | J5: 2008 | K5: 51.5 | L5: 73
A6: 異世界ファンタジー | B6: 転生した凡人は天才に憧れ努力を続ける | C6: ただの冒険者であったアルフ。 住んでいた街が魔物に襲われ、たった一人で魔物の大群と戦い命を落とした。 しかし、次に目が覚めるとアルフレッド・フォン・ヴェルゴールドとして新たな人生を送っていた。 前世の記憶を思い出したアルフレッドは、前の人生では届かなかった天才達を超える力を得る為に努力をする事にした。 二度目の人生でも才能は無いアルフレッドは、前世の記憶を使って高みを目指す。 | D6: 40 | E6: 27 | F6: 92 | G6: 89 | H6: 59 | I6: 3 | J6: 656 | K6: 16.8 | L6: 116
A7: 異世界ファンタジー | B7: 迷宮都市の石路〜その日暮らしの転生者〜 | C7: 異世界のスラム街のような場所に転生した主人公、クロウはチンピラ達とシノギを削りながら、毎日を生きていた。 チンピラ達を倒せるぐらいには強くなっていたクロウだが、前世の日本との暮らしとは比較にならないほど生活水準が低い上、治安も悪い。 とうとう異世界での故郷ともいえるそんな街を捨て、栄えているという迷宮都市に乗り込むことを彼は決心した。 残酷なスラム街に適応して、精神的にヤサグレた彼は、迷宮で名声を得て称賛が欲しい訳ではなかった。ただ、マトモな寝床とマトモな食事を求めている。 自分も信用しておらず、他人はもっと信用していない。彼は一人だった。 これは転生者が、自身の権利や自由を主張するために強さを、そして、失った倫理的なものを取り戻していくお話。 | D7: 40 | E7: 30 | F7: 57 | G7: 91 | H7: 57 | I7: -34 | J7: 881 | K7: 22.6 | L7: 175
A8: 異世界ファンタジー | B8: ロストワーカー～騙された傭兵はヒモ生活を夢に見る～ | C8: ロストワーカーと呼ばれる傭兵が居た。 気分次第で依頼を受け、敵を殲滅する。凄腕だが、少々気分屋の傭兵だ。 しかし、彼はやりすぎてしまった。 気分次第でどの勢力にでも付く彼は、平和になり始めた世界にとって邪魔になったのだ。 国が。ギルドが。教会が。彼1人を消す為に動きだした。 偽の依頼を受けて現れた彼を、世界トップクラスの戦力が待ち構えていた。 そして、ロストワーカ－は表舞台から姿を消した……。 これは騙された結果やる気を無くした男の、二度目の物語である。 | D8: 40 | E8: 30 | F8: 52 | G8: 80 | H8: 48 | I8: -28 | J8: 791 | K8: 20.3 | L8: 175
A9: 異世界ファンタジー | B9: 誰だ、そよ風のレオンなんて言った奴は！ | C9: 日本からの転生者レオン、授けの儀で授かったのは風魔法一つ。日本で見たアニメやラノベの記憶と知識を利用して、風魔法を使い無双する。アイアンランクから冒険者の最高プラチナランクへとのし上がっていく物語です。 | D9: 40 | E9: 30 | F9: 50 | G9: 92 | H9: 46 | I9: -42 | J9: 803 | K9: 20.6 | L9: 209
A10: 異世界ファンタジー | B10: スローライフを送るはずが、スキル『育てる』の使い方を間違えて辺境の貧乏領地が最強へと花開く～前世の妻から枯れたと言われ意地になったオジサンが異世界で咲き誇る～ | C10: 前世の元妻に「枯れたわね」と言って切り捨てられたブラック企業へ勤めるアラフォーおじさんが、神様からスキル【育てる】を授かって異世界転生した。 「絶対に『枯れてない』ってところを見せてやる」 そう意気込むアランは、のんびりスローライフを送りながら、スキルを使って野菜、家畜、技術、果ては領民の「好感度」まで限界突破して育てまくる……あれ？ 間違ったかな…… すると、ただの貧乏領地だったリベイラ領が、王国一の経済・軍事都市へと成長していく。 「あれ、ちょっと『育てる』をやりすぎちゃったかも？ まぁ、いいかぁ……」 元妻への意地から始まった、やりすぎ神童……転生おじさんのドタバタ最強領地スローライフが始まった。 誤字脱字のみAI使用。 『小説家になろう』『カクヨム』で同時掲載中。 | D10: 40 | E10: 30 | F10: 63 | G10: 46 | H10: 46 | I10: 17 | J10: 1006 | K10: 25.8 | L10: 47
A11: 異世界ファンタジー | B11: 魔力０なのに名門魔法学校に入学した俺、ダンジョンに置き去りにされる | C11: 「俺の失態を知っているお前が生きていては困るんだ。あばよ、魔力0の無能」 ――タクトはダンジョン探索の最中、同じパーティのダグラスに裏切られ、ダンジョンの深層に置き去りにされる。 誰もが生還不可能と言う人類未踏の魔境。 絶体絶命のタクトを救ったのは、魔力を探知して喰らう、凶悪な植物型の魔物だった。 魔力測定値『０』ゆえに、魔物から獲物として見向きもされないタクト。彼は生き延びるため、自作の魔導ポーションを植物の魔物に捧げ、奇妙な共存生活を始める。 過酷な環境での日々、タクトの肉体は少しずつ変化を遂げていく。 なんとか深層での生活が軌道に乗ってきたと思ったある日、運悪くダンジョン内に魔物の異常発生が勃発してしまう。 凶悪な魔物がタクトを襲う。 遥かに格上の魔物相手に、タクトはついに自作のナイフを握りしめる――。 ◇ 死線を越えた先に待っていたのは、新たな仲間。 凶悪な植物の魔物の娘『ライア』との出会いだった。 ◇ 一方タクトのパーティメンバーだったダグラス達は、今までタクトを奴隷のように扱い頼り切りだった『つけ』が回ってくる。 タクトが抜けたことで学校の成績を落とし、化けの皮が剥がれていく。 ◇ そしてタクトは深層で、大賢者の遺した隠れ家を発見。 そこで、自身の身体に刻まれた『魔力０の真実』を知ることになる。 地獄の底から這い上がった少年が、家族を守るために安定した職と平穏を目指すハイファンタジー！ | D11: 40 | E11: 30 | F11: 43 | G11: 87 | H11: 35 | I11: -44 | J11: 881 | K11: 22.6 | L11: 83
A12: 異世界ファンタジー | B12: 聖女認定された妹と魔女に堕ちた姉の双子ですが、従者は二人とも守りたいそうです | C12: 親からの愛は双子の妹ばかり向けられる。双子の姉は愛されたいと努力を重ねて、妹より優秀な成績を残す……が、やはり愛されるのは妹ばかり。 そしてトドメとばかりに、妹は聖女に選ばれた。親どころか世界まで妹ばかり選ぶ――その時ついに心が折れた姉は、魔女へと堕ちた。 魔王と並ぶ、人類の怨敵である『魔女』に堕ちた姉は家族や国へと復讐をすべく暗躍し……そして最後には勇者と共に聖女――妹に討たれることになる。 という本来の未来が、偶然双子の姉に拾われて従者になった男によって歪む話。 姉は（親はともかく）妹とは仲良くなるし、聖女は勇者を置いて従者とばかり仲良くなるし、勇者に懐くはずだった『愛し子（チート幼女）』は従者に懐くし、本来の未来を知る者は頭を抱えることになる。 そんな未来を歪ませる（訳あり）従者――主人公キニスが、主である姉（魔女：人類の敵対者）と、その妹（聖女：魔王を討伐しないといけない）の為に色々と頑張る話です。 | D12: 40 | E12: 30 | F12: 27 | G12: 69 | H12: 27 | I12: -42 | J12: 1151 | K12: 29.5 | L12: 64
A13: 異世界ファンタジー | B13: 【6章完結】転生した辺境男爵家の少年は、魔術具で世界を変える | C13: 【6章完結済み】毎日19:00に更新。 愛を知らず、夢を叶えられないまま人生を終えた男は、辺境男爵家の次男サミュエルとして転生する。新しい家族に迎えられた彼は、「今度こそ、自分のやりたいことを形にしたい」と決意する。魔術具を作り、新たな出会いを重ねながら、人々の暮らしを少しずつ変えていく。 小説家になろうにて同時連載中 | D13: 40 | E13: 30 | F13: 44 | G13: 44 | H13: 24 | I13: 0 | J13: 1472 | K13: 37.7 | L13: 86
... A249: 異世界ファンタジー | B249: 四人の天才妹を虐げ続けた兄、英雄となった妹たちに断罪される | C249: 世界を救った四人の姉妹がいた。 剣の頂点に立つ剣聖セリナ。 魔法の頂点に立つ賢者リリア。 錬金術の常識を塗り替えた天才ミリア。 そして世界最大級の商会を築き上げた大商人エマ。 若くしてそれぞれの道の頂点へ辿り着いた彼女たちは、人々から英雄として讃えられていた。 しかし、そんな四姉妹には誰にも語りたくない過去がある。 ――兄、レオン。 幼い妹を魔物の棲む森へ置き去りにした。 毎日のように過酷な虐待を繰り返した。 努力して手に入れた褒美を奪った。 才能を妬み、販路を潰し、夢を邪魔し続けた。 それでも四姉妹は兄に屈することなく、自らの力で世界の頂点まで上り詰めた。 そして魔王との戦いを終えた彼女たちの前に現れたのは、変わり果てた姿となった魔神の兄だった。 すべての因縁に決着がついた後、レオンが犯してきた数々の罪を裁くため、神託裁判が開かれる。 証人は四人の妹。 そして証拠は、過去に起きた出来事をありのままに映し出す神器――《真実の鏡》。 世界中が見守る中、四姉妹は兄から受けた仕打ちを一つずつ告発していく。 誰もが思っていた。 これは、稀代の悪党が犯した罪のすべてを暴き、その報いを受けさせるための裁判なのだと。 だが――。 真実の鏡に映し出された過去は、彼女たちの記憶と同じはずなのに、どこかがおかしい。 一つの真実が明らかになるたび、新たな疑問が生まれる。 世界を救った四人の英雄と、彼女たちの人生を弄び続けた最低の兄。 長きにわたる因縁に、今、決着の時が訪れる――。 | D249: 14 | E249: 12 | F249: 86 | G249: 7 | H249: 7 | I249: 79 | J249: 1572 | K249: 120.9 | L249: 19
A250: 異世界ファンタジー | B250: ゲーム世界に転生したら農家の息子だった | D250: 14 | E250: 10 | F250: 10 | G250: 98 | H250: 10 | I250: -88 | J250: 250 | K250: 19.2 | L250: 1503
A251: 異世界ファンタジー | B251: 駆け引き上等な異能力バトル系の悪役に転生したが、アホなので高度な頭脳戦がわかりません。物理を魔術と言いはって無双します | C251: 異能力バトル世界で最強クラスの頭脳派悪役【リジュン】。 ひょんな拍子に前世の記憶を取り戻し、自分が転生者であることを知った。 前世の知識があれば人生楽々モード。 ……とはいかず、代償として思考力を失っていた。 アホになったのだ。 この世界は、心理戦、騙し合い上等の異能力バトルもの。 昨日までなら勝てた読み合いも、アホになったリジュンにはさっぱりわからなくなっていた。 しかも、リジュンを狙う魔術師は山ほどいる。 魔術師同士は争い合う宿命にあり、このままでは待つのは己の破滅だ。 「このままでは殺される……そうだっ！」 頭では負ける。 なら、頭を使わなければいい。 物理だ。物理がすべてを解決する。 読み合いで勝てないなら真正面から殴ればいい。 罠があるなら全部まとめて吹き飛ばせばいいのだ。 「うおおお！ 物理うおおおお！ パワー is 力ァァ！」 頭脳派異能力バトルの世界で物理を極める。 駆け引きを力でねじ伏せる、脳筋悪役転生ファンタジー！ | D251: 14 | E251: 11 | F251: 77 | G251: 94 | H251: 34 | I251: -17 | J251: 333 | K251: 25.6 | L251: 12
A252: 異世界ファンタジー | B252: 神様の目で世界の全部が視えている俺は、今日も『たまたま』で通したい | C252: 前世は他人の旅程ばかり数えて過労で死んだ会社員。転生した俺には、女神にもらった〝世界の全部が視える目〟がある。地脈の氾濫も、魔物の湧きも、崩れる橋も――起きる前に、全部視える。 だから先回りして、雑用のふりで潰す。 報酬は要らない。名声も要らない。Ｅ級の雑用係として、うまい豆と熱い白湯があればそれでいい。 なのに。 Ｓ級三人ぶんと見積もられた災害が、杭三本の被害で収まった街で。 勘ひとつで生きてきた女剣士が、俺の「たまたま」を黙って数え始めた。 聞かれたら、終わる。俺は嘘がつけない。 でもあの人は、詮索しない主義だ。 誰も俺を知らない。知らないまま、街は救われていく。 これは、世界でいちばん強い雑用係と、気づいているのに聞かない相棒の、静かで痛快な旅の話。 | D252: 14 | E252: 10 | F252: 90 | G252: 97 | H252: 62 | I252: -7 | J252: 107 | K252: 8.2 | L252: 21
A253: 異世界ファンタジー | B253: 尻尾を触らせてもらっただけなのに、ドラゴンのお姫様が離してくれません ～一途すぎるドラゴン姫は、番を絶対に逃がさない～ | C253: 見習い魔法使いの琥珀は、森で悠久の時を生きる魔女に育てられた十六歳。 魔法の才能は天才級。 その一方で、朝は起きられず、勉強は嫌い。女の子を眺めることを生き甲斐にする、自他ともに認める自由人だった。 そんな琥珀は、常識を身につけさせるため、師匠によって半ば強引に魔法学園へ入学させられる。 入学初日、そこで出会ったのは、黄金の角と美しい尻尾を持つドラゴンのお姫様・ルリ。 軽い気持ちで尻尾を触らせてもらった――たったそれだけの出来事が、琥珀の人生を大きく変えてしまう。 龍族にとって「番」は、一生に一人だけの運命の相手。輪廻を越えても見失うことはなく、一度見つけたら決して離さない。 しかし、そんなことを知らない琥珀は、距離感がおかしいルリに首を傾げるばかり。 手を繋がれ、隣を独占され、得意な魔法でも勝てず、少しずつ逃げ道を塞がれていく見習い魔法使いと、運命の番を見つけた一途すぎるドラゴン姫。 これは、自由気ままな女好き魔法使いが、激重な愛情を向けるドラゴン姫に振り回される、学園百合ラブコメディ。 | D253: 14 | E253: 10 | F253: 70 | G253: 86 | H253: 70 | I253: -16 | J253: 223 | K253: 17.2 | L253: 25
A254: 異世界ファンタジー | B254: 前世で遊んでいたアウトロー系アプリゲームのキャラクター達を召喚したら、いつの間にか裏社会のドンになっていたんですけど？ | C254: ある日、主人公であるダルク・フィン・クヴィスト（３８歳）は潰れかけの冒険者クラン、黒竜の爪のクランマスターを引き継ぐ事となる。 本人は今までの恩もある為、潰れ行くと分かっていても残ってくれているメンバーの為にクランマスターを引き継ぐのだが、どうやらこれがダルクの持っている能力の解放条件だったようだ。 その能力とは前世でプレイしていたスマホゲーム『極悪道・天下統一』の能力を引き継ぐというものであった。 その結果ダルクはで極悪道・天下統一で手に入れたキャラクター達をこの世界に呼び出しクランの立て直しを図るのだが、気が付けば裏社会のドンへと上り詰めていたのであった。 | D254: 14 | E254: 6 | F254: 99 | G254: 88 | H254: 88 | I254: 11 | J254: 204 | K254: 15.7 | L254: 52
A255: 現代ファンタジー | B255: スキル『ダンジョンシェルター』 | C255: 突如世界中にダンジョンが発生した。 その現場に偶然居合わせたトオルはダンジョン発生に巻き込まれ、ダンジョンの中に取り込まれてしまう。 お決まりのステータスで自身のスキルを確認すると、現れたのは『ダンジョンシェルター』という聞きなれない言葉だった。 スキルで生み出したシェルター。外にさえ出なければ安全だと判明し、シェルター生活をスタートしたトオル。 案外快適なシェルター生活。このまま何事もなく引きこもり生活を過ごそうとしたトオルだったが、そうは問屋が卸さない。 トオルの元には次々とトラブルが舞い込んでくるのであった。 | D255: 14 | E255: 10 | F255: 60 | G255: 93 | H255: 60 | I255: -33 | J255: 166 | K255: 12.8 | L255: 38
A256: 現代ファンタジー | B256: 【微エロ注意】異世界で最強になった俺、《解析》しかできない無能だと思われている～見た能力をコピー・改造して現代ダンジョンでも無双する～ | C256: 【エロ×微グロ注意！】 「異世界を救って帰ってきたら、今度はダンジョンの主になってた」 異世界で長い年月を戦い抜き、世界を救って現代日本へ帰還した天御門皇牙（あまみかど こうが）。 しかし世間での評価は、第五等級《解析》しか持たない新人探索者。 本当の能力も、異世界で得た力も隠したまま、幼馴染の令嬢・西園寺詩乃と新宿ダンジョンへ挑むことになった皇牙だったが、そこで待っていたのは現代人の知らないダンジョンの秘密だった。 悪魔、謎めいた能力者たち、そして地下で動き始める未知の勢力。 最弱扱いの新人探索者は、誰にも知られないまま現代のダンジョンを攻略していく。 | D256: 14 | E256: 12 | F256: 88 | G256: 68 | H256: 61 | I256: 20 | J256: 134 | K256: 10.3 | L256: 18
A257: 異世界ファンタジー | B257: 【書籍化】凡人の俺は『元』天才令嬢のご奉仕で最強になるらしい～魔力を失って落ちこぼれたお嬢様の代わりに使い魔としてＨなことをしてもらって戦います～ | C257: 『私の全部、あなたにあげる』 平凡な男子高校生の七麻慎也(ナナツマシンヤ）は、ある日突然異世界『ノヴァーリス』に召喚される。シンヤを呼び出したのは魔法の名家グラストベリー家の天才令嬢アルフェリア・グラウンド。彼女の使い魔として召喚されたがシンヤにチート能力はなく、それどころかアルフィリアの魔力のほとんどを吸収してしまっていた。 「この泥棒……！ 私の魔力、返しなさい……！！」 異世界召喚は禁忌の魔法であり、それを使ったことがばれたら大変なことになる上に魔力を失ったことが周囲にバレたら一大事。元の世界に帰りたければ協力しろと脅されたシンヤはアルフィリアと同棲生活を送ることに。 そんなある時、アルフェリアとのスキンシップをトリガーにシンヤの秘められた力が覚醒することが判明する。 「これは…そう！ 仕方なくよ！ あなたに強くなってもらうために仕方なくやっていることなの！」 しかし能力を引き出すスキンシップを行うも過激な行為になるほど魔力が使えることがわかり、段々ヒートアップしていく行為……次第に心の距離も段々近くなって……？ 「ねぇ……シンヤ。もっと私でドキドキして？ 私だけで興奮、して？」 落ちこぼれになった元天才お嬢様とキスで最強の力を得る元凡人の学園ファンタジーラブコメ、ここに開幕！ | D257: 13 | E257: 9 | F257: 47 | G257: 80 | H257: 14 | I257: -33 | J257: 172 | K257: 14.3 | L257: 36
A258: 現代ファンタジー | B258: 【配信中】何でも屋の魔法使いですが、依頼が毎回キチガイじみてて草 | C258: ダンジョンが現れて約半世紀。魔法もスキルも当たり前になった現代日本で、常磐カナタは何でも屋をやっている。 探索者ライセンスはC級。配信の登録者は二万人ちょっと。報酬は安く、依頼は選ばず、本人はいつもローテンション。 ──ただし、依頼の中身がおかしい。 「押し入れにダンジョンができたので塞いでください」 「駅前の噴水に海竜が住み着きました」 「うちの婆ちゃんが迷宮のボスに勝ってしまったんですが」 どう考えても三万円の仕事じゃない。 どう考えもC級の領分じゃない。 なのにカナタは毎回、溜息ひとつで片付けてしまう。 本人曰く、「普通にやってるだけ」。 コメント欄曰く、「普通とは」。 やる気ゼロ、実力カンスト。 コメント欄が毎回阿鼻叫喚の何でも屋配信、本日も開局です。 | D258: 13 | E258: 9 | F258: 38 | G258: 98 | H258: 38 | I258: -60 | J258: 108 | K258: 9 | L258: 52
A259: 現代ファンタジー | B259: ダンシングシーカー ～異世界帰りのおっさん、現代ダンジョンで今日も踊る～ | C259: 勇者として異世界を救い、ようやく日本へ帰ってきた鳩山雄二。 しかし転移先を間違えて送られてしまった現代は。ダンジョンが当たり前の世界にずれてしまっていた。 生活費を稼ぐため探索者になった彼は、異世界で身につけた魔法でモンスターを一撃。 本人は目立つつもりなどない。 だがネットでは、その独特な戦い方から「ダンシングシーカー（仮称）」と呼ばれ始める。 今日も指を鳴らしながらダンジョンを踊るように駆け抜ける。 | D259: 13 | E259: 9 | F259: 15 | G259: 73 | H259: 15 | I259: -58 | J259: 264 | K259: 22 | L259: 13
A260: 現代ファンタジー | B260: 努力厨の転生無双～才能だけが足りなかった男、環境・容姿・運すべてを手に入れ最強となる～ | C260: 「天才とは１％のひらめきと９９％の努力」という言葉がある。 この言葉が正しいのなら、主人公・理玖は天才ではなかった。 ありとあらゆる分野に挑戦し、死ぬほど努力し、しかしあと一歩のところでいつも天才たちに阻まれてきた。 そんなある日、突如世界は魔物たちに襲われ、理玖は命を落とした。 そして次に目覚めた時、理玖はすべてを手に入れていた。 由緒正しい血筋。 優しい家族。 優れた容姿。 魔術の才能。 理玖は決意する。 「この恵まれた条件でもう一度…９９％の向こう側に…天才を目指す！」 これはとっくに天才だった主人公が前世のノリで努力を積み重ねた結果、ダンジョン溢れる現代世界で最強になって無双する物語。 | D260: 13 | E260: 9 | F260: 18 | G260: 94 | H260: 18 | I260: -76 | J260: 134 | K260: 11.2 | L260: 30
A261: 現代ファンタジー | B261: 妹のダンジョン配信にうっかり映った俺、正体不明の最強探索者として世界中に追われ始めた | C261: 妹のミナは、ダンジョン配信者になるのが夢だった。 登録者はまだ少ない。 探索者としての実力も、決して高くない。 それでも夢を諦めない妹を、兄の神代蓮は裏方として支えていた。 機材を運ぶ。 カメラを調整する。 危険がないか確認する。 それだけ。 蓮自身も、目立つつもりなんてなかった。 かつて最上位探索者として名を馳せた過去も、今では隠している。 ところが、ミナの初めての本格的なダンジョン配信で事件が起きた。 妹を助けるため、蓮が動く。 そして――ほんの数秒だけ、配信画面に映り込んだ。 『今の誰？』 『……え？ 動きおかしくない？』 『あの男、何者だよ』 たった数秒の映像は切り抜かれ、SNSへ。 動画は瞬く間に拡散され、掲示板では正体探しが始まり、プロの探索者までその動きを分析し始める。 やがて、一つの噂が広がっていく。 ――あの男は、かつて伝説と呼ばれた最強探索者なのではないか。 一方その頃。 当の蓮は、何も知らずに妹の機材を運んでいた。 「……なんで俺がこんなことになってんだ？」 これは、妹の夢を応援していただけの兄が、うっかり配信に映ったことから始まる物語。 妹の登録者が増えるたび。 配信が盛り上がるたび。 謎の兄の正体に、世界が少しずつ近づいていく。 | D261: 13 | E261: 11 | F261: 69 | G261: 21 | H261: 18 | I261: 48 | J261: 327 | K261: 27.2 | L261: 16
A262: 異世界ファンタジー | B262: 勇者パーティーの回復術師、平和な世界で壊れてゆく～仲間の傷を未来の自分に預けていたら、真実を知った仲間が曇った～ | C262: 自己犠牲と自己陶酔は紙一重だなと。 | D262: 13 | E262: 9 | F262: 55 | G262: 97 | H262: 55 | I262: -42 | J262: 219 | K262: 18.2 | L262: 66
... A441: 異世界ファンタジー | B441: 流れ者のおっさん、なんか強い。 | C441: 孤児オルランドは、貧しさから逃れるため、剣で身を立てることを決意する。行商人の馬車に忍び込み護衛を押し売り、都で冒険者を経験したのち傭兵に転向。数々の戦役で武功を立て、貴族に召し抱えられ、叙勲を受け、騎士となり、名誉ある銀獅子団の長を努めた。 その後、狼の騎士団を設立、王国最強の戦闘集団として名を馳せる。ひいては予言の災厄、暗黒竜を討つため、王国中から選び抜かれた英雄集団『竜滅隊』に抜擢され、見事これを討ち、王国の滅びすら防いだ。 そして、今回、伝説の英雄オルランドは、王の勅命により、南方にて全七軍総兵力120万からなる蛮族蹂躙大軍を指揮することに。これは膠着した南方戦線に決定的な一撃を加え、王国の支配を盤石にする侵攻だったが──。 「……えー、全軍撤退」 全軍司令官オルランド公爵は、なんの気の迷いか全軍に撤退命令を残し、忽然と姿を消してしまった。 これは成り上がり終えて「コレジャナイ」と悟ったおっさんが新しい冒険を始める物語。 | D441: 2 | E441: 2 | F441: 92 | G441: 84 | H441: 84 | I441: 8 | J441: 10 | K441: 10 | L441: 4
A442: 異世界ファンタジー | B442: クラスで集団異世界転移。毎日ゴミ拾いしていたことで善行ポイントがカンストしてたので、ポイント消費して強さよりも生き残ることを優先します。 | D442: 2 | E442: 2 | F442: 89 | G442: 76 | H442: 76 | I442: 13 | J442: 17 | K442: 17 | L442: 5
A443: 異世界ファンタジー | B443: 俺の弟子が俺の彼女を寝取った挙句、俺の尊厳破壊してくるんですが……？復讐するけど大丈夫？〜黒蝕を纏いし英雄は復讐の果てに何を見る〜 | C443: ​元・Aランク冒険者のレオン・ヴァルハイトは、かつて仲間を庇って魔力回路を激しく損傷し、第一線を退いた。それでも絶望せず、手塩にかけて育て上げた弟子・シディスと、長年連れ添った恋人・エリスの未来を信じて誠実に生きていた。 ​しかし──待っていたのは、残酷すぎる裏切りだった。 ​「落ちぶれた貴方と一緒にいても、将来が見えないの」 「師匠、貴方の功績も恋人も……全部僕が奪ってあげましたよ」 ​最年少Sランクへ上り詰めたシディスは、エリスを寝取った挙句、レオンの研究実績を「盗作」と偽ってギルドへ告発。社会的地位、金、名誉、そして愛した女──すべてを奪われ、雨の街で血と泥を舐めるレオン。 ​「殺してやる……絶対に許さない……！」 ​怨念の底で彼が開いたのは、決して触れてはならない古代の禁忌『黒蝕の書』。 激痛と肉体の破壊を引き換えに、触れたものの能力と存在を解体・腐敗させる悪魔の力を手に入れたレオンは、自分を「特別」と愛でる謎の銀髪魔女・シェラとともに、冷酷なる逆・尊厳破壊の復讐劇を開始する。 ​一方、レオンを嘲笑い、最高峰の人生を謳歌していたシディスとエリス。 彼らはまだ知らなかった。 自分たちが誇る「天才の才覚」も「美しき絆」も、すべて内側から黒く蝕まれ、破滅へと向かっていることに──。 ​衰退した元師匠×怪しい秘術を操る魔女が贈る、痛快で凄惨なダークファンタジー・復讐劇。 | D443: 2 | E443: 2 | F443: 79 | G443: 95 | H443: 79 | I443: -16 | J443: 17 | K443: 17 | L443: 9
A444: 現代ファンタジー | B444: ダンジョンで拾った卵から生まれた少女に「ぱぱ」と懐かれたので育てることにした――なお、危険度は国家消滅級らしい | C444: ダンジョン探索中、ソロ探索者の結城朔は、地図には存在しない小部屋で一つの卵を見つける。 魔物の卵なのか、それとも未知のアイテムなのか。鑑定してみても結果は『測定不能』。どう考えても怪しく、関わらない方がいいはずだった。 ところが、朔がどうするか迷っている目の前で、卵にひびが入る。 「……割れた？」 殻の中から現れたのは、魔物ではなかった。 銀色の髪をした、小さな少女だった。 少女はしばらく朔の顔を見つめると、嬉しそうに両手を伸ばす。 「……ぱぱ？」 「違う」 「ぱぱ！」 「だから違うって」 なぜか完全に父親だと思われ、そのままとんでもなく懐かれてしまう。 しかも、この少女――ミアは、どうやら普通の子供ではない。 朔では苦戦するはずの魔物が、ミアを見るだけで逃げ出す。地図に存在しない通路を見つけ、誰にも開けられなかった扉を当たり前のように開いてしまう。 そして朔に危険が迫った時だけ、ダンジョンそのものが異常な反応を見せる。 さすがに何かがおかしい。 そう考えた朔がミアを探索者協会で詳しく調べてもらった結果、告げられた判定は想像を遥かに超えていた。 ――推定危険度、国家消滅級。 「……嘘だろ？」 「ぱぱ、だっこ」 国家消滅級と言われても、朔の腕の中にいるのはどう見ても甘えん坊の小さな女の子だ。 ただ一つだけ、確かなことがある。 あの卵を拾った日から、朔の知っているダンジョンは、もう以前と同じ場所ではなくなっていた。 | D444: 2 | E444: 2 | F444: 50 | G444: 30 | H444: 30 | I444: 20 | J444: 23 | K444: 23 | L444: 5
A445: 現代ファンタジー | B445: 裏社会のジョーカー、現代ダンジョンで成り上がる ～世界最大の賭場に人生を賭ける～ | C445: 十年前、世界各地に突如としてダンジョンが出現した現代日本。 神崎隼人、二十二歳。 裏社会で《JOKER》と呼ばれる彼は、依頼人に代わって大勝負に挑む凄腕の代打ちギャンブラーだった。 すべては、難病《環境魔素不適合症》を患う妹・美咲を救うため。 だが三年に及ぶ治療で借金は四億円近くまで膨れ上がり、一晩で一千万円を稼げるようになった今でさえ、仕事も報酬も裏社会の胴元に握られたまま。 そんなある夜、隼人は一人のトップ探索者の配信を目にする。 魔石。レアドロップ。億単位の希少装備。 ランクを上げれば跳ね上がる収入。 危険なら自分の意思で撤退できる一方、死ねばそれで終わり。 隼人は計算する。 ――A級探索者まで上がれば、妹の治療費も借金も、自分の力だけでどうにかできる。 しかも、この世界には一度のドロップですべてをひっくり返す大当たりまで存在する。 「……なんだ。ちゃんとした賭場があるじゃねえか」 探索者となった隼人に与えられたのは、複数のビルドを持てる《複数人の人生（マルチアカウント）》と、効果すら定かではない《運命の天秤（フェイト・スケール）》。 戦士、魔法、遠距離、そして無数の装備とスキル。 拾い、組み、賭け、時にはすべてを突っ込む。 やがて配信者《JOKER》として知られていく男の、現代ダンジョン成り上がりが始まる。 ――命を賭けるなら、勝ち分は全部いただく。 なろうハーメルンにも掲載してます。 | D445: 2 | E445: 2 | F445: 97 | G445: 85 | H445: 85 | I445: 12 | J445: 8 | K445: 8 | L445: 6
A446: 異世界ファンタジー | B446: 最強おじさん宇宙へ行く 喋る宇宙船と魔法で無双する話 | C446: 色んな異世界を渡り歩いた最強おじさんが、SFっぽい世界で宇宙船を手に入れて無双する話です。 タイトル以上の中身がない！ ノンストレス！ だいたい雰囲気で流してオッケー！ 一応科学っぽい雰囲気をだしたりもしてますけど、とてもSFのジャンルに入れる勇気のなかった感じのヤツです！ 文庫にして、一冊分くらいの分量は更新保証します。 | D446: 2 | E446: 2 | F446: 97 | G446: 94 | H446: 94 | I446: 3 | J446: 23 | K446: 23 | L446: 27
A447: 現代ファンタジー | B447: アラサーからのダンジョン探索～英雄は目指さない。マイペースに遊びながら稼ぎます～【書籍一巻五月二日発売！】 | C447: 【書籍発売！】 『アラサーからのダンジョン探索』 2026年5月2日発売！ ドラゴンノベルス様より刊行！ 世界にダンジョンが現れて二年。いくつもの混乱を巻き起こし、ようやく世界が安定してきた頃。 主人公、小畑楓太（三十二歳）は安定した仕事を捨て、ダンジョン探索者としてデビューすることにした。 二次元オタクな楓太は、ダンジョンへの憧れを捨てきれなかった。しかし、死にたくもないし自分が英雄のような活躍が出来るとも思えない。 だからこそ、楓太は待った。 情報が集まり、安全に探索が出来ると確信できるその日を。 そして、時は来た。 退職を決意し、偶然にも全く同じことを考えていた友人二人と共に、楓太は探索者となる。 億万長者になりたい訳じゃない。英雄になりたい訳じゃない。 ほどほどのスリルを味わい、疲れたら休日。気分で仕事して気分で遊ぶ。 目指すはストレスフリーな自由な生活。他人の目は気にしない、意識低めのアラサー探索者の日々。 （注：なお、本人の意識と周りの評価が重なるとは限らない） 【近況ノートにて十万字ほど先が読めます。限定公開しておりますので、どんどん読みたいと思った人はサポーターをどうぞよろしくお願いします】 【カクヨムコンテスト１０にて、現代ファンタジー部門特別賞を受賞しました！ 注目を集めてくださった皆さんのお蔭です！ ありがとう！】 【AI補助利用しております】 １、 資料検索、相談。辞書代わり ２、 固有名詞のアイディア出し なろうでも投稿しております。 | D447: 2 | E447: 2 | F447: 93 | G447: 92 | H447: 92 | I447: 1 | J447: 13 | K447: 13 | L447: 587
A448: 現代ファンタジー | B448: 大切な家族を守ります 世界崩壊サバイバル ～俺だけドロップテーブルが見える～ | C448: 世界が崩壊した日、朝倉かなめが手に入れたのは《ドロップ》というギフトだった。 魔物を見るだけで、何を落とすのかが分かる《ドロップテーブル》。 ゴブリンなら食料や医療品。 角ウサギなら日用品。 別の魔物なら、燃料や装備まで。 そして《運》を上げれば上げるほど、より希少なもの、より自分に必要なものが手に入りやすくなる。 力を上げれば、自分は強くなれる。 体力を上げれば、生き残りやすくなる。 それでも、かなめが選んだのは――《運》だった。 自分一人が強くなるより、妻と一歳の娘が生きるために必要なものを持ち帰りたい。 食料が足りなければ、食料を落とす魔物を狩る。 薬がなくなれば、医療品を落とす魔物を探す。 娘のおむつが必要なら、日用品を落とす魔物を狙う。 そして足りない戦闘力は、ドロップした装備で補えばいい。 停電した街。 止まった物流。 あふれ出した魔物。 昨日まで金を出せば買えたものが、もう店にはない。 だから今日も、かなめは必要なものを落とす魔物を探しに行く。 家族三人で、この崩壊した世界を生き残るために。 | D448: 2 | E448: 2 | F448: 99 | G448: 80 | H448: 80 | I448: 19 | J448: 4 | K448: 4 | L448: 5
A449: 現代ファンタジー | B449: レベル－1の伝統魔法使い ～ダンジョン発生以前から魔法を探求していた俺は、次元が違いすぎて素人扱いされている～ | C449: １０年前、世界に発生したダンジョン。それにより魔法に目覚めた人類はウィザードと呼ばれた。赤杖蒼夜（あかづえ そうや）は、ダンジョン発生以前より、１０００年の歴史を誇る魔法一族であり、史上唯一天才と呼ばれた魔法使いだ。だが、彼は次元が違いすぎて、ウィザードを測定するステータスではレベルが－１だった。蒼夜にとって、ウィザードとは補助輪付きの素人魔法使いにすぎない。Ｅ級ウィザードにすら見下される存在でありながらも、彼は高ランクダンジョンを次々とクリアしていく。ダンジョンの奥深くに眠るという宝玉。ウィザードの潜在能力を引き出すその高価なレアアイテムを蒼夜はなぜか破壊して回っていた。ウィザード全員を敵に回してまで宝玉を破壊する彼の目的とは――？ ※小説家になろうにも掲載しています。 | D449: 2 | E449: 2 | F449: 95 | G449: 93 | H449: 93 | I449: 2 | J449: 4 | K449: 4 | L449: 10
A450: 異世界ファンタジー | B450: 無録の神匠 〜「才なし」と捨てられた辺境で、壊れた神様と廃村を直して暮らします〜 | C450: 「回路なし」——六歳の鑑定でそう告げられて以来、俺は「無録様」と嘲られてきた。 貴族家の三男アルト（中身は、機械を直して死んだ42歳のエンジニア）は、家督整理のすえ、辺境の廃村リンデ村へ名目だけの領主として捨てられる。 だが村はずれの祠で、左腕の欠けた絡繰り人形を直したことから、すべてが動き出す。 「——千年ぶりに、まともな仕事を見た」 人形に宿っていたのは、忘れられた工匠神ヴェルク。契約により、触れた物をあるべき姿へ還す《万象修復》が目覚める。 井戸を直せば水が湧き、屋根を直せば人が集まり、魔物を治せば——なぜか、慕われる。 直せるものは、直す。それだけの信条で廃村を立て直していくうちに、「呪われた辺境」に眠る千年の秘密が、少しずつ顔を覗かせ始める。 これは、世界で一番小さな村から始まる、世界で一番大きな「修理」の物語。 （全10章[1章11〜12話]で完結予定） | D450: 2 | E450: 2 | F450: 78 | G450: 72 | H450: 72 | I450: 6 | J450: 13 | K450: 13 | L450: 51
A451: 異世界ファンタジー | B451: 転生少女が工房を開いたら、有力者たちのたまり場になった | C451: 転生者のアリエルは才能に恵まれていたものの、出世に興味がなかった。 学生時代の研究は一部の人間にやたらと評価されていたが、それをひけらかすと嫉妬されて面倒だと考えるのがアリエルだ。 あまり人の来ない田舎の故郷で工房を構えることに決めるのは、自然なことだった。 しかしどういうわけか、アリエルの工房には常に学生時代に知り合った有力者が各地から集まってくる。 そんな有力者達にアリエルは「さっさと帰れ」と正面から告げつつ、今日も適当な接客を繰り返すのだった。 「ハーメルン」にも投稿しています。 | D451: 1 | E451: 1 | F451: 91 | G451: 91 | H451: 91 | I451: 0 | J451: 0 | K451: 0 | L451: 0
A452: 現代ファンタジー | B452: 外れ職《案内人》の俺、駅地下ダンジョンで迷子を助けていただけなのに、最短ルートが国家機密になりました | C452: 新宿駅地下にダンジョンが接続されて十年。 探索者、配信者、ギルドが名声と金を求めて潜る時代に、水瀬透が覚醒した職業は《案内人》だった。 能力は、ただ道が見えるだけ。 攻撃力なし。防御力なし。探索者試験では最低評価。 駅員としても探索者としても半端者だった透は、ある夜、ダンジョン崩落事故に巻き込まれた人気配信者・朝倉澪と迷子の少年を助ける。 その瞬間、生配信に映った。 「白い線に沿って走れ。そこだけが生きて帰れる道だ」 誰も知らない安全ルート。 閉ざされた改札の先にある隠し出口。 ボスを倒さず、人を全員生還させる異常な攻略。 掲示板は騒然。 大手ギルドは能力を奪おうとし、ダンジョン庁は彼を国家機密扱いする。 これは、戦えない外れ職の青年が、最短ルートだけで世界最高の探索者になる物語。 | D452: 1 | E452: 1 | F452: 86 | G452: 86 | H452: 86 | I452: 0 | J452: 0 | K452: 0 | L452: 48
A453: 現代ファンタジー | B453: 【悲報】Ｓ級ダンジョンで全滅しかけたおっさん（42）、バグで『不老不死の銀髪幼女』にＴＳ転生してしまう。なお、元のクズパーティが泣きながら追悼配信してる目の前に、ラスボスの遺品を持って乱入した模様 | C453: 【手軽に一気に駆け抜ける、カタルシス極振りの全部盛りバズ無双！】 42歳の冴えない荷物持ち・佐藤タカシは、最悪なクズ勇者と元カノの聖女に嵌められ、Ｓ級ダンジョンの最深部で生贄に捧げられた。 ――誰もが俺の死を確信し、地上ではクズどもが同情を誘う「追悼生配信」で大金を稼ぎ始める。 しかし、ダンジョンのバグが発動した。 目覚めたタカシは、レベル999・全ステータス限界突破の『不老不死の銀髪ロリ真祖（美少女）』へと転生していたのだ！ 「よお、ずいぶん俺の死体で儲かってそうじゃねえか」 敵からドロップしたマントを羽織り、たった今ワンパンで撲殺したＳ級ボスの遺品を引っ提げて、クズどもの生配信スタジオへ窓から乱入！ 中身はおっさん、見た目は最強ロリの圧倒的ギャップに、世界中のネット民（コメント欄）が大熱狂！ クズパーティの言い訳を全世界に暴いて完全社会的に抹殺（ざまぁ）した後は、最高級タワマンを全額一括で購入し、しま〇らのスウェット（キッズサイズ）を着て、気ままなダンジョン散歩＆生姜焼き調理配信で秒で億を稼ぐ無敵のハッピーエンドへ！ 大物ギルドの卑劣な罠も、国家最高戦力の陰陽師の襲来も、ただの「ため息（魔力圧）」で台風のゴミ袋のように吹き飛ばす！ 「おっさんの本気、ちょっとだけ見せてやるわ」 （TS、ダンジョン配信、ロリ真祖、おっさん、ざまぁ、ネットの反応）を極限まで詰め込んだ、超高濃度・即効性のスカッと無双ファンタジー、ここに開幕！ | D453: 1 | E453: 1 | F453: 91 | G453: 91 | H453: 91 | I453: 0 | J453: 0 | K453: 0 | L453: 5
A454: 現代ファンタジー | B454: 元伝説の探索者、辺境でリゾート経営を目指したら世界中のS級冒険者が集まる聖地になっていた | C454: ブラック探索者ギルドで過労死寸前まで働かされた元・SS級探索者のジン。彼は引退し、静かな山奥の未開ダンジョン跡地を買い取って、念願の「温泉サウナリゾート」を開業する。 しかし、彼が「ただの熱源・水風呂」として利用していたのは、人類を滅ぼすレベルの極大古代魔術と、神聖なる精霊の泉だった。本人は至って真面目にサウナの質を追求しているだけなのに、訪れた客（世界トップクラスの配信者やS級冒険者）は「この過酷な試練を笑顔でこなすなんて……！」「この湯、呪いが一瞬で解けるぞ！？」と大勘違い。 知らぬ間にその様子が世界中に配信され、ジンは「世界を陰から支配する謎の隠世神」として崇められていく。平和に温泉を営みたいジンと、勝手に世界規模の事件に巻き込んでくる周りのギャップを描く、勘違い系現代ファンタジー！ | D454: 1 | E454: 1 | F454: 95 | G454: 95 | H454: 95 | I454: 0 | J454: 0 | K454: 0 | L454: 4
... A483: 異世界ファンタジー | B483: 異世界転生･･････ってマイナススタートかよ!?〜前世でも嫌われ、転生先でも嫌わている俺は自由を掴むために好感度を稼ぐ〜 | C483: 男の人生は最悪だった。 告白されたと思ったら罰ゲームであり笑いものにされ、 自分から告白して付き合った女性は寝取られて、 また告白されたと思ったら･･････冤罪で襲った罪を着せられて、 家族や友達にも信じてもらえず、最後は自分自身の手で人生に幕を引いた･･････だったんだが、 「･･････ここはどこだ?」 気がついたらふかふかなベッドに豪華な装飾。 これは異世界転生ってやつで俺は勝ち組なのでは!? と思ったら、めっちゃ嫌なやつだったらしく婚約者やメイドとめっちゃ嫌われていたのだ。 「前世でも嫌われて、今世もそうなのかよ!?」 もうあんな惨めな目に遭うのは嫌だ!! 俺は自由に生きたいんだ!! これは前世でお祓いが必要レベルで地獄だった男が、 転生先で幸せを手に入れるために好感度を稼ぐ･･････はずが、 何故か好感度が異常に上がって依存される存在になってしまう物語。 | D483: 1 | E483: 1 | F483: 100 | G483: 100 | H483: 100 | I483: 0 | J483: 0 | K483: 0 | L483: 17

Sheet 全差分
A1: genre_key | B1: genre | C1: work_id | D1: title | E1: author | F1: work_url | G1: rank | H1: star | I1: episodes | J1: chars | K1: elapsed_days | L1: tags | M1: status | N1: catchphrase | O1: intro | P1: intro_len | Q1: rank_prev | R1: star_prev | S1: episodes_prev | T1: あらすじ | U1: rank_change | V1: star_gain | W1: star_per_day | X1: ep_gain | Y1: growth_pct | Z1: 区分 | AA1: span_days
A2: action | B2: 現代ファンタジー | C2: 16817330649436334413 | D2: 推しにささげるダンジョングルメ〜最強探索者VTuberになる〜 | E2: モノクロウサギ | F2: https://kakuyomu.jp/works/16817330649436334413 | G2: 100 | H2: 42263 | I2: 349 | J2: 1141104 | K2: 1367 | L2: VTuber|ダンジョン|主人公最強|飯テロ|スレ|配信|スキル|ハーレム | M2: 連載中 | N2: 書籍版5巻 4月30日に発売いたします!! もう買えるので是非!! | O2: 『ダンジョン産の食材を食べる機会があったんですけど、それが凄く美味しくって──』 推しのVTuberが配信でそんなことを言っていたので、最強探索者の主人公が中小規模の事務所のライバーとしてデビューして、推しとオフコラボでご飯を振る舞うことを目指すお話。 ──なお、当初の予定以上に伸びてしまって、いろいろな面で段々と引くに引けなくなっていく模様。 | P2: 175 | T2: 『ダンジョン産の食材を食べる機会があったんですけど、それが凄く美味しくって──』 推しのVTuberが配信でそんなことを言っていたので、最強探索者の主人公が中小規模の事務所のライバーとしてデビューして、推しとオフコラボでご飯を振る舞うことを目指すお話。 ──なお、当初の予定以上に伸びてしまって、いろいろな面で段々と引くに引けなくなっていく模様。 | Z2: 新規ランクイン | AA2: 1
A3: action | B3: 現代ファンタジー | C3: 16817330658027210412 | D3: 【悲報】お嬢様系底辺ダンジョン配信者、配信切り忘れに気づかず同業者をボコってしまう～けど相手が若手最強の迷惑系配信者だったらしく動画がアホほどバズって伝説になってますわ!? | E3: ドラゴンタニシ | F3: https://kakuyomu.jp/works/16817330658027210412 | G3: 55 | H3: 55747 | I3: 284 | J3: 1799688 | K3: 1188 | L3: ダンジョン|配信|コメディ|無双|主人公最強|女主人公|掲示板|カクヨムオンリー | M3: 連載中 | N3: 規格外エセお嬢様の現代ダンジョン無双バズ！【書籍５巻発売中ですの！】 | O3: 「はぁ、今日も視聴者０、登録者3……。向いてないのかしら、わたくし……」 女子高生ダンジョン配信者、山田カリンは心が折れかけていた。 アニメの優雅な探索者キャラに憧れ、ドレス姿でダンジョンを攻略するお嬢様として配信をはじめて早１年。コンセプトがよくないせいか、動画が面白くないせいか、探索者として実力はあるはずなのにチャンネルがまったく伸びないのだ。 そんなある日、カリンはダンジョン下層で妙な男を発見する。 「そんじゃいまから爆破すっからな～」 その手には国が使用禁止を呼びかけている危険物質が着火寸前で――、 「なにやっとんじゃオラアアアアアア！」 お嬢様言葉も忘れて拳一閃。お説教とともに男を速攻気絶させてしまう。 「配信を切ったあとでよかったですわ。こんなはしたない姿、配信に乗せられませんもの」 と、男を外まで運び帰宅するカリン。 だがその裏では、 「なんだあのチンピラお嬢様!?」 「若手最強探索者が一方的にやられたんだが!?」 「てかなんで下層にドレス!?」 「頭おかしいのではなくて!?」 カリンがボコった男は有名な迷惑系ダンジョン配信者であり、危険行為を拳で防いだその様子は全世界に配信されていた。若手最強探索者が謎のお嬢様にボッコボコに説教される映像は切り抜かれてバズりにバズり、カリンもまた配信の切り忘れでアカウントが速攻特定。翌朝には本人の望まぬ形で伝説になってしまっているのだった。 そうして日の目を見たカリンの異常な強さと規格外な活躍はその後もバズり続け、その人気と影響は配信者の枠を大きく超えたものとなっていく――。 ※１月２２日、なぜか日間週間月間１位をとらないまま年間総合１位を獲得いたしました！ ありがとうございます！ ※コミカライズもサンデーうぇぶり様（ＷＥＢ版およびアプリ）で連載中です！ | P3: 785 | Q3: 51 | R3: 55736 | S3: 284 | T3: 「はぁ、今日も視聴者０、登録者3……。向いてないのかしら、わたくし……」 女子高生ダンジョン配信者、山田カリンは心が折れかけていた。 アニメの優雅な探索者キャラに憧れ、ドレス姿でダンジョンを攻略するお嬢様として配信をはじめて早１年。コンセプトがよくないせいか、動画が面白くないせいか、探索者として実力はあるはずなのにチャンネルがまったく伸びないのだ。 そんなある日、カリンはダンジョン下層で妙な男を発見する。 「そんじゃいまから爆破すっからな～」 その手には国が使用禁止を呼びかけている危険物質が着火寸前で――、 「なにやっとんじゃオラアアアアアア！」 お嬢様言葉も忘れて拳一閃。お説教とともに男を速攻気絶させてしまう。 「配信を切ったあとでよかったですわ。こんなはしたない姿、配信に乗せられませんもの」 と、男を外まで運び帰宅するカリン。 だがその裏では、 「なんだあのチンピラお嬢様!?」 「若手最強探索者が一方的にやられたんだが!?」 「てかなんで下層にドレス!?」 「頭おかしいのではなくて!?」 カリンがボコった男は有名な迷惑系ダンジョン配信者であり、危険行為を拳で防いだその様子は全世界に配信されていた。若手最強探索者が謎のお嬢様にボッコボコに説教される映像は切り抜かれてバズりにバズり、カリンもまた配信の切り忘れでアカウントが速攻特定。翌朝には本人の望まぬ形で伝説になってしまっているのだった。 そうして日の目を見たカリンの異常な強さと規格外な活躍はその後もバズり続け、その人気と影響は配信者の枠を大きく超えたものとなっていく――。 ※１月２２日、なぜか日間週間月間１位をとらないまま年間総合１位を獲得いたしました！ ありがとうございます！ ※コミカライズもサンデーうぇぶり様（ＷＥＢ版およびアプリ）で連載中です！ | U3: -4 | V3: 11 | W3: 11 | X3: 0 | Y3: 0.019735898 | Z3: 継続 | AA3: 1
A4: action | B4: 現代ファンタジー | C4: 16817330661274615404 | D4: 住んでる場所が田舎すぎて、ダンジョン探索者が俺一人なんだが？【書籍3巻発売中！】 | E4: 赤月ヤモリ | F4: https://kakuyomu.jp/works/16817330661274615404 | G4: 98 | H4: 46046 | I4: 158 | J4: 535555 | K4: 572 | L4: ダンジョン|ハーレム|主人公最強|配信|掲示板|人妻|コメディ | M4: 連載中 | N4: 「仲間？ 他の探索者？ そんなの居ないよ。ここは田舎だからね」 | O4: 【7月10日、第3巻発売！】 【書籍１～3巻発売中！】 【3月3日よりカドコミ・ニコニコ漫画でコミカライズが連載中です！】 【四章準備中】 『ダンジョン配信者』の存在により、世はまさに空前のダンジョンブームとなっていた。 しかしそれは都会に限った話。 Aランク探索者である相馬創の住む田舎町には他に探索者が居らず、彼は仕事に忙殺される日々を送っていた。 これは活動拠点が田舎のため、いまいちパッとしない少年が世界中にその名を轟かせる物語。 ※なろうハーメルンにも公開しております。 | P4: 245 | Q4: 97 | R4: 46043 | S4: 158 | T4: 【7月10日、第3巻発売！】 【書籍１～3巻発売中！】 【3月3日よりカドコミ・ニコニコ漫画でコミカライズが連載中です！】 【四章準備中】 『ダンジョン配信者』の存在により、世はまさに空前のダンジョンブームとなっていた。 しかしそれは都会に限った話。 Aランク探索者である相馬創の住む田舎町には他に探索者が居らず、彼は仕事に忙殺される日々を送っていた。 これは活動拠点が田舎のため、いまいちパッとしない少年が世界中にその名を轟かせる物語。 ※なろうハーメルンにも公開しております。 | U4: -1 | V4: 3 | W4: 3 | X4: 0 | Y4: 0.0065156484 | Z4: 継続 | AA4: 1
A5: action | B5: 現代ファンタジー | C5: 16818093076856145897 | D5: 【書籍化！】 ま！ よ！ け！ の！ 塩！ （１２０年分） | E5: 哀森賢人／哀しみを背負ったゴリラ | F5: https://kakuyomu.jp/works/16818093076856145897 | G5: 82 | H5: 737 | I5: 49 | J5: 281079 | K5: 847 | L5: ホラー|オカルト|都市伝説|怪談|怪異|うす塩|ヤンデレ|コメディ | M5: 連載中 | N5: 少女を【モリガミサマ】から助ける為に少年は体から塩を出した。 | O5: 【書籍化決定！】2026年08月24日 GCノベルズ（GCN文庫）様より発売中です！ 自分の部屋の天井の四隅を同時に見てみよう。 大丈夫。何も起きないから。絶対なにも起きないから、大丈夫だから。ね？ね？ 夜の山をじっと見続けると、何か光るモノが見えるよ。 それが動いていたら、スマホで動画を撮ってみよう。 きっとバズるよ。ほら撮って。 寝る前に布団にはいったら『誰かいますか？』って聞いてみよう。きっとそこに 「 うるっせぇえええ！！！！ 塩撒いてオラあああああ！！！！！！」 少年誌のホラー漫画で義務教育を終えた少年（バカ）は震えながら今日も塩を撒く。 【書籍版タイトル】 洒落怖な世界で、少年は塩を撒く ～ま！ よ！ け！ の！ 塩！ （１２０年分）～ ※「小説家になろう」「ハーメルン」にてマルチ投稿しています。 | P5: 366 | Q5: 77 | R5: 729 | S5: 49 | T5: 【書籍化決定！】2026年08月24日 GCノベルズ（GCN文庫）様より発売中です！ 自分の部屋の天井の四隅を同時に見てみよう。 大丈夫。何も起きないから。絶対なにも起きないから、大丈夫だから。ね？ね？ 夜の山をじっと見続けると、何か光るモノが見えるよ。 それが動いていたら、スマホで動画を撮ってみよう。 きっとバズるよ。ほら撮って。 寝る前に布団にはいったら『誰かいますか？』って聞いてみよう。きっとそこに 「 うるっせぇえええ！！！！ 塩撒いてオラあああああ！！！！！！」 少年誌のホラー漫画で義務教育を終えた少年（バカ）は震えながら今日も塩を撒く。 【書籍版タイトル】 洒落怖な世界で、少年は塩を撒く ～ま！ よ！ け！ の！ 塩！ （１２０年分）～ ※「小説家になろう」「ハーメルン」にてマルチ投稿しています。 | U5: -5 | V5: 8 | W5: 8 | X5: 0 | Y5: 1.0973937 | Z5: 継続 | AA5: 1
A6: action | B6: 現代ファンタジー | C6: 16818093094570180426 | D6: レベル上げ厨、ダンジョンで無双する | E6: 天然水珈琲 | F6: https://kakuyomu.jp/works/16818093094570180426 | G6: 60 | H6: 32784 | I6: 212 | J6: 960297 | K6: 511 | L6: 現代ダンジョン|ステータス|スキル|レベル上げ|ダンジョン配信|掲示板|やがて最強|魔法 | M6: 連載中 | N6: 【書籍化！】レベルアップ気持ち良すぎだろ！！ | O6: ダンジョンが出現したファンタジー黎明期の日本。 レベルにスキルに魔法が世の中に出現し、ダンジョンからもたらされる魔石は極めて発電効率の良い新エネルギー資源として、急速に世界中で広まっていく。 かつてない規模と速度で変革を迎えつつある世界。 主人公、鮫島武男はリアルでレベル上げをしたいとの思いから、高校三年間を準備に費やし、高校を卒業すると同時、進学も就職もせずに探索者となった。 ひたすらレベルを上げることに情熱を燃やす武男。 だが、新時代の争乱は「レベルが高いだけの一般人」という矛盾した存在を放置することはなく、武男は力を手に入れたがゆえに様々な事件に巻き込まれていく――。 【注意】主人公は後に効率的なレベル上げの方法を確立し、世界でも最強レベルの存在となりますが、特殊なレベル上げ方法の前提条件を整えるまで、それなりの時間を要します。「最初から裏技的な方法でレベルを上げて無双する」といった話ではありません。 書籍化に伴い、タイトルを変更しました。 旧題：レベル上げ厨、現代ダンジョンでレベルを上げる ◆◆◆お知らせ◆◆◆ 【極剣のスラッシュ ～初級スキル極めたら、いつの間にか迷宮都市最強とか呼ばれてたんだが～】という小説も連載しています。 主人公最強モノです。完結済み。 お暇な時にでも読んでいただけましたら幸いですm(_ _)m https://kakuyomu.jp/works/16817139556288291993 ※当作品はカクヨムのみ掲載中です。 無断転載、無断翻訳、YouTubeなどでの無断朗読を禁止します。 | P6: 674 | Q6: 60 | R6: 32751 | S6: 212 | T6: ダンジョンが出現したファンタジー黎明期の日本。 レベルにスキルに魔法が世の中に出現し、ダンジョンからもたらされる魔石は極めて発電効率の良い新エネルギー資源として、急速に世界中で広まっていく。 かつてない規模と速度で変革を迎えつつある世界。 主人公、鮫島武男はリアルでレベル上げをしたいとの思いから、高校三年間を準備に費やし、高校を卒業すると同時、進学も就職もせずに探索者となった。 ひたすらレベルを上げることに情熱を燃やす武男。 だが、新時代の争乱は「レベルが高いだけの一般人」という矛盾した存在を放置することはなく、武男は力を手に入れたがゆえに様々な事件に巻き込まれていく――。 【注意】主人公は後に効率的なレベル上げの方法を確立し、世界でも最強レベルの存在となりますが、特殊なレベル上げ方法の前提条件を整えるまで、それなりの時間を要します。「最初から裏技的な方法でレベルを上げて無双する」といった話ではありません。 書籍化に伴い、タイトルを変更しました。 旧題：レベル上げ厨、現代ダンジョンでレベルを上げる ◆◆◆お知らせ◆◆◆ 【極剣のスラッシュ ～初級スキル極めたら、いつの間にか迷宮都市最強とか呼ばれてたんだが～】という小説も連載しています。 主人公最強モノです。完結済み。 お暇な時にでも読んでいただけましたら幸いですm(_ _)m https://kakuyomu.jp/works/16817139556288291993 ※当作品はカクヨムのみ掲載中です。 無断転載、無断翻訳、YouTubeなどでの無断朗読を禁止します。 | U6: 0 | V6: 33 | W6: 33 | X6: 0 | Y6: 0.10076028 | Z6: 継続 | AA6: 1
A7: action | B7: 現代ファンタジー | C7: 16818622170990767935 | D7: 貧乏家族の長男はやがて『魔王』に成り上がる | E7: 城野白 | F7: https://kakuyomu.jp/works/16818622170990767935 | G7: 72 | H7: 23452 | I7: 301 | J7: 910312 | K7: 527 | L7: カクヨムオンリー|妹|ダンジョン|努力で最強|金策|長男|家族想い|お姉さん | M7: 連載中 | N7: 【書籍化】金がないので装備は無課金、魔法を極めてダンジョンをごり押す | O7: 【書籍化決定】 電撃文庫より、2026年2月10日に発売決定！ 各種サイトで予約受付中 一色樹には、三人の妹と二人の弟がいる。 両親はおらず、家族を支えられるのは中卒の樹だけ。 家族を養っていくために選んだのは、ダンジョンへ赴くことだった。 望むのは平凡な生活。 だが、彼の類まれな才能は次第に噂になっていき―― 「稼げるなら、なんだってしますよ」 家族のため、樹はダンジョンの深部へと足を踏み入れていく。 「なんかあいつの魔法、変じゃね？」 | P7: 227 | Q7: 73 | R7: 23449 | S7: 301 | T7: 【書籍化決定】 電撃文庫より、2026年2月10日に発売決定！ 各種サイトで予約受付中 一色樹には、三人の妹と二人の弟がいる。 両親はおらず、家族を支えられるのは中卒の樹だけ。 家族を養っていくために選んだのは、ダンジョンへ赴くことだった。 望むのは平凡な生活。 だが、彼の類まれな才能は次第に噂になっていき―― 「稼げるなら、なんだってしますよ」 家族のため、樹はダンジョンの深部へと足を踏み入れていく。 「なんかあいつの魔法、変じゃね？」 | U7: 1 | V7: 3 | W7: 3 | X7: 0 | Y7: 0.012793723 | Z7: 継続 | AA7: 1
A8: action | B8: 現代ファンタジー | C8: 16818622171979183070 | D8: 【書籍発売】汝、現代ダンジョンに希望を持つべからず | E8: 鋼我 | F8: https://kakuyomu.jp/works/16818622171979183070 | G8: 63 | H8: 8631 | I8: 135 | J8: 808268 | K8: 517 | L8: ダンジョン|魔法|モンスター|成り上がり | M8: 連載中 | N8: 底辺ダンジョン管理業、時給３００円スタート（自営業）。 | O8: 社会人三年目の青年、入川春夫は騙された。 通勤時間短縮のため、格安で購入した一軒家。そこにダンジョンがあったのだ。国の法律で、土地の所有者はダンジョンを管理しなくてはいけない。 そんな家なら買わなかった！ 後悔しても後の祭り。仕事は退職。家族からは縁を切られる。騙した奴は雲隠れ。 かくて始まる、先の見えないダンジョン管理。働いても報酬は雀の涙。過酷な肉体労働。ダンジョン素材による家庭菜園だけが心の支え。 過酷な日々を送っていた春夫にかかってくる一本の電話が、運命の転機となる。 ダンジョンに希望無し。故に、自らの手足で目指すべし。 底辺青年成り上がり物語、ここに開始。 原作 自作やる夫スレ作品「現代ダンジョンに希望を持つのは明らかな間違い」 ハーメルンにて平行連載中。 ＭＦ文庫Ｊ様より出版。 ガンガンオンライン様でコミック連載中。 | P8: 377 | Q8: 59 | R8: 8622 | S8: 135 | T8: 社会人三年目の青年、入川春夫は騙された。 通勤時間短縮のため、格安で購入した一軒家。そこにダンジョンがあったのだ。国の法律で、土地の所有者はダンジョンを管理しなくてはいけない。 そんな家なら買わなかった！ 後悔しても後の祭り。仕事は退職。家族からは縁を切られる。騙した奴は雲隠れ。 かくて始まる、先の見えないダンジョン管理。働いても報酬は雀の涙。過酷な肉体労働。ダンジョン素材による家庭菜園だけが心の支え。 過酷な日々を送っていた春夫にかかってくる一本の電話が、運命の転機となる。 ダンジョンに希望無し。故に、自らの手足で目指すべし。 底辺青年成り上がり物語、ここに開始。 原作 自作やる夫スレ作品「現代ダンジョンに希望を持つのは明らかな間違い」 ハーメルンにて平行連載中。 ＭＦ文庫Ｊ様より出版。 ガンガンオンライン様でコミック連載中。 | U8: -4 | V8: 9 | W8: 9 | X8: 0 | Y8: 0.10438413 | Z8: 継続 | AA8: 1
A9: action | B9: 現代ファンタジー | C9: 16818622173230370861 | D9: 〝金銀花〟は止まらない | E9: 白神 怜司 | F9: https://kakuyomu.jp/works/16818622173230370861 | G9: 77 | H9: 4617 | I9: 344 | J9: 1252814 | K9: 337 | L9: 女主人公|カクヨム先行|反骨精神のギャル|オタクとギャル|いずれは最強|配信|現代ダンジョン|主人公はヤベーヤツ | M9: 連載中 | N9: 【コミカライズ連載予定】オタク少女と反骨精神溢れるギャル達が開拓する | O9: 当たり前にダンジョンがあり、〝ダンジョン因子〟を得ることで様々な力を得られる現代日本。主人公である八咫島流霞こと引っ込み思案のオタク少女は、ひょんなことから同じ学校、同じクラスのスクールカーストトップのギャル、姫屋奏星とその仲間たちと交流を深めることになり、一緒にダンジョンに行くことになる。パーティ〝金銀花――《カプリフォリオ》〟はダンジョンダイブ配信を始めて……。 ◆補足：執筆に関してAIは使用してないです。（最近AIどうのこうの増えてきたので念の為明言しておきます） ◆無断転載禁止 | P9: 245 | Q9: 75 | R9: 4605 | S9: 343 | T9: 当たり前にダンジョンがあり、〝ダンジョン因子〟を得ることで様々な力を得られる現代日本。主人公である八咫島流霞こと引っ込み思案のオタク少女は、ひょんなことから同じ学校、同じクラスのスクールカーストトップのギャル、姫屋奏星とその仲間たちと交流を深めることになり、一緒にダンジョンに行くことになる。パーティ〝金銀花――《カプリフォリオ》〟はダンジョンダイブ配信を始めて……。 ◆補足：執筆に関してAIは使用してないです。（最近AIどうのこうの増えてきたので念の為明言しておきます） ◆無断転載禁止 | U9: -2 | V9: 12 | W9: 12 | X9: 1 | Y9: 0.26058632 | Z9: 継続 | AA9: 1
A10: action | B10: 現代ファンタジー | C10: 16818622174231824069 | D10: 【書籍化決定】はい、こちらダンジョン捜索隊！ ～相棒のタヌキがうっかり記録用録画を配信したら、全世界でバズってしまいました～ | E10: 夢・風魔 | F10: https://kakuyomu.jp/works/16818622174231824069 | G10: 32 | H10: 1851 | I10: 259 | J10: 592050 | K10: 489 | L10: 現代ダンジョン|スキル|無自覚チート|動画配信|ダンジョン配信|視聴者コメント|ヒロインはタヌキ|コメディ要素強め | M10: 連載中 | N10: これより要救助者の捜索を開始します。 | O10: ダンジョンが初めて生成された22年前、主人公の三石悟はダンジョン内で生まれた。 生まれながらにして『総合身体能力強化』のスキルを手に入れた悟は、成長とともに並外れた身体能力を発揮するようになる。 その能力を生かすべく、ダンジョン内で行方不明になった人や救助要請があった時に出動する民間企業『株式会社ATORA捜索隊』に入社した悟は、二十二歳の誕生日を迎えたその日、出動時の相棒としてサクラを紹介された。 「よろしくね、悟くん。私、レッサーパンダのサクラって言うの」 「いや、タヌキじゃ？」 「ぬわぁ～んですってぇ～！？」 これは感情の起伏が薄いダンジョン生まれの青年と、自分をレッサーパンダと疑わない雌タヌキの、人命救助物語である。 たぶん。 ＊他サイトでも投稿しております。 旧タイトル：はい、こちらダンジョン捜索隊～自分はレッサーパンダだと言い張る相棒の♀タヌキが、うっかり記録用録画を配信してしまった件。 | P10: 407 | Q10: 35 | R10: 1836 | S10: 258 | T10: ダンジョンが初めて生成された22年前、主人公の三石悟はダンジョン内で生まれた。 生まれながらにして『総合身体能力強化』のスキルを手に入れた悟は、成長とともに並外れた身体能力を発揮するようになる。 その能力を生かすべく、ダンジョン内で行方不明になった人や救助要請があった時に出動する民間企業『株式会社ATORA捜索隊』に入社した悟は、二十二歳の誕生日を迎えたその日、出動時の相棒としてサクラを紹介された。 「よろしくね、悟くん。私、レッサーパンダのサクラって言うの」 「いや、タヌキじゃ？」 「ぬわぁ～んですってぇ～！？」 これは感情の起伏が薄いダンジョン生まれの青年と、自分をレッサーパンダと疑わない雌タヌキの、人命救助物語である。 たぶん。 ＊他サイトでも投稿しております。 旧タイトル：はい、こちらダンジョン捜索隊～自分はレッサーパンダだと言い張る相棒の♀タヌキが、うっかり記録用録画を配信してしまった件。 | U10: 3 | V10: 15 | W10: 15 | X10: 1 | Y10: 0.81699346 | Z10: 継続 | AA10: 1
A11: action | B11: 現代ファンタジー | C11: 2912051596347777094 | D11: FPSのUIが現実に見える俺が、いつの間にか殺し屋になるまで | E11: 鳥獣跋扈 | F11: https://kakuyomu.jp/works/2912051596347777094 | G11: 76 | H11: 7719 | I11: 62 | J11: 300099 | K11: 159 | L11: 殺し屋|FPS|チート | M11: 連載中 | N11: おかしい、いつの間に殺し屋になってないか？ | O11: 大学を出てから定職にも就けず、倉庫仕事とFPSゲームばかりの生活を続けていた青年・二階堂 恒一（にかいどう こういち）。 彼の人生は、ある日を境におかしくなった。 ゲームを終え、ふと顔を上げた瞬間――現実の世界に、FPSのHUDのような感覚情報が重なって見えるようになったのだ。 他人の視線や足音の方向。 危険が向かってくるアラート。 ――そして、銃を持った時のクロスヘア。 最初は幻覚だと思った。だが、その“UI”は現実世界で役に立った。 ひょんなことから、裏社会の襲撃現場に巻き込まれた恒一は、ただ生き延びるために動いた結果、信じられない手際で修羅場を切り抜けてしまう。 その一件をきっかけに、彼は裏社会の仲介人・雨宮しずくに目をつけられる。 これは、ただの男が裏社会で“最強の殺し屋”として祭り上げられていく、現代暗殺サスペンス。 | P11: 373 | Q11: 78 | R11: 7698 | S11: 62 | T11: 大学を出てから定職にも就けず、倉庫仕事とFPSゲームばかりの生活を続けていた青年・二階堂 恒一（にかいどう こういち）。 彼の人生は、ある日を境におかしくなった。 ゲームを終え、ふと顔を上げた瞬間――現実の世界に、FPSのHUDのような感覚情報が重なって見えるようになったのだ。 他人の視線や足音の方向。 危険が向かってくるアラート。 ――そして、銃を持った時のクロスヘア。 最初は幻覚だと思った。だが、その“UI”は現実世界で役に立った。 ひょんなことから、裏社会の襲撃現場に巻き込まれた恒一は、ただ生き延びるために動いた結果、信じられない手際で修羅場を切り抜けてしまう。 その一件をきっかけに、彼は裏社会の仲介人・雨宮しずくに目をつけられる。 これは、ただの男が裏社会で“最強の殺し屋”として祭り上げられていく、現代暗殺サスペンス。 | U11: 2 | V11: 21 | W11: 21 | X11: 0 | Y11: 0.27279813 | Z11: 継続 | AA11: 1
A12: action | B12: 現代ファンタジー | C12: 2912051597492612020 | D12: ハズレスキル【キャンプ設営】を授かった……追放されたわけじゃないけど、戦えないのでキャンプしてたら、安全地帯を作れるチートスキルだった | E12: ＡＮ＠ＲＣＨＹ | F12: https://kakuyomu.jp/works/2912051597492612020 | G12: 96 | H12: 1481 | I12: 101 | J12: 259317 | K12: 99 | L12: ハズレスキル|キャンプ|ダンジョン|現代ファンタジー|生産系|スローライフ風|配信|ＡＩ補助利用 | M12: 連載中 | N12: 自由を楽しむために、俺は今日もテントを張る | O12: 世界中の人類へ突如与えられた「ユニークスキル」。 剣術、槍術、身体強化――戦闘向きスキルを得た者たちは、現れたダンジョンへ挑み始めた。 そんな中、大学生の九十八（にのまえ）翼（つばさ）が与えられたのは、意味不明なハズレスキル【キャンプ設営】。 友人たちはダンジョンへ向かい、翼は次第に孤立していく。 戦えない自分にできることはない――そう思った彼は、趣味だったキャンプへのめり込むようになった。 だが、そのスキルは『ただのキャンプ』では終わらなかった。 自ら設営したテントの中を、外敵侵入禁止のセーフエリアへ変える能力。 暴力も犯罪も拒絶する絶対安全圏。 そしてスキルが成長した先には、時間すら操る力が眠っていた。 料理、加工、農業、醸造―― 戦えないからこそ辿り着いた、生産と安全の最前線。 これは、世界がダンジョンに飲み込まれていく中で、 １人のキャンパーが「帰れる場所」を作り続ける物語。 | P12: 415 | Q12: 94 | R12: 1475 | S12: 100 | T12: 世界中の人類へ突如与えられた「ユニークスキル」。 剣術、槍術、身体強化――戦闘向きスキルを得た者たちは、現れたダンジョンへ挑み始めた。 そんな中、大学生の九十八（にのまえ）翼（つばさ）が与えられたのは、意味不明なハズレスキル【キャンプ設営】。 友人たちはダンジョンへ向かい、翼は次第に孤立していく。 戦えない自分にできることはない――そう思った彼は、趣味だったキャンプへのめり込むようになった。 だが、そのスキルは『ただのキャンプ』では終わらなかった。 自ら設営したテントの中を、外敵侵入禁止のセーフエリアへ変える能力。 暴力も犯罪も拒絶する絶対安全圏。 そしてスキルが成長した先には、時間すら操る力が眠っていた。 料理、加工、農業、醸造―― 戦えないからこそ辿り着いた、生産と安全の最前線。 これは、世界がダンジョンに飲み込まれていく中で、 １人のキャンパーが「帰れる場所」を作り続ける物語。 | U12: -2 | V12: 6 | W12: 6 | X12: 1 | Y12: 0.40677966 | Z12: 継続 | AA12: 1
A13: action | B13: 現代ファンタジー | C13: 2912051597609166733 | D13: 魔女だらけのレストランで働いてるけど毎日死にそう（でも飯が美味いので辞められない） | E13: タカザ | F13: https://kakuyomu.jp/works/2912051597609166733 | G13: 90 | H13: 2939 | I13: 107 | J13: 612915 | K13: 141 | L13: 男主人公|一人称|魔女|レストラン|グルメ|料理|コメディ|人外ヒロイン | M13: 連載中 | N13: 週休二日。サボりのペナルティは死。 | O13: 魔女しか来ないレストランで働いてます。 なお、普通に死にかけます。 客は全員やばい女。オーナーもやばい女。 でも料理はめちゃくちゃ美味いので（あとイカれた契約書を交わしたので）辞められません。 そんな地獄の職場で生き延びる俺が、休日に出会ったのは理想ど真ん中の清楚な女性。 ──ただし彼女も、やっぱり魔女でした。そんなことある？ 最終的に、ろくでもない女しかいないハーレムが出来上がる模様です。 誰か助けてください。 | P13: 211 | Q13: 84 | R13: 2939 | S13: 107 | T13: 魔女しか来ないレストランで働いてます。 なお、普通に死にかけます。 客は全員やばい女。オーナーもやばい女。 でも料理はめちゃくちゃ美味いので（あとイカれた契約書を交わしたので）辞められません。 そんな地獄の職場で生き延びる俺が、休日に出会ったのは理想ど真ん中の清楚な女性。 ──ただし彼女も、やっぱり魔女でした。そんなことある？ 最終的に、ろくでもない女しかいないハーレムが出来上がる模様です。 誰か助けてください。 | U13: -6 | V13: 0 | W13: 0 | X13: 0 | Y13: 0 | Z13: 継続 | AA13: 1
A14: action | B14: 現代ファンタジー | C14: 2912051597781188749 | D14: 異世界最強の元勇者、今世は陰陽術を極めて無双します | E14: ジャジャ丸 | F14: https://kakuyomu.jp/works/2912051597781188749 | G14: 25 | H14: 1612 | I14: 47 | J14: 133431 | K14: 46 | L14: 転生|陰陽術|式神|妹|ショタ|憑依|無双|努力 | M14: 連載中 | N14: 赤ちゃんの体で動けないなら、式神に動いて貰えばいいじゃない | O14: 異世界に召喚され、勇者として責務を全うした少年は、約束通り元の世界に戻されて──なぜか赤ちゃんに転生して人生をやり直すことに。 しかも、生まれ変わったのは凶悪な怪異から人々を守る陰陽師達が、社会の陰でひっそりと活躍する日本だった。 そんな陰陽師の家系に生まれた理仁は、双子の妹にとんでもない才能があること、その才能が多くの怪異を引き寄せて妹の身を危険に晒してしまうことを知り、自らもまた陰陽師の道を進むことを決意する。 （式神を使えば、赤ちゃんだろうが関係なく戦えるし鍛えられるのは便利だなー） 異世界で培った魔法知識＋新しく覚えた陰陽術の合わせ技で、爆速で強くなっていく理仁。 やがてその実力は、日本中の陰陽師から注目されるようになっていく。 異世界帰りの転生勇者が、赤ちゃんの頃から鍛え上げて無双する現代無双ファンタジー。 | P14: 368 | Q14: 26 | R14: 1568 | S14: 46 | T14: 異世界に召喚され、勇者として責務を全うした少年は、約束通り元の世界に戻されて──なぜか赤ちゃんに転生して人生をやり直すことに。 しかも、生まれ変わったのは凶悪な怪異から人々を守る陰陽師達が、社会の陰でひっそりと活躍する日本だった。 そんな陰陽師の家系に生まれた理仁は、双子の妹にとんでもない才能があること、その才能が多くの怪異を引き寄せて妹の身を危険に晒してしまうことを知り、自らもまた陰陽師の道を進むことを決意する。 （式神を使えば、赤ちゃんだろうが関係なく戦えるし鍛えられるのは便利だなー） 異世界で培った魔法知識＋新しく覚えた陰陽術の合わせ技で、爆速で強くなっていく理仁。 やがてその実力は、日本中の陰陽師から注目されるようになっていく。 異世界帰りの転生勇者が、赤ちゃんの頃から鍛え上げて無双する現代無双ファンタジー。 | U14: 1 | V14: 44 | W14: 44 | X14: 1 | Y14: 2.8061224 | Z14: 継続 | AA14: 1
... A36: action | B36: 現代ファンタジー | C36: 2912051604104950353 | D36: 人斬り高校生は普通の暮らしを送りたいのに、配信で永遠にバズり散らかしてしまう～信濃新陰流の最後の使い手？いやぁ、人違いじゃないですかね～ | E36: イのカンア | F36: https://kakuyomu.jp/works/2912051604104950353 | G36: 33 | H36: 1497 | I36: 48 | J36: 229351 | K36: 38 | L36: 現代ファンタジー|主人公最強|ダンジョン|配信|日本刀|男主人公|アノマリー|カクヨムオンリー | M36: 連載中 | N36: ダンジョン配信が流行るようなこの現代で人斬り、ですかぁ？ | O36: 20年前に突如、全世界に発生したダンジョンは長い年月の末に人間の生活の中に組み込まれ、ダンジョンの中で配信をするに至った。 街中にはダンジョン探索用の武器、防具を携えた老若男女が溢れ、ダンジョン配信でバズることを誰もが夢見るような時代になった。 2026年、令和8年の春。 今年で15歳になる男子高校生、諏訪野 拓海は生まれ育ったド田舎もド田舎の村から離れ、東京へ上京することになった。 ケミカルなハンバーガー、牛の糞の臭いがしない道、キラキラビカビカ光る町並み、午後六時になっても閉店しない店。 拓海はそういった「都会に住む普通の高校生の普通の生活」というものに憧れを抱いて上京することになる。 なるのだが、一つ二つ、彼には問題がある。 一つ、彼はまったくもって現代社会というものを知らない。携帯電話の知識はガラケーで止まっているし、実家には現役の黒電話があるし、彼のおじいちゃんなんて携帯電話すら持っていなかった。 二つ、彼は失伝したはずの【信濃新陰流】の最後の使い手であり、平たく言えば人斬りの才能に溢れた少年であったということ。 平和な普通の生活を望む人斬り高校生は望まずに欲望渦巻くダンジョン配信の渦中へと放り込まれ、 そうして失われるはずであった人斬りの才能が存分に開花することになってしまう。 一度抜けば人が死ぬまで収められぬ、血塗れの刃。業の技と言えば聞こえはいいが、つまるところは殺しの技術。 ダンジョン配信の流行るようなこの現代で人斬り、ですかぁ？ とどのつまり、これはそういう物語。 | P36: 659 | Q36: 30 | R36: 1483 | S36: 47 | T36: 20年前に突如、全世界に発生したダンジョンは長い年月の末に人間の生活の中に組み込まれ、ダンジョンの中で配信をするに至った。 街中にはダンジョン探索用の武器、防具を携えた老若男女が溢れ、ダンジョン配信でバズることを誰もが夢見るような時代になった。 2026年、令和8年の春。 今年で15歳になる男子高校生、諏訪野 拓海は生まれ育ったド田舎もド田舎の村から離れ、東京へ上京することになった。 ケミカルなハンバーガー、牛の糞の臭いがしない道、キラキラビカビカ光る町並み、午後六時になっても閉店しない店。 拓海はそういった「都会に住む普通の高校生の普通の生活」というものに憧れを抱いて上京することになる。 なるのだが、一つ二つ、彼には問題がある。 一つ、彼はまったくもって現代社会というものを知らない。携帯電話の知識はガラケーで止まっているし、実家には現役の黒電話があるし、彼のおじいちゃんなんて携帯電話すら持っていなかった。 二つ、彼は失伝したはずの【信濃新陰流】の最後の使い手であり、平たく言えば人斬りの才能に溢れた少年であったということ。 平和な普通の生活を望む人斬り高校生は望まずに欲望渦巻くダンジョン配信の渦中へと放り込まれ、 そうして失われるはずであった人斬りの才能が存分に開花することになってしまう。 一度抜けば人が死ぬまで収められぬ、血塗れの刃。業の技と言えば聞こえはいいが、つまるところは殺しの技術。 ダンジョン配信の流行るようなこの現代で人斬り、ですかぁ？ とどのつまり、これはそういう物語。 | U36: -3 | V36: 14 | W36: 14 | X36: 1 | Y36: 0.94403237 | Z36: 継続 | AA36: 1
A37: action | C37: 2912051604136221250 | D37: スキルのせいで性別も種族も変わったんだが？！ | E37: おでんの中のがんもどき | N37: 期待して手に入れたスキル…それは『魔女』いやいや、俺男なんだが… | O37: 時は近世…ではなく魔法と科学の発達した現代。この世界では神代の時代からダンジョンというものがある。そんな世界だ。 自分。乙女ヶ崎 夢(おとめがさき ゆめ)はダンジョン配信者を目指しているただの高校生。『一攫千金！』というバカみたいな夢を掲げ毎日ダンジョンについての勉強を行ってる。そしてダンジョン配信者になるためには15歳に鑑定の儀というものを行い、スキルの発現をさせないといけない。 「さて、俺の番ってかねぇ…。何が出るかなっと！」 …そこで目にしたものとは？ | Q37: 98 | R37: 379 | S37: 63 | T37: 時は近世…ではなく魔法と科学の発達した現代。この世界では神代の時代からダンジョンというものがある。そんな世界だ。 自分。乙女ヶ崎 夢(おとめがさき ゆめ)はダンジョン配信者を目指しているただの高校生。『一攫千金！』というバカみたいな夢を掲げ毎日ダンジョンについての勉強を行ってる。そしてダンジョン配信者になるためには15歳に鑑定の儀というものを行い、スキルの発現をさせないといけない。 「さて、俺の番ってかねぇ…。何が出るかなっと！」 …そこで目にしたものとは？ | Z37: 圏外落ち | AA37: 1
A38: action | B38: 現代ファンタジー | C38: 2912051604153063294 | D38: カラスの悪魔がやって来る 〜泣き寝入りするのをやめた元社畜、世界中のカラスを支配して、ナメた探索者を狩り尽くす〜 | E38: 川野笹舟 | F38: https://kakuyomu.jp/works/2912051604153063294 | G38: 10 | H38: 5914 | I38: 33 | J38: 104145 | K38: 32 | L38: 成り上がり|ざまぁ|主人公最強|現代ダンジョン | M38: 連載中 | N38: 悪いことするとカラスの悪魔が来るよ | O38: 残業の帰り道、理不尽な探索者にいきなり殴られた男は警察やダンジョン協会にかけあったが、誰一人として彼を助ける者はいなかった。『暴力こそ正義』という真理に気づいた彼は探索者になることを決意した。覚醒したスキルは『魔人（八咫烏）』『カラスの王』『道案内』。後に『カラスの悪魔』と呼ばれ世界中から恐れられるようになる男の物語。 | P38: 160 | Q38: 9 | R38: 5871 | S38: 33 | T38: 残業の帰り道、理不尽な探索者にいきなり殴られた男は警察やダンジョン協会にかけあったが、誰一人として彼を助ける者はいなかった。『暴力こそ正義』という真理に気づいた彼は探索者になることを決意した。覚醒したスキルは『魔人（八咫烏）』『カラスの王』『道案内』。後に『カラスの悪魔』と呼ばれ世界中から恐れられるようになる男の物語。 | U38: -1 | V38: 43 | W38: 43 | X38: 0 | Y38: 0.73241356 | Z38: 継続 | AA38: 1
A39: action | B39: 現代ファンタジー | C39: 2912051604233963941 | D39: 深夜のダンジョン清掃バイト中、俺だけ「消えたドロップ」が拾えるようになった〜拾った小石が査定額420万円、ついでに救助配信が同接50万でした〜 | E39: 魔王源 | F39: https://kakuyomu.jp/works/2912051604233963941 | G39: 91 | H39: 1944 | I39: 56 | J39: 83797 | K39: 24 | L39: AI本文利用|ダンジョン|現代ダンジョン|配信|成り上がり|兄妹|毎日更新|完結済 | M39: 完結済 | N39: 拾った小石が420万円。消えたドロップは、俺だけが拾える。 | O39: ダンジョン出現から十二年。探索者が子供の憧れの職業になった現代日本で、楠木拾(くすのき・ひろう)二十二歳のスキルは【ピックアップ:落ちているものを拾うことができる】──誰でもできる、史上最弱の判定だった。 探索者になれなかった拾は、妹の学費のため、深夜のダンジョン清掃バイトを四年続けている。時給千四百円。 入学金の期限まであと一週間の夜、スキルが真価を解放する。 討伐のたびに消えていく「ドロップの残滓」。本来この世から失われるはずの素材・スキル片・経験値の欠片が、世界で拾ひとりだけ、拾えるようになった。 拾った小石の査定額、四百二十万円。 さらに、たまたま映り込んだ救助劇が同接五十万でバズり、妹が勝手に開設したチャンネル『ひろいやTV』で、拾は「顔の映らない謎の拾い屋」として世界に知られていく。 なくした結婚指輪から、三年前の遺品、国が追う「氾濫の証拠」まで。落ちているものは、何でも拾う個人事業「ひろいや」、本日開業。 やがて拾は、ドロップが消える理由──ダンジョンそのものの秘密に辿り着く。 戦えない主人公が、拾って、届けて、成り上がる。 毎話スカッと完結気味の低ストレス設計。 全50話・1日2回更新(7時、21時)で完結予定です。 ※本作はAI(Claude)が執筆し、人間が企画したものです。 | P39: 566 | Q39: 86 | R39: 1922 | S39: 56 | T39: ダンジョン出現から十二年。探索者が子供の憧れの職業になった現代日本で、楠木拾(くすのき・ひろう)二十二歳のスキルは【ピックアップ:落ちているものを拾うことができる】──誰でもできる、史上最弱の判定だった。 探索者になれなかった拾は、妹の学費のため、深夜のダンジョン清掃バイトを四年続けている。時給千四百円。 入学金の期限まであと一週間の夜、スキルが真価を解放する。 討伐のたびに消えていく「ドロップの残滓」。本来この世から失われるはずの素材・スキル片・経験値の欠片が、世界で拾ひとりだけ、拾えるようになった。 拾った小石の査定額、四百二十万円。 さらに、たまたま映り込んだ救助劇が同接五十万でバズり、妹が勝手に開設したチャンネル『ひろいやTV』で、拾は「顔の映らない謎の拾い屋」として世界に知られていく。 なくした結婚指輪から、三年前の遺品、国が追う「氾濫の証拠」まで。落ちているものは、何でも拾う個人事業「ひろいや」、本日開業。 やがて拾は、ドロップが消える理由──ダンジョンそのものの秘密に辿り着く。 戦えない主人公が、拾って、届けて、成り上がる。 毎話スカッと完結気味の低ストレス設計。 全50話・1日2回更新(7時、21時)で完結予定です。 ※本作はAI(Claude)が執筆し、人間が企画したものです。 | U39: -5 | V39: 22 | W39: 22 | X39: 0 | Y39: 1.144641 | Z39: 継続 | AA39: 1
A40: action | B40: 現代ファンタジー | C40: 2912051604238555073 | D40: 推しの救助費は六千万円。払えるわけない限界無職女は100均ホウキ一本で女性アイドル配信者を助けに行く ～六畳間ダンジョンを毎日掃除していたら最強になってました～ | E40: 羽黒楓 | F40: https://kakuyomu.jp/works/2912051604238555073 | G40: 62 | H40: 315 | I40: 25 | J40: 56085 | K40: 23 | L40: 百合|主人公最強|女主人公|掲示板|リョナ|現代ダンジョン|配信|無自覚最強 | M40: 連載中 | N40: 限界無職女、探索者レーティングと百合ピラミッドの頂点に立つ。 | O40: 田中紅亜（くれあ）が愛する推しの女性アイドル配信者が、ダンジョンで襲われた。 食人植物に全身を拘束され、精神を保てるのはあと十日。だけど警察は動いてくれない。民間の救助費用は六千万円。無職の紅亜に払えるはずがない。 だから紅亜は、自分で助けに行くことにした。 持っていくのは、100円ショップのホウキとチリトリ。 ブラック飲食店で心を壊した紅亜は、ご先祖さまが支配する「六畳間ダンジョン」に居候し、家賃代わりに毎日掃除をしていた。濃い瘴気の汚れや巨大な虫を片づけ続けるうちに、自分でも知らないまま規格外の強さを身につけていたのだ。 酒を愛する限界無職女が、推しを無事に連れて帰るため、死のダンジョンへ殴り込む。 そして助けた女たちから、なぜか次々と重すぎる愛を向けられ――救えば救うほど、紅亜を頂点とする百合ピラミッドが築かれていく。 無自覚最強×ダンジョン救助×ガールズラブ。 ※欠損を含む強めの残酷描写があります。 | P40: 409 | Q40: 62 | R40: 306 | S40: 25 | T40: 田中紅亜（くれあ）が愛する推しの女性アイドル配信者が、ダンジョンで襲われた。 食人植物に全身を拘束され、精神を保てるのはあと十日。だけど警察は動いてくれない。民間の救助費用は六千万円。無職の紅亜に払えるはずがない。 だから紅亜は、自分で助けに行くことにした。 持っていくのは、100円ショップのホウキとチリトリ。 ブラック飲食店で心を壊した紅亜は、ご先祖さまが支配する「六畳間ダンジョン」に居候し、家賃代わりに毎日掃除をしていた。濃い瘴気の汚れや巨大な虫を片づけ続けるうちに、自分でも知らないまま規格外の強さを身につけていたのだ。 酒を愛する限界無職女が、推しを無事に連れて帰るため、死のダンジョンへ殴り込む。 そして助けた女たちから、なぜか次々と重すぎる愛を向けられ――救えば救うほど、紅亜を頂点とする百合ピラミッドが築かれていく。 無自覚最強×ダンジョン救助×ガールズラブ。 ※欠損を含む強めの残酷描写があります。 | U40: 0 | V40: 9 | W40: 9 | X40: 0 | Y40: 2.9411765 | Z40: 継続 | AA40: 1
A41: action | B41: 現代ファンタジー | C41: 2912051604394129142 | D41: 【悲報】遊び気分で厨二病ダンジョン配信者を始めたらバズってしまう。恥ずかしすぎるからたとえ幼馴染や家族だとしても絶対に正体がバレるわけにはいかない。 | E41: くるみ | F41: https://kakuyomu.jp/works/2912051604394129142 | G41: 49 | H41: 1714 | I41: 31 | J41: 94015 | K41: 31 | L41: ダンジョン配信|主人公最強|掲示板|妹|幼馴染|中二病|バレたくない(バレてます)|ヤンデレ | M41: 連載中 | N41: 助けた人が実は超人気配信者で俺の大捜索が始まってるんだけど！？！？ | O41: 中二病ダンジョン攻略ごっこをしていた零泉紫焔《れいせんしえん》は動きの無い配信に流石に飽きていた。2年経っても面白い出来事が無く、もうやめようと思っていたその時、イレギュラーモンスターが出現する。 そこでとある女性を助けたのだが、なんとその女性が実は超人気配信者で戦いの様子が全世界に発信されていた。 そして配信には中二病ごっこをして超カッコつける俺の姿が映っていて、世界中で俺の中二病ダンジョン攻略の姿が謎の黒仮面として話題になり、大捜索が始まることになる。 「絶対にバレたら終わる。俺の人生終わる。最愛の妹からはきっと冷えた目で見られるし幼馴染には笑われる......。絶対にバレないようにしないと......！」 「私の......私だけのカッコいい兄さんだったのに......！」 「しえんの凄さを知ってるのは私だけ。あとから出てきたぽっと出の女なんて許さないわ！」 これは恥ずかしさの故に黒歴史を絶対にバレたくない男の物語。 | P41: 422 | Q41: 34 | R41: 1708 | S41: 31 | T41: 中二病ダンジョン攻略ごっこをしていた零泉紫焔《れいせんしえん》は動きの無い配信に流石に飽きていた。2年経っても面白い出来事が無く、もうやめようと思っていたその時、イレギュラーモンスターが出現する。 そこでとある女性を助けたのだが、なんとその女性が実は超人気配信者で戦いの様子が全世界に発信されていた。 そして配信には中二病ごっこをして超カッコつける俺の姿が映っていて、世界中で俺の中二病ダンジョン攻略の姿が謎の黒仮面として話題になり、大捜索が始まることになる。 「絶対にバレたら終わる。俺の人生終わる。最愛の妹からはきっと冷えた目で見られるし幼馴染には笑われる......。絶対にバレないようにしないと......！」 「私の......私だけのカッコいい兄さんだったのに......！」 「しえんの凄さを知ってるのは私だけ。あとから出てきたぽっと出の女なんて許さないわ！」 これは恥ずかしさの故に黒歴史を絶対にバレたくない男の物語。 | U41: -15 | V41: 6 | W41: 6 | X41: 0 | Y41: 0.35128806 | Z41: 継続 | AA41: 1
A42: action | B42: 現代ファンタジー | C42: 2912051604434822405 | D42: S級探索者を5人育てたら全員に独立された中年コーチ、暇つぶしの初心者講座配信が「人類の攻略常識」を書き換え始める 〜教え子たちが「先生の本当の価値」に気付いて騒ぎ出すまで、あと3日〜 | E42: さくらろ | F42: https://kakuyomu.jp/works/2912051604434822405 | G42: 1 | H42: 4745 | I42: 28 | J42: 95360 | K42: 17 | L42: 現代ダンジョン|配信|師匠|おっさん主人公|無自覚|曇らせ|成り上がり|AI本文利用 | M42: 連載中 | N42: 育てた俺が、一番育っていなかったらしい。……世界の評価基準のほうがな。 | O42: 「アンタの育成論、ただの寄生だろ」 S級探索者を5人育てた俺は、その全員に独立され、業界から追放同然に引退した。 戦闘の才能はB級止まり。確かに俺自身は、何者にもなれなかった。 ――だから、暇つぶしだった。 初心者向けの攻略講座配信なんて、誰も見ないと思っていた。 「基礎ステップの踏み方が変だね。それじゃ三層で死ぬよ」 「え、なんで分かるんですか！？」 落ちこぼれE級の少女に教えた「ただの基礎」が、一週間でC級相当の動きに化けた。 切り抜きが拡散され、攻略wikiが書き換わり、大手クランの研究班がざわつき始める。 【あの講座、人類最強・剣条玲の動きと同じ事を言ってないか？】 【おい、誰かこのコーチの経歴調べろ】 そして配信に、見覚えのありすぎる人類最強がコメントを残す。 ――『先生。見つけました』 俺を置いていったはずの教え子たちが、世界中で勝手に騒ぎ始めた。 ※主人公は無自覚です。教え子と業界が勝手に騒ぎ、俺を捨てた連中が勝手に曇ります。基本ノンストレス・サクサク更新。 | P42: 442 | Q42: 1 | R42: 4368 | S42: 27 | T42: 「アンタの育成論、ただの寄生だろ」 S級探索者を5人育てた俺は、その全員に独立され、業界から追放同然に引退した。 戦闘の才能はB級止まり。確かに俺自身は、何者にもなれなかった。 ――だから、暇つぶしだった。 初心者向けの攻略講座配信なんて、誰も見ないと思っていた。 「基礎ステップの踏み方が変だね。それじゃ三層で死ぬよ」 「え、なんで分かるんですか！？」 落ちこぼれE級の少女に教えた「ただの基礎」が、一週間でC級相当の動きに化けた。 切り抜きが拡散され、攻略wikiが書き換わり、大手クランの研究班がざわつき始める。 【あの講座、人類最強・剣条玲の動きと同じ事を言ってないか？】 【おい、誰かこのコーチの経歴調べろ】 そして配信に、見覚えのありすぎる人類最強がコメントを残す。 ――『先生。見つけました』 俺を置いていったはずの教え子たちが、世界中で勝手に騒ぎ始めた。 ※主人公は無自覚です。教え子と業界が勝手に騒ぎ、俺を捨てた連中が勝手に曇ります。基本ノンストレス・サクサク更新。 | U42: 0 | V42: 377 | W42: 377 | X42: 1 | Y42: 8.6309524 | Z42: 継続 | AA42: 1
A43: action | B43: 現代ファンタジー | C43: 2912051604627841194 | D43: 未登録の魔法少女 | E43: 浅川 | F43: https://kakuyomu.jp/works/2912051604627841194 | G43: 44 | H43: 1372 | I43: 187 | J43: 703282 | K43: 43 | L43: 魔法少女|バトルファンタジー|TS(性転換)|男性主人公|正体隠し|魔獣討伐|女性キャラ多め|二重生活 | M43: 連載中 | N43: 世界にただ一人、協会に属さぬ魔法少女——その正体は、男子高校生。 | O43: 人類を魔獣から守るため、世界各国に支部を置く魔法少女協会。だが、魔法少女に覚醒するのは女性のみ——それが常識だった。 三神零、十六歳。普段は目立たない優等生を演じる、ごく普通の男子高校生。しかし彼には、誰にも明かせない秘密があった。変身した姿は、なぜか少女——闇属性を操る、協会未登録の魔法少女「ゴースト」。 なろうにも掲載中 | P43: 164 | Q43: 43 | R43: 1334 | S43: 183 | T43: 人類を魔獣から守るため、世界各国に支部を置く魔法少女協会。だが、魔法少女に覚醒するのは女性のみ——それが常識だった。 三神零、十六歳。普段は目立たない優等生を演じる、ごく普通の男子高校生。しかし彼には、誰にも明かせない秘密があった。変身した姿は、なぜか少女——闇属性を操る、協会未登録の魔法少女「ゴースト」。 なろうにも掲載中 | U43: -1 | V43: 38 | W43: 38 | X43: 4 | Y43: 2.8485757 | Z43: 継続 | AA43: 1
A44: action | B44: 現代ファンタジー | C44: 2912051604673684115 | D44: 魔剣を拾ったら中身が飯にしか興味のない生意気少女だった 〜無限の魔力と空間魔法でダンジョン無双〜 | E44: 竜刃丸 | F44: https://kakuyomu.jp/works/2912051604673684115 | G44: 79 | H44: 206 | I44: 52 | J44: 213137 | K44: 41 | L44: 成り上がり|主人公最強|チート|ダンジョン|飯テロ|ざまぁ|配信/掲示板|AI補助利用 | M44: 連載中 | N44: 「力が欲しいか‼︎ 力が欲しいなら……飯をくれ!」 | O44: ダンジョンの奥底で拾ったのは最強の魔剣。それは装備したものに無限の魔力を与える。 しかしその正体は飯にしか興味のない生意気少女だった。 荷物持ちとして捨てられた俺は、この生意気な相棒と無限の魔力、目覚めたチートスキル空間魔法EXでダンジョン無双を始める。 チート無双×ダンジョン×飯テロ、開幕。 毎日7:10投稿 2026.8.24 ⭐︎祝22,000PV⭐︎ 2026.8.29 ⭐︎祝30,000PV⭐︎ 2026.9.01 ⭐︎祝40,000PV⭐︎ 応援ありがとうございます😭 | P44: 246 | Q44: 90 | R44: 195 | S44: 51 | T44: ダンジョンの奥底で拾ったのは最強の魔剣。それは装備したものに無限の魔力を与える。 しかしその正体は飯にしか興味のない生意気少女だった。 荷物持ちとして捨てられた俺は、この生意気な相棒と無限の魔力、目覚めたチートスキル空間魔法EXでダンジョン無双を始める。 チート無双×ダンジョン×飯テロ、開幕。 毎日7:10投稿 2026.8.24 ⭐︎祝22,000PV⭐︎ 2026.8.29 ⭐︎祝30,000PV⭐︎ 2026.9.01 ⭐︎祝40,000PV⭐︎ 応援ありがとうございます😭 | U44: 11 | V44: 11 | W44: 11 | X44: 1 | Y44: 5.6410256 | Z44: 継続 | AA44: 1
A45: action | B45: 現代ファンタジー | C45: 2912051604816728311 | D45: 『【多重連撃（威力1/10）】はゴミスキル？ ——いいえ、固定ダメージを10倍叩き込む神バグです』 〜聖女の幼馴染に打算で捨てられた俺、100円の産廃装備と鉄球で100万ダメージ叩き出して無双する〜 | E45: ぺんぢる | F45: https://kakuyomu.jp/works/2912051604816728311 | G45: 51 | H45: 1544 | I45: 62 | J45: 203862 | K45: 36 | L45: ​成り上がり|男主人公|ざまぁ|不遇スキル|幼馴染|固定ダメージ|産廃装備|学園 | M45: 連載中 | N45: 攻撃力90%カットのゴミ？いいえ、固定ダメ10倍の神バグです | O45: 【「威力1/10」の減衰補正？ ——ハハッ、掛け算の元の数字をデカくして、固定衝撃を重複させれば即死コンボ（神バグ）じゃん】 現代日本にダンジョンと『スキル』が出現して半世紀。 15歳の能力鑑定儀式で、高校生の九重湊（くのえ・みなと）が授かったのは——【多重連撃】。 一回の攻撃で10回の追撃が発生する当たりスキル……と思いきや、追加されたのは【全攻撃の威力が一律1/10（90%カット）になる】という残酷なペナルティ補正だった！ 「装甲値50の敵に威力10で叩いてもダメージゼロ！ 一生かすり傷すらつけられないポカポカパンチのゴミスキルじゃねえかｗｗｗ」 学園の生徒や『剣聖』のライバル・一条蓮から猛烈な嘲笑を浴びる湊。 『聖女』のスキルを発現させた幼馴染・神崎葵も、「落ちこぼれと付き合ったら損をする」という冷たい打算から湊を捨て、一条のパーティーへと乗り換えていく。 しかし、嘲笑され見捨てられた湊の口元は、不敵に歪んでいた。 前世の記憶と冷静な分析力を持つ湊は、この世界のダメージ計算式に潜む【重大なバグ（仕様の穴）】に気づいていたのだ。 （ステータス攻撃力が1/10に減衰する？ ……なら、物理的な入力エネルギーを極限まで引き上げて『固定追加衝撃』を定着・重複させたらどうなる？） 投げ売りされていた『固定追加衝撃』が残るジャンク品の革手袋。 同じく「ゴミスキル」と冷遇されていた少女・白銀莉音が【錬金術】で作る、誤差ゼロの「真円高密度鉄球」。 そして、湊が前世から鍛え上げた高圧「指弾」。 これらを組み合わせた瞬間—— 1/10の減衰計算をシステム上完全バイパスし、敵の外殻を一切傷つけず体内の核（コア）だけを共振粉砕する【内部破壊コンボ】が完成する！！ 「お前らが自慢する『剣聖』の斬撃じゃ素材を傷つけて査定ガタ落ちだろ？ 俺たちは無傷で特級素材を100%最高額回収させてもらうわ」 テンプレの％倍率に頼るエリートたちを遥か置き去りにし、圧倒的合理主義の理屈屋が計算式ひとつで世界の理を塗り替える、痛快無双ファンタジー開幕！ | P45: 879 | Q45: 41 | R45: 1538 | S45: 62 | T45: 【「威力1/10」の減衰補正？ ——ハハッ、掛け算の元の数字をデカくして、固定衝撃を重複させれば即死コンボ（神バグ）じゃん】 現代日本にダンジョンと『スキル』が出現して半世紀。 15歳の能力鑑定儀式で、高校生の九重湊（くのえ・みなと）が授かったのは——【多重連撃】。 一回の攻撃で10回の追撃が発生する当たりスキル……と思いきや、追加されたのは【全攻撃の威力が一律1/10（90%カット）になる】という残酷なペナルティ補正だった！ 「装甲値50の敵に威力10で叩いてもダメージゼロ！ 一生かすり傷すらつけられないポカポカパンチのゴミスキルじゃねえかｗｗｗ」 学園の生徒や『剣聖』のライバル・一条蓮から猛烈な嘲笑を浴びる湊。 『聖女』のスキルを発現させた幼馴染・神崎葵も、「落ちこぼれと付き合ったら損をする」という冷たい打算から湊を捨て、一条のパーティーへと乗り換えていく。 しかし、嘲笑され見捨てられた湊の口元は、不敵に歪んでいた。 前世の記憶と冷静な分析力を持つ湊は、この世界のダメージ計算式に潜む【重大なバグ（仕様の穴）】に気づいていたのだ。 （ステータス攻撃力が1/10に減衰する？ ……なら、物理的な入力エネルギーを極限まで引き上げて『固定追加衝撃』を定着・重複させたらどうなる？） 投げ売りされていた『固定追加衝撃』が残るジャンク品の革手袋。 同じく「ゴミスキル」と冷遇されていた少女・白銀莉音が【錬金術】で作る、誤差ゼロの「真円高密度鉄球」。 そして、湊が前世から鍛え上げた高圧「指弾」。 これらを組み合わせた瞬間—— 1/10の減衰計算をシステム上完全バイパスし、敵の外殻を一切傷つけず体内の核（コア）だけを共振粉砕する【内部破壊コンボ】が完成する！！ 「お前らが自慢する『剣聖』の斬撃じゃ素材を傷つけて査定ガタ落ちだろ？ 俺たちは無傷で特級素材を100%最高額回収させてもらうわ」 テンプレの％倍率に頼るエリートたちを遥か置き去りにし、圧倒的合理主義の理屈屋が計算式ひとつで世界の理を塗り替える、痛快無双ファンタジー開幕！ | U45: -10 | V45: 6 | W45: 6 | X45: 0 | Y45: 0.39011704 | Z45: 継続 | AA45: 1
A46: action | B46: 現代ファンタジー | C46: 2912051604840342790 | D46: 山を買って古民家スローライフ 〜精霊たちと暮らすDIYな田舎暮らし〜 | E46: 猫野いちば | F46: https://kakuyomu.jp/works/2912051604840342790 | G46: 65 | H46: 500 | I46: 315 | J46: 743573 | K46: 39 | L46: スローライフ|異世界|ほのぼの|もふもふ|精霊|ざまぁなし|日常|万人向け | M46: 連載中 | N46: 精霊とDIY、山と古民家。ときどき、異世界の村を救っているらしい。 | O46: ▼あらすじ（パッと見たい人向け） ブラック企業で擦り切れた元SEが、全財産で山と古民家を買った。畑を耕し、DIYで直し、四匹の精霊とのんびり田舎暮らし。——ただ、その山の無人直売所は異世界の村と繋がっていて、彼は気づかぬまま、遠い異世界を救っていた。 ▼読者の方へ この作品は、まったり山暮らしファンタジーです 現在ご指摘いただいている箇所は順次修正中です！ 違和感ある箇所は、一旦精霊のせいと思って読み進めていただけると助かります！ ※応援コメントで批判等のご指摘は御遠慮ください ▼注意 この作品はフィクションです。 作品の都合上、現実の法律とこの世界の法律が違ったりするため、違和感があるかもしれません。 これダメじゃない？はすべて精霊ちゃん達のせいにして緩く見ていただけると幸いです！ ▼詳細あらすじ IT企業で心をすり減らした結城誠、二十九歳。誰にも邪魔されない暮らしを求めて、山ひとつと古民家を買った。 畑を耕し、古民家をDIYで直し、採れた野菜を無人直売所に並べる。それだけの穏やかな日々……のはずが、置いた野菜は毎朝きれいに消え、料金箱には見慣れない金貨や上等な毛皮、きれいな石が残されていく。 「奇特な人がいるもんだなあ」 誠は知らない。その直売所が、魔獣と痩せた土地に苦しむ異世界の辺境の村と繋がっていることを。彼が何気なく並べた甘いトマトが「回復の霊薬」に、DIYした頑丈な罠が「魔獣避けの神具」になって、遠い村をまるごと救っていることを。そして山に棲む四匹の精霊が、彼の豊かになっていく暮らしに合わせて、すくすく育っていることを――。 本人だけが最後まで気づかない、無自覚のスローライフ・ファンタジー。精霊たちと囲む食卓は、今日も賑やか。山では、いい匂いのごはんが炊けています。 ※作者は名前を考えるのが苦手です | P46: 782 | Q46: 71 | R46: 496 | S46: 313 | T46: ▼あらすじ（パッと見たい人向け） ブラック企業で擦り切れた元SEが、全財産で山と古民家を買った。畑を耕し、DIYで直し、四匹の精霊とのんびり田舎暮らし。——ただ、その山の無人直売所は異世界の村と繋がっていて、彼は気づかぬまま、遠い異世界を救っていた。 ▼読者の方へ この作品は、まったり山暮らしファンタジーです 現在ご指摘いただいている箇所は順次修正中です！ 違和感ある箇所は、一旦精霊のせいと思って読み進めていただけると助かります！ ※応援コメントで批判等のご指摘は御遠慮ください ▼注意 この作品はフィクションです。 作品の都合上、現実の法律とこの世界の法律が違ったりするため、違和感があるかもしれません。 これダメじゃない？はすべて精霊ちゃん達のせいにして緩く見ていただけると幸いです！ ▼詳細あらすじ IT企業で心をすり減らした結城誠、二十九歳。誰にも邪魔されない暮らしを求めて、山ひとつと古民家を買った。 畑を耕し、古民家をDIYで直し、採れた野菜を無人直売所に並べる。それだけの穏やかな日々……のはずが、置いた野菜は毎朝きれいに消え、料金箱には見慣れない金貨や上等な毛皮、きれいな石が残されていく。 「奇特な人がいるもんだなあ」 誠は知らない。その直売所が、魔獣と痩せた土地に苦しむ異世界の辺境の村と繋がっていることを。彼が何気なく並べた甘いトマトが「回復の霊薬」に、DIYした頑丈な罠が「魔獣避けの神具」になって、遠い村をまるごと救っていることを。そして山に棲む四匹の精霊が、彼の豊かになっていく暮らしに合わせて、すくすく育っていることを――。 本人だけが最後まで気づかない、無自覚のスローライフ・ファンタジー。精霊たちと囲む食卓は、今日も賑やか。山では、いい匂いのごはんが炊けています。 ※作者は名前を考えるのが苦手です | U46: 6 | V46: 4 | W46: 4 | X46: 2 | Y46: 0.80645161 | Z46: 継続 | AA46: 1
A47: action | B47: 現代ファンタジー | C47: 2912051604996628001 | D47: TCG能力《創世札典》を手に入れた俺、一日一マナから現代社会を攻略する～治療、未来予知、若返り。マナが足りないので山を買います～ | E47: パラレル・ゲーマー | F47: https://kakuyomu.jp/works/2912051604996628001 | G47: 59 | H47: 977 | I47: 41 | J47: 457981 | K47: 37 | L47: AI利用|現代社会|魔法|チート|TCG|主人公以外は現代社会 | M47: 連載中 | N47: 一日一マナ。最初に治したのは、肩こりだった。 | O47: 都内のシステム関連企業で主任として働く、三十六歳の会社員・門倉啓介。 仕事も収入も安定し、独身ゆえに貯金もそれなり。大きな不満はないものの、同じような毎日を繰り返しながら、少しずつ疲れていく人生を送っていた。 そんなある休日の朝、コーヒーを飲んでいた啓介の視界に、突然メッセージが現れる。 『あなたは《創世札典／GENESIS DECK》を獲得しました』 呼び出された分厚いバインダーに収められていた最初の土地カードは、彼が暮らす賃貸マンション――《借宿／Borrowed Haven》。 そこから一日に一度だけ得られる、たった一つのマナ。 チュートリアルとして与えられた生命術式《日々の修繕／Daily Maintenance》を使うと、長年悩まされていた肩こりも、腰の重さも、眼精疲労も、指先の小さな傷も一瞬で消えてしまった。 どうやら啓介が手に入れたのは、土地からマナを生み、そのマナを対価として望んだ効果をカードにできる、TCGそのもののような異能らしい。 生命、知識、物資、熱量、境界。 五種類のマナを使い分ければ、身体の治療、短時間の未来予知、物質の生成、電気や熱の操作、空間収納まで、理論上は何でも実現できる。 啓介はまず、自分の疲労や体調不良を治し、未来を少しだけ先読みしながら、毎日の生活を豊かにしていく。 未来予知を利用して小遣いを稼ぎ、仕事上の失敗を避け、事故や災害を事前に警告する。やがて治癒術式を他人にも使えるようになれば、これまで治らなかった怪我や病気を癒やし、その力を新たな商売へつなげていく。 しかし、慢性疾患の完治、失われた身体組織の再生、そして若返り。 啓介が望む奇跡が大きくなるほど、要求されるマナも三点、五点と増えていく。 一日に得られるマナは、まだ一つだけ。 それなら、増やせばいい。 昔TCGを遊んでいた啓介は、今日のマナを使わず、毎日少しずつ注ぎ込むことで、恒久的にマナを生み出すアーティファクトを作れることに気づく。 さらに、自分の土地を増やせば、もっと多くのマナを得られるのではないか。 そう考えた啓介は、長年貯めてきた預金を使い――山を買った。 格安山林を土地カードへ変え、工房を作り、マナ・アーティファクトを増産する。未来予知と治癒術式で得た資金を次の土地と設備へ投資し、啓介のマナ基盤は雪だるま式に拡大していく。 一日一マナだった小さな奇跡は、やがて人の運命を変え、災害から都市を救い、老いさえ覆す力となる。 そして境界の彼方を観測するカードが完成したとき、啓介は知る。 この世界の外にも、土地は存在する。 これは、普通の中年サラリーマンが一枚の賃貸住宅カードから始め、現代社会に魔法の経済圏を築き、やがて数多の次元を旅するまでの物語。 なろうハーメルンにも掲載してます。 | P47: 1188 | Q47: 56 | R47: 968 | S47: 40 | T47: 都内のシステム関連企業で主任として働く、三十六歳の会社員・門倉啓介。 仕事も収入も安定し、独身ゆえに貯金もそれなり。大きな不満はないものの、同じような毎日を繰り返しながら、少しずつ疲れていく人生を送っていた。 そんなある休日の朝、コーヒーを飲んでいた啓介の視界に、突然メッセージが現れる。 『あなたは《創世札典／GENESIS DECK》を獲得しました』 呼び出された分厚いバインダーに収められていた最初の土地カードは、彼が暮らす賃貸マンション――《借宿／Borrowed Haven》。 そこから一日に一度だけ得られる、たった一つのマナ。 チュートリアルとして与えられた生命術式《日々の修繕／Daily Maintenance》を使うと、長年悩まされていた肩こりも、腰の重さも、眼精疲労も、指先の小さな傷も一瞬で消えてしまった。 どうやら啓介が手に入れたのは、土地からマナを生み、そのマナを対価として望んだ効果をカードにできる、TCGそのもののような異能らしい。 生命、知識、物資、熱量、境界。 五種類のマナを使い分ければ、身体の治療、短時間の未来予知、物質の生成、電気や熱の操作、空間収納まで、理論上は何でも実現できる。 啓介はまず、自分の疲労や体調不良を治し、未来を少しだけ先読みしながら、毎日の生活を豊かにしていく。 未来予知を利用して小遣いを稼ぎ、仕事上の失敗を避け、事故や災害を事前に警告する。やがて治癒術式を他人にも使えるようになれば、これまで治らなかった怪我や病気を癒やし、その力を新たな商売へつなげていく。 しかし、慢性疾患の完治、失われた身体組織の再生、そして若返り。 啓介が望む奇跡が大きくなるほど、要求されるマナも三点、五点と増えていく。 一日に得られるマナは、まだ一つだけ。 それなら、増やせばいい。 昔TCGを遊んでいた啓介は、今日のマナを使わず、毎日少しずつ注ぎ込むことで、恒久的にマナを生み出すアーティファクトを作れることに気づく。 さらに、自分の土地を増やせば、もっと多くのマナを得られるのではないか。 そう考えた啓介は、長年貯めてきた預金を使い――山を買った。 格安山林を土地カードへ変え、工房を作り、マナ・アーティファクトを増産する。未来予知と治癒術式で得た資金を次の土地と設備へ投資し、啓介のマナ基盤は雪だるま式に拡大していく。 一日一マナだった小さな奇跡は、やがて人の運命を変え、災害から都市を救い、老いさえ覆す力となる。 そして境界の彼方を観測するカードが完成したとき、啓介は知る。 この世界の外にも、土地は存在する。 これは、普通の中年サラリーマンが一枚の賃貸住宅カードから始め、現代社会に魔法の経済圏を築き、やがて数多の次元を旅するまでの物語。 なろうハーメルンにも掲載してます。 | U47: -3 | V47: 9 | W47: 9 | X47: 1 | Y47: 0.92975207 | Z47: 継続 | AA47: 1
A48: action | B48: 現代ファンタジー | C48: 2912051605091112292 | D48: 世界崩壊まであと5年、俺は裏山に北海道サイズの地下帝国を建てる ～万能システムと無限の魔石で、地上が滅びる前に絶対安全な理想郷をクラフトします～ | E48: @takanoyuichi | F48: https://kakuyomu.jp/works/2912051605091112292 | G48: 15 | H48: 554 | I48: 50 | J48: 237794 | K48: 12 | L48: タイムリープ|ダンジョン|内政|クラフト|拠点防衛|主人公最強（システム）|男主人公|スローライフ要素あり | M48: 完結済 | N48: 地上が地獄と化すその日、俺たちの地下帝国は「究極の楽園」になる。 | O48: ダンジョンから溢れ出したモンスターと天変地異により、人類が滅亡へと向かう30年後の未来。 泥水をすすり、絶望の中で死を迎えたはずの青年・佐藤拓海は、気がつくと「世界崩壊の5年前」の現代日本へとタイムリープしていた。 「二度とあの地獄は味わわない」 悲劇を完全に回避するため、拓海は回帰と共に得た規格外の能力『万能掘削・建設システム』を起動する。 彼が選んだのは、山梨県の裏山を買い取り、地下深くに「北海道サイズ（約8万平方キロメートル）」の超巨大なシェルターを築き上げることだった。 土木建築の令嬢、天才魔力工学者、元自衛官、凄腕物流コーディネーター、農業のプロフェッショナル。 最高の仲間たちを巻き込み、無機質なAIを完璧なメイドアンドロイドへと進化させながら、拓海の狂気的な地下開拓が幕を開ける。 食料自給率100%の巨大農園、永久稼働するギガ魔力炉、敵を資源に変える全自動防衛網。 さらには、地下300メートルの天然温泉街に、広大な室内海と大図書館まで――。 やがて運命の「Xデー」が訪れ、地上が血と炎の地獄に包まれる中。 拓海たちは分厚い岩盤の下で、温かい食事と完璧な日常を謳歌する。 これは、冷徹な合理主義者の主人公が、滅びゆく世界を完全に置き去りにして「究極のQOL（生活の質）」を極める、痛快な巨大拠点クラフト＆内政ファンタジー。 | P48: 578 | Q48: 14 | R48: 520 | S48: 50 | T48: ダンジョンから溢れ出したモンスターと天変地異により、人類が滅亡へと向かう30年後の未来。 泥水をすすり、絶望の中で死を迎えたはずの青年・佐藤拓海は、気がつくと「世界崩壊の5年前」の現代日本へとタイムリープしていた。 「二度とあの地獄は味わわない」 悲劇を完全に回避するため、拓海は回帰と共に得た規格外の能力『万能掘削・建設システム』を起動する。 彼が選んだのは、山梨県の裏山を買い取り、地下深くに「北海道サイズ（約8万平方キロメートル）」の超巨大なシェルターを築き上げることだった。 土木建築の令嬢、天才魔力工学者、元自衛官、凄腕物流コーディネーター、農業のプロフェッショナル。 最高の仲間たちを巻き込み、無機質なAIを完璧なメイドアンドロイドへと進化させながら、拓海の狂気的な地下開拓が幕を開ける。 食料自給率100%の巨大農園、永久稼働するギガ魔力炉、敵を資源に変える全自動防衛網。 さらには、地下300メートルの天然温泉街に、広大な室内海と大図書館まで――。 やがて運命の「Xデー」が訪れ、地上が血と炎の地獄に包まれる中。 拓海たちは分厚い岩盤の下で、温かい食事と完璧な日常を謳歌する。 これは、冷徹な合理主義者の主人公が、滅びゆく世界を完全に置き去りにして「究極のQOL（生活の質）」を極める、痛快な巨大拠点クラフト＆内政ファンタジー。 | U48: -1 | V48: 34 | W48: 34 | X48: 0 | Y48: 6.5384615 | Z48: 継続 | AA48: 1
A49: action | B49: 現代ファンタジー | C49: 2912051605171684401 | D49: 『ゴミスキル【調理】で追放された俺、モンスター料理で最強になる～ダンジョン飯配信を始めたら世界中が腹を空かせて待っている～』 | E49: @takamatuhorihori | F49: https://kakuyomu.jp/works/2912051605171684401 | G49: 94 | H49: 381 | I49: 67 | J49: 444652 | K49: 33 | L49: ダンジョン配信|主人公最強|モンスター料理|飯テロ|追放ざまぁ|掲示板回|AI本文使用 | M49: 完結済 | N49: 最弱料理人の飯テロ配信が、世界の常識を変えていく！ | O49: 世界各地にダンジョンが出現し、探索の様子を生配信する「ダンジョン配信」が人気となった現代。 御厨レンが授かったスキルは、戦闘には何の役にも立たない【調理】だった。 「ダンジョンで料理して、何の役に立つんだよ」 荷物持ちや雑用ばかりを押しつけられた末、レンは所属していた人気探索者パーティーから追放されてしまう。 一人でダンジョンに取り残されたレンは、空腹を満たすため、仲間たちが捨てていったモンスターの肉を【調理】して食べることにした。 すると――。 《ホーンラビットの香草焼きを食べました》 《俊敏性が上昇しました》 《スキル【跳躍】を獲得しました》 実は【調理】とは、モンスターが持つ力を料理へ変え、食べた者に与える規格外のスキルだった。 オーク肉をステーキにすれば筋力が上がり、ポイズンスライムをゼリーにすれば毒耐性を獲得する。 強力なモンスターを料理して食べるほど、レンはどんどん強くなっていった。 しかし、モンスターを倒して食べるだけでは生活費を稼げない。 そこでレンは、ダンジョン内で料理を作る様子を配信することにした。 巨大な魔獣を丸ごと焼き、スライムを宝石のようなスイーツに変え、ドラゴンの肉を豪快なステーキに仕上げていく。 最初は誰にも注目されなかった配信だったが、見たこともないモンスター料理と、食べるたびに強くなっていくレンの姿が話題となり――。 『討伐はいいから、早く料理してくれ！』 『今日の飯テロはまだか！？』 『ドラゴンステーキ、俺にも食わせてくれ！』 気づけばレンの配信には、戦闘ではなく料理を見るため、世界中から視聴者が集まっていた。 さらに、有名配信者やトップ探索者、巨大企業までもが、レンの料理を求め始める。 一方、レンを追放したパーティーは、彼の料理によって自分たちが強化されていたことを知らず、急速に落ちぶれていき――。 これは、ゴミスキルと笑われた料理人が、モンスターを倒し、料理して、食べて強くなり、世界一のダンジョン配信者へと成り上がる物語。 | P49: 867 | Q49: 91 | R49: 367 | S49: 67 | T49: 世界各地にダンジョンが出現し、探索の様子を生配信する「ダンジョン配信」が人気となった現代。 御厨レンが授かったスキルは、戦闘には何の役にも立たない【調理】だった。 「ダンジョンで料理して、何の役に立つんだよ」 荷物持ちや雑用ばかりを押しつけられた末、レンは所属していた人気探索者パーティーから追放されてしまう。 一人でダンジョンに取り残されたレンは、空腹を満たすため、仲間たちが捨てていったモンスターの肉を【調理】して食べることにした。 すると――。 《ホーンラビットの香草焼きを食べました》 《俊敏性が上昇しました》 《スキル【跳躍】を獲得しました》 実は【調理】とは、モンスターが持つ力を料理へ変え、食べた者に与える規格外のスキルだった。 オーク肉をステーキにすれば筋力が上がり、ポイズンスライムをゼリーにすれば毒耐性を獲得する。 強力なモンスターを料理して食べるほど、レンはどんどん強くなっていった。 しかし、モンスターを倒して食べるだけでは生活費を稼げない。 そこでレンは、ダンジョン内で料理を作る様子を配信することにした。 巨大な魔獣を丸ごと焼き、スライムを宝石のようなスイーツに変え、ドラゴンの肉を豪快なステーキに仕上げていく。 最初は誰にも注目されなかった配信だったが、見たこともないモンスター料理と、食べるたびに強くなっていくレンの姿が話題となり――。 『討伐はいいから、早く料理してくれ！』 『今日の飯テロはまだか！？』 『ドラゴンステーキ、俺にも食わせてくれ！』 気づけばレンの配信には、戦闘ではなく料理を見るため、世界中から視聴者が集まっていた。 さらに、有名配信者やトップ探索者、巨大企業までもが、レンの料理を求め始める。 一方、レンを追放したパーティーは、彼の料理によって自分たちが強化されていたことを知らず、急速に落ちぶれていき――。 これは、ゴミスキルと笑われた料理人が、モンスターを倒し、料理して、食べて強くなり、世界一のダンジョン配信者へと成り上がる物語。 | U49: -3 | V49: 14 | W49: 14 | X49: 0 | Y49: 3.8147139 | Z49: 継続 | AA49: 1
... A53: action | B53: 現代ファンタジー | C53: 2912051605271543183 | D53: 異世界帰還者イッチちゃんねる〜異世界も魔法もあるんだよ！〜 | E53: mitsuzo | F53: https://kakuyomu.jp/works/2912051605271543183 | G53: 35 | H53: 489 | I53: 21 | J53: 45367 | K53: 31 | L53: 男主人公|異世界転生|無双|成り上がり|魔法|配信|掲示板|異世界帰還者 | M53: 連載中 | N53: 異世界も魔法もあるんだよ。本当だよ？ | O53: 【祝・６万PV大感謝！】 【毎週火・金・日の週３投稿（7:00）】 「異世界の話とか誰でも聞きたいんじゃね？」 そんな思いつきから配信者（ライバー）になることを決意した とある異世界帰還者イッチのお話。 | P53: 103 | Q53: 39 | R53: 475 | S53: 21 | T53: 【祝・６万PV大感謝！】 【毎週火・金・日の週３投稿（7:00）】 「異世界の話とか誰でも聞きたいんじゃね？」 そんな思いつきから配信者（ライバー）になることを決意した とある異世界帰還者イッチのお話。 | U53: 4 | V53: 14 | W53: 14 | X53: 0 | Y53: 2.9473684 | Z53: 継続 | AA53: 1
A54: action | C54: 2912051605388942408 | D54: 喫茶店のマスターはバイトのJKを救うためにダンジョンへ向かうそうですよ？～ダンジョン配信で人気の女子高校生を救ったおじさん、実はダンジョン黎明期を戦って今の日本を作った生きる伝説でした～ | E54: リヒト | N54: 最前線から退いても最強のおじさんは、バイトのJKと共に今一度成り上がる | O54: 飯野可憐は、今を時めく女子高校生ダンジョン配信者だった。 高校生離れした高い実力と、可愛らしい容姿。 その二つを武器に、瞬く間に人気を集めた彼女はこのまま順調に実力を磨き続ければ、日本を代表する探索者になると誰もが思っていた。 しかし、ある日の配信中。 「……い、いやっ！」 イレギュラーと呼ばれる圧倒的な力を持つ魔物と遭遇し、可憐は為す術なく追い詰められてしまう。 絶体絶命。 そんな彼女の前に現れたのは、 「ご無事ですかな？」 一人の冴えない中年男性だった。 「何でマスターがここに！？」 その男の名は、神崎健一。 可憐が人気配信者になるよりも前からバイトしている売れない喫茶店のマスターだった。 売れない喫茶店を構える冴えないオジサンだと思っていたその人物の正体。 それは、ダンジョンが出現したばかりのファンタジー黎明期の日本で最強の探索者として君臨し、幾多の命を救って日本のダンジョン攻略の礎を築いた───生きる伝説だった。 一度は最前線を退き、静かな喫茶店のマスターとして余生を過ごしていた神崎健一。 しかし、女子高校生ダンジョン配信者を救ったその瞬間。 忘れられていた英雄の名が、再び日本中を駆け巡る時、また一つ、世界が変わっていく───。 | Q54: 92 | R54: 702 | S54: 35 | T54: 飯野可憐は、今を時めく女子高校生ダンジョン配信者だった。 高校生離れした高い実力と、可愛らしい容姿。 その二つを武器に、瞬く間に人気を集めた彼女はこのまま順調に実力を磨き続ければ、日本を代表する探索者になると誰もが思っていた。 しかし、ある日の配信中。 「……い、いやっ！」 イレギュラーと呼ばれる圧倒的な力を持つ魔物と遭遇し、可憐は為す術なく追い詰められてしまう。 絶体絶命。 そんな彼女の前に現れたのは、 「ご無事ですかな？」 一人の冴えない中年男性だった。 「何でマスターがここに！？」 その男の名は、神崎健一。 可憐が人気配信者になるよりも前からバイトしている売れない喫茶店のマスターだった。 売れない喫茶店を構える冴えないオジサンだと思っていたその人物の正体。 それは、ダンジョンが出現したばかりのファンタジー黎明期の日本で最強の探索者として君臨し、幾多の命を救って日本のダンジョン攻略の礎を築いた───生きる伝説だった。 一度は最前線を退き、静かな喫茶店のマスターとして余生を過ごしていた神崎健一。 しかし、女子高校生ダンジョン配信者を救ったその瞬間。 忘れられていた英雄の名が、再び日本中を駆け巡る時、また一つ、世界が変わっていく───。 | Z54: 圏外落ち | AA54: 1
A55: action | B55: 現代ファンタジー | C55: 2912051605462941593 | D55: 俺だけ異世界転移していないらしい 〜異世界で俺と結婚した三人の嫁が、転移前の俺を必死に攻略してくる | E55: nayaminotake | F55: https://kakuyomu.jp/works/2912051605462941593 | G55: 36 | H55: 434 | I55: 27 | J55: 71149 | K55: 23 | L55: 勘違い系主人公|チートヒロイン|最強クラスメート|異世界帰り（主人公以外）|ハーレム|異世界侵略者とのバトル|皆、主人公大好き | M55: 連載中 | N55: 俺だけが何も知らない。クラス全員、異世界帰りでした。 | O55: 俺――御神巧、17歳。 帝理高校に通う、ごく普通の高校二年生。 家は貧乏。 放課後は喫茶店でバイト。 趣味はアイドルの推し活。 クラスでは陰キャオタク扱い。 そんな俺の日常が、二年生になった春から急におかしくなった。 人気アイドル女子高生の水原真希。 学校一の金持ち大和撫子、黒峰麗華。 喫茶店の看板娘でモテギャルの黄瀬エミリ。 昨日まで俺のことなんて眼中になかったはずの三人が、なぜか俺に異常なほど構ってくる。 クラスメートたちも妙だ。 昨日まで犬猿の仲だった奴らが、まるで昔からの親友のように笑い合っている。 俺だけが知らない、何かがある。 そして俺は、まだ知らない。 ――クラスメート全員が、十年前に一度「異世界転移」していたことを。 魔王と戦い、仲間を失い、世界を救った十年間。 その中心にいたのは、俺――御神巧だった。 異世界で「深皇」と呼ばれ、三人の美女とエンゲージを結び、仲間たちを導き、皆を助ける為、愛する三人の妻を守る為、命を散らした英雄。 しかし、女神が彼らの願いを叶えたことで、全員は異世界へ召喚される直前の時間へ戻された。 既に異世界で死んでいた一人を除いて。 その一人である俺だけは――十年間の記憶を持たない。 つまり今の俺にとって、彼らはただのクラスメート。 そして彼らにとって俺は――命を懸けて守り、愛した「親友」であり「英雄」。 記憶を失った俺と、俺を知り尽くしているクラスメートたち。 これは、 「俺だけが何も知らない」 そんな状態から始まる、二度目の異世界と青春の物語。 | P55: 675 | Q55: 37 | R55: 420 | S55: 26 | T55: 俺――御神巧、17歳。 帝理高校に通う、ごく普通の高校二年生。 家は貧乏。 放課後は喫茶店でバイト。 趣味はアイドルの推し活。 クラスでは陰キャオタク扱い。 そんな俺の日常が、二年生になった春から急におかしくなった。 人気アイドル女子高生の水原真希。 学校一の金持ち大和撫子、黒峰麗華。 喫茶店の看板娘でモテギャルの黄瀬エミリ。 昨日まで俺のことなんて眼中になかったはずの三人が、なぜか俺に異常なほど構ってくる。 クラスメートたちも妙だ。 昨日まで犬猿の仲だった奴らが、まるで昔からの親友のように笑い合っている。 俺だけが知らない、何かがある。 そして俺は、まだ知らない。 ――クラスメート全員が、十年前に一度「異世界転移」していたことを。 魔王と戦い、仲間を失い、世界を救った十年間。 その中心にいたのは、俺――御神巧だった。 異世界で「深皇」と呼ばれ、三人の美女とエンゲージを結び、仲間たちを導き、皆を助ける為、愛する三人の妻を守る為、命を散らした英雄。 しかし、女神が彼らの願いを叶えたことで、全員は異世界へ召喚される直前の時間へ戻された。 既に異世界で死んでいた一人を除いて。 その一人である俺だけは――十年間の記憶を持たない。 つまり今の俺にとって、彼らはただのクラスメート。 そして彼らにとって俺は――命を懸けて守り、愛した「親友」であり「英雄」。 記憶を失った俺と、俺を知り尽くしているクラスメートたち。 これは、 「俺だけが何も知らない」 そんな状態から始まる、二度目の異世界と青春の物語。 | U55: 1 | V55: 14 | W55: 14 | X55: 1 | Y55: 3.3333333 | Z55: 継続 | AA55: 1
A56: action | B56: 現代ファンタジー | C56: 2912051605503235345 | D56: 凝り性ダンジョンマスターの神運営 ～レアドロップは"面白い条件"ほど割安になると気づいたので、俺のダンジョンを完成度で日本一にします～ | E56: だらすく | F56: https://kakuyomu.jp/works/2912051605503235345 | G56: 29 | H56: 656 | I56: 32 | J56: 341172 | K56: 30 | L56: 現代ダンジョン|ダンジョン|ダンジョン配信|成り上がり|ダンジョン経営|掲示板|ダンジョンマスター|AI本文利用 | M56: 連載中 | N56: ダンジョンは集客業。レアドロップは"面白い条件"ほど安くなる | O56: ダンジョン運営で一番大事なのは、強いモンスターじゃない。Wi-Fiだ。 世界に247、日本に10。突如出現したダンジョンは、完全攻略されれば消滅し、客が来なければコアが飢えて崩壊する。つまりマスターの仕事は――集客業。ゲーム運営と、まったく同じだった。 元ソシャゲ会社のレベルデザイナー・間宮創、28歳・無職。愛した自社ゲームを重課金路線に潰されて帰郷した彼が拾ったのは、日本最弱・最小・最僻地の霧谷ダンジョン。残高3,000DP、週間来訪者3人（全員公務員）、注目度ランキング最下位。 だが、誰も読まない利用規約・全1,247条を徹夜で読破した彼は、とんでもない仕様を見つけてしまう。 「レアドロップの設定コストは、条件を凝るほど割安になる。ただし理不尽な条件は割り引かれない」 ――面白いゲームデザインほど安くなる世界で、まだ誰もレベルデザインをしていない。それ、俺の専門分野じゃん。 | P56: 399 | Q56: 22 | R56: 645 | S56: 31 | T56: ダンジョン運営で一番大事なのは、強いモンスターじゃない。Wi-Fiだ。 世界に247、日本に10。突如出現したダンジョンは、完全攻略されれば消滅し、客が来なければコアが飢えて崩壊する。つまりマスターの仕事は――集客業。ゲーム運営と、まったく同じだった。 元ソシャゲ会社のレベルデザイナー・間宮創、28歳・無職。愛した自社ゲームを重課金路線に潰されて帰郷した彼が拾ったのは、日本最弱・最小・最僻地の霧谷ダンジョン。残高3,000DP、週間来訪者3人（全員公務員）、注目度ランキング最下位。 だが、誰も読まない利用規約・全1,247条を徹夜で読破した彼は、とんでもない仕様を見つけてしまう。 「レアドロップの設定コストは、条件を凝るほど割安になる。ただし理不尽な条件は割り引かれない」 ――面白いゲームデザインほど安くなる世界で、まだ誰もレベルデザインをしていない。それ、俺の専門分野じゃん。 | U56: -7 | V56: 11 | W56: 11 | X56: 1 | Y56: 1.7054264 | Z56: 継続 | AA56: 1
A57: action | B57: 現代ファンタジー | C57: 2912051605507569959 | D57: 異世界で魔王を倒して帰還した俺、気分転換にVRMMOを始めたら戦闘技術がおかしいらしい | E57: 海鳴 雫 | F57: https://kakuyomu.jp/works/2912051605507569959 | G57: 9 | H57: 1158 | I57: 32 | J57: 83907 | K57: 30 | L57: VRMMO|配信|主人公最強|男主人公|異世界帰還|ラブコメ|現代|カクヨムオンリー | M57: 連載中 | N57: 世界を救った剣技でゲームしてるだけなのに、なぜか配信がバズっている。 | O57: 十二年間の旅の果て、勇者・天城悠真は魔王を倒した。 多くの出会いと別れを経験し、何度も死線を潜り抜け、ようやく成し遂げた世界の平和。 その功績を称えた女神から「望む褒美を与えましょう」と告げられた悠真が願ったものは、富でも名誉でも最強の力でもなかった。 「元の世界に、帰してください」 そして悠真は帰還する。 十六歳だった、あの日へ。 異世界で過ごした十二年間の記憶と経験、そのすべてを残したまま。 家族がいる。 学校がある。 命を狙ってくる魔物はいない。 そんな当たり前の日常を噛み締めていた悠真は、ある日、世間で大流行しているフルダイブ型VRMMORPG《Another Frontier Online》――通称AFOの存在を知る。 「気分転換には、ちょうどいいか」 軽い気持ちでAFOを購入した悠真は、ゲーム内に誰でも利用できる配信機能があることを知り、せっかくだからと配信を始める。 最初の視聴者は、たった三人。 しかし、その三人はすぐに気づいてしまった。 『……今の避け方なに？』 『初心者だよな？』 『なんでゴブリンの急所を一発で抜けるんだよ』 敵の攻撃は紙一重で回避。 剣を振れば急所へ直撃。 難しいはずのパリィさえ、異世界で培った技術で当然のように成功させる。 悠真にとって、それは十二年間生き残るために身につけた当たり前の技術。 だがAFOプレイヤーからすれば――完全に異常だった。 やがて一つの切り抜き動画をきっかけに、無名だった悠真の配信は爆発的に広まっていく。 トップ配信者。 最強のPvPプレイヤー。 大手ギルド。 そして世界中の猛者たち。 さまざまなプレイヤーが謎の新人《ユーマ》へ注目し始める。 けれど悠真が求めているのは、最強の称号でも有名配信者の座でもない。 かつての冒険では、負ければ誰かが死んだ。 今度は違う。 失敗してもやり直せる。 仲間が倒れても、また会える。 これは世界を救った元勇者が―― 今度こそ純粋に「冒険」を楽しむ物語。 | P57: 898 | Q57: 10 | R57: 1096 | S57: 31 | T57: 十二年間の旅の果て、勇者・天城悠真は魔王を倒した。 多くの出会いと別れを経験し、何度も死線を潜り抜け、ようやく成し遂げた世界の平和。 その功績を称えた女神から「望む褒美を与えましょう」と告げられた悠真が願ったものは、富でも名誉でも最強の力でもなかった。 「元の世界に、帰してください」 そして悠真は帰還する。 十六歳だった、あの日へ。 異世界で過ごした十二年間の記憶と経験、そのすべてを残したまま。 家族がいる。 学校がある。 命を狙ってくる魔物はいない。 そんな当たり前の日常を噛み締めていた悠真は、ある日、世間で大流行しているフルダイブ型VRMMORPG《Another Frontier Online》――通称AFOの存在を知る。 「気分転換には、ちょうどいいか」 軽い気持ちでAFOを購入した悠真は、ゲーム内に誰でも利用できる配信機能があることを知り、せっかくだからと配信を始める。 最初の視聴者は、たった三人。 しかし、その三人はすぐに気づいてしまった。 『……今の避け方なに？』 『初心者だよな？』 『なんでゴブリンの急所を一発で抜けるんだよ』 敵の攻撃は紙一重で回避。 剣を振れば急所へ直撃。 難しいはずのパリィさえ、異世界で培った技術で当然のように成功させる。 悠真にとって、それは十二年間生き残るために身につけた当たり前の技術。 だがAFOプレイヤーからすれば――完全に異常だった。 やがて一つの切り抜き動画をきっかけに、無名だった悠真の配信は爆発的に広まっていく。 トップ配信者。 最強のPvPプレイヤー。 大手ギルド。 そして世界中の猛者たち。 さまざまなプレイヤーが謎の新人《ユーマ》へ注目し始める。 けれど悠真が求めているのは、最強の称号でも有名配信者の座でもない。 かつての冒険では、負ければ誰かが死んだ。 今度は違う。 失敗してもやり直せる。 仲間が倒れても、また会える。 これは世界を救った元勇者が―― 今度こそ純粋に「冒険」を楽しむ物語。 | U57: 1 | V57: 62 | W57: 62 | X57: 1 | Y57: 5.6569343 | Z57: 継続 | AA57: 1
A58: action | B58: 現代ファンタジー | C58: 2912051605508521275 | D58: 祝小説フォロー800人及び4万PV達成！！！最強探索者、配信者のマネージャーになる | E58: はっちゃん | F58: https://kakuyomu.jp/works/2912051605508521275 | G58: 58 | H58: 249 | I58: 15 | J58: 43502 | K58: 29 | L58: ダンジョン|配信|主人公最強|マネージャー|現代ファンタジー|社畜|推し活 | M58: 連載中 | N58: 貯金ないなぁ…どこかに就職しなきゃ… | O58: ダンジョン大国日本の首都東京 そこには世界最強の探索者 黒崎蓮 が住んでいる。 負けることがないと言われているが… 「金ほしぃ…」現在金に負けている。 そんな所に「——なので、白峰プロダクションはマネージャーを募集します！」 「これだ！！！！！」 彼の推しの探索者ユニットが所属している会社でマネージャー募集されていることに気づいた。 「推しを応援できて金も貰える。完璧だ」 そんなこんなでマネージャーになって彼女らを支えるそんなお話。 ——なお思ってたより業務多すぎて過労死まっしぐらとの事 | P58: 249 | Q58: 58 | R58: 240 | S58: 15 | T58: ダンジョン大国日本の首都東京 そこには世界最強の探索者 黒崎蓮 が住んでいる。 負けることがないと言われているが… 「金ほしぃ…」現在金に負けている。 そんな所に「——なので、白峰プロダクションはマネージャーを募集します！」 「これだ！！！！！」 彼の推しの探索者ユニットが所属している会社でマネージャー募集されていることに気づいた。 「推しを応援できて金も貰える。完璧だ」 そんなこんなでマネージャーになって彼女らを支えるそんなお話。 ——なお思ってたより業務多すぎて過労死まっしぐらとの事 | U58: 0 | V58: 9 | W58: 9 | X58: 0 | Y58: 3.75 | Z58: 継続 | AA58: 1
A59: action | B59: 現代ファンタジー | C59: 2912051605570028912 | D59: 『引きこもり魔道士、現実のダンジョンでも最強でした……ただし本人だけ気づいてません』 | E59: うちお | F59: https://kakuyomu.jp/works/2912051605570028912 | G59: 57 | H59: 128 | I59: 106 | J59: 205481 | K59: 30 | L59: 引きこもり主人公|ゲーム廃人|コメディ|無自覚無双|本人だけ気づいていない|食料品ダンジョン|ほのぼの|AI本文利用 | M59: 連載中 | N59: 「ダンジョンより怖いのは、冷蔵庫が空っぽなこと。」 | O59: 2045年、現実世界に突如としてダンジョンが出現した。 未知の魔物による襲撃で世界は混乱し、人々は生き残るため必死に戦っていた。 ……しかし、その危機にまったく気づいていない男が一人。 波白斗真、35歳。 引きこもり歴多数。 外見はボサボサ頭に伸び放題の無精ひげ。 誰が見ても怪しい男。 そんな彼は、世界が崩壊していることを知らず、いつも通りゲームをして朝を迎えていた。 斗真の唯一の才能。 それはゲーム内で培った圧倒的な魔法操作技術。 仮想世界では筆頭魔道士として無双し、女性プレイヤーからも人気の完璧な存在。 もちろん現実では引きこもりのままだった。 そんなある日、食料を買うため久しぶりに外へ出た斗真は、瓦礫だらけになった街を見て首を傾げる。 「……寝てる間にテロでもあったのか？」 世界が魔物に侵略されているとは夢にも思わない。 そこで出会ったのは、ゴブリンに襲われ倒れていた女子高生。 彼女は必死に助けを求めるが、斗真は――。 「ゴブリン？ 新しいゲーム？」 と本気で勘違い。 しかし、彼女の必死な姿に押され、人生で初めて女性から頼られた斗真は勢いで助けることを決意する。 そして始まる。 世界の危機を理解していない最強魔道士と、常識を持った女子高生による奇妙な冒険。 本人だけが知らない。 ゲームで磨いた魔法技術が、現実世界では世界を救うほどの力になっていることを。 | P59: 589 | Q59: 61 | R59: 121 | S59: 103 | T59: 2045年、現実世界に突如としてダンジョンが出現した。 未知の魔物による襲撃で世界は混乱し、人々は生き残るため必死に戦っていた。 ……しかし、その危機にまったく気づいていない男が一人。 波白斗真、35歳。 引きこもり歴多数。 外見はボサボサ頭に伸び放題の無精ひげ。 誰が見ても怪しい男。 そんな彼は、世界が崩壊していることを知らず、いつも通りゲームをして朝を迎えていた。 斗真の唯一の才能。 それはゲーム内で培った圧倒的な魔法操作技術。 仮想世界では筆頭魔道士として無双し、女性プレイヤーからも人気の完璧な存在。 もちろん現実では引きこもりのままだった。 そんなある日、食料を買うため久しぶりに外へ出た斗真は、瓦礫だらけになった街を見て首を傾げる。 「……寝てる間にテロでもあったのか？」 世界が魔物に侵略されているとは夢にも思わない。 そこで出会ったのは、ゴブリンに襲われ倒れていた女子高生。 彼女は必死に助けを求めるが、斗真は――。 「ゴブリン？ 新しいゲーム？」 と本気で勘違い。 しかし、彼女の必死な姿に押され、人生で初めて女性から頼られた斗真は勢いで助けることを決意する。 そして始まる。 世界の危機を理解していない最強魔道士と、常識を持った女子高生による奇妙な冒険。 本人だけが知らない。 ゲームで磨いた魔法技術が、現実世界では世界を救うほどの力になっていることを。 | U59: 4 | V59: 7 | W59: 7 | X59: 3 | Y59: 5.785124 | Z59: 継続 | AA59: 1
A60: action | B60: 現代ファンタジー | C60: 2912051605598246153 | D60: 魔王を倒したおっさん、三十年ぶりに日本へ帰還し現代ダンジョンで無双する ～今どきダンジョン攻略も科学の時代らしいけど、おじさんは昔ながらに剣と魔法で戦うよ～ | E60: 厳座励主（ごんざれす） | F60: https://kakuyomu.jp/works/2912051605598246153 | G60: 86 | H60: 942 | I60: 15 | J60: 48316 | K60: 14 | L60: カクヨムオンリー|イケオジ|おっさん|剣と魔法|現代ダンジョン|ダンジョン配信|チート|無双 | M60: 完結済 | N60: S級ダンジョン？ おじさんにはちょっと物足りないなあ | O60: 十五歳で異世界へ転移してから、はや三十年。 勇者となった日比野は、仲間たちと共に魔王を討ち果たした。 あとは討伐の証を持ち帰り、人間と魔族の戦争を終わらせる……はずだったのだが、魔王が死に際に放った謎の魔法に巻き込まれ、日本へ帰還してしまう。 三十年が経過した日本は、大きく変わっていた。 魔力と科学技術を組み合わせた最新装備で、ダンジョンを攻略するようになっていたのだ。 そんなことを何も知らない日比野は、帰還早々、空港を襲った強力な魔物――ドラゴンを借り物のビニール傘で一刀両断。 どうやら三十年も異世界で戦っているうちに、現代日本では少々規格外の存在になってしまったらしい。 しかし日比野には、日本でチヤホヤされるつもりなど毛頭ない。 異世界には、日比野の帰還を待つ人々がいる。 戦争を終わらせるためにも、もう一度、異世界転移を起こさなくてはならない。 科学でダンジョンを攻略する現代人たちと、剣と魔法で戦う原始的なおっさん勇者。 三十年ぶりの故郷で、規格外なおっさんの最強譚が幕を開ける。 | P60: 453 | Q60: 81 | R60: 934 | S60: 15 | T60: 十五歳で異世界へ転移してから、はや三十年。 勇者となった日比野は、仲間たちと共に魔王を討ち果たした。 あとは討伐の証を持ち帰り、人間と魔族の戦争を終わらせる……はずだったのだが、魔王が死に際に放った謎の魔法に巻き込まれ、日本へ帰還してしまう。 三十年が経過した日本は、大きく変わっていた。 魔力と科学技術を組み合わせた最新装備で、ダンジョンを攻略するようになっていたのだ。 そんなことを何も知らない日比野は、帰還早々、空港を襲った強力な魔物――ドラゴンを借り物のビニール傘で一刀両断。 どうやら三十年も異世界で戦っているうちに、現代日本では少々規格外の存在になってしまったらしい。 しかし日比野には、日本でチヤホヤされるつもりなど毛頭ない。 異世界には、日比野の帰還を待つ人々がいる。 戦争を終わらせるためにも、もう一度、異世界転移を起こさなくてはならない。 科学でダンジョンを攻略する現代人たちと、剣と魔法で戦う原始的なおっさん勇者。 三十年ぶりの故郷で、規格外なおっさんの最強譚が幕を開ける。 | U60: -5 | V60: 8 | W60: 8 | X60: 0 | Y60: 0.85653105 | Z60: 継続 | AA60: 1
A61: action | B61: 現代ファンタジー | C61: 2912051605640458336 | D61: 男女比1:100の貞操逆転世界でヒーラーとして生きたい！ | E61: 智者猫 | F61: https://kakuyomu.jp/works/2912051605640458336 | G61: 89 | H61: 236 | I61: 28 | J61: 76371 | K61: 27 | L61: 男性向け|学園|貞操逆転|男女比|魔法|ダンジョン|ヒーラー | M61: 連載中 | N61: 男女比1:100の貞操逆転世界だけど、僕は女の子を助けるために――― | O61: トラックにひかれ転生したらそこは… 男女比1:100の貞操逆転世界だったーーーー！？ 現代社会にダンジョン！？魔法！？冒険者！？ 前世のネトゲでヒーラーとして活動していた白間 法経（しろま ほうけい）性別：男はヒーラーとして冒険者になることを決心する。 そんな世界で必死に貞操を守りつつ、ヒーラーとして冒険者になるというお話。 不定期更新予定？ | P61: 177 | Q61: 85 | R61: 234 | S61: 27 | T61: トラックにひかれ転生したらそこは… 男女比1:100の貞操逆転世界だったーーーー！？ 現代社会にダンジョン！？魔法！？冒険者！？ 前世のネトゲでヒーラーとして活動していた白間 法経（しろま ほうけい）性別：男はヒーラーとして冒険者になることを決心する。 そんな世界で必死に貞操を守りつつ、ヒーラーとして冒険者になるというお話。 不定期更新予定？ | U61: -4 | V61: 2 | W61: 2 | X61: 1 | Y61: 0.85470085 | Z61: 継続 | AA61: 1
A62: action | B62: 現代ファンタジー | C62: 2912051605643694466 | D62: アンチだらけの元最強プロゲーマー、ダンジョン配信でも永久コンボでハメ殺す ～国民的アイドルの妹と夕飯を食べたいだけなのに、世界だけが毎回大炎上～ | E62: 白洲りつ | F62: https://kakuyomu.jp/works/2912051605643694466 | G62: 12 | H62: 1590 | I62: 32 | J62: 140783 | K62: 27 | L62: ダンジョン|兄妹|主人公最強|配信|探索者|掲示板|AI本文利用|グルメ | M62: 連載中 | N62: 夕飯を獲りに行っただけなのに、毎回世界が大炎上。 | O62: 【第1章完結！ 第2章『隠れない配信』毎日20:00更新中！】 元最強プロゲーマー、二年ぶりの復活配信。 復帰配信の舞台は、まさかのダンジョン。 ダンジョンで永久コンボ。SNS大炎上。 ──本人の目的は、妹との夕飯だった。 永久コンボで格ゲー界を大炎上させ、姿を消した元最強プロゲーマー《REN》。 その正体は、国民的アイドルの妹と暮らす、ごく普通の兄。 二年ぶりに始めた配信は、まさかの現代ダンジョン配信だった。 忙しく働く妹との貴重な休日に、美味しい夕飯を食べさせたい。 そのために高級ダンジョン食材を獲りに行くだけなのに…… 世界中が勝手に騒ぎ始める。 Aランク推奨モンスターを一度も行動させない永久コンボ。 切り抜き動画は爆発的に拡散。 探索者協会も芸能界も巻き込み、SNSは毎回トレンド入り。 それでも本人だけは、 「スーパーで買うより狩った方が安い」 と本気で思っている。 今日の夕飯を獲りに行くだけなのに、世界だけが毎回大騒ぎ。 これは、兄妹の食卓から始まるダンジョン配信コメディ。 | P62: 465 | Q62: 12 | R62: 1570 | S62: 31 | T62: 【第1章完結！ 第2章『隠れない配信』毎日20:00更新中！】 元最強プロゲーマー、二年ぶりの復活配信。 復帰配信の舞台は、まさかのダンジョン。 ダンジョンで永久コンボ。SNS大炎上。 ──本人の目的は、妹との夕飯だった。 永久コンボで格ゲー界を大炎上させ、姿を消した元最強プロゲーマー《REN》。 その正体は、国民的アイドルの妹と暮らす、ごく普通の兄。 二年ぶりに始めた配信は、まさかの現代ダンジョン配信だった。 忙しく働く妹との貴重な休日に、美味しい夕飯を食べさせたい。 そのために高級ダンジョン食材を獲りに行くだけなのに…… 世界中が勝手に騒ぎ始める。 Aランク推奨モンスターを一度も行動させない永久コンボ。 切り抜き動画は爆発的に拡散。 探索者協会も芸能界も巻き込み、SNSは毎回トレンド入り。 それでも本人だけは、 「スーパーで買うより狩った方が安い」 と本気で思っている。 今日の夕飯を獲りに行くだけなのに、世界だけが毎回大騒ぎ。 これは、兄妹の食卓から始まるダンジョン配信コメディ。 | U62: 0 | V62: 20 | W62: 20 | X62: 1 | Y62: 1.2738854 | Z62: 継続 | AA62: 1
A63: action | B63: 現代ファンタジー | C63: 2912051605689984510 | D63: ステッキを拾った。魔法少女になった（３０代男性）。 | E63: 稲荷竜 | F63: https://kakuyomu.jp/works/2912051605689984510 | G63: 50 | H63: 387 | I63: 28 | J63: 69182 | K63: 27 | L63: おっさん主人公|魔法少女|TS（変身）|掲示板回あり|第32回スニーカー大賞 | M63: 連載中 | N63: ３０代無職、魔法少女になる。 | O63: 道端に落ちていた魔法のステッキを拾い上げたせいで、タイミング悪く魔法少女になってしまった３０代男性。しかも闇属性。 かわいい女の子のフリをするのは心苦しいが、戦う力があるのにまだ幼い少女たちにだけ戦わせるのはもっと心苦しい。 そういうわけで魔法少女活動を続けることにした。……退職金でまだ暮らせるうちは。 魔法少女活動はなんで昼が多いの？ 社会人には不向きすぎない？ 生活費が尽きる前にどうにか悪のボスを倒して少女たちを戦いの運命から解放しようとあがく、期限（貯金額）つき魔法少女おじさんの物語。 全46話。9／21 11時完結予定 ※8／11 ハーメルンで投稿開始しました | P63: 288 | Q63: 55 | R63: 356 | S63: 27 | T63: 道端に落ちていた魔法のステッキを拾い上げたせいで、タイミング悪く魔法少女になってしまった３０代男性。しかも闇属性。 かわいい女の子のフリをするのは心苦しいが、戦う力があるのにまだ幼い少女たちにだけ戦わせるのはもっと心苦しい。 そういうわけで魔法少女活動を続けることにした。……退職金でまだ暮らせるうちは。 魔法少女活動はなんで昼が多いの？ 社会人には不向きすぎない？ 生活費が尽きる前にどうにか悪のボスを倒して少女たちを戦いの運命から解放しようとあがく、期限（貯金額）つき魔法少女おじさんの物語。 全46話。9／21 11時完結予定 ※8／11 ハーメルンで投稿開始しました | U63: 5 | V63: 31 | W63: 31 | X63: 1 | Y63: 8.7078652 | Z63: 継続 | AA63: 1
A64: action | B64: 現代ファンタジー | C64: 2912051605717497440 | D64: 氷河期ストレージ ～生き返った俺はすべての甘さを捨てて、この絶望を生き抜く～ | E64: 宵白レン | F64: https://kakuyomu.jp/works/2912051605717497440 | G64: 2 | H64: 4608 | I64: 104 | J64: 626994 | K64: 27 | L64: 現代ファンタジー|終末|秩序崩壊|人間ドラマ|ざまぁ|タイムリープ|群像劇|AI本文一部利用 | M64: 連載中 | N64: 生きるためなら、人はどこまで人を捨てられるのか。 | O64: 世界を襲った、予測不能の異常寒波。 気温は急降下し、物流は止まり、電気も水道も失われていく。 食料が尽き、救助も来ないと悟った時、人々が当たり前だと思っていた秩序は崩れ始めた。 奪う者。従う者。裏切る者。そして、生きるために誰かを見捨てる者。 法律も善意も意味を失った極寒の世界で、人はどこまで人間でいられるのか。 そんな世界で一度命を落とした神崎蓮は、寒波が訪れる一ヶ月前へと戻っていた。 手にしたのは、あらゆる物資を保存できる謎の能力。 前の人生で人を信じ、裏切られ、雪の中で死んだ蓮は決める。 今度は、すべての甘さを捨てる。 善意ではなく対価を。情ではなく合理を。助ける人間さえ、自分で選ぶ。 やがて文明が崩れたその先で、生き残った人々は再び集まり、新たな秩序を作り始める。 それは以前と同じ社会なのか。 それとも、生存だけを正義とする別の何かなのか。 これは極寒の世界を舞台に、人間の本質と、崩壊した文明の先に生まれる新たな社会を描く物語。 | P64: 428 | Q64: 2 | R64: 4435 | S64: 102 | T64: 世界を襲った、予測不能の異常寒波。 気温は急降下し、物流は止まり、電気も水道も失われていく。 食料が尽き、救助も来ないと悟った時、人々が当たり前だと思っていた秩序は崩れ始めた。 奪う者。従う者。裏切る者。そして、生きるために誰かを見捨てる者。 法律も善意も意味を失った極寒の世界で、人はどこまで人間でいられるのか。 そんな世界で一度命を落とした神崎蓮は、寒波が訪れる一ヶ月前へと戻っていた。 手にしたのは、あらゆる物資を保存できる謎の能力。 前の人生で人を信じ、裏切られ、雪の中で死んだ蓮は決める。 今度は、すべての甘さを捨てる。 善意ではなく対価を。情ではなく合理を。助ける人間さえ、自分で選ぶ。 やがて文明が崩れたその先で、生き残った人々は再び集まり、新たな秩序を作り始める。 それは以前と同じ社会なのか。 それとも、生存だけを正義とする別の何かなのか。 これは極寒の世界を舞台に、人間の本質と、崩壊した文明の先に生まれる新たな社会を描く物語。 | U64: 0 | V64: 173 | W64: 173 | X64: 2 | Y64: 3.9007892 | Z64: 継続 | AA64: 1
A65: action | B65: 現代ファンタジー | C65: 2912051605778147354 | D65: 「画面映えしない」とS級配信パーティを追放された荷物持ち、最深部でヤケクソキャンプ飯を作ったら神話級の魔狼王が餌付けされた〜配信切り忘れで世界中が熱狂する中、もふもふ神獣とスローライフを満喫中〜 | E65: @0m0chi_petit | F65: https://kakuyomu.jp/works/2912051605778147354 | G65: 53 | H65: 181 | I65: 39 | J65: 102415 | K65: 18 | L65: 現代ダンジョン|ダンジョン配信|追放ざまぁ|飯テロ|無自覚チート|もふもふ|スローライフ|AIhonbunsiyou | M65: 連載中 | N65: えっ、ただのまかない飯を食べただけでS級ボスの呪いが解けるんですか！？ | O65: 戦力外として追放された荷物持ちのおっさんが、無自覚に神次元の料理スキル（極上のバフ効果）を発揮し、その様子が偶然世界中に配信されることで、追放したクズ達が炎上して没落する一方、本人は最深部で最強の魔狼王を餌付けしてもふもふスローライフを送る物語。 | P65: 123 | Q65: 53 | R65: 163 | S65: 38 | T65: 戦力外として追放された荷物持ちのおっさんが、無自覚に神次元の料理スキル（極上のバフ効果）を発揮し、その様子が偶然世界中に配信されることで、追放したクズ達が炎上して没落する一方、本人は最深部で最強の魔狼王を餌付けしてもふもふスローライフを送る物語。 | U65: 0 | V65: 18 | W65: 18 | X65: 1 | Y65: 11.042945 | Z65: 継続 | AA65: 1
A66: action | B66: 現代ファンタジー | C66: 2912051605849299462 | D66: 『転生したのに転移で地球に戻っちゃった?! しかも何故43歳?! 王国の魔法革命児 〜爆鳴の鬼と呼ばれた男Ⅱ』 | E66: だいきち | F66: https://kakuyomu.jp/works/2912051605849299462 | G66: 85 | H66: 531 | I66: 24 | J66: 83387 | K66: 23 | L66: おっさん|魔法|異世界転生|ハーレム|現代ファンタジー|異世界帰還|AI補助利用 | M66: 連載中 | N66: 転生したのに現代へ転移?! しかも主人公は転生前のオジサンに?! | O66: 43歳、心筋梗塞で人生を終えた松本賢人は、異世界ノキア王国の少年・ケントとして転生した。 そこで現代知識で魔法を強化し、爆鳴気でなにもかも吹き飛ばす理不尽暴君となっていた。 龍を狩っている時に、真龍が出てきて道連れに自爆 したのだが、気が付くとそこは転生前の自分の部屋 そして自分も43歳の「松本賢人」に 傷も消えた愛する女たちも一緒に転移してきて、何故かイグアナサイズの龍もいる 「ねえ旦那！あの箱走ってるのは何でだ?!」「あそこを歩いてる人が来てる服綺麗だわ」「ケ、ケント様、このベッドの下の本はウェヘヘヘ」 「……まいったなあ」 ケント、いや賢人は令和の日本で、すぐ敵を殺しちゃう彼女達とどう生きるのか というか養っていけるのか?! 小説家になろうでも投稿してます 使用AIはgeminiでAI本文利用 2000字程度のプロット書いて、それを基にAIに書いてもらい、それを手直ししたり文をいれかえたりで作ってます、結局6割程度は自分が書いてますが、AI本文利用としてます | P66: 444 | Q66: 82 | R66: 522 | S66: 23 | T66: 43歳、心筋梗塞で人生を終えた松本賢人は、異世界ノキア王国の少年・ケントとして転生した。 そこで現代知識で魔法を強化し、爆鳴気でなにもかも吹き飛ばす理不尽暴君となっていた。 龍を狩っている時に、真龍が出てきて道連れに自爆 したのだが、気が付くとそこは転生前の自分の部屋 そして自分も43歳の「松本賢人」に 傷も消えた愛する女たちも一緒に転移してきて、何故かイグアナサイズの龍もいる 「ねえ旦那！あの箱走ってるのは何でだ?!」「あそこを歩いてる人が来てる服綺麗だわ」「ケ、ケント様、このベッドの下の本はウェヘヘヘ」 「……まいったなあ」 ケント、いや賢人は令和の日本で、すぐ敵を殺しちゃう彼女達とどう生きるのか というか養っていけるのか?! 小説家になろうでも投稿してます 使用AIはgeminiでAI本文利用 2000字程度のプロット書いて、それを基にAIに書いてもらい、それを手直ししたり文をいれかえたりで作ってます、結局6割程度は自分が書いてますが、AI本文利用としてます | U66: -3 | V66: 9 | W66: 9 | X66: 1 | Y66: 1.7241379 | Z66: 継続 | AA66: 1
... A88: action | B88: 現代ファンタジー | C88: 2912051606752937307 | D88: 世界最高峰の大賢者、失声症の少女に転生する | E88: パパ目 | F88: https://kakuyomu.jp/works/2912051606752937307 | G88: 34 | H88: 220 | I88: 31 | J88: 43520 | K88: 13 | L88: ライトノベル|主人公最強|TS転生|異世界転生|魔法|ガールズラブ|ダンジョン配信|無双 | M88: 連載中 | N88: 不器用でも、不便でも、この気持ちが伝わるのなら… | O88: 無数にある世界のうちの、たった一つの小さな世界。 そこには『大賢者』と呼ばれ、その身を犠牲に、魔王を討ち滅ぼした男がいた。 彼は死んだはずだった。魔王と共に。これからの世界に自分は必要ないと、そう信じて。 しかし、何の因果か、そして何故そうなったかも知らぬまま、彼は再び目を覚ました。 『地球』という世界で。失声症を患った幼き少女として。 かつて魔王を打ち破った『大賢者』は、ダンジョンが存在する現代世界で戸惑いつつも生きていく。 魔法の行使に必要不可欠な詠唱ができずとも、前世の経験を活かし、地球の常識を打ち砕きながら。 | P88: 262 | Q88: 42 | R88: 188 | S88: 30 | T88: 無数にある世界のうちの、たった一つの小さな世界。 そこには『大賢者』と呼ばれ、その身を犠牲に、魔王を討ち滅ぼした男がいた。 彼は死んだはずだった。魔王と共に。これからの世界に自分は必要ないと、そう信じて。 しかし、何の因果か、そして何故そうなったかも知らぬまま、彼は再び目を覚ました。 『地球』という世界で。失声症を患った幼き少女として。 かつて魔王を打ち破った『大賢者』は、ダンジョンが存在する現代世界で戸惑いつつも生きていく。 魔法の行使に必要不可欠な詠唱ができずとも、前世の経験を活かし、地球の常識を打ち砕きながら。 | U88: 8 | V88: 32 | W88: 32 | X88: 1 | Y88: 17.021277 | Z88: 継続 | AA88: 1
A89: action | B89: 現代ファンタジー | C89: 2912051606788687244 | D89: ダンジョン配信に映り込むピクトグラムの怪異になった | E89: ＠脳タリン | F89: https://kakuyomu.jp/works/2912051606788687244 | G89: 78 | H89: 203 | I89: 76 | J89: 342955 | K89: 6 | L89: ダンジョン|配信|ピクトグラム|人外|掲示板|AI作品|現代ダンジョン | M89: 完結済 | N89: 困った時、危ない時にひょっこり登場 | O89: 注意)めちゃくちゃ緩い内容です！ 趣味なので許して！ 本作はAI作品になります ダンジョン配信に、時折映り込む謎のピクトグラム。 配信者にもモンスターにも、その姿は見えない。 けれど、配信を見ている視聴者にだけは、はっきりと見えていた。 瀕死の探索者がいれば医者の姿になって治療し、危険なモンスターが現れれば武器を持った姿へ変わる。 映像にしか存在しないように見えて、その手は確かに現実へ干渉する。 誰なのか。 何なのか。 なぜダンジョン配信に現れるのか。 今日もまた、どこかの配信画面の端から、白い人型が歩いてくる。 | P89: 266 | T89: 注意)めちゃくちゃ緩い内容です！ 趣味なので許して！ 本作はAI作品になります ダンジョン配信に、時折映り込む謎のピクトグラム。 配信者にもモンスターにも、その姿は見えない。 けれど、配信を見ている視聴者にだけは、はっきりと見えていた。 瀕死の探索者がいれば医者の姿になって治療し、危険なモンスターが現れれば武器を持った姿へ変わる。 映像にしか存在しないように見えて、その手は確かに現実へ干渉する。 誰なのか。 何なのか。 なぜダンジョン配信に現れるのか。 今日もまた、どこかの配信画面の端から、白い人型が歩いてくる。 | Z89: 新規ランクイン | AA89: 1
A90: action | B90: 現代ファンタジー | C90: 2912051606811828023 | D90: TS転生してダンジョンで暮らしていた俺、迷子になって配信に映り込む | E90: モヘンジョロ | F90: https://kakuyomu.jp/works/2912051606811828023 | G90: 8 | H90: 709 | I90: 20 | J90: 125100 | K90: 11 | L90: TS転生|ダンジョン配信|主人公最強|異世界|もふもふ|配信|AI本文使用 | M90: 連載中 | N90: 災害級？ 俺の家の近くにはもっとでかいのがいるけど | O90: 現代日本で死に、女性の身体で異世界へTS転生した主人公。しかし、転生先は街でも村でもなかった。 気づけばダンジョンの遥か奥。 自分が何階にいるのかすら分からない場所だった。 それから長い年月を生き延び、今では謎の白いモフモフ「モチ」と暮らすのが彼（♀）の日常になっていた。 そんなある日、見知らぬ魔法陣によって知らない場所へ飛ばされ、巨大な魔物に襲われている女性を助けることになる。 主人公にとっては、家の近くにいるものより小さな「でかいトカゲ」。 しかし地上では――災害級モンスターだった。 助けた女性は、有名なダンジョン配信者…！ その戦いは世界中へ生配信されていて……。 魔物も、薬も、素材も、装備も。 主人公の「普通」は、地上ではまるで普通ではない。 そして誰も知らない。 彼（♀）が今まで、一体どこで暮らしていたのかを。 | P90: 373 | Q90: 8 | R90: 643 | S90: 20 | T90: 現代日本で死に、女性の身体で異世界へTS転生した主人公。しかし、転生先は街でも村でもなかった。 気づけばダンジョンの遥か奥。 自分が何階にいるのかすら分からない場所だった。 それから長い年月を生き延び、今では謎の白いモフモフ「モチ」と暮らすのが彼（♀）の日常になっていた。 そんなある日、見知らぬ魔法陣によって知らない場所へ飛ばされ、巨大な魔物に襲われている女性を助けることになる。 主人公にとっては、家の近くにいるものより小さな「でかいトカゲ」。 しかし地上では――災害級モンスターだった。 助けた女性は、有名なダンジョン配信者…！ その戦いは世界中へ生配信されていて……。 魔物も、薬も、素材も、装備も。 主人公の「普通」は、地上ではまるで普通ではない。 そして誰も知らない。 彼（♀）が今まで、一体どこで暮らしていたのかを。 | U90: 0 | V90: 66 | W90: 66 | X90: 0 | Y90: 10.264386 | Z90: 継続 | AA90: 1
A91: action | B91: 現代ファンタジー | C91: 2912051606816175074 | D91: ウチの山に異世界の騎士が落ちてきた | E91: 道造 | F91: https://kakuyomu.jp/works/2912051606816175074 | G91: 99 | H91: 284 | I91: 11 | J91: 33316 | K91: 12 | L91: 女主人公|ライトノベル|騎士|現代転送|コメディ|女性向け|成り上がり|因習村 | M91: 連載中 | N91: ウチの山に異世界の騎士が落ちてきた話 | O91: タイトルまんま。イケオジ小説コンテスト期間中、午後7時更新 ハーメルンでも掲載しています | P91: 45 | Q91: 83 | R91: 275 | S91: 10 | T91: タイトルまんま。イケオジ小説コンテスト期間中、午後7時更新 ハーメルンでも掲載しています | U91: -16 | V91: 9 | W91: 9 | X91: 1 | Y91: 3.2727273 | Z91: 継続 | AA91: 1
A92: action | B92: 現代ファンタジー | C92: 2912051606854917513 | D92: 推しと結婚したい２４歳脱サラ男、ダンジョン配信で年収1億を狙う | E92: 音有 五角 | F92: https://kakuyomu.jp/works/2912051606854917513 | G92: 24 | H92: 279 | I92: 13 | J92: 22690 | K92: 11 | L92: ダンジョン配信|和服ヒロイン|コメディ|魔法|主人公最強|成り上がり|努力系 | M92: 連載中 | N92: 魔物を吸収して、ステータスを爆伸びさせる。推しのために億を稼ぐ物語。 | O92: 「えっと、年収１億越えの男性でしたら……OKです」 推しの和服美女インフルエンサー・しずえの一言で、24歳会社員・工藤武の人生は激変した。 「つまり億プレイヤーになれば、俺にもワンチャンある！」 勢いで会社を辞め、ダンジョン探索者へ転職。 手にしたユニークスキルは──“吸収”。 倒したモンスターのステータスとスキルを取り込む、超成長型能力だった。 推し活から始まる、億プレイヤーを目指す戦いが開幕した。 | P92: 206 | Q92: 24 | R92: 257 | S92: 12 | T92: 「えっと、年収１億越えの男性でしたら……OKです」 推しの和服美女インフルエンサー・しずえの一言で、24歳会社員・工藤武の人生は激変した。 「つまり億プレイヤーになれば、俺にもワンチャンある！」 勢いで会社を辞め、ダンジョン探索者へ転職。 手にしたユニークスキルは──“吸収”。 倒したモンスターのステータスとスキルを取り込む、超成長型能力だった。 推し活から始まる、億プレイヤーを目指す戦いが開幕した。 | U92: 0 | V92: 22 | W92: 22 | X92: 1 | Y92: 8.5603113 | Z92: 継続 | AA92: 1
A93: action | B93: 現代ファンタジー | C93: 2912051607053590864 | D93: 【10万PV感謝】性能しか見ていない鍛冶師、左遷先でなぜかバズる 〜性能特化で赤字子会社を立て直す〜 | E93: 剛己 | F93: https://kakuyomu.jp/works/2912051607053590864 | G93: 22 | H93: 241 | I93: 65 | J93: 161695 | K93: 8 | L93: 天才主人公|生産職|左遷|配信|会社再建|AI補佐 | M93: 連載中 | N93: 包丁に見える？ なら、よく切れるということだ。 | O93: 性能だけを突き詰めた武器を作る若き鍛冶師、一条翠。 彼の作る魔装具は、切断効率も魔力伝導も耐久性も高水準。 ただし、見た目は地味。 というか、包丁にしか見えない。 国内最大手メーカーA.M.I.の商品会議で評価されなかった翠は、赤字子会社・桜坂魔装製作所へ主任として出向することになる。 肩書きは昇格。 待遇は低下。 要するに左遷。 配属先は、売れる武器を何年も作れず、いつ潰れてもおかしくない桜坂魔装製作所。 だが彼は気にしない。 「性能が良ければ売れるだろ」 その常識外れの設計は、量産武器の性能をわずか数日で大幅に向上。 さらに始めた会社公式配信が予想外の大反響を呼び、誰にも期待されていなかった工場は少しずつ注目を集めていく。 これは、性能しか見ない天才鍛冶師と、個性豊かな仲間たちが、潰れかけの工場を日本一の武器メーカーへ変えていく物語。 | P93: 381 | Q93: 27 | R93: 193 | S93: 64 | T93: 性能だけを突き詰めた武器を作る若き鍛冶師、一条翠。 彼の作る魔装具は、切断効率も魔力伝導も耐久性も高水準。 ただし、見た目は地味。 というか、包丁にしか見えない。 国内最大手メーカーA.M.I.の商品会議で評価されなかった翠は、赤字子会社・桜坂魔装製作所へ主任として出向することになる。 肩書きは昇格。 待遇は低下。 要するに左遷。 配属先は、売れる武器を何年も作れず、いつ潰れてもおかしくない桜坂魔装製作所。 だが彼は気にしない。 「性能が良ければ売れるだろ」 その常識外れの設計は、量産武器の性能をわずか数日で大幅に向上。 さらに始めた会社公式配信が予想外の大反響を呼び、誰にも期待されていなかった工場は少しずつ注目を集めていく。 これは、性能しか見ない天才鍛冶師と、個性豊かな仲間たちが、潰れかけの工場を日本一の武器メーカーへ変えていく物語。 | U93: 5 | V93: 48 | W93: 48 | X93: 1 | Y93: 24.870466 | Z93: 継続 | AA93: 1
A94: action | B94: 現代ファンタジー | C94: 2912051607151208161 | D94: ダンジョンで拾った卵から生まれた少女に「ぱぱ」と懐かれたので育てることにした――なお、危険度は国家消滅級らしい | E94: アリババ | F94: https://kakuyomu.jp/works/2912051607151208161 | G94: 30 | H94: 144 | I94: 8 | J94: 33077 | K94: 5 | L94: ダンジョン|卵|銀髪美少女|擬似親子|最強少女|現代ファンタジー|AI補助|主人公成長 | M94: 連載中 | N94: 周り「絶対に刺激するな」少女「ぱぱ、だっこ」 | O94: ダンジョン探索中、ソロ探索者の結城朔は、地図には存在しない小部屋で一つの卵を見つける。 魔物の卵なのか、それとも未知のアイテムなのか。鑑定してみても結果は『測定不能』。どう考えても怪しく、関わらない方がいいはずだった。 ところが、朔がどうするか迷っている目の前で、卵にひびが入る。 「……割れた？」 殻の中から現れたのは、魔物ではなかった。 銀色の髪をした、小さな少女だった。 少女はしばらく朔の顔を見つめると、嬉しそうに両手を伸ばす。 「……ぱぱ？」 「違う」 「ぱぱ！」 「だから違うって」 なぜか完全に父親だと思われ、そのままとんでもなく懐かれてしまう。 しかも、この少女――ミアは、どうやら普通の子供ではない。 朔では苦戦するはずの魔物が、ミアを見るだけで逃げ出す。地図に存在しない通路を見つけ、誰にも開けられなかった扉を当たり前のように開いてしまう。 そして朔に危険が迫った時だけ、ダンジョンそのものが異常な反応を見せる。 さすがに何かがおかしい。 そう考えた朔がミアを探索者協会で詳しく調べてもらった結果、告げられた判定は想像を遥かに超えていた。 ――推定危険度、国家消滅級。 「……嘘だろ？」 「ぱぱ、だっこ」 国家消滅級と言われても、朔の腕の中にいるのはどう見ても甘えん坊の小さな女の子だ。 ただ一つだけ、確かなことがある。 あの卵を拾った日から、朔の知っているダンジョンは、もう以前と同じ場所ではなくなっていた。 | P94: 637 | Q94: 50 | R94: 121 | S94: 7 | T94: ダンジョン探索中、ソロ探索者の結城朔は、地図には存在しない小部屋で一つの卵を見つける。 魔物の卵なのか、それとも未知のアイテムなのか。鑑定してみても結果は『測定不能』。どう考えても怪しく、関わらない方がいいはずだった。 ところが、朔がどうするか迷っている目の前で、卵にひびが入る。 「……割れた？」 殻の中から現れたのは、魔物ではなかった。 銀色の髪をした、小さな少女だった。 少女はしばらく朔の顔を見つめると、嬉しそうに両手を伸ばす。 「……ぱぱ？」 「違う」 「ぱぱ！」 「だから違うって」 なぜか完全に父親だと思われ、そのままとんでもなく懐かれてしまう。 しかも、この少女――ミアは、どうやら普通の子供ではない。 朔では苦戦するはずの魔物が、ミアを見るだけで逃げ出す。地図に存在しない通路を見つけ、誰にも開けられなかった扉を当たり前のように開いてしまう。 そして朔に危険が迫った時だけ、ダンジョンそのものが異常な反応を見せる。 さすがに何かがおかしい。 そう考えた朔がミアを探索者協会で詳しく調べてもらった結果、告げられた判定は想像を遥かに超えていた。 ――推定危険度、国家消滅級。 「……嘘だろ？」 「ぱぱ、だっこ」 国家消滅級と言われても、朔の腕の中にいるのはどう見ても甘えん坊の小さな女の子だ。 ただ一つだけ、確かなことがある。 あの卵を拾った日から、朔の知っているダンジョンは、もう以前と同じ場所ではなくなっていた。 | U94: 20 | V94: 23 | W94: 23 | X94: 1 | Y94: 19.008264 | Z94: 継続 | AA94: 1
A95: action | B95: 現代ファンタジー | C95: 2912051607178213419 | D95: 借金の保証人になった優しい田舎のおじさんのダンジョン配信 | E95: 月瀬リュカ | F95: https://kakuyomu.jp/works/2912051607178213419 | G95: 17 | H95: 272 | I95: 16 | J95: 115885 | K95: 7 | L95: 現代ダンジョン|スキル|成長|配信|おじさん主人公|ざまぁ|田舎暮らし|もふもふ | M95: 連載中 | N95: 借金を返すたび、押し付けたA級探索者の力が俺に来る。 | O95: 幼馴染のA級探索者を信じて保証人になった、四十六歳の農家・森健司。 ある日届いたのは――三百万円の借金の催促状だった。 電話をしても幼馴染は出ない。 「まあ、なんとかなるさ」 健司は十年以上離れていたダンジョンへ戻り、農業の合間に借金を返すことにした。 ところが、最初の十万円を返済した直後から、なぜか昔より剣が扱いやすくなる。 次の十万円を返せば、身体が強くなる。 さらに返せば、魔物の気配まで分かるようになっていく。 健司が持つ、長年まったく役に立たなかった謎のギフト――《肩代わり》。 その本当の能力は、健司が肩代わりした借金を返すたび、借金を押しつけた者たちから能力を徴収することだった。 しかし本人は、そんなことには気づかない。 「最近、身体の調子がいいな」 畑を耕し、ダンジョンへ潜り、母の塩むすびを食べる。 秋田犬のゴンを散歩させ、ダンジョンで拾ったモフモフ魔物・モチと暮らしながら、ついでに始めた配信までなぜか人気になっていく。 一方その頃。 健司に借金を押しつけたA級探索者たちは、一人、また一人と自分たちの力を失い始めていた。 借金を返すほど強くなる。 田舎のおじさんの、のんびり借金返済ダンジョン配信。 | P95: 528 | Q95: 23 | R95: 169 | S95: 15 | T95: 幼馴染のA級探索者を信じて保証人になった、四十六歳の農家・森健司。 ある日届いたのは――三百万円の借金の催促状だった。 電話をしても幼馴染は出ない。 「まあ、なんとかなるさ」 健司は十年以上離れていたダンジョンへ戻り、農業の合間に借金を返すことにした。 ところが、最初の十万円を返済した直後から、なぜか昔より剣が扱いやすくなる。 次の十万円を返せば、身体が強くなる。 さらに返せば、魔物の気配まで分かるようになっていく。 健司が持つ、長年まったく役に立たなかった謎のギフト――《肩代わり》。 その本当の能力は、健司が肩代わりした借金を返すたび、借金を押しつけた者たちから能力を徴収することだった。 しかし本人は、そんなことには気づかない。 「最近、身体の調子がいいな」 畑を耕し、ダンジョンへ潜り、母の塩むすびを食べる。 秋田犬のゴンを散歩させ、ダンジョンで拾ったモフモフ魔物・モチと暮らしながら、ついでに始めた配信までなぜか人気になっていく。 一方その頃。 健司に借金を押しつけたA級探索者たちは、一人、また一人と自分たちの力を失い始めていた。 借金を返すほど強くなる。 田舎のおじさんの、のんびり借金返済ダンジョン配信。 | U95: 6 | V95: 103 | W95: 103 | X95: 1 | Y95: 60.946746 | Z95: 継続 | AA95: 1
A96: action | B96: 現代ファンタジー | C96: 2912051607190318771 | D96: 悪役令嬢（本物）ですが、現代ダンジョンで高飛車に配信したらツンデレお嬢様と崇められてスパチャが止まりませんわ！ | E96: 冰藍雷夏(ヒョウアイライカ) | F96: https://kakuyomu.jp/works/2912051607190318771 | G96: 74 | H96: 116 | I96: 8 | J96: 13798 | K96: 7 | L96: 悪役令嬢配信者|ダンジョン|ですわ|成り上がり|配信|短編シリーズ|たぶん短編 | M96: 連載中 | N96: この汚ねえアンチコメントは何ですの？ | O96: ​「オーホッホッホ！ この程度の魔物、わたくしの敵ではありませんわ！」 ​乙女ゲームの悪役令嬢エレオノーラは、断罪の果てに現代日本の「底辺ダンジョン配信者」の少女へと転生した。 魔法も失われ、気品もなきこの荒廃した世界で、彼女は決意する――「この現代社会でも、わたくしが頂点に君臨して差し上げますわ！」 ​手始めにダンジョンへ乗り込み、圧倒的な細剣術と魔術でモンスターを華麗に蹴散らしていくエレオノーラ。 高貴な高飛車スタイルを一切崩さない彼女の配信に、ネット民（リスナー）は一瞬で大騒ぎとなる。 ​『うわぁ……痛いキャラ作り配信者だ……』 ↓ 『待って、剣術のキレがガチすぎるんだが！？』 ↓ 『高額スパチャ投げたら「わたくしを金で買う気ですの！？」って本気でブチギレられたｗｗｗ』 ↓ 『「ツンデレ助かる」「神のレスバ」「もっと罵って」』 ​本人は大真面目に下民（現代人）を見下し、金を積んでくる無礼者に激怒しているだけ。 なのに、育ちの良さからくる「礼儀正しさ」と「圧倒的な実力」が裏目に出て、リスナーからは「てぇてぇ神ツンデレ」「煽りの語彙力が高貴すぎる」と大絶賛！ ​アンチを気品あるレスバで黙らせ、高額スパチャ（お小遣い）の嵐にパニックになりながら、彼女はいつの間にか世界を熱狂させる伝説のS級配信者へと駆け上がっていく～？ | P96: 575 | Q96: 87 | R96: 98 | S96: 7 | T96: ​「オーホッホッホ！ この程度の魔物、わたくしの敵ではありませんわ！」 ​乙女ゲームの悪役令嬢エレオノーラは、断罪の果てに現代日本の「底辺ダンジョン配信者」の少女へと転生した。 魔法も失われ、気品もなきこの荒廃した世界で、彼女は決意する――「この現代社会でも、わたくしが頂点に君臨して差し上げますわ！」 ​手始めにダンジョンへ乗り込み、圧倒的な細剣術と魔術でモンスターを華麗に蹴散らしていくエレオノーラ。 高貴な高飛車スタイルを一切崩さない彼女の配信に、ネット民（リスナー）は一瞬で大騒ぎとなる。 ​『うわぁ……痛いキャラ作り配信者だ……』 ↓ 『待って、剣術のキレがガチすぎるんだが！？』 ↓ 『高額スパチャ投げたら「わたくしを金で買う気ですの！？」って本気でブチギレられたｗｗｗ』 ↓ 『「ツンデレ助かる」「神のレスバ」「もっと罵って」』 ​本人は大真面目に下民（現代人）を見下し、金を積んでくる無礼者に激怒しているだけ。 なのに、育ちの良さからくる「礼儀正しさ」と「圧倒的な実力」が裏目に出て、リスナーからは「てぇてぇ神ツンデレ」「煽りの語彙力が高貴すぎる」と大絶賛！ ​アンチを気品あるレスバで黙らせ、高額スパチャ（お小遣い）の嵐にパニックになりながら、彼女はいつの間にか世界を熱狂させる伝説のS級配信者へと駆け上がっていく～？ | U96: 13 | V96: 18 | W96: 18 | X96: 1 | Y96: 18.367347 | Z96: 継続 | AA96: 1
A97: action | B97: 現代ファンタジー | C97: 2912051607190955051 | D97: ダンジョンの最下層に落ちた俺は神からいただいたスキルで最強になる･･････のに周りから化け物扱いなんだけど!? | E97: ドラゴロイド | F97: https://kakuyomu.jp/works/2912051607190955051 | G97: 70 | H97: 85 | I97: 6 | J97: 9993 | K97: 5 | L97: ダンジョン|主人公最強|現代|魔法|破壊 | M97: 連載中 | N97: 突如足元が崩落→ダンジョンの最下層に落ちる→結果、化け物誕生 | O97: 高校1年生の波多野 弘大(はたの こうた)はある日、 親のお使いで外に出ていたときに謎の地震によって理由もわからないところに落とされた。 そこには大好きなラノベとかで読んでいる異世界のような場所だったのだ。 いきなりそんな場所に、何の武器とかもない弘大は息を殺して逃げることしかできなかったのだが、ある場所にたどり着いてしまう。 石碑のような場所であり、そこから現れたのはなんとこの世界の神という少女が。 神様いわく、 ①どうやら、この地球が資源が枯渇してしまいいずれ滅びの一途をたどる!? ②そこで目をつけたのが、別の星の管理をしている神が生み出したダンジョンとのこと。 ･･････つまり、現在俺はこの神が生み出したダンジョンの最下層に落とされてしまったらしい。 そして、俺はその神様から最初の最下層到達記念としてあるスキルをもらい地上に帰還する。 これは不運でダンジョン最下層に落ちてしまった男が世界最強になるまでの物語です。 | P97: 420 | Q97: 89 | R97: 61 | S97: 5 | T97: 高校1年生の波多野 弘大(はたの こうた)はある日、 親のお使いで外に出ていたときに謎の地震によって理由もわからないところに落とされた。 そこには大好きなラノベとかで読んでいる異世界のような場所だったのだ。 いきなりそんな場所に、何の武器とかもない弘大は息を殺して逃げることしかできなかったのだが、ある場所にたどり着いてしまう。 石碑のような場所であり、そこから現れたのはなんとこの世界の神という少女が。 神様いわく、 ①どうやら、この地球が資源が枯渇してしまいいずれ滅びの一途をたどる!? ②そこで目をつけたのが、別の星の管理をしている神が生み出したダンジョンとのこと。 ･･････つまり、現在俺はこの神が生み出したダンジョンの最下層に落とされてしまったらしい。 そして、俺はその神様から最初の最下層到達記念としてあるスキルをもらい地上に帰還する。 これは不運でダンジョン最下層に落ちてしまった男が世界最強になるまでの物語です。 | U97: 19 | V97: 24 | W97: 24 | X97: 1 | Y97: 39.344262 | Z97: 継続 | AA97: 1
A98: action | B98: 現代ファンタジー | C98: 2912051607243871368 | D98: 貞操逆転世界で没落お嬢様のダンジョン配信を裏方で手伝っていたら、従者の俺がバズりました ～男女比1:9の世界では男が女を守るのは珍しいらしい～ | E98: たけのこ | F98: https://kakuyomu.jp/works/2912051607243871368 | G98: 97 | H98: 51 | I98: 13 | J98: 46610 | K98: 6 | L98: 貞操逆転|勘違い|ハーレム|配信|あべこべ|現代ダンジョン|お嬢様 | M98: 連載中 | N98: 守られるのが男の常識？ 俺はお嬢様を守る従者ですが。 | O98: 男女比が、およそ一対九の世界。 男は希少で、女性に守られるのが当たり前。華奢で大人しく、女性の庇護を受ける男性ほど好まれる――そんな現代日本で、九条征司は少しばかり普通から外れた高校生だった。 代々、名家・十六夜家に仕えてきた家系に生まれ、幼い頃から要人警護の訓練を受けてきた征司は、同級生であり主人でもある十六夜紅羽に今も従者として仕えている。 そんなある日、没落した十六夜家を再興したい紅羽が言い出した。 「私、ダンジョン配信を始めるわ」 紅羽が有名になり、十六夜の名前を世間に広める。そのためなら協力するのが従者の役目だ。 征司は撮影係兼護衛として、紅羽のダンジョン配信に同行する。 ところが初配信で予定外の魔物が出現。 危機に陥った紅羽を守るため、征司がカメラを置いて前へ出た結果――。 『男が女を守ってる！？』 『この男誰！？』 『従者って設定じゃなくて本物なの？』 なぜか紅羽ではなく、征司の方まで大バズりしてしまった。 女性を守る男が珍しい？ 男が料理をするのも珍しい？ 女の荷物を持っただけで勘違いされる？ 本人にとっては、どれも従者として当たり前のこと。 没落お嬢様のダンジョン配信を支えるだけだったはずが、人気配信者、数字に厳しい同級生、女性探索者たちまで征司へ注目し始めて――。 これは、男が守られることが常識の世界で、お嬢様を守ることしか考えていない従者が、無自覚に女性たちの常識を壊しながらバズっていくダンジョン配信ラブコメ。 | P98: 640 | T98: 男女比が、およそ一対九の世界。 男は希少で、女性に守られるのが当たり前。華奢で大人しく、女性の庇護を受ける男性ほど好まれる――そんな現代日本で、九条征司は少しばかり普通から外れた高校生だった。 代々、名家・十六夜家に仕えてきた家系に生まれ、幼い頃から要人警護の訓練を受けてきた征司は、同級生であり主人でもある十六夜紅羽に今も従者として仕えている。 そんなある日、没落した十六夜家を再興したい紅羽が言い出した。 「私、ダンジョン配信を始めるわ」 紅羽が有名になり、十六夜の名前を世間に広める。そのためなら協力するのが従者の役目だ。 征司は撮影係兼護衛として、紅羽のダンジョン配信に同行する。 ところが初配信で予定外の魔物が出現。 危機に陥った紅羽を守るため、征司がカメラを置いて前へ出た結果――。 『男が女を守ってる！？』 『この男誰！？』 『従者って設定じゃなくて本物なの？』 なぜか紅羽ではなく、征司の方まで大バズりしてしまった。 女性を守る男が珍しい？ 男が料理をするのも珍しい？ 女の荷物を持っただけで勘違いされる？ 本人にとっては、どれも従者として当たり前のこと。 没落お嬢様のダンジョン配信を支えるだけだったはずが、人気配信者、数字に厳しい同級生、女性探索者たちまで征司へ注目し始めて――。 これは、男が守られることが常識の世界で、お嬢様を守ることしか考えていない従者が、無自覚に女性たちの常識を壊しながらバズっていくダンジョン配信ラブコメ。 | Z98: 新規ランクイン | AA98: 1
A99: action | B99: 現代ファンタジー | C99: 2912051607259346472 | D99: 世界樹ダンジョンで囮にされた僕、風精霊と同化して銀髪美少女へ 〜学園では落ちこぼれDクラスなのに、配信者を救いまくっていたらネットの神になっていた件〜 | E99: あかぱん | F99: https://kakuyomu.jp/works/2912051607259346472 | G99: 56 | H99: 86 | I99: 25 | J99: 57894 | K99: 6 | L99: TS|ダンジョン配信|追放|ざまぁ|学園|女体化|主人公最強|ガールズラブ | M99: 連載中 | N99: 落ちこぼれDクラスの銀髪美少女、実は同接200万の救世主でした | O99: 「おいアルト、お前ここで囮な」 世界樹ダンジョン深層で、所属クラン『剛腕の鉄血隊』に囮として切り捨てられた少年・一ノ瀬アルト。 瀕死の底で彼が出会ったのは、消えかけていた風の大精霊の核だった。 自身の固有スキル『魔力調律』で精霊を救おうとした瞬間――魂が完全同調し、アルトは白銀の髪を持つ美少女『ノア』へと新生・受肉してしまう。 人智を超えた権能【大気統律】を手に入れたノアは、地上への帰還途中に超人気美少女配信者・水無瀬マリンの遭難現場に遭遇。 白い仮面で素顔を隠し、災害級の変異種を一瞬でサイコロステーキにして立ち去る。 ――その様子が全世界200万人に生配信されていたとも知らずに。 ネット上では「世界樹の守護天使」「翠光の仮面様」と崇められ、カルト的人気で神格化されていく一方、当の本人は探索者学園の支援科（2年Dクラス）へ編入。 「目立たず平穏に、学食のかけうどん（200円）を食べて暮らしたい……！」 そう願うノアだったが、オタクな回復術士、大型ワンコ系闇タンク後輩、氷の生徒会長、そして過保護な元Sランク担任教師に囲まれ、日常でもダンジョンでも無自覚に規格外の存在感を発揮してしまい――！？ ※元男子のお荷物サポートが、TS美少女精霊として無双しながらネットの神になるお話です。 ※元仲間へのざまぁ・学園無双・配信バズ・掲示板要素を含みます。 | P99: 586 | Q99: 66 | R99: 77 | S99: 23 | T99: 「おいアルト、お前ここで囮な」 世界樹ダンジョン深層で、所属クラン『剛腕の鉄血隊』に囮として切り捨てられた少年・一ノ瀬アルト。 瀕死の底で彼が出会ったのは、消えかけていた風の大精霊の核だった。 自身の固有スキル『魔力調律』で精霊を救おうとした瞬間――魂が完全同調し、アルトは白銀の髪を持つ美少女『ノア』へと新生・受肉してしまう。 人智を超えた権能【大気統律】を手に入れたノアは、地上への帰還途中に超人気美少女配信者・水無瀬マリンの遭難現場に遭遇。 白い仮面で素顔を隠し、災害級の変異種を一瞬でサイコロステーキにして立ち去る。 ――その様子が全世界200万人に生配信されていたとも知らずに。 ネット上では「世界樹の守護天使」「翠光の仮面様」と崇められ、カルト的人気で神格化されていく一方、当の本人は探索者学園の支援科（2年Dクラス）へ編入。 「目立たず平穏に、学食のかけうどん（200円）を食べて暮らしたい……！」 そう願うノアだったが、オタクな回復術士、大型ワンコ系闇タンク後輩、氷の生徒会長、そして過保護な元Sランク担任教師に囲まれ、日常でもダンジョンでも無自覚に規格外の存在感を発揮してしまい――！？ ※元男子のお荷物サポートが、TS美少女精霊として無双しながらネットの神になるお話です。 ※元仲間へのざまぁ・学園無双・配信バズ・掲示板要素を含みます。 | U99: 10 | V99: 9 | W99: 9 | X99: 2 | Y99: 11.688312 | Z99: 継続 | AA99: 1
A100: action | B100: 現代ファンタジー | C100: 2912051607326206740 | D100: 大切な家族を守ります 世界崩壊サバイバル ～俺だけドロップテーブルが見える～ | E100: 月瀬リュカ | F100: https://kakuyomu.jp/works/2912051607326206740 | G100: 80 | H100: 80 | I100: 13 | J100: 63841 | K100: 5 | L100: 世界崩壊|サバイバル|愛する家族|レベルアップ|ドロップ|レア装備 | M100: 連載中 | N100: 食料も、薬も、おむつも。今は魔物から手に入れろ！ | O100: 世界が崩壊した日、朝倉かなめが手に入れたのは《ドロップ》というギフトだった。 魔物を見るだけで、何を落とすのかが分かる《ドロップテーブル》。 ゴブリンなら食料や医療品。 角ウサギなら日用品。 別の魔物なら、燃料や装備まで。 そして《運》を上げれば上げるほど、より希少なもの、より自分に必要なものが手に入りやすくなる。 力を上げれば、自分は強くなれる。 体力を上げれば、生き残りやすくなる。 それでも、かなめが選んだのは――《運》だった。 自分一人が強くなるより、妻と一歳の娘が生きるために必要なものを持ち帰りたい。 食料が足りなければ、食料を落とす魔物を狩る。 薬がなくなれば、医療品を落とす魔物を探す。 娘のおむつが必要なら、日用品を落とす魔物を狙う。 そして足りない戦闘力は、ドロップした装備で補えばいい。 停電した街。 止まった物流。 あふれ出した魔物。 昨日まで金を出せば買えたものが、もう店にはない。 だから今日も、かなめは必要なものを落とす魔物を探しに行く。 家族三人で、この崩壊した世界を生き残るために。 | P100: 471 | Q100: 99 | R100: 76 | S100: 12 | T100: 世界が崩壊した日、朝倉かなめが手に入れたのは《ドロップ》というギフトだった。 魔物を見るだけで、何を落とすのかが分かる《ドロップテーブル》。 ゴブリンなら食料や医療品。 角ウサギなら日用品。 別の魔物なら、燃料や装備まで。 そして《運》を上げれば上げるほど、より希少なもの、より自分に必要なものが手に入りやすくなる。 力を上げれば、自分は強くなれる。 体力を上げれば、生き残りやすくなる。 それでも、かなめが選んだのは――《運》だった。 自分一人が強くなるより、妻と一歳の娘が生きるために必要なものを持ち帰りたい。 食料が足りなければ、食料を落とす魔物を狩る。 薬がなくなれば、医療品を落とす魔物を探す。 娘のおむつが必要なら、日用品を落とす魔物を狙う。 そして足りない戦闘力は、ドロップした装備で補えばいい。 停電した街。 止まった物流。 あふれ出した魔物。 昨日まで金を出せば買えたものが、もう店にはない。 だから今日も、かなめは必要なものを落とす魔物を探しに行く。 家族三人で、この崩壊した世界を生き残るために。 | U100: 19 | V100: 4 | W100: 4 | X100: 1 | Y100: 5.2631579 | Z100: 継続 | AA100: 1
A101: action | C101: 7667601420112820499 | D101: いきなり許嫁候補！？ ～分家序列最下位からの成り上がり？！私、望んでませんから！ほっといてくださいよ！～ | E101: 天野建 | N101: 記憶を持ったまま、転生した！？ よろしい！先行逃げ切りを目指そう！ | O101: 私は前世、戦場で死んだー。 これでやっと休めると思ったら、次の瞬間には生まれ変わっていた。 なんだと！？少しは休ませて欲しいのである！ それになんということか！ 生まれた世界は、前世とはまったく異なっていたのである！ そこには馬もつけずに高速で走る乗り物、車なるもの。 金属の平面に、人間が入り込み情報を無限に発するもの、テレビなるもの。 私が驚愕する数々の文明の利器が、この世界にはあったのである！ この世界でなら、前世死ぬ直前に思った願いがなせるかもしれない！ 何かなしたかったという、曖昧な望みがな！ はははは！ 曖昧な望み！大いに結構である！ 私はその望みを胸に奮い立つ！ 私は早くからの努力を惜しまない！ そう、赤子からでもだ！ ……そう思っていた時もありました。 その気持ちは忘れてはいない。 けれど、この世界を楽しまねば、生まれてきた意味なし！ せっかく自由な世界に生まれてきたのである！ 少しはのんびりしても問題なかろう？ はっ！父よ！今なんと！本家からの招待状（命令書）が届いた！？ 本家の跡取り息子、７才の許嫁を選ぶ為、儀式に１８才までの分家の女子は全員参加せよ！？ 分家である我が家灰咲家。私は５才。本家の命令は絶対である。 断ることなどできはしない。きな臭くなってきたのである。 が、父曰く、我が家は分家序列最下位。その上、末流の末であるとのこと。 ならば、許嫁に選ばれる可能性は限りなく低かろう！ よかろう！若君の許嫁を選ぶ儀式とやらに参加しようではないか！ ５才になり、初めての遠出、新しい情報が満載に得られよう！ そして！本家は金持ちであると聞いている。我が家では食べられぬ美味なるものが、私を待っていよう！ それらを存分に味わいに行くのである！ ああ！！何事であるか！？予定外の事が起ったようである！ 本家の方々、速やかな解決をお願いする！ え！？無理そう！？ 仕方ないのである！私が手を貸そうではないか！！ この作品は、小説家になろう、ハーメルンでも掲載。 | Q101: 88 | R101: 530 | S101: 164 | T101: 私は前世、戦場で死んだー。 これでやっと休めると思ったら、次の瞬間には生まれ変わっていた。 なんだと！？少しは休ませて欲しいのである！ それになんということか！ 生まれた世界は、前世とはまったく異なっていたのである！ そこには馬もつけずに高速で走る乗り物、車なるもの。 金属の平面に、人間が入り込み情報を無限に発するもの、テレビなるもの。 私が驚愕する数々の文明の利器が、この世界にはあったのである！ この世界でなら、前世死ぬ直前に思った願いがなせるかもしれない！ 何かなしたかったという、曖昧な望みがな！ はははは！ 曖昧な望み！大いに結構である！ 私はその望みを胸に奮い立つ！ 私は早くからの努力を惜しまない！ そう、赤子からでもだ！ ……そう思っていた時もありました。 その気持ちは忘れてはいない。 けれど、この世界を楽しまねば、生まれてきた意味なし！ せっかく自由な世界に生まれてきたのである！ 少しはのんびりしても問題なかろう？ はっ！父よ！今なんと！本家からの招待状（命令書）が届いた！？ 本家の跡取り息子、７才の許嫁を選ぶ為、儀式に１８才までの分家の女子は全員参加せよ！？ 分家である我が家灰咲家。私は５才。本家の命令は絶対である。 断ることなどできはしない。きな臭くなってきたのである。 が、父曰く、我が家は分家序列最下位。その上、末流の末であるとのこと。 ならば、許嫁に選ばれる可能性は限りなく低かろう！ よかろう！若君の許嫁を選ぶ儀式とやらに参加しようではないか！ ５才になり、初めての遠出、新しい情報が満載に得られよう！ そして！本家は金持ちであると聞いている。我が家では食べられぬ美味なるものが、私を待っていよう！ それらを存分に味わいに行くのである！ ああ！！何事であるか！？予定外の事が起ったようである！ 本家の方々、速やかな解決をお願いする！ え！？無理そう！？ 仕方ないのである！私が手を貸そうではないか！！ この作品は、小説家になろう、ハーメルンでも掲載。 | Z101: 圏外落ち | AA101: 1
A102: action | B102: 現代ファンタジー | C102: 7667601420162999739 | D102: 双剣無頼 ～現代ダンジョンで雑魚狩りしてた底辺掃除屋、神話級の剣を手に入れてしまう。しかも二本～ | E102: モモンガ・アイリス | F102: https://kakuyomu.jp/works/7667601420162999739 | G102: 37 | H102: 25341 | I102: 90 | J102: 509409 | K102: 288 | L102: 主人公最強|現代ダンジョン|ダンジョン配信|探索者|勇者 | M102: 連載中 | N102: 探索者未満の掃除屋、神話級の剣を拾ってしまう。二本も。 | O102: 【カクヨムコン11 エンタメ総合部門大賞＆コミカライズ賞】西暦一九九九年、恐怖の大王は落ちて来なかったが、世界は異世界と融合し、地球上には魔法と異種族、そしてダンジョンが現れるようになった。人々は『世界融合』後の様々な大混乱を乗り越え、ダンジョン探索者がもたらす資源を利用して新たな日々を送るようになり――四半世紀が経過する。 人々はダンジョン探索配信を楽しむようになり、探索者は世界中で最も人気の職業になっていた。彼らはダンジョンへ潜り、様々な資源を社会へ還元し、ダンジョンを攻略することで『迷宮暴走』を抑えるという役割を果たしている。実力主義の探索者クランや、アイドル的人気のある女性クラン、無国籍に集まって世界中を渡り歩く探索者クランなどが活躍する……そんな社会の中、早坂透は地元ダンジョンの掃除屋をしていた。 迷宮適正ナシとされた者は探索者になれず、しかし人気のないダンジョンを放置し続けると『迷宮暴走』のリスクが増すということで、市営Ｄ級ダンジョンの上層限定で雑魚狩りをする掃除屋が必要であり、早坂透は三年ほど掃除屋を続けていた。毎日毎日Ｄ級ダンジョンの上層で雑魚狩りを続ける日々。 そんなおり、ふとしたことから透はダンジョンの異常に遭遇し、転移罠を踏んでしまう。そこにはＤ級ダンジョンの上層とはとても思えない強力な魔物が闊歩しており、命からがらで逃げ込んだ隠し部屋の中で、床に突き刺さった神話級の剣を見つけてしまう。しかも二本。 現代ダンジョンで聖剣と妖刀を手に入れてしまった底辺掃除屋の物語。 | P102: 653 | Q102: 36 | R102: 25320 | S102: 90 | T102: 【カクヨムコン11 エンタメ総合部門大賞＆コミカライズ賞】西暦一九九九年、恐怖の大王は落ちて来なかったが、世界は異世界と融合し、地球上には魔法と異種族、そしてダンジョンが現れるようになった。人々は『世界融合』後の様々な大混乱を乗り越え、ダンジョン探索者がもたらす資源を利用して新たな日々を送るようになり――四半世紀が経過する。 人々はダンジョン探索配信を楽しむようになり、探索者は世界中で最も人気の職業になっていた。彼らはダンジョンへ潜り、様々な資源を社会へ還元し、ダンジョンを攻略することで『迷宮暴走』を抑えるという役割を果たしている。実力主義の探索者クランや、アイドル的人気のある女性クラン、無国籍に集まって世界中を渡り歩く探索者クランなどが活躍する……そんな社会の中、早坂透は地元ダンジョンの掃除屋をしていた。 迷宮適正ナシとされた者は探索者になれず、しかし人気のないダンジョンを放置し続けると『迷宮暴走』のリスクが増すということで、市営Ｄ級ダンジョンの上層限定で雑魚狩りをする掃除屋が必要であり、早坂透は三年ほど掃除屋を続けていた。毎日毎日Ｄ級ダンジョンの上層で雑魚狩りを続ける日々。 そんなおり、ふとしたことから透はダンジョンの異常に遭遇し、転移罠を踏んでしまう。そこにはＤ級ダンジョンの上層とはとても思えない強力な魔物が闊歩しており、命からがらで逃げ込んだ隠し部屋の中で、床に突き刺さった神話級の剣を見つけてしまう。しかも二本。 現代ダンジョンで聖剣と妖刀を手に入れてしまった底辺掃除屋の物語。 | U102: -1 | V102: 21 | W102: 21 | X102: 0 | Y102: 0.082938389 | Z102: 継続 | AA102: 1
A103: action | B103: 現代ファンタジー | C103: 822139845421536345 | D103: 最悪な人生を歩んでいた男のやり直し～過去に戻ったら、ダンジョンがあるんだが?～ | E103: ドラゴロイド | F103: https://kakuyomu.jp/works/822139845421536345 | G103: 92 | H103: 12669 | I103: 193 | J103: 362358 | K103: 190 | L103: 学園|青春|やり直し|主人公最強(徐々に)|努力|精霊|ダンジョン|不信 | M103: 連載中 | N103: 俺はもう後悔をしたくない!!→ダンジョンサイコー!! | O103: ある男の人生は散々だった。 ①小学生の時、幼馴染みに告白して振られて、それをクラス内にばらまかれて馬鹿にされる。 ②中学1年になって初めての彼女を部活の先輩に奪われる。 ③中学2年で付き合った後輩の子を部活の後輩に奪われる。 ④高校2年の時に同級生を襲った屑野郎っという冤罪で居場所を失い、 その結果、学校は退学、実家からも絶縁され、失意のまま死んでしまった。 だが、神様はこの男を見捨ててはいなかった。 ふと気が付いたら、高校入学時に巻き戻ったのだ。 巻き戻ったならば、今度こそ自分らしく生きてやる。 周りのことなんて関係ない、1人で生きて見せるんだ・・・ と活き込んでいたら、ふとあるニュースに驚きを隠せなかった。 そのニュースとはなんとダンジョンについてのニュースだったのだ。 これは、一度死んでしまった男が巻き戻った人生でダンジョン攻略にのめり込む物語。 | P103: 383 | Q103: 93 | R103: 12663 | S103: 192 | T103: ある男の人生は散々だった。 ①小学生の時、幼馴染みに告白して振られて、それをクラス内にばらまかれて馬鹿にされる。 ②中学1年になって初めての彼女を部活の先輩に奪われる。 ③中学2年で付き合った後輩の子を部活の後輩に奪われる。 ④高校2年の時に同級生を襲った屑野郎っという冤罪で居場所を失い、 その結果、学校は退学、実家からも絶縁され、失意のまま死んでしまった。 だが、神様はこの男を見捨ててはいなかった。 ふと気が付いたら、高校入学時に巻き戻ったのだ。 巻き戻ったならば、今度こそ自分らしく生きてやる。 周りのことなんて関係ない、1人で生きて見せるんだ・・・ と活き込んでいたら、ふとあるニュースに驚きを隠せなかった。 そのニュースとはなんとダンジョンについてのニュースだったのだ。 これは、一度死んでしまった男が巻き戻った人生でダンジョン攻略にのめり込む物語。 | U103: 1 | V103: 6 | W103: 6 | X103: 1 | Y103: 0.047382137 | Z103: 継続 | AA103: 1
